Workbook
Name _ftn1: OVERVIEW!#REF!
Name _ftnref1: OVERVIEW!$B$3

Sheet OVERVIEW
A1: OVERVIEW of the Risk Stress Test (RiST) tool
A2: Purpose | B2: RiST provides a simple approach to test a project's resilience to climate change and natural disasters based on its economic analysis. Although uncertainty around climate futures is too large to provide a precise estimate of climate impacts over a project's lifetime, this "stress test" can help to improve understanding of possible impacts, enhance preparation and project design, as well as inform decision-makers.
A3: How RiST works | B3: The analysis estimates climate and disaster impacts on the cost and benefit flows of a project’s net present value (NPV). The methodology accounts for: (i) changes in average climate conditions, (ii) impacts from natural disasters, and (iii) changes in the frequency of disasters. The results of this analysis should be considered as a stress test of project robustness: If the NPV or a project’s benefit cost ration (BCR) fall below a certain threshold (e.g. NPV<0 or BCR<1), due to the additional impact of climate and disasters, project teams can modify the project to include risk management measures where necessary, and report to stakeholders on how risks were considered.
A4: Disclaimer | B4: The Risk Stress Testing Methodology (http://hdl.handle.net/10986/35751) and associated RiST Tool can help identify potential climate and disaster risks to a project and inform decision makers on project robustness. However, findings, interpretations, and conclusions derived from applying this Methodology or Tool should not be attributed to the World Bank, its affiliated institutions, the Executive Directors of the World Bank or the governments they represent. Use of this tool is at the user's own risk and under no circumstances shall the World Bank be liable for any loss, damage, liability, or expense incurred or suffered which is claimed to result from the use of this Methodology/Tool.

Sheet Excel Sheet Navigation
B2: Excel-Sheet Navigation
B4: Color Guide
B5: Inputs: Light green cells/sheets indicate inputs needed from users
B6: Calculation: Light orange cells/sheets indicate model calculations
B7: Result: Grey/blue represents parameters and results
B8: Guidance: Beige indicates further guidance

Sheet Calculations >>

Sheet Net Benefit Calculations
A1: Year | B1: 2020 | C1: 2021 | D1: 2022 | E1: 2023 | F1: 2024 | G1: 2025 | H1: 2026 | I1: 2027 | J1: 2028 | K1: 2029 | L1: 2030 | M1: 2031 | N1: 2032 | O1: 2033 | P1: 2034 | Q1: 2035 | R1: 2036 | S1: 2037 | T1: 2038 | U1: 2039 | V1: 2040 | W1: 2041 | X1: 2042 | Y1: 2043 | Z1: 2044
A2: Costs
A3: CAPEX with project | B3: 0 | C3: 933.08134 | D3: 974.2647 | E3: 1456.1167 | F3: 379.78744 | G3: 0 | H3: 0 | I3: 0 | J3: 0 | K3: 56.88 | L3: 63.00045 | M3: 0 | N3: 0 | O3: 0 | P3: 0 | Q3: 56.88 | R3: 63.00045 | S3: 0 | T3: 0 | U3: 0 | V3: 0 | W3: 56.88 | X3: 63.00045 | Y3: 0 | Z3: -748.65003
A4: OPEX without project | B4: 0.14417977 | C4: 0.89825962 | D4: 1.7986269 | E4: 2.5203077 | F4: 2.9916177 | G4: 3.1691729 | H4: 3.3006501 | I4: 3.4383134 | J4: 3.5829907 | K4: 3.7350721 | L4: 3.8948852 | M4: 4.0627427 | N4: 4.1919374 | O4: 4.2931482 | P4: 4.3975446 | Q4: 4.507815 | R4: 4.628631 | S4: 4.7617587 | T4: 4.9055742 | U4: 5.0578663 | V4: 5.2184691 | W4: 5.3877134 | X4: 5.5660372 | Y4: 5.753922 | Z4: 5.9518778
A5: OPEX with project | B5: =((0.14417977)*-1)*-1 -> 0.14417977 | C5: 0 | D5: 0 | E5: 59.151552 | F5: 50.619565 | G5: 0 | H5: 0 | I5: 0 | J5: 0 | K5: 0.15310362 | L5: 0.07655181 | M5: 0 | N5: 0 | O5: 0 | P5: 0 | Q5: 0.0377728 | R5: 0.01783389 | S5: 0 | T5: 0 | U5: 0 | V5: 0 | W5: 0.05590701 | X5: 0.01783389 | Y5: 0 | Z5: 0
A6: MT Vehicle Operation without project | B6: 1761.338 | C6: 1866.0167 | D6: 1995.1374 | E6: 2167.7769 | F6: 2376.2885 | G6: 2571.8985 | H6: 2745.6024 | I6: 2939.3105 | J6: 3158.276 | K6: 3378.8507 | L6: 3579.1352 | M6: 3780.2661 | N6: 3988.094 | O6: 4206.3651 | P6: 4438.6088 | Q6: 4686.647 | R6: 4950.5822 | S6: 5226.7897 | T6: 5513.5773 | U6: 5819.8678 | V6: 6148.6449 | W6: 6506.6403 | X6: 6901.5262 | Y6: 7329.6234 | Z6: 7802.2375
A7: MT Vehicle Operation with project | B7: -1761.338 | C7: -1866.0167 | D7: -1960.7502 | E7: -2060.3957 | F7: -2071.4 | G7: -2081.8416 | H7: -2187.5408 | I7: -2298.877 | J7: -2805.7318 | K7: -2949.7509 | L7: -3101.8531 | M7: -3260.3296 | N7: -3427.2927 | O7: -3606.0633 | P7: -3796.1759 | Q7: -4002.4476 | R7: -4226.9589 | S7: -4463.461 | T7: -4714.1847 | U7: -4988.0531 | V7: -5280.2389 | W7: -5591.4093 | X7: -5916.078 | Y7: -6229.6882 | Z7: -6558.034
A8: MT Travel Time without project | B8: 1237.552 | C8: 1303.9513 | D8: 1376.6631 | E8: 1467.7078 | F8: 1615.4276 | G8: 1762.485 | H8: 1870.2687 | I8: 1996.999 | J8: 2151.5879 | K8: 2316.4837 | L8: 2467.6918 | M8: 2618.108 | N8: 2773.4452 | O8: 2938.8564 | P8: 3117.4905 | Q8: 3311.9717 | R8: 3522.2408 | S8: 3747.0233 | T8: 3985.0053 | U8: 4247.1061 | V8: 4535.2139 | W8: 4859.2455 | X8: 5226.053 | Y8: 5626.6205 | Z8: 6076.1513
A9: MT Travel Time with project | B9: -1237.552 | C9: -1303.9513 | D9: -1373.2119 | E9: -1446.4023 | F9: -1312.0825 | G9: -1171.8848 | H9: -1233.9469 | I9: -1299.5369 | J9: -1565.9648 | K9: -1650.6831 | L9: -1740.4736 | M9: -1835.7054 | N9: -1937.8651 | O9: -2051.4564 | P9: -2173.7733 | Q9: -2312.4253 | R9: -2469.5849 | S9: -2643.9236 | T9: -2840.6304 | U9: -3068.1739 | V9: -3312.2325 | W9: -3565.7871 | X9: -3820.3527 | Y9: -4039.5191 | Z9: -4279.5964
A10: NMT Travel and Operation without project | B10: 47.174228 | C10: 48.862871 | D10: 52.658607 | E10: 59.168352 | F10: 67.33336 | G10: 73.026481 | H10: 74.827963 | I10: 76.916101 | J10: 79.399789 | K10: 81.663805 | L10: 83.13894 | M10: 84.588853 | N10: 86.026605 | O10: 87.552318 | P10: 89.202248 | Q10: 91.009995 | R10: 92.950485 | S10: 94.629695 | T10: 95.861529 | U10: 96.819786 | V10: 97.787716 | W10: 98.765481 | X10: 99.753087 | Y10: 100.75056 | Z10: 101.75801
A11: NMT Travel and Operation with project | B11: -47.174228 | C11: -48.862871 | D11: -49.351501 | E11: -49.845015 | F11: -41.054601 | G11: -39.384956 | H11: -39.826797 | I11: -40.277769 | J11: -47.101804 | K11: -47.652631 | L11: -48.212899 | M11: -48.742214 | N11: -49.269022 | O11: -49.809035 | P11: -50.365491 | Q11: -50.946118 | R11: -51.546214 | S11: -52.113372 | T11: -52.681849 | U11: -53.265712 | V11: -53.868514 | W11: -54.499122 | X11: -55.151427 | Y11: -55.765043 | Z11: -56.379843
B12: -1
A13: Net Benefit With Project | B13: 2019 | C13: 2020 | D13: 2021 | E13: 2022 | F13: 2023 | G13: 2024 | H13: 2025 | I13: 2026 | J13: 2027 | K13: 2028 | L13: 2029 | M13: 2030 | N13: 2031 | O13: 2032 | P13: 2033 | Q13: 2034 | R13: 2035 | S13: 2036 | T13: 2037 | U13: 2038 | V13: 2039 | W13: 2040 | X13: 2041 | Y13: 2042 | Z13: 2043
A14: MT Vehicle Operation with project | B14: 1761.338 | C14: 1866.0167 | D14: 1960.7502 | E14: 2060.3957 | F14: 2071.4 | G14: 2081.8416 | H14: 2187.5408 | I14: 2298.877 | J14: 2805.7318 | K14: 2949.7509 | L14: 3101.8531 | M14: 3260.3296 | N14: 3427.2927 | O14: 3606.0633 | P14: 3796.1759 | Q14: 4002.4476 | R14: 4226.9589 | S14: 4463.461 | T14: 4714.1847 | U14: 4988.0531 | V14: 5280.2389 | W14: 5591.4093 | X14: 5916.078 | Y14: 6229.6882 | Z14: 6558.034
A15: MT Travel Time with project | B15: 1237.552 | C15: 1303.9513 | D15: 1373.2119 | E15: 1446.4023 | F15: 1312.0825 | G15: 1171.8848 | H15: 1233.9469 | I15: 1299.5369 | J15: 1565.9648 | K15: 1650.6831 | L15: 1740.4736 | M15: 1835.7054 | N15: 1937.8651 | O15: 2051.4564 | P15: 2173.7733 | Q15: 2312.4253 | R15: 2469.5849 | S15: 2643.9236 | T15: 2840.6304 | U15: 3068.1739 | V15: 3312.2325 | W15: 3565.7871 | X15: 3820.3527 | Y15: 4039.5191 | Z15: 4279.5964
A16: NMT Travel and Operation with project | B16: 47.174228 | C16: 48.862871 | D16: 49.351501 | E16: 49.845015 | F16: 41.054601 | G16: 39.384956 | H16: 39.826797 | I16: 40.277769 | J16: 47.101804 | K16: 47.652631 | L16: 48.212899 | M16: 48.742214 | N16: 49.269022 | O16: 49.809035 | P16: 50.365491 | Q16: 50.946118 | R16: 51.546214 | S16: 52.113372 | T16: 52.681849 | U16: 53.265712 | V16: 53.868514 | W16: 54.499122 | X16: 55.151427 | Y16: 55.765043 | Z16: 56.379843
A17: Carbon Emission | B17: 1766.4686 | C17: 1865.5029 | D17: 1972.0249 | E17: 2088.0662 | F17: 2230.3334 | G17: 2370.6138 | H17: 2520.4711 | I17: 2689.0394 | J17: 2970.9472 | K17: 3173.686 | L17: 3358.9609 | M17: 3555.2794 | N17: 3764.951 | O17: 3989.7306 | P17: 4230.6114 | Q17: 4490.1698 | R17: 4771.855 | S17: 5071.8919 | T17: 5397.1667 | U17: 5764.5526 | V17: 6169.4207 | W17: 6617.7058 | X17: 7139.6974 | Y17: 7712.8336 | Z17: 8393.4331 | AA17: 108289.95
A18: Net Benefit with project | B18: =((SUM(B14:B17))) -> 4812.5328 | C18: =((SUM(C14:C17))*-1)*-1 -> 5084.3337 | D18: =((SUM(D14:D17))*-1)*-1 -> 5355.3384 | E18: =((SUM(E14:E17))*-1)*-1 -> 5644.7092 | F18: =((SUM(F14:F17))*-1)*-1 -> 5654.8706 | G18: =((SUM(G14:G17))*-1)*-1 -> 5663.7252 | H18: =((SUM(H14:H17))*-1)*-1 -> 5981.7857 | I18: =((SUM(I14:I17))*-1)*-1 -> 6327.7309 | J18: =((SUM(J14:J17))*-1)*-1 -> 7389.7455 | ... Z18: =((SUM(Z14:Z17))*-1)*-1 -> 19287.443 | AA18: =SUM(B18:Z18) -> 252201.19
A20: Net Benefit Without Project | B20: 2019 | C20: 2020 | D20: 2021 | E20: 2022 | F20: 2023 | G20: 2024 | H20: 2025 | I20: 2026 | J20: 2027 | K20: 2028 | L20: 2029 | M20: 2030 | N20: 2031 | O20: 2032 | P20: 2033 | Q20: 2034 | R20: 2035 | S20: 2036 | T20: 2037 | U20: 2038 | V20: 2039 | W20: 2040 | X20: 2041 | Y20: 2042 | Z20: 2043
A21: MT Vehicle Operation without project | B21: 1761.338 | C21: 1866.0167 | D21: 1995.1374 | E21: 2167.7769 | F21: 2376.2885 | G21: 2571.8985 | H21: 2745.6024 | I21: 2939.3105 | J21: 3158.276 | K21: 3378.8507 | L21: 3579.1352 | M21: 3780.2661 | N21: 3988.094 | O21: 4206.3651 | P21: 4438.6088 | Q21: 4686.647 | R21: 4950.5822 | S21: 5226.7897 | T21: 5513.5773 | U21: 5819.8678 | V21: 6148.6449 | W21: 6506.6403 | X21: 6901.5262 | Y21: 7329.6234 | Z21: 7802.2375
A22: MT Travel Time without project | B22: 1237.552 | C22: 1303.9513 | D22: 1376.6631 | E22: 1467.7078 | F22: 1615.4276 | G22: 1762.485 | H22: 1870.2687 | I22: 1996.999 | J22: 2151.5879 | K22: 2316.4837 | L22: 2467.6918 | M22: 2618.108 | N22: 2773.4452 | O22: 2938.8564 | P22: 3117.4905 | Q22: 3311.9717 | R22: 3522.2408 | S22: 3747.0233 | T22: 3985.0053 | U22: 4247.1061 | V22: 4535.2139 | W22: 4859.2455 | X22: 5226.053 | Y22: 5626.6205 | Z22: 6076.1513
A23: NMT Travel and Operation without project | B23: 47.174228 | C23: 48.862871 | D23: 52.658607 | E23: 59.168352 | F23: 67.33336 | G23: 73.026481 | H23: 74.827963 | I23: 76.916101 | J23: 79.399789 | K23: 81.663805 | L23: 83.13894 | M23: 84.588853 | N23: 86.026605 | O23: 87.552318 | P23: 89.202248 | Q23: 91.009995 | R23: 92.950485 | S23: 94.629695 | T23: 95.861529 | U23: 96.819786 | V23: 97.787716 | W23: 98.765481 | X23: 99.753087 | Y23: 100.75056 | Z23: 101.75801
A24: Carbon emission | B24: 1766.4686 | C24: 1865.5029 | D24: 1972.0282 | E24: 2088.0768 | F24: 2230.3456 | G24: 2370.6535 | H24: 2520.5219 | I24: 2689.106 | J24: 2971.0244 | K24: 3173.7875 | L24: 3359.0787 | M24: 3555.4146 | N24: 3765.1056 | O24: 3989.9089 | P24: 4230.8155 | Q24: 4490.4046 | R24: 4772.1219 | S24: 5072.1981 | T24: 5397.5251 | U24: 5764.9718 | V24: 6169.9189 | W24: 6618.3063 | X24: 7140.4365 | Y24: 7713.7646 | Z24: 8394.636 | AA24: 104082.12
A25: Net Benefit Without Project | B25: =((SUM(B21:B24))) -> 4812.5328 | C25: =((SUM(C21:C24))*-1)*-1 -> 5084.3337 | D25: =((SUM(D21:D24))*-1)*-1 -> 5396.4872 | E25: =((SUM(E21:E24))*-1)*-1 -> 5782.7299 | F25: =((SUM(F21:F24))*-1)*-1 -> 6289.395 | G25: =((SUM(G21:G24))*-1)*-1 -> 6778.0636 | H25: =((SUM(H21:H24))*-1)*-1 -> 7211.2209 | I25: =((SUM(I21:I24))*-1)*-1 -> 7702.3316 | J25: =((SUM(J21:J24))*-1)*-1 -> 8360.2881 | ... Z25: =((SUM(Z21:Z24))*-1)*-1 -> 22374.783 | AA25: =SUM(B25:Z25) -> 288134.2
A27: Difference | B27: =B25-B18 -> 0 | C27: =C25-C18 -> 0 | D27: =D25-D18 -> 41.148807 | E27: =E25-E18 -> 138.02068 | F27: =F25-F18 -> 634.52441 | G27: =G25-G18 -> 1114.3384 | H27: =H25-H18 -> 1229.4352 | I27: =I25-I18 -> 1374.6006 | ... Z27: =Z25-Z18 -> 3087.3394
A28: 1.1
B29: 1826.8178 | C29: 1932.2726 | D29: 2042.8781 | E29: 2163.2103 | F29: 2300.9319 | G29: 2454.9545 | H29: 2599.6344 | I29: 2754.0338 | J29: 3121.5794 | K29: 3308.5685 | L29: 3508.7976 | M29: 3720.8259 | N29: 3946.2491 | O29: 4188.9086 | P29: 4450.0756 | Q29: 4731.9894 | R29: 5037.6486 | S29: 5368.2565 | T29: 5712.4588 | U29: 6081.5251 | V29: 6480.6746 | W29: 6913.7812 | X29: 7382.5358 | Y29: 7873.9586 | Z29: 8387.3845
A30: Pessimistic Costs | B30: 5293.9447 | C30: 5592.7671 | D30: 5890.8723 | E30: 6274.2469 | F30: 6276.0391 | G30: 6230.0977 | H30: 6579.9643 | I30: 6960.504 | J30: 8128.7201 | K30: 8604.1183 | L30: 9074.5349 | M30: 9570.0623 | N30: 10097.316 | O30: 10666.765 | P30: 11276.019 | Q30: 11941.629 | R30: 12671.959 | S30: 13454.529 | T30: 14305.13 | U30: 15261.45 | V30: 16297.337 | W30: 17412.403 | X30: 18624.427 | Y30: 19841.587 | Z30: 21216.188
A33: Carbon Emissions | B33: Without Project | C33: With Project
B34: 1766.4686 | C34: 1766.4686
B35: 1865.5029 | C35: 1865.5029
B36: 1972.0282 | C36: 1972.0249
B37: 2088.0768 | C37: 2088.0662
B38: 2230.3456 | C38: 2230.3334
B39: 2370.6535 | C39: 2370.6138
B40: 2520.5219 | C40: 2520.4711
B41: 2689.106 | C41: 2689.0394
B42: 2971.0244 | C42: 2970.9472
B43: 3173.7875 | C43: 3173.686
B44: 3359.0787 | C44: 3358.9609
B45: 3555.4146 | C45: 3555.2794
... B58: 8394.636 | C58: 8393.4331

Sheet Floods and Landslides 
C1: Floods | H1: Landslides
D2: Percentage Change with project (Low) | E2: Percentage Change with Project High | F2: Percenatge Change without Project Low | G2: Percentage Change Without Project High | H2: Percentage Change with project (Low) | I2: Percentage Change with Project High | J2: Percenatge Change without Project Low | K2: Percentage Change Without Project High
D3: =(D7-$D$29)/$D$29 *100 -> 0.24657534 | E3: =(E7-$D$29)/$D$29 *100 -> 0.49315068 | F3: =(F7-$D$30)/$D$30*100 -> 0.49315068 | G3: =(G7-$D$30)/$D$30*100 -> 0.73972603 | H3: =(H7-$D$29)/$D$29*100 -> 0.49315068 | I3: =(I7-$D$29)/$D$29*100 -> 0.73972603 | J3: =(J7-$D$30)/$D$30*100 -> 0.61643836 | K3: =(K7-$D$30)/$D$30*100 -> 0.8630137
D4: =(D8-$D$29)/$D$29 *100 -> 0.14794521 | E4: =(E8-$D$29)/$D$29 *100 -> 0.19726027 | F4: =(F8-$D$30)/$D$30*100 -> 0.19726027 | G4: =(G8-$D$30)/$D$30*100 -> 0.29589041 | H4: =(H8-$D$29)/$D$29*100 -> 0.19726027 | I4: =(I8-$D$29)/$D$29*100 -> 0.29589041 | J4: =(J8-$D$30)/$D$30*100 -> 0.22191781 | K4: =(K8-$D$30)/$D$30*100 -> 0.32054795
D5: =(D9-$D$29)/$D$29 *100 -> 0.036986301 | E5: =(E9-$D$29)/$D$29 *100 -> 0.051780822 | F5: =(F9-$D$30)/$D$30*100 -> 0.059178082 | G5: =(G9-$D$30)/$D$30*100 -> 0.073972603 | H5: =(H9-$D$29)/$D$29*100 -> 0.059178082 | I5: =(I9-$D$29)/$D$29*100 -> 0.073972603 | J5: =(J9-$D$30)/$D$30*100 -> 0.062876712 | K5: =(K9-$D$30)/$D$30*100 -> 0.077671233
A6: Ratio | B6: Prob a | C6: Return Period | D6: User Costs with project (Low) | E6: User Costs with project (High) | F6: Cost without low | G6: Costs without High | H6: Cost with Low | I6: Cost with High | J6: Cost without low | K6: Costs without High | L6: 100
A7: 2 | B7: =C7-C8 -> 0.09 | C7: =1/10 -> 0.1 | D7: =D15+D11 -> 252823.05 | E7: =E15+E11 -> 253444.92 | F7: =F15+F11 -> 289555.14 | G7: =G15+G11 -> 290265.6 | H7: =H15+H11 -> 253444.92 | I7: =I15+I11 -> 254066.79 | J7: =J15+J11 -> 289910.37 | K7: =K15+K11 -> 290620.84
A8: 3 | B8: =C8-C9 -> 0.009 | C8: =1/100 -> 0.01 | D8: =D16+D12 -> 252574.31 | E8: =E16+E12 -> 252698.68 | F8: =F16+F12 -> 288702.57 | G8: =G16+G12 -> 288986.76 | H8: =H16+H12 -> 252698.68 | I8: =I16+I12 -> 252947.43 | J8: =J16+J12 -> 288773.62 | K8: =K16+K12 -> 289057.81
A9: 4 | B9: 0.0009 | C9: =1/1000 -> 0.001 | D9: =D17+D13 -> 252294.47 | E9: =E17+E13 -> 252331.78 | F9: =F17+F13 -> 288304.71 | G9: =G17+G13 -> 288347.34 | H9: =H17+H13 -> 252350.44 | I9: =I17+I13 -> 252387.75 | J9: =J17+J13 -> 288315.37 | K9: =K17+K13 -> 288358
D10: Part 2 with Low | E10: Part 2 with High | F10: Part 2 without Low | G10: Part 2 without High | H10: Part 2 with Low | I10: Part 2 with High | J10: Part 2 without Low | K10: Part 2 without High
A11: 2 | B11: 0.09 | C11: 0.1 | D11: =$B11*D19*$A11*$D$29 -> 1243.7319 | E11: =$B11*E19*$A11*$D$29 -> 2487.4638 | F11: =$B11*F19*$A11*$D$30 -> 2841.8716 | G11: =$B11*G19*$A11*$D$30 -> 4262.8073 | H11: =$B11*H19*$A11*$D$29 -> 2487.4638 | I11: =$B11*I19*$A11*$D$29 -> 3731.1957 | J11: =$B11*J19*$A11*$D$30 -> 3552.3394 | K11: =$B11*K19*$A11*$D$30 -> 4973.2752
A12: 3 | B12: 0.009 | C12: 0.01 | D12: =$B12*D20*$A12*$D$29 -> 559.67935 | E12: =$B12*E20*$A12*$D$29 -> 746.23913 | F12: =$B12*F20*$A12*$D$30 -> 852.56147 | G12: =$B12*G20*$A12*$D$30 -> 1278.8422 | H12: =$B12*H20*$A12*$D$29 -> 746.23913 | I12: =$B12*I20*$A12*$D$29 -> 1119.3587 | J12: =$B12*J20*$A12*$D$30 -> 959.13165 | K12: =$B12*K20*$A12*$D$30 -> 1385.4124
A13: 4 | B13: 0.0009 | C13: 0.001 | D13: =$B13*D21*$A13*$D$29 -> 124.37319 | E13: =$B13*E21*$A13*$D$29 -> 174.12246 | F13: =$B13*F21*$A13*$D$30 -> 227.34972 | G13: =$B13*G21*$A13*$D$30 -> 284.18716 | H13: =$B13*H21*$A13*$D$29 -> 198.9971 | I13: =$B13*I21*$A13*$D$29 -> 248.74638 | J13: =$B13*J21*$A13*$D$30 -> 241.55908 | K13: =$B13*K21*$A13*$D$30 -> 298.39651
D14: Part 1 with Low | E14: Part 1 with High | F14: Part 1 without Low | G14: Part 1 without High | H14: Part 1 with Low | I14: Part 1 with High | J14: Part 1 without Low | K14: Part 1 without High
A15: 2 | B15: 0.09 | C15: 0.1 | D15: =(1-$B15*D19)*$D$29 -> 251579.32 | E15: =(1-$B15*E19)*$D$29 -> 250957.46 | F15: =(1-$B15*F19)*$D$30 -> 286713.26 | G15: =(1-$B15*G19)*$D$30 -> 286002.8 | H15: =(1-$B15*H19)*$D$29 -> 250957.46 | I15: =(1-$B15*I19)*$D$29 -> 250335.59 | J15: =(1-$B15*J19)*$D$30 -> 286358.03 | K15: =(1-$B15*K19)*$D$30 -> 285647.56
A16: 3 | B16: 0.009 | C16: 0.01 | D16: =(1-$B16*D20)*$D$29 -> 252014.63 | E16: =(1-$B16*E20)*$D$29 -> 251952.44 | F16: =(1-$B16*F20)*$D$30 -> 287850.01 | G16: =(1-$B16*G20)*$D$30 -> 287707.92 | H16: =(1-$B16*H20)*$D$29 -> 251952.44 | I16: =(1-$B16*I20)*$D$29 -> 251828.07 | J16: =(1-$B16*J20)*$D$30 -> 287814.49 | K16: =(1-$B16*K20)*$D$30 -> 287672.4
A17: 4 | B17: 0.0009 | C17: 0.001 | D17: =(1-$B17*D21)*$D$29 -> 252170.1 | E17: =(1-$B17*E21)*$D$29 -> 252157.66 | F17: =(1-$B17*F21)*$D$30 -> 288077.36 | G17: =(1-$B17*G21)*$D$30 -> 288063.15 | H17: =(1-$B17*H21)*$D$29 -> 252151.44 | I17: =(1-$B17*I21)*$D$29 -> 252139 | J17: =(1-$B17*J21)*$D$30 -> 288073.81 | K17: =(1-$B17*K21)*$D$30 -> 288059.6
C18: Prob a | D18: Loss of Service with Low Impact | E18: Loss of Service with High | F18: Loss of Service without Low | G18: Loss of service without High | H18: Loss of Service with project (Low) | I18: Loss of Service with project (High) | J18: Loss of Service without project (Low) | K18: Loss of service without project (High)
C19: =1/10 -> 0.1 | D19: =D23/365 -> 0.02739726 | E19: =E23/365 -> 0.054794521 | F19: =F23/365 -> 0.054794521 | G19: =G23/365 -> 0.082191781 | H19: =H23/365 -> 0.054794521 | I19: =I23/365 -> 0.082191781 | J19: =J23/365 -> 0.068493151 | K19: =K23/365 -> 0.095890411
C20: =1/100 -> 0.01 | D20: =D24/365 -> 0.082191781 | E20: =E24/365 -> 0.10958904 | F20: =F24/365 -> 0.10958904 | G20: =G24/365 -> 0.16438356 | H20: =H24/365 -> 0.10958904 | I20: =I24/365 -> 0.16438356 | J20: =J24/365 -> 0.12328767 | K20: =K24/365 -> 0.17808219
C21: =1/1000 -> 0.001 | D21: =D25/365 -> 0.1369863 | E21: =E25/365 -> 0.19178082 | F21: =F25/365 -> 0.21917808 | G21: =G25/365 -> 0.2739726 | H21: =H25/365 -> 0.21917808 | I21: =I25/365 -> 0.2739726 | J21: =J25/365 -> 0.23287671 | K21: =K25/365 -> 0.28767123
D22: Days with project (low impact) | E22: Days with project (high impact) | F22: Days without project (low impact) | G22: Days without (high impact) | H22: Days with Low | I22: Days with High | J22: Days without Low | K22: Days without High
C23: =1/10 -> 0.1 | D23: 10 | E23: 20 | F23: 20 | G23: 30 | H23: 20 | I23: 30 | J23: 25 | K23: 35
C24: =1/100 -> 0.01 | D24: 30 | E24: 40 | F24: 40 | G24: 60 | H24: 40 | I24: 60 | J24: 45 | K24: 65
C25: =1/1000 -> 0.001 | D25: 50 | E25: 70 | F25: 80 | G25: 100 | H25: 80 | I25: 100 | J25: 85 | K25: 105
D29: 252201.19
D30: 288134.2
A32: Change in Average Conditions | D32: With Project Low | E32: Without Project High | F32: Without Project Low | G32: Without Project High
C33: User Costs without Climate Change | D33: =ABS(SUM('Baseline scenario'!$D$15:$AB$15)) -> 252311.46 | E33: =ABS(SUM('Baseline scenario'!$D$15:$AB$15)) -> 252311.46 | F33: =ABS(SUM('Baseline scenario'!$D$16:$AB$16)) -> 288232.36 | G33: =ABS(SUM('Baseline scenario'!$D$16:$AB$16)) -> 288232.36
C34: 2030 | D34: =(1-D40)*D$33+D40*D43*D$33 -> 252311.46 | E34: =(1-E40)*E$33+E40*E43*E$33 -> 251205.44 | F34: =(1-F40)*F$33+F40*F43*F$33 -> 285705.39 | G34: =(1-G40)*G$33+G40*G43*G$33 -> 288232.36
C35: % change | D35: =(D34-D33)/D33 -> 0 | E35: =(E34-E33)/E33 -> -0.0043835616 | F35: =(F34-F33)/F33 -> -0.0087671233 | G35: =(G34-G33)/G33 -> 0
C36: 2050 | D36: =(1-D41)*D$33+D41*D44*D$33 -> 251205.44 | E36: =(1-E41)*E$33+E41*E44*E$33 -> 250237.67 | F36: =(1-F41)*F$33+F41*F44*F$33 -> 294549.78 | G36: =(1-G41)*G$33+G41*G44*G$33 -> 300077.52
C37: % change | D37: =(D36-D33)/D33 -> -0.0043835616 | E37: =(E36-E33)/E33 -> -0.0082191781 | F37: =(F36-F33)/F33 -> 0.021917808 | G37: =(G36-G33)/G33 -> 0.04109589
D38: With Project Low | E38: Without Project High | F38: Without Project Low | G38: Without Project High
C39: Alpha
C40: 2030 | D40: =0/365 -> 0 | E40: =2/365 -> 0.0054794521 | F40: =4/365 -> 0.010958904 | G40: =D18=6/365 -> FALSE
C41: 2044 | D41: =2/365 -> 0.0054794521 | E41: =4/365 -> 0.010958904 | F41: =8/365 -> 0.021917808 | G41: =10/365 -> 0.02739726
C42: Ratio
C43: 2030 | D43: 0 | E43: 0.2 | F43: 0.2 | G43: 0.25
C44: 2044 | D44: 0.2 | E44: 0.25 | F44: 2 | G44: 2.5

Sheet Input >>

Sheet Parameters_Results
B2: Main parameters and results
B3: Two functions of this sheet: (1) Decide on unacceptable NPV in the range of possible future (2) Identify "switching" scenario
B6: Guidance: 1. Step: Decision point - Is the project viable in the high impact climate and pessimistic baseline scenario? Actions: - Set 'All climate parameters' and 'Baseline level of pessimism' at 100% (red cells) - Decide if NPV and BCR for 'All climate risk adjusted results' is above threshold (if yes, no further actions required, if no -> proceed to step 2) 2. Step: Identify climate switching scenario - Identify what level of climate impact would be needed to make the project fail (NPV or BCR below threshold) at a given level of baseline pessimism? - Set 'Level of pessimism on baseline' at a certain value (e.g. 50%) - Identify approximate level of climate impact by looking at the NPV or BCR result graphs below - Change "All climate parameters" value until you have found the 'switching value' (the level of climate impact which leads to a NPV/BCR below threshold) - Look at the result boxes below which show your input parameters for this switching value. -> Continue with steps xy of gudiance
B9: INPUT: Change main parameters of analysis | F9: Guidance on Intepreting Results: Step 1: Decision point - Is the project viable in the high climate impact and pessimistic baseline scenario? - Set 'All climate parameters' and 'Baseline level of pessimism' at 100% (red cells) - Decide if NPV and BCR for 'All climate risk adjusted results' is above threshold (if yes, no further actions required, if no -> proceed to Step 2) Step 2: Identify climate switching scenario - Identify what level of climate impact would be needed to make the project fail (NPV or BCR below threshold) at a given level of baseline pessimism? - Set 'Level of pessimism on baseline' (cell D22) at a certain value (e.g. 50%) - Identify approximate level of climate impact by looking at the NPV or BCR result graphs below - Change "All climate parameters" value (cell D14) until you have found the 'switching value' (the level of climate impact which leads to a NPV/BCR below threshold) - Look at the result boxes below which show your input parameters for this switching value. Step 3: Report NPV and BCRs of the extreme scenarios (i.e. results when climate impacts are set to 0% and 100% and pessimism is set at 0% and 100%). Input results in reporting table and include in project documents/discussions with decisions makers. See sample table below.
B10: Project start date | D10: 2018
B11: Project end date | D11: 2044
B12: Discount rate | D12: 0.06
B14: Parameters to change climate impact (0%=no/low impact, 100%=high impact):
B15: Level of climate impact: All climate parameters (0 - 100%) | D15: 1
B16: Level of climate impact on quantities (0 - 100%) | D16: =D15 -> 1
B17: Level of climate impact on prices (0 - 100%) | D17: =D15 -> 1
B18: Level of climate impact on costs (0 - 100%) | D18: =D15 -> 1
B19: Magnitude of extreme event impacts (0 - 100%) Floods | D19: =D15 -> 1
B20: Future change in extreme event frequency (0 - 100%) Floods | D20: =D15 -> 1
B21: Magnitude of extreme event impacts (0 - 100%) Landslides | D21: =D15 -> 1
B22: Future change in extreme event frequency (0 - 100%) Landslides | D22: =D15 -> 1
B23: Magnitude of extreme event impacts (0 - 100%) | D23: =D15 -> 1
B24: Future change in extreme event frequency (0 - 100%) | D24: =D15 -> 1 | F24: SAMPLE REPORTING TABLE: NPVs and BCRs Under Extreme Scenarios (climate impact at 0% and 100%; project pessimism at 0% and 100%)
F25: Adjusted NPVs and BCRs Under Extreme Scenarios | H25: Level of climate impact
B26: Parameter to change CBA baseline (0%=optimistic, 100%=pessimistic): | H26: No/low impact | J26: High impact
B27: Level of pessimism on baseline (0 -100%) | D27: 1 | H27: NPV | I27: BC ratio | J27: NPV | K27: BC ratio
F28: Baseline scenario | G28: Optimistic | H28: 767.22485 | I28: 2.1250826 | J28: 632.65459 | K28: 1.5703317
G29: Pessimistic | H29: 140.58522 | I29: 1.2061586 | J29: 128.74862 | K29: 1.1160656
B30: RESULT: NPV and BCR for parameters set above
C32: NPV | D32: BCR
B33: Baseline results (without climate impact) | C33: ='Expected flows'!$C$20 -> 11478.573 | D33: ='Expected flows'!$C$21 -> 4.2165149
B34: All climate risks adjusted results | C34: ='Expected flows'!$C$52 -> 4362.5106 | D34: ='Expected flows'!$C$53 -> 1.6844521
B37: RESULT: Graphs for parameters set above
B64: RESULT: Change in average climate conditions for parameters set above
D66: 2030 | E66: 2050 | F66: 2100
B67: Expected change in quantity produced (e.g., corn yield) | C67: User Costs With Project | D67: =Parameters_Results!$D$16*'Climate impacts'!G11+(1-Parameters_Results!$D$16)*'Climate impacts'!F11 -> -0.004 | E67: =Parameters_Results!$D$16*'Climate impacts'!I11+(1-Parameters_Results!$D$16)*'Climate impacts'!H11 -> -0.008 | F67: =Parameters_Results!$D$16*'Climate impacts'!K11+(1-Parameters_Results!$D$16)*'Climate impacts'!J11 -> 0
C68: User Coss Without Project | D68: =Parameters_Results!$D$16*'Climate impacts'!G12+(1-Parameters_Results!$D$16)*'Climate impacts'!F12 -> -0.012 | E68: =Parameters_Results!$D$16*'Climate impacts'!I12+(1-Parameters_Results!$D$16)*'Climate impacts'!H12 -> -0.041 | F68: =Parameters_Results!$D$16*'Climate impacts'!K12+(1-Parameters_Results!$D$16)*'Climate impacts'!J12 -> 0
D69: =Parameters_Results!$D$16*'Climate impacts'!G13+(1-Parameters_Results!$D$16)*'Climate impacts'!F13 -> 0 | E69: =Parameters_Results!$D$16*'Climate impacts'!I13+(1-Parameters_Results!$D$16)*'Climate impacts'!H13 -> 0 | F69: =Parameters_Results!$D$16*'Climate impacts'!K13+(1-Parameters_Results!$D$16)*'Climate impacts'!J13 -> 0
B70: Expected change in price of supply (e.g., unit corn price) | C70: User Costs With Project | D70: =Parameters_Results!$D$16*'Climate impacts'!G14+(1-Parameters_Results!$D$16)*'Climate impacts'!F14 -> 0 | E70: =Parameters_Results!$D$16*'Climate impacts'!I14+(1-Parameters_Results!$D$16)*'Climate impacts'!H14 -> 0 | F70: =Parameters_Results!$D$16*'Climate impacts'!K14+(1-Parameters_Results!$D$16)*'Climate impacts'!J14 -> 0
C71: User Coss Without Project | D71: =Parameters_Results!$D$16*'Climate impacts'!G15+(1-Parameters_Results!$D$16)*'Climate impacts'!F15 -> 0 | E71: =Parameters_Results!$D$16*'Climate impacts'!I15+(1-Parameters_Results!$D$16)*'Climate impacts'!H15 -> 0 | F71: =Parameters_Results!$D$16*'Climate impacts'!K15+(1-Parameters_Results!$D$16)*'Climate impacts'!J15 -> 0
D72: =Parameters_Results!$D$16*'Climate impacts'!G16+(1-Parameters_Results!$D$16)*'Climate impacts'!F16 -> 0 | E72: =Parameters_Results!$D$16*'Climate impacts'!I16+(1-Parameters_Results!$D$16)*'Climate impacts'!H16 -> 0 | F72: =Parameters_Results!$D$16*'Climate impacts'!K16+(1-Parameters_Results!$D$16)*'Climate impacts'!J16 -> 0
B73: Expected change in operational or production costs | C73: CAPEX | D73: =Parameters_Results!$D$16*'Climate impacts'!G17+(1-Parameters_Results!$D$16)*'Climate impacts'!F17 -> 0 | E73: =Parameters_Results!$D$16*'Climate impacts'!I17+(1-Parameters_Results!$D$16)*'Climate impacts'!H17 -> 0 | F73: =Parameters_Results!$D$16*'Climate impacts'!K17+(1-Parameters_Results!$D$16)*'Climate impacts'!J17 -> 0
C74: OPEX With Project | D74: =Parameters_Results!$D$16*'Climate impacts'!G18+(1-Parameters_Results!$D$16)*'Climate impacts'!F18 -> 0.02 | E74: =Parameters_Results!$D$16*'Climate impacts'!I18+(1-Parameters_Results!$D$16)*'Climate impacts'!H18 -> 0.04 | F74: =Parameters_Results!$D$16*'Climate impacts'!K18+(1-Parameters_Results!$D$16)*'Climate impacts'!J18 -> 0
C75: OPEX Without Project | D75: =Parameters_Results!$D$16*'Climate impacts'!G19+(1-Parameters_Results!$D$16)*'Climate impacts'!F19 -> 0.06 | E75: =Parameters_Results!$D$16*'Climate impacts'!I19+(1-Parameters_Results!$D$16)*'Climate impacts'!H19 -> 0.1 | F75: =Parameters_Results!$D$16*'Climate impacts'!K19+(1-Parameters_Results!$D$16)*'Climate impacts'!J19 -> 0
B78: RESULT: Natural disaster estimates for parameters set above
D80: =Parameters_Results!D10 -> 2018 | E80: 2030 | F80: 2050 | G80: 2100
B81: Weak intensity level (Once every 2 years)
B82: Return period (to calculate probability of occurrence), in years | D82: =Parameters_Results!$D$24*'Climate impacts'!E27+(1-Parameters_Results!$D$24)*'Climate impacts'!D27 -> 0 | E82: =Parameters_Results!$D$24*'Climate impacts'!G63+(1-Parameters_Results!$D$24)*'Climate impacts'!F63 -> 2 | F82: =Parameters_Results!$D$24*'Climate impacts'!I63+(1-Parameters_Results!$D$24)*'Climate impacts'!H63 -> 2 | G82: =Parameters_Results!$D$24*'Climate impacts'!J63+(1-Parameters_Results!$D$24)*'Climate impacts'!K63 -> 0
B83: Impact on quantity produced, in % of yearly output | D83: =Parameters_Results!$D$24*'Climate impacts'!E28+(1-Parameters_Results!$D$24)*'Climate impacts'!D28 -> 0 | E83: =Parameters_Results!$D$24*'Climate impacts'!G64+(1-Parameters_Results!$D$24)*'Climate impacts'!F64 -> 0 | F83: =Parameters_Results!$D$24*'Climate impacts'!I64+(1-Parameters_Results!$D$24)*'Climate impacts'!H64 -> 0 | G83: =Parameters_Results!$D$24*'Climate impacts'!J64+(1-Parameters_Results!$D$24)*'Climate impacts'!K64 -> 0
B84: Repair/Reconstruction cost (CAPEX), in absolute amount/monetary unit | D84: =Parameters_Results!$D$24*'Climate impacts'!D29+(1-Parameters_Results!$D$24)*'Climate impacts'!D30 -> 0 | E84: =Parameters_Results!$D$24*'Climate impacts'!G66+(1-Parameters_Results!$D$24)*'Climate impacts'!F66 -> 0 | F84: =Parameters_Results!$D$24*'Climate impacts'!I66+(1-Parameters_Results!$D$24)*'Climate impacts'!H66 -> 0 | G84: =Parameters_Results!$D$24*'Climate impacts'!J66+(1-Parameters_Results!$D$24)*'Climate impacts'!K66 -> 0
B85: Additional out-of-system impacts, in absolute amount/monetary unit | D85: =Parameters_Results!$D$24*'Climate impacts'!E31+(1-Parameters_Results!$D$24)*'Climate impacts'!D31 -> 0 | E85: =Parameters_Results!$D$24*'Climate impacts'!G67+(1-Parameters_Results!$D$24)*'Climate impacts'!F67 -> 0 | F85: =Parameters_Results!$D$24*'Climate impacts'!I67+(1-Parameters_Results!$D$24)*'Climate impacts'!H67 -> 0 | G85: =Parameters_Results!$D$24*'Climate impacts'!J67+(1-Parameters_Results!$D$24)*'Climate impacts'!K67 -> 0
B86: Moderate intensity level (Once every 10 years)
B87: Return period (to calculate probability of occurrence), in years | D87: =Parameters_Results!$D$24*'Climate impacts'!E33+(1-Parameters_Results!$D$24)*'Climate impacts'!D33 -> 0 | E87: =Parameters_Results!$D$24*'Climate impacts'!G69+(1-Parameters_Results!$D$24)*'Climate impacts'!F69 -> 5 | F87: =Parameters_Results!$D$24*'Climate impacts'!I69+(1-Parameters_Results!$D$24)*'Climate impacts'!H69 -> 5 | G87: =Parameters_Results!$D$24*'Climate impacts'!K69+(1-Parameters_Results!$D$24)*'Climate impacts'!J69 -> 0
B88: Impact on quantity produced, in % of yearly output | D88: =Parameters_Results!$D$24*'Climate impacts'!E34+(1-Parameters_Results!$D$24)*'Climate impacts'!D34 -> 0 | E88: =Parameters_Results!$D$24*'Climate impacts'!G70+(1-Parameters_Results!$D$24)*'Climate impacts'!F70 -> 0 | F88: =Parameters_Results!$D$24*'Climate impacts'!I70+(1-Parameters_Results!$D$24)*'Climate impacts'!H70 -> 0 | G88: =Parameters_Results!$D$24*'Climate impacts'!K70+(1-Parameters_Results!$D$24)*'Climate impacts'!J70 -> 0
B89: Repair/Reconstruction cost (CAPEX), in absolute amount/monetary unit | D89: =Parameters_Results!$D$24*'Climate impacts'!E36+(1-Parameters_Results!$D$24)*'Climate impacts'!D36 -> 0 | E89: =Parameters_Results!$D$24*'Climate impacts'!G72+(1-Parameters_Results!$D$24)*'Climate impacts'!F72 -> 0 | F89: =Parameters_Results!$D$24*'Climate impacts'!I72+(1-Parameters_Results!$D$24)*'Climate impacts'!H72 -> 0 | G89: =Parameters_Results!$D$24*'Climate impacts'!K72+(1-Parameters_Results!$D$24)*'Climate impacts'!J72 -> 0
B90: Additional out-of-system impacts, in absolute amount/monetary unit | D90: =Parameters_Results!$D$24*'Climate impacts'!E37+(1-Parameters_Results!$D$24)*'Climate impacts'!D37 -> 0 | E90: =Parameters_Results!$D$24*'Climate impacts'!G73+(1-Parameters_Results!$D$24)*'Climate impacts'!F73 -> 0 | F90: =Parameters_Results!$D$24*'Climate impacts'!I73+(1-Parameters_Results!$D$24)*'Climate impacts'!H73 -> 0 | G90: =Parameters_Results!$D$24*'Climate impacts'!K73+(1-Parameters_Results!$D$24)*'Climate impacts'!J73 -> 0
B91: Strong intensity level (Once every 100 years)
B92: Return period (to calculate probability of occurrence), in years | D92: =Parameters_Results!$D$24*'Climate impacts'!E39+(1-Parameters_Results!$D$24)*'Climate impacts'!D39 -> 0 | E92: =Parameters_Results!$D$24*'Climate impacts'!G75+(1-Parameters_Results!$D$24)*'Climate impacts'!F75 -> 50 | F92: =Parameters_Results!$D$24*'Climate impacts'!I75+(1-Parameters_Results!$D$24)*'Climate impacts'!H75 -> 50 | G92: =Parameters_Results!$D$24*'Climate impacts'!K75+(1-Parameters_Results!$D$24)*'Climate impacts'!J75 -> 0
B93: Impact on quantity produced, in % of yearly output | D93: =Parameters_Results!$D$24*'Climate impacts'!E40+(1-Parameters_Results!$D$24)*'Climate impacts'!D40 -> 0 | E93: =Parameters_Results!$D$24*'Climate impacts'!G76+(1-Parameters_Results!$D$24)*'Climate impacts'!F76 -> 0 | F93: =Parameters_Results!$D$24*'Climate impacts'!I76+(1-Parameters_Results!$D$24)*'Climate impacts'!H76 -> 0 | G93: =Parameters_Results!$D$24*'Climate impacts'!K76+(1-Parameters_Results!$D$24)*'Climate impacts'!J76 -> 0
B94: Repair/Reconstruction cost (CAPEX), in absolute amount/monetary unit | D94: =Parameters_Results!$D$24*'Climate impacts'!E42+(1-Parameters_Results!$D$24)*'Climate impacts'!D42 -> 0 | E94: =Parameters_Results!$D$24*'Climate impacts'!G78+(1-Parameters_Results!$D$24)*'Climate impacts'!F78 -> 0 | F94: =Parameters_Results!$D$24*'Climate impacts'!I78+(1-Parameters_Results!$D$24)*'Climate impacts'!H78 -> 0 | G94: =Parameters_Results!$D$24*'Climate impacts'!K78+(1-Parameters_Results!$D$24)*'Climate impacts'!J78 -> 0
B95: Additional out-of-system impacts, in absolute amount/monetary unit | D95: =Parameters_Results!$D$24*'Climate impacts'!E43+(1-Parameters_Results!$D$24)*'Climate impacts'!D43 -> 0 | E95: =Parameters_Results!$D$24*'Climate impacts'!G79+(1-Parameters_Results!$D$24)*'Climate impacts'!F79 -> 0 | F95: =Parameters_Results!$D$24*'Climate impacts'!I79+(1-Parameters_Results!$D$24)*'Climate impacts'!H79 -> 0 | G95: =Parameters_Results!$D$24*'Climate impacts'!K79+(1-Parameters_Results!$D$24)*'Climate impacts'!J79 -> 0
B96: Extreme intensity level (Once every 1000 years)
B97: Return period (to calculate probability of occurrence), in years | D97: =Parameters_Results!$D$24*'Climate impacts'!E45+(1-Parameters_Results!$D$24)*'Climate impacts'!D45 -> 0 | E97: =Parameters_Results!$D$24*'Climate impacts'!G81+(1-Parameters_Results!$D$24)*'Climate impacts'!F81 -> 500 | F97: =Parameters_Results!$D$24*'Climate impacts'!I81+(1-Parameters_Results!$D$24)*'Climate impacts'!H81 -> 500 | G97: =Parameters_Results!$D$24*'Climate impacts'!K81+(1-Parameters_Results!$D$24)*'Climate impacts'!J81 -> 0
B98: Impact on quantity produced, in % of yearly output | D98: =Parameters_Results!$D$24*'Climate impacts'!E46+(1-Parameters_Results!$D$24)*'Climate impacts'!D46 -> 0 | E98: =Parameters_Results!$D$24*'Climate impacts'!G82+(1-Parameters_Results!$D$24)*'Climate impacts'!F82 -> 0 | F98: =Parameters_Results!$D$24*'Climate impacts'!I82+(1-Parameters_Results!$D$24)*'Climate impacts'!H82 -> 0 | G98: =Parameters_Results!$D$24*'Climate impacts'!K82+(1-Parameters_Results!$D$24)*'Climate impacts'!J82 -> 0
B99: Repair/Reconstruction cost (CAPEX), in absolute amount/monetary unit | D99: =Parameters_Results!$D$24*'Climate impacts'!E48+(1-Parameters_Results!$D$24)*'Climate impacts'!D48 -> 0 | E99: =Parameters_Results!$D$24*'Climate impacts'!G84+(1-Parameters_Results!$D$24)*'Climate impacts'!F84 -> 0 | F99: =Parameters_Results!$D$24*'Climate impacts'!I84+(1-Parameters_Results!$D$24)*'Climate impacts'!H84 -> 0 | G99: =Parameters_Results!$D$24*'Climate impacts'!K84+(1-Parameters_Results!$D$24)*'Climate impacts'!J84 -> 0
B100: Additional out-of-system impacts, in absolute amount/monetary unit | D100: =Parameters_Results!$D$24*'Climate impacts'!E49+(1-Parameters_Results!$D$24)*'Climate impacts'!D49 -> 0 | E100: =Parameters_Results!$D$24*'Climate impacts'!G85+(1-Parameters_Results!$D$24)*'Climate impacts'!F85 -> 0 | F100: =Parameters_Results!$D$24*'Climate impacts'!I85+(1-Parameters_Results!$D$24)*'Climate impacts'!H85 -> 0 | G100: =Parameters_Results!$D$24*'Climate impacts'!K85+(1-Parameters_Results!$D$24)*'Climate impacts'!J85 -> 0
B109: Please don't change the following background calculations:
B111: CALCULATION: NPV and BCR for different levels of climate impact and baseline pessimism
B112: NPV
D113: Baseline pessimism
C114: =Parameters_Results!C34 -> 4362.5106 | D114: 0 | E114: 0.1 | F114: 0.2 | G114: 0.3 | H114: 0.4 | I114: 0.5 | J114: 0.6 | K114: 0.7 | L114: 0.8 | M114: 0.9 | N114: 1
B115: Level of climate impact | C115: 0 | D115: 9015.7948 | E115: 8966.1498 | F115: 8916.5048 | G115: 8866.8599 | H115: 8817.2149 | I115: 8767.5699 | J115: 8717.9249 | K115: 8668.2799 | L115: 8618.635 | M115: 8568.99 | N115: 8519.345
C116: 0.1 | D116: 8759.7247 | E116: 8710.0797 | F116: 8660.4347 | G116: 8610.7897 | H116: 8561.1447 | I116: 8511.4998 | J116: 8461.8548 | K116: 8412.2098 | L116: 8362.5648 | M116: 8312.9199 | N116: 8263.2749
C117: 0.2 | D117: 8483.9464 | E117: 8434.3014 | F117: 8384.6564 | G117: 8335.0114 | H117: 8285.3665 | I117: 8235.7215 | J117: 8186.0765 | K117: 8136.4315 | L117: 8086.7866 | M117: 8037.1416 | N117: 7987.4966
C118: 0.3 | D118: 8184.9832 | E118: 8135.3382 | F118: 8085.6932 | G118: 8036.0482 | H118: 7986.4032 | I118: 7936.7583 | J118: 7887.1133 | K118: 7837.4683 | L118: 7787.8233 | M118: 7738.1783 | N118: 7688.5334
C119: 0.4 | D119: 7858.489 | E119: 7808.844 | F119: 7759.199 | G119: 7709.554 | H119: 7659.9091 | I119: 7610.2641 | J119: 7560.6191 | K119: 7510.9741 | L119: 7461.3292 | M119: 7411.6842 | N119: 7362.0392
C120: 0.5 | D120: 7498.9589 | E120: 7449.314 | F120: 7399.669 | G120: 7350.024 | H120: 7300.379 | I120: 7250.7341 | J120: 7201.0891 | K120: 7151.4441 | L120: 7101.7991 | M120: 7052.1541 | N120: 7002.5092
C121: 0.6 | D121: 7099.3153 | E121: 7049.6703 | F121: 7000.0253 | G121: 6950.3803 | H121: 6900.7354 | I121: 6851.0904 | J121: 6801.4454 | K121: 6751.8004 | L121: 6702.1554 | M121: 6652.5105 | N121: 6602.8655
C122: 0.7 | D122: 6650.3024 | E122: 6600.6575 | F122: 6551.0125 | G122: 6501.3675 | H122: 6451.7225 | I122: 6402.0775 | J122: 6352.4326 | K122: 6302.7876 | L122: 6253.1426 | M122: 6203.4976 | N122: 6153.8527
C123: 0.8 | D123: 6139.5797 | E123: 6089.9347 | F123: 6040.2898 | G123: 5990.6448 | H123: 5940.9998 | I123: 5891.3548 | J123: 5841.7098 | K123: 5792.0649 | L123: 5742.4199 | M123: 5692.7749 | N123: 5643.1299
C124: 0.9 | D124: 5550.3189 | E124: 5500.6739 | F124: 5451.0289 | G124: 5401.3839 | H124: 5351.739 | I124: 5302.094 | J124: 5252.449 | K124: 5202.804 | L124: 5153.159 | M124: 5103.5141 | N124: 5053.8691
C125: 1 | D125: 4858.9603 | E125: 4809.3154 | F125: 4759.6704 | G125: 4710.0254 | H125: 4660.3804 | I125: 4610.7354 | J125: 4561.0905 | K125: 4511.4455 | L125: 4461.8005 | M125: 4412.1555 | N125: 4362.5106
B127: BCR
D128: Baseline pessimism
C129: =D34 -> 1.6844521 | D129: 0 | E129: 0.1 | F129: 0.2 | G129: 0.3 | H129: 0.4 | I129: 0.5 | J129: 0.6 | K129: 0.7 | L129: 0.8 | M129: 0.9 | N129: 1
B130: Level of climate impact | C130: 0 | D130: 3.2442746 | E130: 3.2046713 | F130: 3.1660233 | G130: 3.1282964 | H130: 3.091458 | I130: 3.055477 | J130: 3.0203241 | K130: 2.9859707 | L130: 2.9523901 | M130: 2.9195564 | N130: 2.8874449
C131: 0.1 | D131: 3.1207286 | E131: 3.0836659 | F131: 3.0474732 | G131: 3.0121202 | H131: 2.977578 | I131: 2.9438191 | J131: 2.9108172 | K131: 2.8785469 | L131: 2.8469843 | M131: 2.8161064 | N131: 2.7858911
C132: 0.2 | D132: 2.9949143 | E132: 2.9603565 | F132: 2.9265872 | G132: 2.8935795 | H132: 2.8613082 | I132: 2.8297487 | J132: 2.7988778 | K132: 2.7686732 | L132: 2.7391136 | M132: 2.7101785 | N132: 2.6818483
C133: 0.3 | D133: 2.8663268 | E133: 2.8342432 | F133: 2.80287 | G133: 2.7721837 | H133: 2.742162 | I133: 2.7127836 | J133: 2.6840281 | K133: 2.6558758 | L133: 2.6283079 | M133: 2.6013064 | N133: 2.5748541
C134: 0.4 | D134: 2.7343918 | E134: 2.7047563 | F134: 2.6757563 | G134: 2.6473716 | H134: 2.6195828 | I134: 2.5923714 | J134: 2.5657194 | K134: 2.5396099 | L134: 2.5140264 | M134: 2.4889532 | N134: 2.4643752
C135: 0.5 | D135: 2.5984501 | E135: 2.5712409 | F135: 2.5445956 | G135: 2.5184969 | H135: 2.4929281 | I135: 2.4678732 | J135: 2.443317 | K135: 2.4192446 | L135: 2.395642 | M135: 2.3724954 | N135: 2.3497919
C136: 0.6 | D136: 2.457739 | E136: 2.4329379 | F136: 2.4086324 | G136: 2.3848078 | H136: 2.3614498 | I136: 2.338545 | J136: 2.3160802 | K136: 2.2940429 | L136: 2.272421 | M136: 2.251203 | N136: 2.2303774
C137: 0.7 | D137: 2.3113673 | E137: 2.2889597 | F137: 2.2669823 | G137: 2.245423 | H137: 2.2242698 | I137: 2.2035115 | J137: 2.1831371 | K137: 2.163136 | L137: 2.143498 | M137: 2.1242134 | N137: 2.1052727
C138: 0.8 | D138: 2.1582851 | E138: 2.1382583 | F138: 2.1185997 | G138: 2.0992993 | H138: 2.0803473 | I138: 2.0617345 | J138: 2.0434518 | K138: 2.0254905 | L138: 2.0078422 | M138: 1.9904988 | N138: 1.9734524
C139: 0.9 | D139: 1.9972424 | E139: 1.9795848 | F139: 1.9622367 | G139: 1.94519 | H139: 1.9284369 | I139: 1.9119699 | J139: 1.8957818 | K139: 1.8798654 | L139: 1.8642142 | M139: 1.8488214 | N139: 1.8336806
C140: 1 | D140: 1.8267367 | E140: 1.8114356 | F140: 1.7963887 | G140: 1.7815898 | H140: 1.7670326 | I140: 1.7527115 | J140: 1.7386206 | K140: 1.7247544 | L140: 1.7111077 | M140: 1.6976753 | N140: 1.6844521
B143: CALCULATION: Sensitivity analysis
B145: Quantity | C145: =Parameters_Results!C34 -> 4362.5106 | D145: =ABS(C146-C150) -> 261.77163
B146: 0 | C146: 4624.2822
B147: 0.25 | C147: 4558.8393
B148: 0.5 | C148: 4493.3964
B149: 0.75 | C149: 4427.9535
B150: 1 | C150: 4362.5106
B152: Price | C152: =Parameters_Results!$C$34 -> 4362.5106 | D152: =ABS(C153-C157) -> 0
B153: 0 | C153: 4362.5106 | D153: 0
...

Sheet Baseline scenario
B2: INPUT (Step 1): Baseline scenario (no climate impact)
B3: Inputs needed from the former CBA analysis which does not include climate impact aspects
B5: Please fill all green fields
D6: -1 | E6: 1.05
B7: OPTIMISTIC BASELINE SCENARIO:
D8: -1
B9: INPUT: Optimistic baseline scenario results from former CBA (no climate impact)
B10: 0.02
B11: Year | D11: =Parameters_Results!$D$10+COLUMN()-3 -> 2019 | E11: =Parameters_Results!$D$10+COLUMN()-3 -> 2020 | F11: =Parameters_Results!$D$10+COLUMN()-3 -> 2021 | G11: =Parameters_Results!$D$10+COLUMN()-3 -> 2022 | H11: =Parameters_Results!$D$10+COLUMN()-3 -> 2023 | I11: =Parameters_Results!$D$10+COLUMN()-3 -> 2024 | J11: =Parameters_Results!$D$10+COLUMN()-3 -> 2025 | K11: =Parameters_Results!$D$10+COLUMN()-3 -> 2026 | ... AC11: =Parameters_Results!$D$10+COLUMN()-3 -> 2044
B12: Flow of costs | C12: CAPEX | D12: 0 | E12: 933.08134 | F12: 974.2647 | G12: 1456.1167 | I12: 0 | J12: 0 | K12: 0 | L12: 0 | M12: 56.88 | N12: 63.00045 | O12: 0 | P12: 0 | Q12: 0 | R12: 0 | S12: 56.88 | T12: 63.00045 | U12: 0 | V12: 0 | W12: 0 | X12: 0 | Y12: 56.88 | Z12: 63.00045 | AA12: 0 | AB12: -748.65003 | AC12: 0
C13: OPEX With Project | D13: 0.14417977 | E13: 0 | F13: 0 | G13: 59.151552 | H13: 50.619565 | I13: 0 | J13: 0 | K13: 0 | L13: 0 | M13: 0.15310362 | N13: 0.07655181 | O13: 0 | P13: 0 | Q13: 0 | R13: 0 | S13: 0.0377728 | T13: 0.01783389 | U13: 0 | V13: 0 | W13: 0 | X13: 0 | Y13: 0.05590701 | Z13: 0.01783389 | AA13: 0 | AB13: 0
C14: OPEX Without Project | D14: 0.14417977 | E14: 0.89825962 | F14: 1.7986269 | G14: 2.5203077 | H14: 2.9916177 | I14: 3.1691729 | J14: 3.3006501 | K14: 3.4383134 | L14: 3.5829907 | M14: 3.7350721 | N14: 3.8948852 | O14: 4.0627427 | P14: 4.1919374 | Q14: 4.2931482 | R14: 4.3975446 | S14: 4.507815 | T14: 4.628631 | U14: 4.7617587 | V14: 4.9055742 | W14: 5.0578663 | X14: 5.2184691 | Y14: 5.3877134 | Z14: 5.5660372 | AA14: 5.753922 | AB14: 5.9518778
B15: Flow of benefits | C15: User Costs With Project | D15: -4812.677 | E15: -5084.3337 | F15: -5355.3384 | G15: -5703.8608 | H15: -5705.4901 | I15: -5663.7252 | J15: -5981.7857 | K15: -6327.7309 | L15: -7389.7455 | M15: -7821.9258 | N15: -8249.5771 | O15: -8700.0566 | P15: -9179.3778 | Q15: -9697.0593 | R15: -10250.926 | S15: -10856.027 | T15: -11519.963 | U15: -12231.39 | V15: -13004.664 | W15: -13874.045 | X15: -14815.761 | Y15: -15829.457 | Z15: -16931.297 | AA15: -18037.806 | AB15: -19287.443
C16: User Costs Without Project | D16: -4812.677 | E16: -5085.232 | F16: -5398.2859 | G16: -5785.2502 | H16: -6292.3866 | I16: -6781.2328 | J16: -7214.5215 | K16: -7705.7699 | L16: -8363.871 | M16: -8954.5207 | N16: -9492.9395 | O16: -10042.44 | P16: -10616.863 | Q16: -11226.976 | R16: -11880.515 | S16: -12584.541 | T16: -13342.524 | U16: -14145.402 | V16: -14996.875 | W16: -15933.823 | X16: -16956.784 | Y16: -18088.345 | Z16: -19373.335 | AA16: -20776.513 | AB16: -22380.735
B19: CALCULATION: NPV and BCR of baseline optimistic scenario
B20: Baseline discounted costs | D20: =(D12+D13-D14)/(1+Parameters_Results!$D$12)^('Baseline scenario'!D$11-'Baseline scenario'!$D$11) -> 2.7755576e-17 | E20: =(E12+E13-E14)/(1+Parameters_Results!$D$12)^('Baseline scenario'!E$11-'Baseline scenario'!$D$11) -> 879.418 | F20: =(F12+F13-F14)/(1+Parameters_Results!$D$12)^('Baseline scenario'!F$11-'Baseline scenario'!$D$11) -> 865.49135 | G20: =(G12+G13-G14)/(1+Parameters_Results!$D$12)^('Baseline scenario'!G$11-'Baseline scenario'!$D$11) -> 1270.1324 | H20: =(H12+H13-H14)/(1+Parameters_Results!$D$12)^('Baseline scenario'!H$11-'Baseline scenario'!$D$11) -> 37.725795 | I20: =(I12+I13-I14)/(1+Parameters_Results!$D$12)^('Baseline scenario'!I$11-'Baseline scenario'!$D$11) -> -2.3681904 | J20: =(J12+J13-J14)/(1+Parameters_Results!$D$12)^('Baseline scenario'!J$11-'Baseline scenario'!$D$11) -> -2.3268281 | K20: =(K12+K13-K14)/(1+Parameters_Results!$D$12)^('Baseline scenario'!K$11-'Baseline scenario'!$D$11) -> -2.2866748 | ... AB20: =(AB12+AB13-AB14)/(1+Parameters_Results!$D$12)^('Baseline scenario'!AB$11-'Baseline scenario'!$D$11) -> -186.37048 | AC20: =SUM(AC12:AC14)/(1+Parameters_Results!$D$12)^('Baseline scenario'!AC$11-'Baseline scenario'!$D$11) -> 0
B21: Baseline discounted benefits | D21: =(D15-D16)/(1+Parameters_Results!$D$12)^('Baseline scenario'!D$11-'Baseline scenario'!$D$11) -> 0 | E21: =(E15-E16)/(1+Parameters_Results!$D$12)^('Baseline scenario'!E$11-'Baseline scenario'!$D$11) -> 0.84741474 | F21: =(F15-F16)/(1+Parameters_Results!$D$12)^('Baseline scenario'!F$11-'Baseline scenario'!$D$11) -> 38.223063 | G21: =(G15-G16)/(1+Parameters_Results!$D$12)^('Baseline scenario'!G$11-'Baseline scenario'!$D$11) -> 68.33614 | H21: =(H15-H16)/(1+Parameters_Results!$D$12)^('Baseline scenario'!H$11-'Baseline scenario'!$D$11) -> 464.87697 | I21: =(I15-I16)/(1+Parameters_Results!$D$12)^('Baseline scenario'!I$11-'Baseline scenario'!$D$11) -> 835.06664 | J21: =(J15-J16)/(1+Parameters_Results!$D$12)^('Baseline scenario'!J$11-'Baseline scenario'!$D$11) -> 869.03013 | K21: =(K15-K16)/(1+Parameters_Results!$D$12)^('Baseline scenario'!K$11-'Baseline scenario'!$D$11) -> 916.4746 | ... AB21: =(AB15-AB16)/(1+Parameters_Results!$D$12)^('Baseline scenario'!AB$11-'Baseline scenario'!$D$11) -> 763.9766 | AC21: =SUM(AC15:AC17)/(1+Parameters_Results!$D$12)^('Baseline scenario'!AC$11-'Baseline scenario'!$D$11) -> 0
B23: Optimistic baseline NPV | D23: =SUM(D21:XY21)-SUM(D20:XY20) -> 12065.961 | F23: Discounted cost | H23: =SUM(D20:XY20) -> 2981.248
B24: Optimistic baseline BCR | D24: =SUM(D21:XY21)/SUM(D20:XY20) -> 5.0472853 | F24: Discounted benefits | H24: =SUM(D21:XY21) -> 15047.209
B26: PESSIMISTIC BASELINE SCENARIO:
B28: INPUT: Pessimistic baseline scenario results from former CBA (no climate impact)
B29: -0.02
B30: Year | D30: =Parameters_Results!$D$10+COLUMN()-3 -> 2019 | E30: =Parameters_Results!$D$10+COLUMN()-3 -> 2020 | F30: =Parameters_Results!$D$10+COLUMN()-3 -> 2021 | G30: =Parameters_Results!$D$10+COLUMN()-3 -> 2022 | H30: =Parameters_Results!$D$10+COLUMN()-3 -> 2023 | I30: =Parameters_Results!$D$10+COLUMN()-3 -> 2024 | J30: =Parameters_Results!$D$10+COLUMN()-3 -> 2025 | K30: =Parameters_Results!$D$10+COLUMN()-3 -> 2026 | ... AC30: =Parameters_Results!$D$10+COLUMN()-3 -> 2044
B31: Flow of costs | C31: CAPEX | D31: 0 | E31: 933.08134 | F31: 974.2647 | G31: 1456.1167 | H31: 56.88 | I31: 63.00045 | J31: 0 | K31: 0 | L31: 0 | M31: 56.88 | N31: 63.00045 | O31: 0 | P31: 56.88 | Q31: 63.00045 | R31: 0 | S31: 56.88 | T31: 63.00045 | U31: 933.08134 | V31: 0 | W31: 0 | X31: 0 | Y31: 56.88 | Z31: 63.00045 | AA31: 0 | AB31: -748.65003 | AC31: 0
C32: OPEX With Project | D32: 0.14417977 | E32: 0 | F32: 0 | G32: 59.151552 | H32: 50.619565 | I32: 0 | J32: 0 | K32: 0 | L32: 0 | M32: 0.15310362 | N32: 0.07655181 | O32: 0 | P32: 0 | Q32: 0 | R32: 0 | S32: 0.0377728 | T32: 0.01783389 | U32: 0 | V32: 0 | W32: 0 | X32: 0 | Y32: 0.05590701 | Z32: 0.01783389 | AA32: 0 | AB32: 0 | AC32: 0
C33: OPEX Without Project | D33: 0.14417977 | E33: 0.89825962 | F33: 1.7986269 | G33: 2.5203077 | H33: 2.9916177 | I33: 3.1691729 | J33: 3.3006501 | K33: 3.4383134 | L33: 3.5829907 | M33: 3.7350721 | N33: 3.8948852 | O33: 4.0627427 | P33: 4.1919374 | Q33: 4.2931482 | R33: 4.3975446 | S33: 4.507815 | T33: 4.628631 | U33: 4.7617587 | V33: 4.9055742 | W33: 5.0578663 | X33: 5.2184691 | Y33: 5.3877134 | Z33: 5.5660372 | AA33: 5.753922 | AB33: 5.9518778
B34: Flow of benefits | C34: User Costs With Project | D34: -4812.677 | E34: -5084.3337 | F34: -5355.3384 | G34: -5703.8608 | H34: -5705.4901 | I34: -5663.7252 | J34: -5981.7857 | K34: -6327.7309 | L34: -7389.7455 | M34: -7821.9258 | N34: -8249.5771 | O34: -8700.0566 | P34: -9179.3778 | Q34: -9697.0593 | R34: -10250.926 | S34: -10856.027 | T34: -11519.963 | U34: -12231.39 | V34: -13004.664 | W34: -13874.045 | X34: -14815.761 | Y34: -15829.457 | Z34: -16931.297 | AA34: -18037.806 | AB34: -19287.443
C35: User Coss Without Project | D35: -4812.677 | E35: -5085.232 | F35: -5398.2859 | G35: -5785.2502 | H35: -6292.3866 | I35: -6781.2328 | J35: -7214.5215 | K35: -7705.7699 | L35: -8363.871 | M35: -8954.5207 | N35: -9492.9395 | O35: -10042.44 | P35: -10616.863 | Q35: -11226.976 | R35: -11880.515 | S35: -12584.541 | T35: -13342.524 | U35: -14145.402 | V35: -14996.875 | W35: -15933.823 | X35: -16956.784 | Y35: -18088.345 | Z35: -19373.335 | AA35: -20776.513 | AB35: -22380.735
B38: CALCULATION: NPV and BCR of baseline pessimistic scenario
B39: Baseline discounted costs | D39: =(D31+D32-D33)/(1+Parameters_Results!$D$12)^('Baseline scenario'!D$30-'Baseline scenario'!$D$30) -> 2.7755576e-17 | E39: =SUM(E31:E33)/(1+Parameters_Results!$D$12)^('Baseline scenario'!E$30-'Baseline scenario'!$D$30) -> 881.11283 | F39: =SUM(F31:F33)/(1+Parameters_Results!$D$12)^('Baseline scenario'!F$30-'Baseline scenario'!$D$30) -> 868.69289 | G39: =SUM(G31:G33)/(1+Parameters_Results!$D$12)^('Baseline scenario'!G$30-'Baseline scenario'!$D$30) -> 1274.3646 | H39: =SUM(H31:H33)/(1+Parameters_Results!$D$12)^('Baseline scenario'!H$30-'Baseline scenario'!$D$30) -> 87.519366 | I39: =SUM(I31:I33)/(1+Parameters_Results!$D$12)^('Baseline scenario'!I$30-'Baseline scenario'!$D$30) -> 49.445792 | J39: =SUM(J31:J33)/(1+Parameters_Results!$D$12)^('Baseline scenario'!J$30-'Baseline scenario'!$D$30) -> 2.3268281 | K39: =SUM(K31:K33)/(1+Parameters_Results!$D$12)^('Baseline scenario'!K$30-'Baseline scenario'!$D$30) -> 2.2866748 | L39: =SUM(L31:L33)/(1+Parameters_Results!$D$12)^('Baseline scenario'!L$30-'Baseline scenario'!$D$30) -> 2.2480127 | ... AC39: =SUM(AC31:AC33)/(1+Parameters_Results!$D$12)^('Baseline scenario'!AC$30-'Baseline scenario'!$D$30) -> 0
B40: Baseline discounted benefits | D40: =(D34-D35)/(1+Parameters_Results!$D$12)^('Baseline scenario'!D$30-'Baseline scenario'!$D$30) -> 0 | E40: =(E34-E35)/(1+Parameters_Results!$D$12)^('Baseline scenario'!E$30-'Baseline scenario'!$D$30) -> 0.84741474 | F40: =(F34-F35)/(1+Parameters_Results!$D$12)^('Baseline scenario'!F$30-'Baseline scenario'!$D$30) -> 38.223063 | G40: =(G34-G35)/(1+Parameters_Results!$D$12)^('Baseline scenario'!G$30-'Baseline scenario'!$D$30) -> 68.33614 | H40: =(H34-H35)/(1+Parameters_Results!$D$12)^('Baseline scenario'!H$30-'Baseline scenario'!$D$30) -> 464.87697 | I40: =(I34-I35)/(1+Parameters_Results!$D$12)^('Baseline scenario'!I$30-'Baseline scenario'!$D$30) -> 835.06664 | J40: =(J34-J35)/(1+Parameters_Results!$D$12)^('Baseline scenario'!J$30-'Baseline scenario'!$D$30) -> 869.03013 | K40: =(K34-K35)/(1+Parameters_Results!$D$12)^('Baseline scenario'!K$30-'Baseline scenario'!$D$30) -> 916.4746 | ... AB40: =(AB34-AB35)/(1+Parameters_Results!$D$12)^('Baseline scenario'!AB$30-'Baseline scenario'!$D$30) -> 763.9766 | AC40: =SUM(AC34:AC36)/(1+Parameters_Results!$D$12)^('Baseline scenario'!AC$30-'Baseline scenario'!$D$30) -> 0
B42: Pessimistic baseline NPV | D42: =SUM(D40:XY40)-SUM(D39:XY39) -> 11478.861 | F42: Discounted cost | H42: =SUM(D39:XY39) -> 3568.3482
B43: Pessimistic baseline BCR | D43: =SUM(D40:XY40)/SUM(D39:XY39) -> 4.2168557 | F43: Discounted benefits | H43: =SUM(D40:XY40) -> 15047.209

Sheet Climate impacts
B2: Climate risks input parameters
B3: Inputs needed to calculate climate change impacts on project's costs and benefits
B5: Please fill all green fields | F5: -1
B7: INPUT (Step 2a): Estimates to assess the economic impacts of changes in average conditions
B8: Guidance: For guidance on how to estimate the required input please see "Guidance Note" chapter xy
D9: =Parameters_Results!D10 -> 2018 | F9: 2030 | H9: 2050 | J9: 2100
B10: Climate impact scenario: | F10: No/low impact | G10: High impact | H10: No/low impact | I10: High impact | J10: No/low impact | K10: High impact
B11: Expected change in user costs and operations cost, in % | C11: User costs with project | F11: 0 | G11: -0.004 | H11: -0.004 | I11: -0.008
C12: User costs without project | F12: -0.009 | G12: -0.012 | H12: -0.022 | I12: -0.041
B14: Expected change in price/value of supply, in % | C14: User costs with project | F14: 0 | G14: 0 | H14: 0 | I14: 0
C15: User costs without project | F15: 0 | G15: 0 | H15: 0 | I15: 0
B17: Expected change in investment costs, in % | C17: CAPEX | F17: 0 | G17: 0 | H17: 0 | I17: 0
C18: OPEX With Project | F18: 0.01 | G18: 0.02 | H18: 0.02 | I18: 0.04
C19: OPEX Without Project | F19: 0.04 | G19: 0.06 | H19: 0.08 | I19: 0.1
B21: Disaster 1 - | G21: Disaster 2 - Floods | L21: Disaster 3 - [Landslides]
B22: INPUT (Step 2b i): Estimates to assess the economic impacts of natural disasters in the current context | G22: INPUT (Step 2b ii): Estimates to assess the economic impacts of natural disasters in the current context | L22: INPUT (Step 2b iii): Estimates to assess the economic impacts of natural disasters in the current context
B23: Guidance: - Team has to assess the impacts of extreme events, for various probabilities of occurrence (or return periods). If the team wants only 2 or 3 intensity levels, then they can start from the most extreme (at the bottom) and fill the various levels going up, puting zero impacts for the residual ones. - Impacts of extreme events are in three metrics: impact of project outputs (%), repair/reconstruction costs (monetary), and additional out-of-system impacts (monetary). For guidance on how to estimate impacts, please see "Guidance Note" chapter xy - Return periods (yellow cells) are pre-selected, but can be modified | G23: Guidance : Follow the same instructions as the previous box for another natural disaster that you would like to include in your analysis | L23: Guidance: Follow the same instructions as the first box for another natural disaster that you would like to include in your analysis
D24: =Parameters_Results!D10 -> 2018 | I24: =Parameters_Results!D10 -> 2018 | N24: =Parameters_Results!D10 -> 2018
B25: Climate impact scenario : | D25: No/low impact | E25: High impact | G25: Climate impact scenario : | I25: No/low impact | J25: High impact | L25: Climate impact scenario: | N25: No/low impact | O25: High impact
B26: Weak intensity level | G26: Weak intensity level | L26: Weak intensity level
B27: Return period (to calculate probability of occurrence), in years | D27: 2 | G27: Return period (to calculate probability of occurrence), in years | I27: 2 | L27: Return period (to calculate probability of occurrence), in years | N27: 2
B28: Impact on quantity produced, in % of yearly output with project | D28: 0 | E28: 0 | G28: Impact on quantity produced, in % of yearly output with project | I28: 0 | J28: 0 | L28: Impact on quantity produced, in % of yearly output | N28: 0 | O28: 0
B29: Impact on quantity produced, in % of yearly output without project | D29: 0 | E29: 0 | G29: Impact on quantity produced, in % of yearly output without project | I29: 0 | J29: 0 | N29: 0 | O29: 0
B30: Repair/Reconstruction cost (CAPEX), in absolute amount/monetary unit | D30: 0 | E30: 0 | G30: Repair/Reconstruction cost (CAPEX), in absolute amount/monetary unit | I30: 0 | J30: 0 | L30: Repair/Reconstruction cost (CAPEX), in absolute amount/monetary unit | N30: 0 | O30: 0
B31: Additional out-of-system impacts, in absolute amount/monetary unit | D31: 0 | E31: 0 | G31: Additional out-of-system impacts, in absolute amount/monetary unit | I31: 0 | J31: 0 | L31: Additional out-of-system impacts, in absolute amount/monetary unit | N31: 0 | O31: 0
B32: Moderate intensity level | G32: Moderate intensity level | L32: Moderate intensity level
B33: Return period (to calculate probability of occurrence), in years | D33: 10 | G33: Return period (to calculate probability of occurrence), in years | I33: 10 | L33: Return period (to calculate probability of occurrence), in years | N33: 10
B34: Impact on quantity produced, in % of yearly output with project | D34: 0 | E34: 0 | G34: Impact on quantity produced, in % of yearly output with project | I34: -0.24657534 | J34: -0.49315068 | L34: Impact on quantity produced, in % of yearly output | N34: -0.49315068 | O34: -0.73972603
B35: Impact on quantity produced, in % of yearly output without project | D35: 0 | E35: 0 | G35: Impact on quantity produced, in % of yearly output without project | I35: -0.49315068 | J35: -0.73972603 | N35: -0.61643836 | O35: -0.8630137
B36: Repair/Reconstruction cost (CAPEX), in absolute amount/monetary unit | D36: 0 | E36: 0 | G36: Repair/Reconstruction cost (CAPEX), in absolute amount/monetary unit | I36: =I54*$C$54 -> 297.44541 | J36: =J54*$C$54 -> 594.89081 | L36: Repair/Reconstruction cost (CAPEX), in absolute amount/monetary unit | N36: =N54*$H54 -> 297.44541 | O36: =O54*$H54 -> 594.89081
B37: Additional out-of-system impacts, in absolute amount/monetary unit | D37: 0 | E37: 0 | G37: Additional out-of-system impacts, in absolute amount/monetary unit | I37: 0 | J37: 0 | L37: Additional out-of-system impacts, in absolute amount/monetary unit | N37: 0 | O37: 0
B38: Strong intensity level | G38: Strong intensity level | L38: Strong intensity level
B39: Return period (to calculate probability of occurrence), in years | D39: 100 | G39: Return period (to calculate probability of occurrence), in years | I39: 100 | L39: Return period (to calculate probability of occurrence), in years | N39: 100
B40: Impact on quantity produced, in % of yearly output with project | D40: 0 | E40: 0 | G40: Impact on quantity produced, in % of yearly output with project | I40: -0.14794521 | J40: -0.19726027 | L40: Impact on quantity produced, in % of yearly output | N40: -0.19726027 | O40: -0.29589041
B41: Impact on quantity produced, in % of yearly output without project | D41: 0 | E41: 0 | G41: Impact on quantity produced, in % of yearly output without project | I41: -0.19726027 | J41: -0.29589041 | L41: Impact on quantity produced, in % of yearly output without project | N41: -0.22191781 | O41: -0.32054795
B42: Repair/Reconstruction cost (CAPEX), in absolute amount/monetary unit | D42: 0 | E42: 0 | G42: Repair/Reconstruction cost (CAPEX), in absolute amount/monetary unit | I42: =I55*$C55 -> 743.61352 | J42: =J55*$C55 -> 1041.0589 | L42: Repair/Reconstruction cost (CAPEX), in absolute amount/monetary unit | N42: =N55*$H55 -> 743.61352 | O42: =O55*$H55 -> 1041.0589
B43: Additional out-of-system impacts, in absolute amount/monetary unit | D43: 0 | E43: 0 | G43: Additional out-of-system impacts, in absolute amount/monetary unit | I43: 0 | J43: 0 | L43: Additional out-of-system impacts, in absolute amount/monetary unit | N43: 0 | O43: 0
B44: Extreme intensity level | G44: Extreme intensity level | L44: Extreme intensity level
B45: Return period (to calculate probability of occurrence), in years | D45: 1000 | G45: Return period (to calculate probability of occurrence), in years | I45: 1000 | L45: Return period (to calculate probability of occurrence), in years | N45: 1000
B46: Impact on quantity produced, in % of yearly output with project | D46: 0 | E46: 0 | G46: Impact on quantity produced, in % of yearly output with project | I46: -0.036986301 | J46: -0.051780822 | L46: Impact on quantity produced, in % of yearly output | N46: -0.059178082 | O46: -0.073972603
B47: Impact on quantity produced, in % of yearly output without project | D47: 0 | E47: 0 | G47: Impact on quantity produced, in % of yearly output without project | I47: -0.059178082 | J47: -0.073972603 | L47: Impact on quantity produced, in % of yearly output without project | N47: -0.062876712 | O47: -0.077671233
B48: Repair/Reconstruction cost (CAPEX), in absolute amount/monetary unit | D48: 0 | E48: 0 | G48: Repair/Reconstruction cost (CAPEX), in absolute amount/monetary unit | I48: =I56*$C56 -> 1338.5043 | J48: =J56*$C56 -> 1635.9497 | L48: Repair/Reconstruction cost (CAPEX), in absolute amount/monetary unit | N48: =N56*$H56 -> 1338.5043 | O48: =O56*$H56 -> 1635.9497
B49: Additional out-of-system impacts, in absolute amount/monetary unit | D49: 0 | E49: 0 | G49: Additional out-of-system impacts, in absolute amount/monetary unit | I49: 0 | J49: 0 | L49: Additional out-of-system impacts, in absolute amount/monetary unit | N49: 0 | O49: 0
B51: Impact on Infrastructure (CAPEX Calculations) | D51: % of Roads Damaged | G51: Impact on Infrastructure (CAPEX Calculations) | I51: % of Roads Damaged | L51: Impact on Infrastructure (CAPEX Calculations) | N51: % of Roads Damaged
B52: Return Period | C52: Total CAPEX | D52: No/ Low | E52: High Impact | G52: Return Period | H52: Total CAPEX | I52: No/ Low | J52: High Impact | L52: Return Period | M52: Total CAPEX | N52: No/ Low | O52: High Impact
B53: 2 | C53: =SUM('Baseline scenario'!$D$12:$AB$12) -> 2974.4541 | D53: 0 | E53: 0 | G53: 2 | H53: =SUM('Baseline scenario'!$D$12:$AB$12) -> 2974.4541 | I53: 0 | J53: 0 | L53: 2 | M53: =SUM('Baseline scenario'!$D$12:$AB$12) -> 2974.4541 | N53: 0 | O53: 0
B54: 10 | C54: =SUM('Baseline scenario'!$D$12:$AB$12) -> 2974.4541 | D54: 0.1 | E54: 0.2 | G54: 10 | H54: =SUM('Baseline scenario'!$D$12:$AB$12) -> 2974.4541 | I54: 0.1 | J54: 0.2 | L54: 10 | M54: =SUM('Baseline scenario'!$D$12:$AB$12) -> 2974.4541 | N54: 0.1 | O54: 0.2
B55: 100 | C55: =SUM('Baseline scenario'!$D$12:$AB$12) -> 2974.4541 | D55: 0.25 | E55: 0.35 | G55: 100 | H55: =SUM('Baseline scenario'!$D$12:$AB$12) -> 2974.4541 | I55: 0.25 | J55: 0.35 | L55: 100 | M55: =SUM('Baseline scenario'!$D$12:$AB$12) -> 2974.4541 | N55: 0.25 | O55: 0.35
B56: 1000 | C56: =SUM('Baseline scenario'!$D$12:$AB$12) -> 2974.4541 | D56: 0.45 | E56: 0.55 | G56: 1000 | H56: =SUM('Baseline scenario'!$D$12:$AB$12) -> 2974.4541 | I56: 0.45 | J56: 0.55 | L56: 1000 | M56: =SUM('Baseline scenario'!$D$12:$AB$12) -> 2974.4541 | N56: 0.45 | O56: 0.55
B58: INPUT (Step 2c i) : Estimates to assess how the frequency of disastes is likely to change | L58: INPUT (Step 2c ii) : Estimates to assess how the frequency of disastes is likely to change | U58: INPUT (Step 2c iii): Estimates to assess how the frequency of disasters is likely to change
B59: Guidance: - Team has to assess how the probabilities of occurrence (or return periods) may change with climate change, in an optimistic and a pessimistic case (corresponding to natural disaster mentioned in box 2b i ) - For guidance on how to estimate these changes, please see "Guidance Note" chapter xy | L59: Guidance: - Team has to assess how the probabilities of occurrence (or return periods) may change with climate change, in an optimistic and a pessimistic case (corresponding to natural disaster mentioned in box 2b i ) - For guidance on how to estimate these changes, please see "Guidance Note" chapter xy | U59: Guidance: - Team has to assess how the probabilities of occurrence (or return periods) may change with climate change, in an optimistic and a pessimistic case (corresponding to natural disaster mentioned in box 2b iii) - For guidance on how to estimate these changes, please see "Guidance Note" chapter xy
D60: 2020 | F60: 2030 | H60: 2050 | J60: 2100 | M60: 2020 | O60: 2030 | Q60: 2050 | S60: 2100 | W60: 2020 | Y60: 2030 | AA60: 2050 | AC60: 2100
B61: Climate impact scenario: | D61: No/low impact | E61: High impact | F61: No/low impact | G61: High impact | H61: No/low impact | I61: High impact | J61: No/low impact | K61: High impact | L61: Climate Impact Scenario | M61: No/low impact | N61: High impact | O61: No/low impact | P61: High impact | Q61: No/low impact | R61: High impact | S61: No/low impact | T61: High impact | U61: Climate impact scenario: | W61: No/low impact | X61: High impact | Y61: No/low impact | Z61: High impact | AA61: No/low impact | AB61: High impact | AC61: No/low impact | AD61: High impact
B62: Weak intensity level | L62: Weak Intensity Level | U62: Weak intensity level
B63: Return period (to calB54:B72culate probability of occurrence), in years | D63: =D27 -> 2 | F63: 2 | G63: 2 | H63: 2 | I63: 2 | J63: 0 | K63: 0 | L63: Return period (to calB54:B72culate probability of occurrence), in years | M63: =I27 -> 2 | O63: 2 | P63: 2 | Q63: 2 | R63: 2 | S63: 0 | T63: 0 | U63: Return period (to calculate probability of occurrence), in years | W63: =N27 -> 2 | Y63: 2 | Z63: 2 | AA63: 2 | AB63: 2 | AC63: 0 | AD63: 0
B64: Impact on quantity produced, in % of yearly output | D64: =D28 -> 0 | E64: =E28 -> 0 | F64: =$D28 -> 0 | G64: =$E28 -> 0 | H64: =$D28 -> 0 | I64: =$E28 -> 0 | J64: =$D28 -> 0 | K64: =$E28 -> 0 | L64: Impact on quantity produced, in % of yearly output | M64: =I28 -> 0 | N64: =J28 -> 0 | O64: =$I28 -> 0 | P64: =$J28 -> 0 | Q64: =$I28 -> 0 | R64: =$J28 -> 0 | S64: =$I28 -> 0 | T64: =$J28 -> 0 | U64: Impact on quantity produced, in % of yearly output | W64: =N28 -> 0 | X64: =O28 -> 0 | Y64: =$N28 -> 0 | Z64: =$O28 -> 0 | AA64: =$N28 -> 0 | AB64: =$O28 -> 0 | AC64: =$N28 -> 0 | AD64: =$O28 -> 0
B65: Impact on quantity produced, in % of yearly output without project | F65: =$D29 -> 0 | G65: =$E29 -> 0 | H65: =$D29 -> 0 | I65: =$E29 -> 0 | J65: =$D29 -> 0 | K65: =$E29 -> 0 | L65: Impact on quantity produced, in % of yearly output without project | O65: =$I29 -> 0 | P65: =$J29 -> 0 | Q65: =$I29 -> 0 | R65: =$J29 -> 0 | S65: =$I29 -> 0 | T65: =$J29 -> 0 | U65: Impact on quantity produced, in % of yearly output without project | Y65: =$N29 -> 0 | Z65: =$O29 -> 0 | AA65: =$N29 -> 0 | AB65: =$O29 -> 0 | AC65: =$N29 -> 0 | AD65: =$O29 -> 0
B66: Repair/Reconstruction cost (CAPEX), in absolute amount/monetary unit | D66: =D30 -> 0 | E66: =D29 -> 0 | F66: =$D30 -> 0 | G66: =$D29 -> 0 | H66: =$D30 -> 0 | I66: =$D29 -> 0 | J66: =$D30 -> 0 | K66: =$D29 -> 0 | L66: Repair/Reconstruction cost (CAPEX), in absolute amount/monetary unit | M66: =I30 -> 0 | N66: =J30 -> 0 | O66: =$I30 -> 0 | P66: =$J30 -> 0 | Q66: =$I30 -> 0 | R66: =$J30 -> 0 | S66: =$I30 -> 0 | T66: =$J30 -> 0 | U66: Repair/Reconstruction cost (CAPEX), in absolute amount/monetary unit | W66: =N30 -> 0 | X66: =O30 -> 0 | Y66: =$N30 -> 0 | Z66: =$O30 -> 0 | AA66: =$N30 -> 0 | AB66: =$O30 -> 0 | AC66: =$N30 -> 0 | AD66: =$O30 -> 0
B67: Additional out-of-system impacts, in absolute amount/monetary unit | D67: =D31 -> 0 | E67: =E31 -> 0 | F67: =$D31 -> 0 | G67: =$E31 -> 0 | H67: =$D31 -> 0 | I67: =$E31 -> 0 | J67: =$D31 -> 0 | K67: =$E31 -> 0 | L67: Additional out-of-system impacts, in absolute amount/monetary unit | M67: =I31 -> 0 | N67: =J31 -> 0 | O67: =$I31 -> 0 | P67: =$J31 -> 0 | Q67: =$I31 -> 0 | R67: =$J31 -> 0 | S67: =$I31 -> 0 | T67: =$J31 -> 0 | U67: Additional out-of-system impacts, in absolute amount/monetary unit | W67: =N31 -> 0 | X67: =O31 -> 0 | Y67: =$N31 -> 0 | Z67: =$O31 -> 0 | AA67: =$N31 -> 0 | AB67: =$O31 -> 0 | AC67: =$N31 -> 0 | AD67: =$O31 -> 0
B68: Moderate intensity level | L68: Moderate intensity level | U68: Moderate intensity level
B69: Return period (to calculate probability of occurrence), in years | D69: =D33 -> 10 | F69: 10 | G69: 5 | H69: 10 | I69: 5 | J69: 0 | K69: 0 | L69: Return period (to calculate probability of occurrence), in years | M69: =I32 -> 0 | O69: 10 | P69: 5 | Q69: 10 | R69: 5 | S69: 0 | T69: 0 | U69: Return period (to calculate probability of occurrence), in years | W69: =N33 -> 10 | Y69: 10 | Z69: 5 | AA69: 10 | AB69: 5 | AC69: 0 | AD69: 0
B70: Impact on quantity produced, in % of yearly output | D70: =D34 -> 0 | E70: =E34 -> 0 | F70: =$D34 -> 0 | G70: =$E34 -> 0 | H70: =$D34 -> 0 | I70: =$E34 -> 0 | J70: =$D34 -> 0 | K70: =$E34 -> 0 | L70: Impact on quantity produced, in % of yearly output | M70: =I34 -> -0.24657534 | N70: =J34 -> -0.49315068 | O70: =$I34 -> -0.24657534 | P70: =$J34 -> -0.49315068 | Q70: =$I34 -> -0.24657534 | R70: =$J34 -> -0.49315068 | S70: =$I34 -> -0.24657534 | T70: =$J34 -> -0.49315068 | U70: Impact on quantity produced, in % of yearly output | W70: =N34 -> -0.49315068 | X70: =O34 -> -0.73972603 | Y70: =$N34 -> -0.49315068 | Z70: =$O34 -> -0.73972603 | AA70: =$N34 -> -0.49315068 | AB70: =$O34 -> -0.73972603 | AC70: =$N34 -> -0.49315068 | AD70: =$O34 -> -0.73972603
B71: Impact on quantity produced, in % of yearly output without project | F71: =$D35 -> 0 | G71: =$E35 -> 0 | H71: =$D35 -> 0 | I71: =$E35 -> 0 | J71: =$D35 -> 0 | K71: =$E35 -> 0 | L71: Impact on quantity produced, in % of yearly output without project | O71: =$I35 -> -0.49315068 | P71: =$J35 -> -0.73972603 | Q71: =$I35 -> -0.49315068 | R71: =$J35 -> -0.73972603 | S71: =$I35 -> -0.49315068 | T71: =$J35 -> -0.73972603 | U71: Impact on quantity produced, in % of yearly output without project | Y71: =$N35 -> -0.61643836 | Z71: =$O35 -> -0.8630137 | AA71: =$N35 -> -0.61643836 | AB71: =$O35 -> -0.8630137 | AC71: =$N35 -> -0.61643836 | AD71: =$O35 -> -0.8630137
B72: Repair/Reconstruction cost (CAPEX), in absolute amount/monetary unit | D72: =D36 -> 0 | E72: =E36 -> 0 | F72: =$D36 -> 0 | G72: =$E36 -> 0 | H72: =$D36 -> 0 | I72: =$E36 -> 0 | J72: =$D36 -> 0 | K72: =$E36 -> 0 | L72: Repair/Reconstruction cost (CAPEX), in absolute amount/monetary unit | M72: =I36 -> 297.44541 | N72: =J36 -> 594.89081 | O72: =$I36 -> 297.44541 | P72: =$J36 -> 594.89081 | Q72: =$I36 -> 297.44541 | R72: =$J36 -> 594.89081 | S72: =$I36 -> 297.44541 | T72: =$J36 -> 594.89081 | U72: Repair/Reconstruction cost (CAPEX), in absolute amount/monetary unit | W72: =N36 -> 297.44541 | X72: =O36 -> 594.89081 | Y72: =$N36 -> 297.44541 | Z72: =$O36 -> 594.89081 | AA72: =$N36 -> 297.44541 | AB72: =$O36 -> 594.89081 | AC72: =$N36 -> 297.44541 | AD72: =$O36 -> 594.89081
B73: Additional out-of-system impacts, in absolute amount/monetary unit | D73: =D37 -> 0 | E73: =E37 -> 0 | F73: =$D37 -> 0 | G73: =$E37 -> 0 | H73: =$D37 -> 0 | I73: =$E37 -> 0 | J73: =$D37 -> 0 | K73: =$E37 -> 0 | L73: Additional out-of-system impacts, in absolute amount/monetary unit | M73: =I37 -> 0 | N73: =J37 -> 0 | O73: =$I37 -> 0 | P73: =$J37 -> 0 | Q73: =$I37 -> 0 | R73: =$J37 -> 0 | S73: =$I37 -> 0 | T73: =$J37 -> 0 | U73: Additional out-of-system impacts, in absolute amount/monetary unit | W73: =N37 -> 0 | X73: =O37 -> 0 | Y73: =$N37 -> 0 | Z73: =$O37 -> 0 | AA73: =$N37 -> 0 | AB73: =$O37 -> 0 | AC73: =$N37 -> 0 | AD73: =$O37 -> 0
B74: Strong intensity level | L74: Strong intensity level | U74: Strong intensity level
B75: Return period (to calculate probability of occurrence), in years | D75: =D39 -> 100 | F75: 100 | G75: 50 | H75: 100 | I75: 50 | J75: 0 | K75: 0 | L75: Return period (to calculate probability of occurrence), in years | M75: =I37 -> 0 | O75: 100 | P75: 50 | Q75: 100 | R75: 50 | S75: 0 | T75: 0 | U75: Return period (to calculate probability of occurrence), in years | W75: =N39 -> 100 | Y75: 100 | Z75: 50 | AA75: 100 | AB75: 50 | AC75: 0 | AD75: 0
B76: Impact on quantity produced, in % of yearly output | D76: =D40 -> 0 | E76: =E40 -> 0 | F76: =$D40 -> 0 | G76: =$E40 -> 0 | H76: =$D40 -> 0 | I76: =$E40 -> 0 | J76: =$D40 -> 0 | K76: =$E40 -> 0 | L76: Impact on quantity produced, in % of yearly output | M76: =I40 -> -0.14794521 | N76: =J40 -> -0.19726027 | O76: =I40 -> -0.14794521 | P76: =$J40 -> -0.19726027 | Q76: =$I40 -> -0.14794521 | R76: =$J40 -> -0.19726027 | S76: =$I40 -> -0.14794521 | T76: =$J40 -> -0.19726027 | U76: Impact on quantity produced, in % of yearly output | W76: =N40 -> -0.19726027 | X76: =O40 -> -0.29589041 | Y76: =$N40 -> -0.19726027 | Z76: =$O40 -> -0.29589041 | AA76: =$N40 -> -0.19726027 | AB76: =$O40 -> -0.29589041 | AC76: =$N40 -> -0.19726027 | AD76: =$O40 -> -0.29589041
B77: Impact on quantity produced, in % of yearly output without project | F77: =$D41 -> 0 | G77: =$E41 -> 0 | H77: =$D41 -> 0 | I77: =$E41 -> 0 | J77: =$D41 -> 0 | K77: =$E41 -> 0 | L77: Impact on quantity produced, in % of yearly output without project | O77: =I41 -> -0.19726027 | P77: =$J41 -> -0.29589041 | Q77: =$I41 -> -0.19726027 | R77: =$J41 -> -0.29589041 | S77: =$I41 -> -0.19726027 | T77: =$J41 -> -0.29589041 | U77: Impact on quantity produced, in % of yearly output without project | Y77: =$N41 -> -0.22191781 | Z77: =$O41 -> -0.32054795 | AA77: =$N41 -> -0.22191781 | AB77: =$O41 -> -0.32054795 | AC77: =$N41 -> -0.22191781 | AD77: =$O41 -> -0.32054795
B78: Repair/Reconstruction cost (CAPEX), in absolute amount/monetary unit | D78: =D42 -> 0 | E78: =E42 -> 0 | F78: =$D42 -> 0 | G78: =$E42 -> 0 | H78: =$D42 -> 0 | I78: =$E42 -> 0 | J78: =$D42 -> 0 | K78: =$E42 -> 0 | L78: Repair/Reconstruction cost (CAPEX), in absolute amount/monetary unit | M78: =I42 -> 743.61352 | N78: =J42 -> 1041.0589 | O78: =I42 -> 743.61352 | P78: =$J42 -> 1041.0589 | Q78: =$I42 -> 743.61352 | R78: =$J42 -> 1041.0589 | S78: =$I42 -> 743.61352 | T78: =$J42 -> 1041.0589 | U78: Repair/Reconstruction cost (CAPEX), in absolute amount/monetary unit | W78: =N42 -> 743.61352 | X78: =O42 -> 1041.0589 | Y78: =$N42 -> 743.61352 | Z78: =$O42 -> 1041.0589 | AA78: =$N42 -> 743.61352 | AB78: =$O42 -> 1041.0589 | AC78: =$N42 -> 743.61352 | AD78: =$O42 -> 1041.0589
B79: Additional out-of-system impacts, in absolute amount/monetary unit | D79: =D43 -> 0 | E79: =E43 -> 0 | F79: =$D43 -> 0 | G79: =$E43 -> 0 | H79: =$D43 -> 0 | I79: =$E43 -> 0 | J79: =$D43 -> 0 | K79: =$E43 -> 0 | L79: Additional out-of-system impacts, in absolute amount/monetary unit | M79: =I43 -> 0 | N79: =J43 -> 0 | O79: =I43 -> 0 | P79: =$J43 -> 0 | Q79: =$I43 -> 0 | R79: =$J43 -> 0 | S79: =$I43 -> 0 | T79: =$J43 -> 0 | U79: Additional out-of-system impacts, in absolute amount/monetary unit | W79: =N43 -> 0 | X79: =O43 -> 0 | Y79: =$N43 -> 0 | Z79: =$O43 -> 0 | AA79: =$N43 -> 0 | AB79: =$O43 -> 0 | AC79: =$N43 -> 0 | AD79: =$O43 -> 0
B80: Extreme intensity level | L80: Extreme intensity level | M80: =N44 -> 0 | U80: Extreme intensity level
B81: Return period (to calculate probability of occurrence), in years | D81: =D45 -> 1000 | F81: 1000 | G81: 500 | H81: 1000 | I81: 500 | J81: 0 | K81: 0 | L81: Return period (to calculate probability of occurrence), in years | M81: =I42 -> 743.61352 | O81: 1000 | P81: 500 | Q81: 1000 | R81: 500 | S81: 0 | T81: 0 | U81: Return period (to calculate probability of occurrence), in years | W81: =N45 -> 1000 | Y81: 1000 | Z81: 500 | AA81: 1000 | AB81: 500 | AC81: 0 | AD81: 0
B82: Impact on quantity produced, in % of yearly output | D82: =D46 -> 0 | E82: =E46 -> 0 | F82: =$D46 -> 0 | G82: =$E46 -> 0 | H82: =$D46 -> 0 | I82: =$E46 -> 0 | J82: =$D46 -> 0 | K82: =$E46 -> 0 | L82: Impact on quantity produced, in % of yearly output | M82: =I46 -> -0.036986301 | N82: =J46 -> -0.051780822 | O82: =I46 -> -0.036986301 | P82: =$J46 -> -0.051780822 | Q82: =$I46 -> -0.036986301 | R82: =$J46 -> -0.051780822 | S82: =$I46 -> -0.036986301 | T82: =$J46 -> -0.051780822 | U82: Impact on quantity produced, in % of yearly output | W82: =N46 -> -0.059178082 | X82: =O46 -> -0.073972603 | Y82: =$N46 -> -0.059178082 | Z82: =$O46 -> -0.073972603 | AA82: =$N46 -> -0.059178082 | AB82: =$O46 -> -0.073972603 | AC82: =$N46 -> -0.059178082 | AD82: =$O46 -> -0.073972603
B83: Impact on quantity produced, in % of yearly output without project | F83: =$D47 -> 0 | G83: =$E47 -> 0 | H83: =$D47 -> 0 | I83: =$E47 -> 0 | J83: =$D47 -> 0 | K83: =$E47 -> 0 | L83: Impact on quantity produced, in % of yearly output without project | O83: =I47 -> -0.059178082 | P83: =$J47 -> -0.073972603 | Q83: =$I47 -> -0.059178082 | R83: =$J47 -> -0.073972603 | S83: =$I47 -> -0.059178082 | T83: =$J47 -> -0.073972603 | U83: Impact on quantity produced, in % of yearly output without project | Y83: =$N47 -> -0.062876712 | Z83: =$O47 -> -0.077671233 | AA83: =$N47 -> -0.062876712 | AB83: =$O47 -> -0.077671233 | AC83: =$N47 -> -0.062876712 | AD83: =$O47 -> -0.077671233
B84: Repair/Reconstruction cost (CAPEX), in absolute amount/monetary unit | D84: =D48 -> 0 | E84: =E48 -> 0 | F84: =$D48 -> 0 | G84: =$E48 -> 0 | H84: =$D48 -> 0 | I84: =$E48 -> 0 | J84: =$D48 -> 0 | K84: =$E48 -> 0 | L84: Repair/Reconstruction cost (CAPEX), in absolute amount/monetary unit | M84: =I48 -> 1338.5043 | N84: =J48 -> 1635.9497 | O84: =I48 -> 1338.5043 | P84: =$J48 -> 1635.9497 | Q84: =$I48 -> 1338.5043 | R84: =$J48 -> 1635.9497 | S84: =$I48 -> 1338.5043 | T84: =$J48 -> 1635.9497 | U84: Repair/Reconstruction cost (CAPEX), in absolute amount/monetary unit | W84: =N48 -> 1338.5043 | X84: =O48 -> 1635.9497 | Y84: =$N48 -> 1338.5043 | Z84: =$O48 -> 1635.9497 | AA84: =$N48 -> 1338.5043 | AB84: =$O48 -> 1635.9497 | AC84: =$N48 -> 1338.5043 | AD84: =$O48 -> 1635.9497
B85: Additional out-of-system impacts, in absolute amount/monetary unit | D85: =D49 -> 0 | E85: =E49 -> 0 | F85: =$D49 -> 0 | G85: =$E49 -> 0 | H85: =$D49 -> 0 | I85: =$E49 -> 0 | J85: =$D49 -> 0 | K85: =$E49 -> 0 | L85: Additional out-of-system impacts, in absolute amount/monetary unit | M85: =I49 -> 0 | N85: =J49 -> 0 | O85: =I49 -> 0 | P85: =$J49 -> 0 | Q85: =$I49 -> 0 | R85: =$J49 -> 0 | S85: =$I49 -> 0 | T85: =$J49 -> 0 | U85: Additional out-of-system impacts, in absolute amount/monetary unit | W85: =N49 -> 0 | X85: =O49 -> 0 | Y85: =$N49 -> 0 | Z85: =$O49 -> 0 | AA85: =$N49 -> 0 | AB85: =$O49 -> 0 | AC85: =$N49 -> 0 | AD85: =$O49 -> 0

Sheet Extrapolation disasters
B1: SIMULATION
B3: Calculation: (2bi) | I3: Calculation (2b ii) | P3: Calculation: (2biii)
B4: Calculates one weighted value per year based on selected "level of climate impact" in "Input_Parameters" | I4: Calculates one weighted value per year based on selected "level of climate impact" in "Input_Parameters" | P4: Calculates one weighted value per year based on selected "level of climate impact" in "Input_Parameters"
B5: Input: All from "Input_Parameters" | I5: Input: All from "Input_Parameters" | P5: Input: All from "Input_Parameters"
B7: Natural disasters | D7: =Parameters_Results!D10 -> 2018 | E7: 2030 | F7: 2050 | G7: 2100 | I7: Natural Disasters | K7: 2020 | L7: 2030 | M7: 2050 | N7: 2100 | P7: Natural disasters | R7: 2020 | S7: 2030 | T7: 2050 | U7: 2100
B8: Once every 2 years | I8: Once every 2 years | P8: Once every 2 years
B9: Return period | D9: ='Climate impacts'!D27 -> 2 | E9: =Parameters_Results!$D$20*'Climate impacts'!G63+(1-Parameters_Results!$D$24)*'Climate impacts'!F63 -> 2 | F9: =Parameters_Results!$D$20*'Climate impacts'!I63+(1-Parameters_Results!$D$20)*'Climate impacts'!H63 -> 2 | G9: =Parameters_Results!$D$20*'Climate impacts'!K63+(1-Parameters_Results!$D$20)*'Climate impacts'!J63 -> 0 | I9: Return period | K9: ='Climate impacts'!I27 -> 2 | L9: =Parameters_Results!$D$22*'Climate impacts'!P63+(1-Parameters_Results!$D$22)*'Climate impacts'!O63 -> 2 | M9: =Parameters_Results!$D$22*'Climate impacts'!R63+(1-Parameters_Results!$D$22)*'Climate impacts'!Q63 -> 2 | N9: =Parameters_Results!$D$22*'Climate impacts'!T63+(1-Parameters_Results!$D$22)*'Climate impacts'!S63 -> 0 | P9: Return period | R9: ='Climate impacts'!N27 -> 2 | S9: =Parameters_Results!$D$24*'Climate impacts'!Z63+(1-Parameters_Results!$D$24)*'Climate impacts'!Y63 -> 2 | T9: =Parameters_Results!$D$24*'Climate impacts'!AB63+(1-Parameters_Results!$D$24)*'Climate impacts'!AA63 -> 2 | U9: =Parameters_Results!$D$24*'Climate impacts'!AD63+(1-Parameters_Results!$D$24)*'Climate impacts'!AC63 -> 0
B10: Impact on quantity produced (% of yearly output) | D10: =Parameters_Results!$D$19*'Climate impacts'!E28+(1-Parameters_Results!$D$19)*'Climate impacts'!D28 -> 0 | E10: =Parameters_Results!$D$19*'Climate impacts'!G64+(1-Parameters_Results!$D$19)*'Climate impacts'!F64 -> 0 | F10: =Parameters_Results!$D$19*'Climate impacts'!I64+(1-Parameters_Results!$D$19)*'Climate impacts'!H64 -> 0 | G10: =Parameters_Results!$D$19*'Climate impacts'!K64+(1-Parameters_Results!$D$19)*'Climate impacts'!J64 -> 0 | I10: Impact on quantity produced (% of yearly output) | K10: =Parameters_Results!$D$21*'Climate impacts'!J28+(1-Parameters_Results!$D$21)*'Climate impacts'!I28 -> 0 | L10: =Parameters_Results!$D$21*'Climate impacts'!P64+(1-Parameters_Results!$D$21)*'Climate impacts'!O64 -> 0 | M10: =Parameters_Results!$D$21*'Climate impacts'!R64+(1-Parameters_Results!$D$21)*'Climate impacts'!Q64 -> 0 | N10: =Parameters_Results!$D$21*'Climate impacts'!T64+(1-Parameters_Results!$D$21)*'Climate impacts'!S64 -> 0 | P10: Impact on quantity produced (% of yearly output) | R10: =Parameters_Results!$D$23*'Climate impacts'!O28+(1-Parameters_Results!$D$23)*'Climate impacts'!N28 -> 0 | S10: =Parameters_Results!$D$23*'Climate impacts'!Z64+(1-Parameters_Results!$D$23)*'Climate impacts'!Y64 -> 0 | T10: =Parameters_Results!$D$23*'Climate impacts'!AA64+(1-Parameters_Results!$D$23)*'Climate impacts'!Z64 -> 0 | U10: =Parameters_Results!$D$23*'Climate impacts'!AD64+(1-Parameters_Results!$D$23)*'Climate impacts'!AC64 -> 0
B11: Impact on quantity produced (% of yearly output) without project | D11: =Parameters_Results!$D$19*'Climate impacts'!E29+(1-Parameters_Results!$D$19)*'Climate impacts'!D29 -> 0 | E11: =Parameters_Results!$D$19*'Climate impacts'!G65+(1-Parameters_Results!$D$19)*'Climate impacts'!F65 -> 0 | F11: =Parameters_Results!$D$19*'Climate impacts'!I65+(1-Parameters_Results!$D$19)*'Climate impacts'!H65 -> 0 | G11: =Parameters_Results!$D$19*'Climate impacts'!K65+(1-Parameters_Results!$D$19)*'Climate impacts'!J65 -> 0 | I11: Impact on quantity produced (% of yearly output) without project | K11: =Parameters_Results!$D$21*'Climate impacts'!J29+(1-Parameters_Results!$D$21)*'Climate impacts'!I29 -> 0 | L11: =Parameters_Results!$D$21*'Climate impacts'!P65+(1-Parameters_Results!$D$21)*'Climate impacts'!O65 -> 0 | M11: =Parameters_Results!$D$21*'Climate impacts'!R65+(1-Parameters_Results!$D$21)*'Climate impacts'!Q65 -> 0 | N11: =Parameters_Results!$D$21*'Climate impacts'!T65+(1-Parameters_Results!$D$21)*'Climate impacts'!S65 -> 0 | P11: Impact on quantity produced (% of yearly output) without project | R11: =Parameters_Results!$D$23*'Climate impacts'!O29+(1-Parameters_Results!$D$23)*'Climate impacts'!N29 -> 0 | S11: =Parameters_Results!$D$23*'Climate impacts'!Z66+(1-Parameters_Results!$D$23)*'Climate impacts'!Y66 -> 0 | T11: =Parameters_Results!$D$23*'Climate impacts'!AA66+(1-Parameters_Results!$D$23)*'Climate impacts'!Z66 -> 0 | U11: =Parameters_Results!$D$23*'Climate impacts'!AD66+(1-Parameters_Results!$D$23)*'Climate impacts'!AC66 -> 0
B12: Repair/Reconstruction cost (CAPEX) | D12: =Parameters_Results!$D$19*'Climate impacts'!D29+(1-Parameters_Results!$D$19)*'Climate impacts'!D30 -> 0 | E12: =Parameters_Results!$D$19*'Climate impacts'!G66+(1-Parameters_Results!$D$19)*'Climate impacts'!F66 -> 0 | F12: =Parameters_Results!$D$19*'Climate impacts'!I66+(1-Parameters_Results!$D$19)*'Climate impacts'!H66 -> 0 | G12: =Parameters_Results!$D$19*'Climate impacts'!K66+(1-Parameters_Results!$D$19)*'Climate impacts'!J66 -> 0 | I12: Repair/Reconstruction cost (CAPEX) | K12: =Parameters_Results!$D$21*'Climate impacts'!J30+(1-Parameters_Results!$D$21)*'Climate impacts'!I30 -> 0 | L12: =Parameters_Results!$D$21*'Climate impacts'!P66+(1-Parameters_Results!$D$21)*'Climate impacts'!O66 -> 0 | M12: =Parameters_Results!$D$21*'Climate impacts'!R66+(1-Parameters_Results!$D$21)*'Climate impacts'!Q66 -> 0 | N12: =Parameters_Results!$D$21*'Climate impacts'!T66+(1-Parameters_Results!$D$21)*'Climate impacts'!S66 -> 0 | P12: Repair/Reconstruction cost (CAPEX) | R12: =Parameters_Results!$D$23*'Climate impacts'!O30+(1-Parameters_Results!$D$23)*'Climate impacts'!N30 -> 0 | S12: =Parameters_Results!$D$23*'Climate impacts'!Z66+(1-Parameters_Results!$D$23)*'Climate impacts'!Y66 -> 0 | T12: =Parameters_Results!$D$23*'Climate impacts'!AA66+(1-Parameters_Results!$D$23)*'Climate impacts'!Z66 -> 0 | U12: =Parameters_Results!$D$23*'Climate impacts'!AD66+(1-Parameters_Results!$D$23)*'Climate impacts'!AC66 -> 0
B13: Additional out-of-system impacts | D13: =Parameters_Results!$D$19*'Climate impacts'!E31+(1-Parameters_Results!$D$19)*'Climate impacts'!D31 -> 0 | E13: =Parameters_Results!$D$19*'Climate impacts'!G67+(1-Parameters_Results!$D$19)*'Climate impacts'!F67 -> 0 | F13: =Parameters_Results!$D$19*'Climate impacts'!I67+(1-Parameters_Results!$D$19)*'Climate impacts'!H67 -> 0 | G13: =Parameters_Results!$D$19*'Climate impacts'!K67+(1-Parameters_Results!$D$19)*'Climate impacts'!J67 -> 0 | I13: Additional out-of-system impacts | K13: =Parameters_Results!$D$21*'Climate impacts'!J31+(1-Parameters_Results!$D$21)*'Climate impacts'!I31 -> 0 | L13: =Parameters_Results!$D$21*'Climate impacts'!P67+(1-Parameters_Results!$D$21)*'Climate impacts'!O67 -> 0 | M13: =Parameters_Results!$D$21*'Climate impacts'!R67+(1-Parameters_Results!$D$21)*'Climate impacts'!Q67 -> 0 | N13: =Parameters_Results!$D$21*'Climate impacts'!T67+(1-Parameters_Results!$D$21)*'Climate impacts'!S67 -> 0 | P13: Additional out-of-system impacts | R13: =Parameters_Results!$D$23*'Climate impacts'!O31+(1-Parameters_Results!$D$23)*'Climate impacts'!N31 -> 0 | S13: =Parameters_Results!$D$23*'Climate impacts'!Z67+(1-Parameters_Results!$D$23)*'Climate impacts'!Y67 -> 0 | T13: =Parameters_Results!$D$23*'Climate impacts'!AA67+(1-Parameters_Results!$D$23)*'Climate impacts'!Z67 -> 0 | U13: =Parameters_Results!$D$23*'Climate impacts'!AD67+(1-Parameters_Results!$D$23)*'Climate impacts'!AC67 -> 0
B14: Once every 10 years | I14: Once every 10 years | P14: Once every 10 years
B15: Return period | D15: ='Climate impacts'!D33:E33 -> 10 | E15: =Parameters_Results!$D$20*'Climate impacts'!G69+(1-Parameters_Results!$D$20)*'Climate impacts'!F69 -> 5 | F15: =Parameters_Results!$D$20*'Climate impacts'!I69+(1-Parameters_Results!$D$20)*'Climate impacts'!H69 -> 5 | G15: =Parameters_Results!$D$20*'Climate impacts'!K69+(1-Parameters_Results!$D$20)*'Climate impacts'!J69 -> 0 | I15: Return period | K15: ='Climate impacts'!I33 -> 10 | L15: =Parameters_Results!$D$22*'Climate impacts'!P69+(1-Parameters_Results!$D$22)*'Climate impacts'!O69 -> 5 | M15: =Parameters_Results!$D$22*'Climate impacts'!R69+(1-Parameters_Results!$D$22)*'Climate impacts'!Q69 -> 5 | N15: =Parameters_Results!$D$22*'Climate impacts'!T69+(1-Parameters_Results!$D$22)*'Climate impacts'!S69 -> 0 | P15: Return period | R15: ='Climate impacts'!N33 -> 10 | S15: =Parameters_Results!$D$24*'Climate impacts'!Z69+(1-Parameters_Results!$D$24)*'Climate impacts'!Y69 -> 5 | T15: =Parameters_Results!$D$24*'Climate impacts'!AB69+(1-Parameters_Results!$D$24)*'Climate impacts'!AA69 -> 5 | U15: =Parameters_Results!$D$24*'Climate impacts'!AD69+(1-Parameters_Results!$D$24)*'Climate impacts'!AC69 -> 0
B16: Impact on quantity produced (% of yearly output) with project | D16: =Parameters_Results!$D$19*'Climate impacts'!E34+(1-Parameters_Results!$D$19)*'Climate impacts'!D34 -> 0 | E16: =Parameters_Results!$D$19*'Climate impacts'!G70+(1-Parameters_Results!$D$19)*'Climate impacts'!F70 -> 0 | F16: =Parameters_Results!$D$19*'Climate impacts'!I70+(1-Parameters_Results!$D$19)*'Climate impacts'!H70 -> 0 | G16: =Parameters_Results!$D$19*'Climate impacts'!K70+(1-Parameters_Results!$D$19)*'Climate impacts'!J70 -> 0 | I16: Impact on quantity produced (% of yearly output) | K16: =Parameters_Results!$D$21*'Climate impacts'!J34+(1-Parameters_Results!$D$21)*'Climate impacts'!I34 -> -0.49315068 | L16: =Parameters_Results!$D$21*'Climate impacts'!P70+(1-Parameters_Results!$D$21)*'Climate impacts'!O70 -> -0.49315068 | M16: =Parameters_Results!$D$21*'Climate impacts'!R70+(1-Parameters_Results!$D$21)*'Climate impacts'!Q70 -> -0.49315068 | N16: =Parameters_Results!$D$21*'Climate impacts'!T70+(1-Parameters_Results!$D$21)*'Climate impacts'!S70 -> -0.49315068 | P16: Impact on quantity produced (% of yearly output) | R16: =Parameters_Results!$D$23*'Climate impacts'!O34+(1-Parameters_Results!$D$23)*'Climate impacts'!N34 -> -0.73972603 | S16: =Parameters_Results!$D$23*'Climate impacts'!Z70+(1-Parameters_Results!$D$23)*'Climate impacts'!Y70 -> -0.73972603 | T16: =Parameters_Results!$D$23*'Climate impacts'!AB70+(1-Parameters_Results!$D$23)*'Climate impacts'!AA70 -> -0.73972603 | U16: =Parameters_Results!$D$23*'Climate impacts'!AD70+(1-Parameters_Results!$D$23)*'Climate impacts'!AC70 -> -0.73972603
B17: Impact on quantity produced (% of yearly output) without project | D17: =Parameters_Results!$D$19*'Climate impacts'!E35+(1-Parameters_Results!$D$19)*'Climate impacts'!D35 -> 0 | E17: =Parameters_Results!$D$19*'Climate impacts'!F35+(1-Parameters_Results!$D$19)*'Climate impacts'!E35 -> 0 | F17: =Parameters_Results!$D$19*'Climate impacts'!I71+(1-Parameters_Results!$D$19)*'Climate impacts'!H71 -> 0 | G17: =Parameters_Results!$D$19*'Climate impacts'!K71+(1-Parameters_Results!$D$19)*'Climate impacts'!J71 -> 0 | I17: Impact on quantity produced (% of yearly output) without project | K17: =Parameters_Results!$D$21*'Climate impacts'!J35+(1-Parameters_Results!$D$21)*'Climate impacts'!I35 -> -0.73972603 | L17: =Parameters_Results!$D$21*'Climate impacts'!P71+(1-Parameters_Results!$D$21)*'Climate impacts'!O71 -> -0.73972603 | M17: =Parameters_Results!$D$21*'Climate impacts'!R71+(1-Parameters_Results!$D$21)*'Climate impacts'!Q71 -> -0.73972603 | N17: =Parameters_Results!$D$21*'Climate impacts'!T71+(1-Parameters_Results!$D$21)*'Climate impacts'!S71 -> -0.73972603 | P17: Impact on quantity produced (% of yearly output) without project | R17: =Parameters_Results!$D$23*'Climate impacts'!O35+(1-Parameters_Results!$D$23)*'Climate impacts'!N35 -> -0.8630137 | S17: =Parameters_Results!$D$23*'Climate impacts'!Z72+(1-Parameters_Results!$D$23)*'Climate impacts'!Y72 -> 594.89081 | T17: =Parameters_Results!$D$23*'Climate impacts'!AB72+(1-Parameters_Results!$D$23)*'Climate impacts'!AA72 -> 594.89081 | U17: =Parameters_Results!$D$23*'Climate impacts'!AD72+(1-Parameters_Results!$D$23)*'Climate impacts'!AC72 -> 594.89081
B18: Repair/Reconstruction cost (CAPEX) | D18: =Parameters_Results!$D$19*'Climate impacts'!E36+(1-Parameters_Results!$D$19)*'Climate impacts'!D36 -> 0 | E18: =Parameters_Results!$D$19*'Climate impacts'!G72+(1-Parameters_Results!$D$19)*'Climate impacts'!F72 -> 0 | F18: =Parameters_Results!$D$19*'Climate impacts'!I72+(1-Parameters_Results!$D$19)*'Climate impacts'!H72 -> 0 | G18: =Parameters_Results!$D$19*'Climate impacts'!K72+(1-Parameters_Results!$D$19)*'Climate impacts'!J72 -> 0 | I18: Repair/Reconstruction cost (CAPEX) | K18: =Parameters_Results!$D$21*'Climate impacts'!J36+(1-Parameters_Results!$D$21)*'Climate impacts'!I36 -> 594.89081 | L18: =Parameters_Results!$D$21*'Climate impacts'!P72+(1-Parameters_Results!$D$21)*'Climate impacts'!O72 -> 594.89081 | M18: =Parameters_Results!$D$21*'Climate impacts'!R72+(1-Parameters_Results!$D$21)*'Climate impacts'!Q72 -> 594.89081 | N18: =Parameters_Results!$D$21*'Climate impacts'!T72+(1-Parameters_Results!$D$21)*'Climate impacts'!S72 -> 594.89081 | P18: Repair/Reconstruction cost (CAPEX) | R18: =Parameters_Results!$D$23*'Climate impacts'!O36+(1-Parameters_Results!$D$23)*'Climate impacts'!N36 -> 594.89081 | S18: =Parameters_Results!$D$23*'Climate impacts'!Z72+(1-Parameters_Results!$D$23)*'Climate impacts'!Y72 -> 594.89081 | T18: =Parameters_Results!$D$23*'Climate impacts'!AB72+(1-Parameters_Results!$D$23)*'Climate impacts'!AA72 -> 594.89081 | U18: =Parameters_Results!$D$23*'Climate impacts'!AD72+(1-Parameters_Results!$D$23)*'Climate impacts'!AC72 -> 594.89081
B19: Additional out-of-system impacts | D19: =Parameters_Results!$D$19*'Climate impacts'!E37+(1-Parameters_Results!$D$19)*'Climate impacts'!D37 -> 0 | E19: =Parameters_Results!$D$19*'Climate impacts'!G73+(1-Parameters_Results!$D$19)*'Climate impacts'!F73 -> 0 | F19: =Parameters_Results!$D$19*'Climate impacts'!I73+(1-Parameters_Results!$D$19)*'Climate impacts'!H73 -> 0 | G19: =Parameters_Results!$D$19*'Climate impacts'!K73+(1-Parameters_Results!$D$19)*'Climate impacts'!J73 -> 0 | I19: Additional out-of-system impacts | K19: =Parameters_Results!$D$21*'Climate impacts'!J37+(1-Parameters_Results!$D$21)*'Climate impacts'!I37 -> 0 | L19: =Parameters_Results!$D$21*'Climate impacts'!P73+(1-Parameters_Results!$D$21)*'Climate impacts'!O73 -> 0 | M19: =Parameters_Results!$D$21*'Climate impacts'!R73+(1-Parameters_Results!$D$21)*'Climate impacts'!Q73 -> 0 | N19: =Parameters_Results!$D$21*'Climate impacts'!T73+(1-Parameters_Results!$D$21)*'Climate impacts'!S73 -> 0 | P19: Additional out-of-system impacts | R19: =Parameters_Results!$D$23*'Climate impacts'!O37+(1-Parameters_Results!$D$23)*'Climate impacts'!N37 -> 0 | S19: =Parameters_Results!$D$23*'Climate impacts'!Z73+(1-Parameters_Results!$D$23)*'Climate impacts'!Y73 -> 0 | T19: =Parameters_Results!$D$23*'Climate impacts'!AB73+(1-Parameters_Results!$D$23)*'Climate impacts'!AA73 -> 0 | U19: =Parameters_Results!$D$23*'Climate impacts'!AD73+(1-Parameters_Results!$D$23)*'Climate impacts'!AC73 -> 0
B20: Once every 100 years | I20: Once every 100 years | P20: Once every 100 years
B21: Return period | D21: ='Climate impacts'!D39:E39 -> 100 | E21: =Parameters_Results!$D$20*'Climate impacts'!G75+(1-Parameters_Results!$D$20)*'Climate impacts'!F75 -> 50 | F21: =Parameters_Results!$D$20*'Climate impacts'!I75+(1-Parameters_Results!$D$20)*'Climate impacts'!H75 -> 50 | G21: =Parameters_Results!$D$20*'Climate impacts'!K75+(1-Parameters_Results!$D$20)*'Climate impacts'!J75 -> 0 | I21: Return period | K21: ='Climate impacts'!I39 -> 100 | L21: =Parameters_Results!$D$22*'Climate impacts'!P75+(1-Parameters_Results!$D$22)*'Climate impacts'!O75 -> 50 | M21: =Parameters_Results!$D$22*'Climate impacts'!R75+(1-Parameters_Results!$D$22)*'Climate impacts'!Q75 -> 50 | N21: =Parameters_Results!$D$270*'Climate impacts'!T75+(1-Parameters_Results!$D$22)*'Climate impacts'!S75 -> 0 | P21: Return period | R21: ='Climate impacts'!N39 -> 100 | S21: =Parameters_Results!$D$24*'Climate impacts'!Z75+(1-Parameters_Results!$D$24)*'Climate impacts'!Y75 -> 50 | T21: =Parameters_Results!$D$24*'Climate impacts'!AB75+(1-Parameters_Results!$D$24)*'Climate impacts'!AA75 -> 50 | U21: =Parameters_Results!$D$24*'Climate impacts'!AD75+(1-Parameters_Results!$D$24)*'Climate impacts'!AC75 -> 0
B22: Impact on quantity produced (% of yearly output) | D22: =Parameters_Results!$D$19*'Climate impacts'!E40+(1-Parameters_Results!$D$19)*'Climate impacts'!D40 -> 0 | E22: =Parameters_Results!$D$19*'Climate impacts'!G76+(1-Parameters_Results!$D$19)*'Climate impacts'!F76 -> 0 | F22: =Parameters_Results!$D$19*'Climate impacts'!I76+(1-Parameters_Results!$D$19)*'Climate impacts'!H76 -> 0 | G22: =Parameters_Results!$D$19*'Climate impacts'!K76+(1-Parameters_Results!$D$19)*'Climate impacts'!J76 -> 0 | I22: Impact on quantity produced (% of yearly output) | K22: =Parameters_Results!$D$21*'Climate impacts'!J40+(1-Parameters_Results!$D$21)*'Climate impacts'!I40 -> -0.19726027 | L22: =Parameters_Results!$D$21*'Climate impacts'!P76+(1-Parameters_Results!$D$21)*'Climate impacts'!O76 -> -0.19726027 | M22: =Parameters_Results!$D$21*'Climate impacts'!R76+(1-Parameters_Results!$D$21)*'Climate impacts'!Q76 -> -0.19726027 | N22: =Parameters_Results!$D$21*'Climate impacts'!T76+(1-Parameters_Results!$D$21)*'Climate impacts'!S76 -> -0.19726027 | P22: Impact on quantity produced (% of yearly output) | R22: =Parameters_Results!$D$23*'Climate impacts'!O40+(1-Parameters_Results!$D$23)*'Climate impacts'!N40 -> -0.29589041 | S22: =Parameters_Results!$D$23*'Climate impacts'!Z76+(1-Parameters_Results!$D$23)*'Climate impacts'!Y76 -> -0.29589041 | T22: =Parameters_Results!$D$23*'Climate impacts'!AB76+(1-Parameters_Results!$D$23)*'Climate impacts'!AA76 -> -0.29589041 | U22: =Parameters_Results!$D$23*'Climate impacts'!AD76+(1-Parameters_Results!$D$23)*'Climate impacts'!AC76 -> -0.29589041
B23: Impact on quantity produced (% of yearly output) without project | D23: =Parameters_Results!$D$19*'Climate impacts'!E41+(1-Parameters_Results!$D$19)*'Climate impacts'!D41 -> 0 | E23: =Parameters_Results!$D$19*'Climate impacts'!G77+(1-Parameters_Results!$D$19)*'Climate impacts'!F77 -> 0 | F23: =Parameters_Results!$D$19*'Climate impacts'!I77+(1-Parameters_Results!$D$19)*'Climate impacts'!H77 -> 0 | G23: =Parameters_Results!$D$19*'Climate impacts'!K77+(1-Parameters_Results!$D$19)*'Climate impacts'!J77 -> 0 | I23: Impact on quantity produced (% of yearly output) without project | K23: =Parameters_Results!$D$21*'Climate impacts'!J41+(1-Parameters_Results!$D$21)*'Climate impacts'!I41 -> -0.29589041 | L23: =Parameters_Results!$D$21*'Climate impacts'!P77+(1-Parameters_Results!$D$21)*'Climate impacts'!O77 -> -0.29589041 | M23: =Parameters_Results!$D$21*'Climate impacts'!R77+(1-Parameters_Results!$D$21)*'Climate impacts'!Q77 -> -0.29589041 | N23: =Parameters_Results!$D$21*'Climate impacts'!T77+(1-Parameters_Results!$D$21)*'Climate impacts'!S77 -> -0.29589041 | P23: Impact on quantity produced (% of yearly output) without project | R23: =Parameters_Results!$D$23*'Climate impacts'!O41+(1-Parameters_Results!$D$23)*'Climate impacts'!N41 -> -0.32054795 | S23: =Parameters_Results!$D$23*'Climate impacts'!Z78+(1-Parameters_Results!$D$23)*'Climate impacts'!Y78 -> 1041.0589 | T23: =Parameters_Results!$D$23*'Climate impacts'!AB78+(1-Parameters_Results!$D$23)*'Climate impacts'!AA78 -> 1041.0589 | U23: =Parameters_Results!$D$23*'Climate impacts'!AD78+(1-Parameters_Results!$D$23)*'Climate impacts'!AC78 -> 1041.0589
B24: Repair/Reconstruction cost (CAPEX) | D24: =Parameters_Results!$D$19*'Climate impacts'!E42+(1-Parameters_Results!$D$19)*'Climate impacts'!D42 -> 0 | E24: =Parameters_Results!$D$19*'Climate impacts'!G78+(1-Parameters_Results!$D$19)*'Climate impacts'!F78 -> 0 | F24: =Parameters_Results!$D$19*'Climate impacts'!I78+(1-Parameters_Results!$D$19)*'Climate impacts'!H78 -> 0 | G24: =Parameters_Results!$D$19*'Climate impacts'!K78+(1-Parameters_Results!$D$19)*'Climate impacts'!J78 -> 0 | I24: Repair/Reconstruction cost (CAPEX) | K24: =Parameters_Results!$D$21*'Climate impacts'!J42+(1-Parameters_Results!$D$21)*'Climate impacts'!I42 -> 1041.0589 | L24: =Parameters_Results!$D$21*'Climate impacts'!P78+(1-Parameters_Results!$D$21)*'Climate impacts'!O78 -> 1041.0589 | M24: =Parameters_Results!$D$21*'Climate impacts'!R78+(1-Parameters_Results!$D$21)*'Climate impacts'!Q78 -> 1041.0589 | N24: =Parameters_Results!$D$21*'Climate impacts'!T78+(1-Parameters_Results!$D$21)*'Climate impacts'!S78 -> 1041.0589 | P24: Repair/Reconstruction cost (CAPEX) | R24: =Parameters_Results!$D$23*'Climate impacts'!O42+(1-Parameters_Results!$D$23)*'Climate impacts'!N42 -> 1041.0589 | S24: =Parameters_Results!$D$23*'Climate impacts'!Z78+(1-Parameters_Results!$D$23)*'Climate impacts'!Y78 -> 1041.0589 | T24: =Parameters_Results!$D$23*'Climate impacts'!AB78+(1-Parameters_Results!$D$23)*'Climate impacts'!AA78 -> 1041.0589 | U24: =Parameters_Results!$D$23*'Climate impacts'!AD78+(1-Parameters_Results!$D$23)*'Climate impacts'!AC78 -> 1041.0589
B25: Additional out-of-system impacts | D25: =Parameters_Results!$D$19*'Climate impacts'!E43+(1-Parameters_Results!$D$19)*'Climate impacts'!D43 -> 0 | E25: =Parameters_Results!$D$19*'Climate impacts'!G79+(1-Parameters_Results!$D$19)*'Climate impacts'!F79 -> 0 | F25: =Parameters_Results!$D$19*'Climate impacts'!I79+(1-Parameters_Results!$D$19)*'Climate impacts'!H79 -> 0 | G25: =Parameters_Results!$D$19*'Climate impacts'!K79+(1-Parameters_Results!$D$19)*'Climate impacts'!J79 -> 0 | I25: Additional out-of-system impacts | K25: =Parameters_Results!$D$21*'Climate impacts'!J43+(1-Parameters_Results!$D$21)*'Climate impacts'!I43 -> 0 | L25: =Parameters_Results!$D$21*'Climate impacts'!P79+(1-Parameters_Results!$D$21)*'Climate impacts'!O79 -> 0 | M25: =Parameters_Results!$D$21*'Climate impacts'!R79+(1-Parameters_Results!$D$21)*'Climate impacts'!Q79 -> 0 | N25: =Parameters_Results!$D$21*'Climate impacts'!T79+(1-Parameters_Results!$D$21)*'Climate impacts'!S79 -> 0 | P25: Additional out-of-system impacts | R25: =Parameters_Results!$D$23*'Climate impacts'!O43+(1-Parameters_Results!$D$23)*'Climate impacts'!N43 -> 0 | S25: =Parameters_Results!$D$23*'Climate impacts'!Z79+(1-Parameters_Results!$D$23)*'Climate impacts'!Y79 -> 0 | T25: =Parameters_Results!$D$23*'Climate impacts'!AB79+(1-Parameters_Results!$D$23)*'Climate impacts'!AA79 -> 0 | U25: =Parameters_Results!$D$23*'Climate impacts'!AD79+(1-Parameters_Results!$D$23)*'Climate impacts'!AC79 -> 0
B26: Once every 1000 years | I26: Once every 1000 years | P26: Once every 1000 years
B27: Return period | D27: ='Climate impacts'!D45:E45 -> 1000 | E27: =Parameters_Results!$D$20*'Climate impacts'!G81+(1-Parameters_Results!$D$20)*'Climate impacts'!F81 -> 500 | F27: =Parameters_Results!$D$20*'Climate impacts'!I81+(1-Parameters_Results!$D$20)*'Climate impacts'!H81 -> 500 | G27: =Parameters_Results!$D$20*'Climate impacts'!K81+(1-Parameters_Results!$D$20)*'Climate impacts'!J81 -> 0 | I27: Return period | K27: ='Climate impacts'!I45 -> 1000 | L27: =Parameters_Results!$D$22*'Climate impacts'!P81+(1-Parameters_Results!$D$22)*'Climate impacts'!O81 -> 500 | M27: =Parameters_Results!$D$22*'Climate impacts'!R81+(1-Parameters_Results!$D$22)*'Climate impacts'!Q81 -> 500 | N27: =Parameters_Results!$D$22*'Climate impacts'!T81+(1-Parameters_Results!$D$22)*'Climate impacts'!S81 -> 0 | P27: Return period | R27: ='Climate impacts'!N45 -> 1000 | S27: =Parameters_Results!$D$24*'Climate impacts'!Z81+(1-Parameters_Results!$D$24)*'Climate impacts'!Y81 -> 500 | T27: =Parameters_Results!$D$24*'Climate impacts'!AB81+(1-Parameters_Results!$D$24)*'Climate impacts'!AA81 -> 500 | U27: =Parameters_Results!$D$24*'Climate impacts'!AD81+(1-Parameters_Results!$D$24)*'Climate impacts'!AC81 -> 0
B28: Impact on quantity produced (% of yearly output) | D28: =Parameters_Results!$D$19*'Climate impacts'!E46+(1-Parameters_Results!$D$19)*'Climate impacts'!D46 -> 0 | E28: =Parameters_Results!$D$19*'Climate impacts'!G82+(1-Parameters_Results!$D$19)*'Climate impacts'!F82 -> 0 | F28: =Parameters_Results!$D$19*'Climate impacts'!I82+(1-Parameters_Results!$D$19)*'Climate impacts'!H82 -> 0 | G28: =Parameters_Results!$D$19*'Climate impacts'!K82+(1-Parameters_Results!$D$19)*'Climate impacts'!J82 -> 0 | I28: Impact on quantity produced (% of yearly output) | K28: =Parameters_Results!$D$21*'Climate impacts'!J46+(1-Parameters_Results!$D$21)*'Climate impacts'!I46 -> -0.051780822 | L28: =Parameters_Results!$D$21*'Climate impacts'!P82+(1-Parameters_Results!$D$21)*'Climate impacts'!O82 -> -0.051780822 | M28: =Parameters_Results!$D$21*'Climate impacts'!R82+(1-Parameters_Results!$D$21)*'Climate impacts'!Q82 -> -0.051780822 | N28: =Parameters_Results!$D$21*'Climate impacts'!T82+(1-Parameters_Results!$D$21)*'Climate impacts'!S82 -> -0.051780822 | P28: Impact on quantity produced (% of yearly output) | R28: =Parameters_Results!$D$23*'Climate impacts'!O46+(1-Parameters_Results!$D$23)*'Climate impacts'!N46 -> -0.073972603 | S28: =Parameters_Results!$D$23*'Climate impacts'!Z82+(1-Parameters_Results!$D$23)*'Climate impacts'!Y82 -> -0.073972603 | T28: =Parameters_Results!$D$23*'Climate impacts'!AB82+(1-Parameters_Results!$D$23)*'Climate impacts'!AA82 -> -0.073972603 | U28: =Parameters_Results!$D$23*'Climate impacts'!AD82+(1-Parameters_Results!$D$23)*'Climate impacts'!AC82 -> -0.073972603
B29: Impact on quantity produced (% of yearly output) without project | D29: =Parameters_Results!$D$19*'Climate impacts'!E47+(1-Parameters_Results!$D$19)*'Climate impacts'!D47 -> 0 | E29: =Parameters_Results!$D$19*'Climate impacts'!G83+(1-Parameters_Results!$D$19)*'Climate impacts'!F83 -> 0 | F29: =Parameters_Results!$D$19*'Climate impacts'!I83+(1-Parameters_Results!$D$19)*'Climate impacts'!H83 -> 0 | G29: =Parameters_Results!$D$19*'Climate impacts'!K83+(1-Parameters_Results!$D$19)*'Climate impacts'!J83 -> 0 | I29: Impact on quantity produced (% of yearly output) without project | K29: =Parameters_Results!$D$21*'Climate impacts'!J47+(1-Parameters_Results!$D$21)*'Climate impacts'!I47 -> -0.073972603 | L29: =Parameters_Results!$D$21*'Climate impacts'!P83+(1-Parameters_Results!$D$21)*'Climate impacts'!O83 -> -0.073972603 | M29: =Parameters_Results!$D$21*'Climate impacts'!R83+(1-Parameters_Results!$D$21)*'Climate impacts'!Q83 -> -0.073972603 | N29: =Parameters_Results!$D$21*'Climate impacts'!T83+(1-Parameters_Results!$D$21)*'Climate impacts'!S83 -> -0.073972603 | P29: Impact on quantity produced (% of yearly output) without project | R29: =Parameters_Results!$D$23*'Climate impacts'!O47+(1-Parameters_Results!$D$23)*'Climate impacts'!N47 -> -0.077671233 | S29: =Parameters_Results!$D$23*'Climate impacts'!Z84+(1-Parameters_Results!$D$23)*'Climate impacts'!Y84 -> 1635.9497 | T29: =Parameters_Results!$D$23*'Climate impacts'!AB84+(1-Parameters_Results!$D$23)*'Climate impacts'!AA84 -> 1635.9497 | U29: =Parameters_Results!$D$23*'Climate impacts'!AD84+(1-Parameters_Results!$D$23)*'Climate impacts'!AC84 -> 1635.9497
B30: Repair/Reconstruction cost (CAPEX) | D30: =Parameters_Results!$D$19*'Climate impacts'!E48+(1-Parameters_Results!$D$19)*'Climate impacts'!D48 -> 0 | E30: =Parameters_Results!$D$19*'Climate impacts'!G84+(1-Parameters_Results!$D$19)*'Climate impacts'!F84 -> 0 | F30: =Parameters_Results!$D$19*'Climate impacts'!I84+(1-Parameters_Results!$D$19)*'Climate impacts'!H84 -> 0 | G30: =Parameters_Results!$D$19*'Climate impacts'!K84+(1-Parameters_Results!$D$19)*'Climate impacts'!J84 -> 0 | I30: Repair/Reconstruction cost (CAPEX) | K30: =Parameters_Results!$D$21*'Climate impacts'!J48+(1-Parameters_Results!$D$21)*'Climate impacts'!I48 -> 1635.9497 | L30: =Parameters_Results!$D$21*'Climate impacts'!P84+(1-Parameters_Results!$D$21)*'Climate impacts'!O84 -> 1635.9497 | M30: =Parameters_Results!$D$21*'Climate impacts'!R84+(1-Parameters_Results!$D$21)*'Climate impacts'!Q84 -> 1635.9497 | N30: =Parameters_Results!$D$21*'Climate impacts'!T84+(1-Parameters_Results!$D$21)*'Climate impacts'!S84 -> 1635.9497 | P30: Repair/Reconstruction cost (CAPEX) | R30: =Parameters_Results!$D$23*'Climate impacts'!O48+(1-Parameters_Results!$D$23)*'Climate impacts'!N48 -> 1635.9497 | S30: =Parameters_Results!$D$23*'Climate impacts'!Z84+(1-Parameters_Results!$D$23)*'Climate impacts'!Y84 -> 1635.9497 | T30: =Parameters_Results!$D$23*'Climate impacts'!AB84+(1-Parameters_Results!$D$23)*'Climate impacts'!AA84 -> 1635.9497 | U30: =Parameters_Results!$D$23*'Climate impacts'!AD84+(1-Parameters_Results!$D$23)*'Climate impacts'!AC84 -> 1635.9497
B31: Additional out-of-system impacts | D31: =Parameters_Results!$D$19*'Climate impacts'!E49+(1-Parameters_Results!$D$19)*'Climate impacts'!D49 -> 0 | E31: =Parameters_Results!$D$19*'Climate impacts'!G85+(1-Parameters_Results!$D$19)*'Climate impacts'!F85 -> 0 | F31: =Parameters_Results!$D$19*'Climate impacts'!I85+(1-Parameters_Results!$D$19)*'Climate impacts'!H85 -> 0 | G31: =Parameters_Results!$D$19*'Climate impacts'!K85+(1-Parameters_Results!$D$19)*'Climate impacts'!J85 -> 0 | I31: Additional out-of-system impacts | K31: =Parameters_Results!$D$21*'Climate impacts'!J49+(1-Parameters_Results!$D$21)*'Climate impacts'!I49 -> 0 | L31: =Parameters_Results!$D$21*'Climate impacts'!P85+(1-Parameters_Results!$D$21)*'Climate impacts'!O85 -> 0 | M31: =Parameters_Results!$D$21*'Climate impacts'!R85+(1-Parameters_Results!$D$21)*'Climate impacts'!Q85 -> 0 | N31: =Parameters_Results!$D$21*'Climate impacts'!T85+(1-Parameters_Results!$D$21)*'Climate impacts'!S85 -> 0 | P31: Additional out-of-system impacts | R31: =Parameters_Results!$D$23*'Climate impacts'!O49+(1-Parameters_Results!$D$23)*'Climate impacts'!N49 -> 0 | S31: =Parameters_Results!$D$23*'Climate impacts'!Z85+(1-Parameters_Results!$D$23)*'Climate impacts'!Y85 -> 0 | T31: =Parameters_Results!$D$23*'Climate impacts'!AB85+(1-Parameters_Results!$D$23)*'Climate impacts'!AA85 -> 0 | U31: =Parameters_Results!$D$23*'Climate impacts'!AD85+(1-Parameters_Results!$D$23)*'Climate impacts'!AC85 -> 0
AF32: =COLUMN() -> 32 | BH32: =COLUMN() -> 60
B34: Calculation: (2bi) | AD34: Calculation: (2bii) | BF34: Calculation: (2biii)
B35: Extrapolates data above for each ear. Calculates "frequency" based on "Return period". | AD35: Extrapolates data above for each ear. Calculates "frequency" based on "Return period". | BF35: Extrapolates data above for each ear. Calculates "frequency" based on "Return period".
B36: Input: All this sheet (table above) | AD36: Input: All this sheet (table above) | BF36: Input: All this sheet (table above)
B38: Year | D38: =Parameters_Results!$D$10+COLUMN()-3 -> 2019 | E38: =Parameters_Results!$D$10+COLUMN()-3 -> 2020 | F38: =Parameters_Results!$D$10+COLUMN()-3 -> 2021 | G38: =Parameters_Results!$D$10+COLUMN()-3 -> 2022 | H38: =Parameters_Results!$D$10+COLUMN()-3 -> 2023 | I38: =Parameters_Results!$D$10+COLUMN()-3 -> 2024 | J38: =Parameters_Results!$D$10+COLUMN()-3 -> 2025 | K38: =Parameters_Results!$D$10+COLUMN()-3 -> 2026 | ... AB38: =Parameters_Results!$D$10+COLUMN()-3 -> 2043 | AD38: Year | AF38: =Parameters_Results!$D$10+COLUMN()-31 -> 2019 | AG38: =Parameters_Results!$D$10+COLUMN()-31 -> 2020 | AH38: =Parameters_Results!$D$10+COLUMN()-31 -> 2021 | AI38: =Parameters_Results!$D$10+COLUMN()-31 -> 2022 | AJ38: =Parameters_Results!$D$10+COLUMN()-31 -> 2023 | AK38: =Parameters_Results!$D$10+COLUMN()-31 -> 2024 | AL38: =Parameters_Results!$D$10+COLUMN()-31 -> 2025 | AM38: =Parameters_Results!$D$10+COLUMN()-31 -> 2026 | ... BD38: =Parameters_Results!$D$10+COLUMN()-31 -> 2043 | BF38: Year | BH38: =Parameters_Results!$D$10+COLUMN()-59 -> 2019 | BI38: =Parameters_Results!$D$10+COLUMN()-59 -> 2020 | BJ38: =Parameters_Results!$D$10+COLUMN()-59 -> 2021 | BK38: =Parameters_Results!$D$10+COLUMN()-59 -> 2022 | BL38: =Parameters_Results!$D$10+COLUMN()-59 -> 2023 | BM38: =Parameters_Results!$D$10+COLUMN()-59 -> 2024 | BN38: =Parameters_Results!$D$10+COLUMN()-59 -> 2025 | BO38: =Parameters_Results!$D$10+COLUMN()-59 -> 2026 | ... CF38: =Parameters_Results!$D$10+COLUMN()-59 -> 2043
B39: Once every 2 years | AD39: Once every 2 years | BF39: Once every 2 years
B40: Probability of occurence (in %) | D40: =(1/$E9-1/$D9)*(D$38-$D$7)/($E$7-$D$7)+1/$D9 -> 0.5 | E40: =(1/$E9-1/$D9)*(E$38-$D$7)/($E$7-$D$7)+1/$D9 -> 0.5 | F40: =(1/$E9-1/$D9)*(F$38-$D$7)/($E$7-$D$7)+1/$D9 -> 0.5 | G40: =(1/$E9-1/$D9)*(G$38-$D$7)/($E$7-$D$7)+1/$D9 -> 0.5 | H40: =(1/$E9-1/$D9)*(H$38-$D$7)/($E$7-$D$7)+1/$D9 -> 0.5 | I40: =(1/$E9-1/$D9)*(I$38-$D$7)/($E$7-$D$7)+1/$D9 -> 0.5 | J40: =(1/$E9-1/$D9)*(J$38-$D$7)/($E$7-$D$7)+1/$D9 -> 0.5 | K40: =(1/$E9-1/$D9)*(K$38-$D$7)/($E$7-$D$7)+1/$D9 -> 0.5 | ... M40: =(1/$E9-1/$D9)*(M$38-$D$7)/($E$7-$D$7)+1/$D9 -> 0.5 | N40: =(1/$F9-1/$E9)*(N$38-$E$7)/($F$7-$E$7)+1/$E9 -> 0.5 | O40: =(1/$F9-1/$E9)*(O$38-$E$7)/($F$7-$E$7)+1/$E9 -> 0.5 | P40: =(1/$F9-1/$E9)*(P$38-$E$7)/($F$7-$E$7)+1/$E9 -> 0.5 | Q40: =(1/$F9-1/$E9)*(Q$38-$E$7)/($F$7-$E$7)+1/$E9 -> 0.5 | R40: =(1/$F9-1/$E9)*(R$38-$E$7)/($F$7-$E$7)+1/$E9 -> 0.5 | S40: =(1/$F9-1/$E9)*(S$38-$E$7)/($F$7-$E$7)+1/$E9 -> 0.5 | T40: =(1/$F9-1/$E9)*(T$38-$E$7)/($F$7-$E$7)+1/$E9 -> 0.5 | U40: =(1/$F9-1/$E9)*(U$38-$E$7)/($F$7-$E$7)+1/$E9 -> 0.5 | ... AB40: =(1/$F9-1/$E9)*(AB$38-$E$7)/($F$7-$E$7)+1/$E9 -> 0.5 | AD40: Probability of occurence (in %) | AF40: =(1/$L9-1/$K9)*(AF$38-$K$7)/($L$7-$K$7)+1/$K9 -> 0.5 | AG40: =(1/$L9-1/$K9)*(AG$38-$K$7)/($L$7-$K$7)+1/$K9 -> 0.5 | AH40: =(1/$L9-1/$K9)*(AH$38-$K$7)/($L$7-$K$7)+1/$K9 -> 0.5 | AI40: =(1/$L9-1/$K9)*(AI$38-$K$7)/($L$7-$K$7)+1/$K9 -> 0.5 | AJ40: =(1/$L9-1/$K9)*(AJ$38-$K$7)/($L$7-$K$7)+1/$K9 -> 0.5 | AK40: =(1/$L9-1/$K9)*(AK$38-$K$7)/($L$7-$K$7)+1/$K9 -> 0.5 | AL40: =(1/$L9-1/$K9)*(AL$38-$K$7)/($L$7-$K$7)+1/$K9 -> 0.5 | AM40: =(1/$L9-1/$K9)*(AM$38-$K$7)/($L$7-$K$7)+1/$K9 -> 0.5 | ... AO40: =(1/$L9-1/$K9)*(AO$38-$K$7)/($L$7-$K$7)+1/$K9 -> 0.5 | AP40: =(1/$M9-1/$L9)*(AP$38-$L$7)/($M$7-$L$7)+1/$L9 -> 0.5 | AQ40: =(1/$M9-1/$L9)*(AQ$38-$L$7)/($M$7-$L$7)+1/$L9 -> 0.5 | AR40: =(1/$M9-1/$L9)*(AR$38-$L$7)/($M$7-$L$7)+1/$L9 -> 0.5 | AS40: =(1/$M9-1/$L9)*(AS$38-$L$7)/($M$7-$L$7)+1/$L9 -> 0.5 | AT40: =(1/$M9-1/$L9)*(AT$38-$L$7)/($M$7-$L$7)+1/$L9 -> 0.5 | AU40: =(1/$M9-1/$L9)*(AU$38-$L$7)/($M$7-$L$7)+1/$L9 -> 0.5 | AV40: =(1/$M9-1/$L9)*(AV$38-$L$7)/($M$7-$L$7)+1/$L9 -> 0.5 | AW40: =(1/$M9-1/$L9)*(AW$38-$L$7)/($M$7-$L$7)+1/$L9 -> 0.5 | ... BD40: =(1/$M9-1/$L9)*(BD$38-$L$7)/($M$7-$L$7)+1/$L9 -> 0.5 | BF40: Probability of occurence (in %) | BH40: =(1/$S9-1/$R9)*(BH$38-$R$7)/($S$7-$R$7)+1/$R9 -> 0.5 | BI40: =(1/$S9-1/$R9)*(BI$38-$R$7)/($S$7-$R$7)+1/$R9 -> 0.5 | BJ40: =(1/$S9-1/$R9)*(BJ$38-$R$7)/($S$7-$R$7)+1/$R9 -> 0.5 | BK40: =(1/$S9-1/$R9)*(BK$38-$R$7)/($S$7-$R$7)+1/$R9 -> 0.5 | BL40: =(1/$S9-1/$R9)*(BL$38-$R$7)/($S$7-$R$7)+1/$R9 -> 0.5 | BM40: =(1/$S9-1/$R9)*(BM$38-$R$7)/($S$7-$R$7)+1/$R9 -> 0.5 | BN40: =(1/$S9-1/$R9)*(BN$38-$R$7)/($S$7-$R$7)+1/$R9 -> 0.5 | BO40: =(1/$S9-1/$R9)*(BO$38-$R$7)/($S$7-$R$7)+1/$R9 -> 0.5 | ... BQ40: =(1/$S9-1/$R9)*(BQ$38-$R$7)/($S$7-$R$7)+1/$R9 -> 0.5 | BR40: =(1/$T9-1/$S9)*(BR$38-$S$7)/($T$7-$S$7)+1/$S9 -> 0.5 | BS40: =(1/$T9-1/$S9)*(BS$38-$S$7)/($T$7-$S$7)+1/$S9 -> 0.5 | BT40: =(1/$T9-1/$S9)*(BT$38-$S$7)/($T$7-$S$7)+1/$S9 -> 0.5 | BU40: =(1/$T9-1/$S9)*(BU$38-$S$7)/($T$7-$S$7)+1/$S9 -> 0.5 | BV40: =(1/$T9-1/$S9)*(BV$38-$S$7)/($T$7-$S$7)+1/$S9 -> 0.5 | BW40: =(1/$T9-1/$S9)*(BW$38-$S$7)/($T$7-$S$7)+1/$S9 -> 0.5 | BX40: =(1/$T9-1/$S9)*(BX$38-$S$7)/($T$7-$S$7)+1/$S9 -> 0.5 | BY40: =(1/$T9-1/$S9)*(BY$38-$S$7)/($T$7-$S$7)+1/$S9 -> 0.5 | ... CF40: =(1/$T9-1/$S9)*(CF$38-$S$7)/($T$7-$S$7)+1/$S9 -> 0.5
B41: Impact on quantity produced (% of yearly output) | D41: =($E10-$D10)*(D$38-$D$7)/($E$7-$D$7)+$D10 -> 0 | E41: =($E10-$D10)*(E$38-$D$7)/($E$7-$D$7)+$D10 -> 0 | F41: =($E10-$D10)*(F$38-$D$7)/($E$7-$D$7)+$D10 -> 0 | G41: =($E10-$D10)*(G$38-$D$7)/($E$7-$D$7)+$D10 -> 0 | H41: =($E10-$D10)*(H$38-$D$7)/($E$7-$D$7)+$D10 -> 0 | I41: =($E10-$D10)*(I$38-$D$7)/($E$7-$D$7)+$D10 -> 0 | J41: =($E10-$D10)*(J$38-$D$7)/($E$7-$D$7)+$D10 -> 0 | K41: =($E10-$D10)*(K$38-$D$7)/($E$7-$D$7)+$D10 -> 0 | ... M41: =($E10-$D10)*(M$38-$D$7)/($E$7-$D$7)+$D10 -> 0 | N41: =($F10-$E10)*(N$38-$E$7)/($F$7-$E$7)+$E10 -> 0 | O41: =($F10-$E10)*(O$38-$E$7)/($F$7-$E$7)+$E10 -> 0 | P41: =($F10-$E10)*(P$38-$E$7)/($F$7-$E$7)+$E10 -> 0 | Q41: =($F10-$E10)*(Q$38-$E$7)/($F$7-$E$7)+$E10 -> 0 | R41: =($F10-$E10)*(R$38-$E$7)/($F$7-$E$7)+$E10 -> 0 | S41: =($F10-$E10)*(S$38-$E$7)/($F$7-$E$7)+$E10 -> 0 | T41: =($F10-$E10)*(T$38-$E$7)/($F$7-$E$7)+$E10 -> 0 | U41: =($F10-$E10)*(U$38-$E$7)/($F$7-$E$7)+$E10 -> 0 | ... AB41: =($F10-$E10)*(AB$38-$E$7)/($F$7-$E$7)+$E10 -> 0 | AD41: Impact on quantity produced (% of yearly output) | AF41: =($L10-$K10)*(AF$38-$K$7)/($L$7-$K$7)+$K10 -> 0 | AG41: =($L10-$K10)*(AG$38-$K$7)/($L$7-$K$7)+$K10 -> 0 | AH41: =($L10-$K10)*(AH$38-$K$7)/($L$7-$K$7)+$K10 -> 0 | AI41: =($L10-$K10)*(AI$38-$K$7)/($L$7-$K$7)+$K10 -> 0 | AJ41: =($L10-$K10)*(AJ$38-$K$7)/($L$7-$K$7)+$K10 -> 0 | AK41: =($L10-$K10)*(AK$38-$K$7)/($L$7-$K$7)+$K10 -> 0 | AL41: =($L10-$K10)*(AL$38-$K$7)/($L$7-$K$7)+$K10 -> 0 | AM41: =($L10-$K10)*(AM$38-$K$7)/($L$7-$K$7)+$K10 -> 0 | ... BD41: =($L10-$K10)*(BD$38-$K$7)/($L$7-$K$7)+$K10 -> 0 | BF41: Impact on quantity produced (% of yearly output) | BH41: =($S10-$R10)*(BH$38-$R$7)/($S$7-$R$7)+$R10 -> 0 | BI41: =($S10-$R10)*(BI$38-$R$7)/($S$7-$R$7)+$R10 -> 0 | BJ41: =($S10-$R10)*(BJ$38-$R$7)/($S$7-$R$7)+$R10 -> 0 | BK41: =($S10-$R10)*(BK$38-$R$7)/($S$7-$R$7)+$R10 -> 0 | BL41: =($S10-$R10)*(BL$38-$R$7)/($S$7-$R$7)+$R10 -> 0 | BM41: =($S10-$R10)*(BM$38-$R$7)/($S$7-$R$7)+$R10 -> 0 | BN41: =($S10-$R10)*(BN$38-$R$7)/($S$7-$R$7)+$R10 -> 0 | BO41: =($S10-$R10)*(BO$38-$R$7)/($S$7-$R$7)+$R10 -> 0 | ... BQ41: =($S10-$R10)*(BQ$38-$R$7)/($S$7-$R$7)+$R10 -> 0 | BR41: =($T10-$S10)*(BR$38-$S$7)/($T$7-$S$7)+$S10 -> 0 | BS41: =($T10-$S10)*(BS$38-$S$7)/($T$7-$S$7)+$S10 -> 0 | BT41: =($T10-$S10)*(BT$38-$S$7)/($T$7-$S$7)+$S10 -> 0 | BU41: =($T10-$S10)*(BU$38-$S$7)/($T$7-$S$7)+$S10 -> 0 | BV41: =($T10-$S10)*(BV$38-$S$7)/($T$7-$S$7)+$S10 -> 0 | BW41: =($T10-$S10)*(BW$38-$S$7)/($T$7-$S$7)+$S10 -> 0 | BX41: =($T10-$S10)*(BX$38-$S$7)/($T$7-$S$7)+$S10 -> 0 | BY41: =($T10-$S10)*(BY$38-$S$7)/($T$7-$S$7)+$S10 -> 0 | ... CF41: =($T10-$S10)*(CF$38-$S$7)/($T$7-$S$7)+$S10 -> 0
B42: Impact on quantity produced (% of yearly output) without project | D42: =($E11-$D11)*(D$38-$D$7)/($E$7-$D$7)+$D11 -> 0 | E42: =($E11-$D11)*(E$38-$D$7)/($E$7-$D$7)+$D11 -> 0 | F42: =($E11-$D11)*(F$38-$D$7)/($E$7-$D$7)+$D11 -> 0 | G42: =($E11-$D11)*(G$38-$D$7)/($E$7-$D$7)+$D11 -> 0 | H42: =($E11-$D11)*(H$38-$D$7)/($E$7-$D$7)+$D11 -> 0 | I42: =($E11-$D11)*(I$38-$D$7)/($E$7-$D$7)+$D11 -> 0 | J42: =($E11-$D11)*(J$38-$D$7)/($E$7-$D$7)+$D11 -> 0 | K42: =($E11-$D11)*(K$38-$D$7)/($E$7-$D$7)+$D11 -> 0 | ... M42: =($E11-$D11)*(M$38-$D$7)/($E$7-$D$7)+$D11 -> 0 | N42: =($F11-$E11)*(N$38-$E$7)/($F$7-$E$7)+$E11 -> 0 | O42: =($F11-$E11)*(O$38-$E$7)/($F$7-$E$7)+$E11 -> 0 | P42: =($F11-$E11)*(P$38-$E$7)/($F$7-$E$7)+$E11 -> 0 | Q42: =($F11-$E11)*(Q$38-$E$7)/($F$7-$E$7)+$E11 -> 0 | R42: =($F11-$E11)*(R$38-$E$7)/($F$7-$E$7)+$E11 -> 0 | S42: =($F11-$E11)*(S$38-$E$7)/($F$7-$E$7)+$E11 -> 0 | T42: =($F11-$E11)*(T$38-$E$7)/($F$7-$E$7)+$E11 -> 0 | U42: =($F11-$E11)*(U$38-$E$7)/($F$7-$E$7)+$E11 -> 0 | ... AB42: =($F11-$E11)*(AB$38-$E$7)/($F$7-$E$7)+$E11 -> 0 | AD42: Impact on quantity produced (% of yearly output) without project | AF42: =($L11-$K11)*(AF$38-$K$7)/($L$7-$K$7)+$K11 -> 0 | AG42: =($L11-$K11)*(AG$38-$K$7)/($L$7-$K$7)+$K11 -> 0 | AH42: =($L11-$K11)*(AH$38-$K$7)/($L$7-$K$7)+$K11 -> 0 | AI42: =($L11-$K11)*(AI$38-$K$7)/($L$7-$K$7)+$K11 -> 0 | AJ42: =($L11-$K11)*(AJ$38-$K$7)/($L$7-$K$7)+$K11 -> 0 | AK42: =($L11-$K11)*(AK$38-$K$7)/($L$7-$K$7)+$K11 -> 0 | AL42: =($L11-$K11)*(AL$38-$K$7)/($L$7-$K$7)+$K11 -> 0 | AM42: =($L11-$K11)*(AM$38-$K$7)/($L$7-$K$7)+$K11 -> 0 | ... BD42: =($L11-$K11)*(BD$38-$K$7)/($L$7-$K$7)+$K11 -> 0 | BF42: Impact on quantity produced (% of yearly output) without project | BH42: =($S11-$R11)*(BH$38-$R$7)/($S$7-$R$7)+$R11 -> 0 | BI42: =($S11-$R11)*(BI$38-$R$7)/($S$7-$R$7)+$R11 -> 0 | BJ42: =($S11-$R11)*(BJ$38-$R$7)/($S$7-$R$7)+$R11 -> 0 | BK42: =($S11-$R11)*(BK$38-$R$7)/($S$7-$R$7)+$R11 -> 0 | BL42: =($S11-$R11)*(BL$38-$R$7)/($S$7-$R$7)+$R11 -> 0 | BM42: =($S11-$R11)*(BM$38-$R$7)/($S$7-$R$7)+$R11 -> 0 | BN42: =($S11-$R11)*(BN$38-$R$7)/($S$7-$R$7)+$R11 -> 0 | BO42: =($S11-$R11)*(BO$38-$R$7)/($S$7-$R$7)+$R11 -> 0 | ... BQ42: =($S11-$R11)*(BQ$38-$R$7)/($S$7-$R$7)+$R11 -> 0 | BR42: =($T11-$S11)*(BR$38-$S$7)/($T$7-$S$7)+$S11 -> 0 | BS42: =($T11-$S11)*(BS$38-$S$7)/($T$7-$S$7)+$S11 -> 0 | BT42: =($T11-$S11)*(BT$38-$S$7)/($T$7-$S$7)+$S11 -> 0 | BU42: =($T11-$S11)*(BU$38-$S$7)/($T$7-$S$7)+$S11 -> 0 | BV42: =($T11-$S11)*(BV$38-$S$7)/($T$7-$S$7)+$S11 -> 0 | BW42: =($T11-$S11)*(BW$38-$S$7)/($T$7-$S$7)+$S11 -> 0 | BX42: =($T11-$S11)*(BX$38-$S$7)/($T$7-$S$7)+$S11 -> 0 | BY42: =($T11-$S11)*(BY$38-$S$7)/($T$7-$S$7)+$S11 -> 0 | ... CF42: =($T11-$S11)*(CF$38-$S$7)/($T$7-$S$7)+$S11 -> 0
B43: Repair/Reconstruction cost (CAPEX) (in absolute terms) | D43: =($E12-$D12)*(D$38-$D$7)/($E$7-$D$7)+$D12 -> 0 | E43: =($E12-$D12)*(E$38-$D$7)/($E$7-$D$7)+$D12 -> 0 | F43: =($E12-$D12)*(F$38-$D$7)/($E$7-$D$7)+$D12 -> 0 | G43: =($E12-$D12)*(G$38-$D$7)/($E$7-$D$7)+$D12 -> 0 | H43: =($E12-$D12)*(H$38-$D$7)/($E$7-$D$7)+$D12 -> 0 | I43: =($E12-$D12)*(I$38-$D$7)/($E$7-$D$7)+$D12 -> 0 | J43: =($E12-$D12)*(J$38-$D$7)/($E$7-$D$7)+$D12 -> 0 | K43: =($E12-$D12)*(K$38-$D$7)/($E$7-$D$7)+$D12 -> 0 | ... M43: =($E12-$D12)*(M$38-$D$7)/($E$7-$D$7)+$D12 -> 0 | N43: =($F12-$E12)*(N$38-$E$7)/($F$7-$E$7)+$E12 -> 0 | O43: =($F12-$E12)*(O$38-$E$7)/($F$7-$E$7)+$E12 -> 0 | P43: =($F12-$E12)*(P$38-$E$7)/($F$7-$E$7)+$E12 -> 0 | Q43: =($F12-$E12)*(Q$38-$E$7)/($F$7-$E$7)+$E12 -> 0 | R43: =($F12-$E12)*(R$38-$E$7)/($F$7-$E$7)+$E12 -> 0 | S43: =($F12-$E12)*(S$38-$E$7)/($F$7-$E$7)+$E12 -> 0 | T43: =($F12-$E12)*(T$38-$E$7)/($F$7-$E$7)+$E12 -> 0 | U43: =($F12-$E12)*(U$38-$E$7)/($F$7-$E$7)+$E12 -> 0 | ... AB43: =($F12-$E12)*(AB$38-$E$7)/($F$7-$E$7)+$E12 -> 0 | AD43: Repair/Reconstruction cost (CAPEX) (in absolute terms) | AF43: =($L12-$K12)*(AF$38-$K$7)/($L$7-$K$7)+$K12 -> 0 | AG43: =($L12-$K12)*(AG$38-$K$7)/($L$7-$K$7)+$K12 -> 0 | AH43: =($L12-$K12)*(AH$38-$K$7)/($L$7-$K$7)+$K12 -> 0 | AI43: =($L12-$K12)*(AI$38-$K$7)/($L$7-$K$7)+$K12 -> 0 | AJ43: =($L12-$K12)*(AJ$38-$K$7)/($L$7-$K$7)+$K12 -> 0 | AK43: =($L12-$K12)*(AK$38-$K$7)/($L$7-$K$7)+$K12 -> 0 | AL43: =($L12-$K12)*(AL$38-$K$7)/($L$7-$K$7)+$K12 -> 0 | AM43: =($L12-$K12)*(AM$38-$K$7)/($L$7-$K$7)+$K12 -> 0 | ... BD43: =($L12-$K12)*(BD$38-$K$7)/($L$7-$K$7)+$K12 -> 0 | BF43: Repair/Reconstruction cost (CAPEX) (in absolute terms) | BH43: =($S12-$R12)*(BH$38-$R$7)/($S$7-$R$7)+$R12 -> 0 | BI43: =($S12-$R12)*(BI$38-$R$7)/($S$7-$R$7)+$R12 -> 0 | BJ43: =($S12-$R12)*(BJ$38-$R$7)/($S$7-$R$7)+$R12 -> 0 | BK43: =($S12-$R12)*(BK$38-$R$7)/($S$7-$R$7)+$R12 -> 0 | BL43: =($S12-$R12)*(BL$38-$R$7)/($S$7-$R$7)+$R12 -> 0 | BM43: =($S12-$R12)*(BM$38-$R$7)/($S$7-$R$7)+$R12 -> 0 | BN43: =($S12-$R12)*(BN$38-$R$7)/($S$7-$R$7)+$R12 -> 0 | BO43: =($S12-$R12)*(BO$38-$R$7)/($S$7-$R$7)+$R12 -> 0 | ... BQ43: =($S12-$R12)*(BQ$38-$R$7)/($S$7-$R$7)+$R12 -> 0 | BR43: =($T12-$S12)*(BR$38-$S$7)/($T$7-$S$7)+$S12 -> 0 | BS43: =($T12-$S12)*(BS$38-$S$7)/($T$7-$S$7)+$S12 -> 0 | BT43: =($T12-$S12)*(BT$38-$S$7)/($T$7-$S$7)+$S12 -> 0 | BU43: =($T12-$S12)*(BU$38-$S$7)/($T$7-$S$7)+$S12 -> 0 | BV43: =($T12-$S12)*(BV$38-$S$7)/($T$7-$S$7)+$S12 -> 0 | BW43: =($T12-$S12)*(BW$38-$S$7)/($T$7-$S$7)+$S12 -> 0 | BX43: =($T12-$S12)*(BX$38-$S$7)/($T$7-$S$7)+$S12 -> 0 | BY43: =($T12-$S12)*(BY$38-$S$7)/($T$7-$S$7)+$S12 -> 0 | ... CF43: =($T12-$S12)*(CF$38-$S$7)/($T$7-$S$7)+$S12 -> 0
B44: Additional out-of-system impacts (in absolute terms) | D44: =($E13-$D13)*(D$38-$D$7)/($E$7-$D$7)+$D13 -> 0 | E44: =($E13-$D13)*(E$38-$D$7)/($E$7-$D$7)+$D13 -> 0 | F44: =($E13-$D13)*(F$38-$D$7)/($E$7-$D$7)+$D13 -> 0 | G44: =($E13-$D13)*(G$38-$D$7)/($E$7-$D$7)+$D13 -> 0 | H44: =($E13-$D13)*(H$38-$D$7)/($E$7-$D$7)+$D13 -> 0 | I44: =($E13-$D13)*(I$38-$D$7)/($E$7-$D$7)+$D13 -> 0 | J44: =($E13-$D13)*(J$38-$D$7)/($E$7-$D$7)+$D13 -> 0 | K44: =($E13-$D13)*(K$38-$D$7)/($E$7-$D$7)+$D13 -> 0 | ... M44: =($E13-$D13)*(M$38-$D$7)/($E$7-$D$7)+$D13 -> 0 | N44: =($F13-$E13)*(N$38-$E$7)/($F$7-$E$7)+$E13 -> 0 | O44: =($F13-$E13)*(O$38-$E$7)/($F$7-$E$7)+$E13 -> 0 | P44: =($F13-$E13)*(P$38-$E$7)/($F$7-$E$7)+$E13 -> 0 | Q44: =($F13-$E13)*(Q$38-$E$7)/($F$7-$E$7)+$E13 -> 0 | R44: =($F13-$E13)*(R$38-$E$7)/($F$7-$E$7)+$E13 -> 0 | S44: =($F13-$E13)*(S$38-$E$7)/($F$7-$E$7)+$E13 -> 0 | T44: =($F13-$E13)*(T$38-$E$7)/($F$7-$E$7)+$E13 -> 0 | U44: =($F13-$E13)*(U$38-$E$7)/($F$7-$E$7)+$E13 -> 0 | ... AB44: =($F13-$E13)*(AB$38-$E$7)/($F$7-$E$7)+$E13 -> 0 | AD44: Additional out-of-system impacts (in absolute terms) | AF44: =($L13-$K13)*(AF$38-$K$7)/($L$7-$K$7)+$K13 -> 0 | AG44: =($L13-$K13)*(AG$38-$K$7)/($L$7-$K$7)+$K13 -> 0 | AH44: =($L13-$K13)*(AH$38-$K$7)/($L$7-$K$7)+$K13 -> 0 | AI44: =($L13-$K13)*(AI$38-$K$7)/($L$7-$K$7)+$K13 -> 0 | AJ44: =($L13-$K13)*(AJ$38-$K$7)/($L$7-$K$7)+$K13 -> 0 | AK44: =($L13-$K13)*(AK$38-$K$7)/($L$7-$K$7)+$K13 -> 0 | AL44: =($L13-$K13)*(AL$38-$K$7)/($L$7-$K$7)+$K13 -> 0 | AM44: =($L13-$K13)*(AM$38-$K$7)/($L$7-$K$7)+$K13 -> 0 | ... BD44: =($L13-$K13)*(BD$38-$K$7)/($L$7-$K$7)+$K13 -> 0 | BF44: Additional out-of-system impacts (in absolute terms) | BH44: =($S13-$R13)*(BH$38-$R$7)/($S$7-$R$7)+$R13 -> 0 | BI44: =($S13-$R13)*(BI$38-$R$7)/($S$7-$R$7)+$R13 -> 0 | BJ44: =($S13-$R13)*(BJ$38-$R$7)/($S$7-$R$7)+$R13 -> 0 | BK44: =($S13-$R13)*(BK$38-$R$7)/($S$7-$R$7)+$R13 -> 0 | BL44: =($S13-$R13)*(BL$38-$R$7)/($S$7-$R$7)+$R13 -> 0 | BM44: =($S13-$R13)*(BM$38-$R$7)/($S$7-$R$7)+$R13 -> 0 | BN44: =($S13-$R13)*(BN$38-$R$7)/($S$7-$R$7)+$R13 -> 0 | BO44: =($S13-$R13)*(BO$38-$R$7)/($S$7-$R$7)+$R13 -> 0 | ... BQ44: =($S13-$R13)*(BQ$38-$R$7)/($S$7-$R$7)+$R13 -> 0 | BR44: =($T13-$S13)*(BR$38-$S$7)/($T$7-$S$7)+$S13 -> 0 | BS44: =($T13-$S13)*(BS$38-$S$7)/($T$7-$S$7)+$S13 -> 0 | BT44: =($T13-$S13)*(BT$38-$S$7)/($T$7-$S$7)+$S13 -> 0 | BU44: =($T13-$S13)*(BU$38-$S$7)/($T$7-$S$7)+$S13 -> 0 | BV44: =($T13-$S13)*(BV$38-$S$7)/($T$7-$S$7)+$S13 -> 0 | BW44: =($T13-$S13)*(BW$38-$S$7)/($T$7-$S$7)+$S13 -> 0 | BX44: =($T13-$S13)*(BX$38-$S$7)/($T$7-$S$7)+$S13 -> 0 | BY44: =($T13-$S13)*(BY$38-$S$7)/($T$7-$S$7)+$S13 -> 0 | ... CF44: =($T13-$S13)*(CF$38-$S$7)/($T$7-$S$7)+$S13 -> 0
B45: Once every 50 years | AD45: Once every 50 years | BF45: Once every 50 years
B46: Probability of occurence (in %) | D46: =(1/$E15-1/$D15)*(D$38-$D$7)/($E$7-$D$7)+1/$D15 -> 0.10833333 | E46: =(1/$E15-1/$D15)*(E$38-$D$7)/($E$7-$D$7)+1/$D15 -> 0.11666667 | F46: =(1/$E15-1/$D15)*(F$38-$D$7)/($E$7-$D$7)+1/$D15 -> 0.125 | G46: =(1/$E15-1/$D15)*(G$38-$D$7)/($E$7-$D$7)+1/$D15 -> 0.13333333 | H46: =(1/$E15-1/$D15)*(H$38-$D$7)/($E$7-$D$7)+1/$D15 -> 0.14166667 | I46: =(1/$E15-1/$D15)*(I$38-$D$7)/($E$7-$D$7)+1/$D15 -> 0.15 | J46: =(1/$E15-1/$D15)*(J$38-$D$7)/($E$7-$D$7)+1/$D15 -> 0.15833333 | K46: =(1/$E15-1/$D15)*(K$38-$D$7)/($E$7-$D$7)+1/$D15 -> 0.16666667 | ... M46: =(1/$E15-1/$D15)*(M$38-$D$7)/($E$7-$D$7)+1/$D15 -> 0.18333333 | N46: =(1/$F15-1/$E15)*(N$38-$E$7)/($F$7-$E$7)+1/$E15 -> 0.2 | O46: =(1/$F15-1/$E15)*(O$38-$E$7)/($F$7-$E$7)+1/$E15 -> 0.2 | P46: =(1/$F15-1/$E15)*(P$38-$E$7)/($F$7-$E$7)+1/$E15 -> 0.2 | Q46: =(1/$F15-1/$E15)*(Q$38-$E$7)/($F$7-$E$7)+1/$E15 -> 0.2 | R46: =(1/$F15-1/$E15)*(R$38-$E$7)/($F$7-$E$7)+1/$E15 -> 0.2 | S46: =(1/$F15-1/$E15)*(S$38-$E$7)/($F$7-$E$7)+1/$E15 -> 0.2 | T46: =(1/$F15-1/$E15)*(T$38-$E$7)/($F$7-$E$7)+1/$E15 -> 0.2 | U46: =(1/$F15-1/$E15)*(U$38-$E$7)/($F$7-$E$7)+1/$E15 -> 0.2 | ... AB46: =(1/$F15-1/$E15)*(AB$38-$E$7)/($F$7-$E$7)+1/$E15 -> 0.2 | AD46: Probability of occurence (in %) | AF46: =(1/$L15-1/$K15)*(AF$38-$K$7)/($L$7-$K$7)+1/$K15 -> 0.09 | AG46: =(1/$L15-1/$K15)*(AG$38-$K$7)/($L$7-$K$7)+1/$K15 -> 0.1 | AH46: =(1/$L15-1/$K15)*(AH$38-$K$7)/($L$7-$K$7)+1/$K15 -> 0.11 | AI46: =(1/$L15-1/$K15)*(AI$38-$K$7)/($L$7-$K$7)+1/$K15 -> 0.12 | AJ46: =(1/$L15-1/$K15)*(AJ$38-$K$7)/($L$7-$K$7)+1/$K15 -> 0.13 | AK46: =(1/$L15-1/$K15)*(AK$38-$K$7)/($L$7-$K$7)+1/$K15 -> 0.14 | AL46: =(1/$L15-1/$K15)*(AL$38-$K$7)/($L$7-$K$7)+1/$K15 -> 0.15 | AM46: =(1/$L15-1/$K15)*(AM$38-$K$7)/($L$7-$K$7)+1/$K15 -> 0.16 | ... AO46: =(1/$L15-1/$K15)*(AO$38-$K$7)/($L$7-$K$7)+1/$K15 -> 0.18 | AP46: =(1/$M15-1/$L15)*(AP$38-$L$7)/($M$7-$L$7)+1/$L15 -> 0.2 | AQ46: =(1/$M15-1/$L15)*(AQ$38-$L$7)/($M$7-$L$7)+1/$L15 -> 0.2 | AR46: =(1/$M15-1/$L15)*(AR$38-$L$7)/($M$7-$L$7)+1/$L15 -> 0.2 | AS46: =(1/$M15-1/$L15)*(AS$38-$L$7)/($M$7-$L$7)+1/$L15 -> 0.2 | AT46: =(1/$M15-1/$L15)*(AT$38-$L$7)/($M$7-$L$7)+1/$L15 -> 0.2 | AU46: =(1/$M15-1/$L15)*(AU$38-$L$7)/($M$7-$L$7)+1/$L15 -> 0.2 | AV46: =(1/$M15-1/$L15)*(AV$38-$L$7)/($M$7-$L$7)+1/$L15 -> 0.2 | AW46: =(1/$M15-1/$L15)*(AW$38-$L$7)/($M$7-$L$7)+1/$L15 -> 0.2 | ... BD46: =(1/$M15-1/$L15)*(BD$38-$L$7)/($M$7-$L$7)+1/$L15 -> 0.2 | BF46: Probability of occurence (in %) | BH46: =(1/$S15-1/$R15)*(BH$38-$R$7)/($S$7-$R$7)+1/$R15 -> 0.09 | BI46: =(1/$S15-1/$R15)*(BI$38-$R$7)/($S$7-$R$7)+1/$R15 -> 0.1 | BJ46: =(1/$S15-1/$R15)*(BJ$38-$R$7)/($S$7-$R$7)+1/$R15 -> 0.11 | BK46: =(1/$S15-1/$R15)*(BK$38-$R$7)/($S$7-$R$7)+1/$R15 -> 0.12 | BL46: =(1/$S15-1/$R15)*(BL$38-$R$7)/($S$7-$R$7)+1/$R15 -> 0.13 | BM46: =(1/$S15-1/$R15)*(BM$38-$R$7)/($S$7-$R$7)+1/$R15 -> 0.14 | BN46: =(1/$S15-1/$R15)*(BN$38-$R$7)/($S$7-$R$7)+1/$R15 -> 0.15 | BO46: =(1/$S15-1/$R15)*(BO$38-$R$7)/($S$7-$R$7)+1/$R15 -> 0.16 | ... BQ46: =(1/$S15-1/$R15)*(BQ$38-$R$7)/($S$7-$R$7)+1/$R15 -> 0.18 | BR46: =(1/$T15-1/$S15)*(BR$38-$S$7)/($T$7-$S$7)+1/$S15 -> 0.2 | BS46: =(1/$T15-1/$S15)*(BS$38-$S$7)/($T$7-$S$7)+1/$S15 -> 0.2 | BT46: =(1/$T15-1/$S15)*(BT$38-$S$7)/($T$7-$S$7)+1/$S15 -> 0.2 | BU46: =(1/$T15-1/$S15)*(BU$38-$S$7)/($T$7-$S$7)+1/$S15 -> 0.2 | BV46: =(1/$T15-1/$S15)*(BV$38-$S$7)/($T$7-$S$7)+1/$S15 -> 0.2 | BW46: =(1/$T15-1/$S15)*(BW$38-$S$7)/($T$7-$S$7)+1/$S15 -> 0.2 | BX46: =(1/$T15-1/$S15)*(BX$38-$S$7)/($T$7-$S$7)+1/$S15 -> 0.2 | BY46: =(1/$T15-1/$S15)*(BY$38-$S$7)/($T$7-$S$7)+1/$S15 -> 0.2 | ... CF46: =(1/$T15-1/$S15)*(CF$38-$S$7)/($T$7-$S$7)+1/$S15 -> 0.2
B47: Impact on quantity produced (% of yearly output) | D47: =($E16-$D16)*(D$38-$D$7)/($E$7-$D$7)+$D16 -> 0 | E47: =($E16-$D16)*(E$38-$D$7)/($E$7-$D$7)+$D16 -> 0 | F47: =($E16-$D16)*(F$38-$D$7)/($E$7-$D$7)+$D16 -> 0 | G47: =($E16-$D16)*(G$38-$D$7)/($E$7-$D$7)+$D16 -> 0 | H47: =($E16-$D16)*(H$38-$D$7)/($E$7-$D$7)+$D16 -> 0 | I47: =($E16-$D16)*(I$38-$D$7)/($E$7-$D$7)+$D16 -> 0 | J47: =($E16-$D16)*(J$38-$D$7)/($E$7-$D$7)+$D16 -> 0 | K47: =($E16-$D16)*(K$38-$D$7)/($E$7-$D$7)+$D16 -> 0 | ... M47: =($E16-$D16)*(M$38-$D$7)/($E$7-$D$7)+$D16 -> 0 | N47: =($F16-$E16)*(N$38-$E$7)/($F$7-$E$7)+$E16 -> 0 | O47: =($F16-$E16)*(O$38-$E$7)/($F$7-$E$7)+$E16 -> 0 | P47: =($F16-$E16)*(P$38-$E$7)/($F$7-$E$7)+$E16 -> 0 | Q47: =($F16-$E16)*(Q$38-$E$7)/($F$7-$E$7)+$E16 -> 0 | R47: =($F16-$E16)*(R$38-$E$7)/($F$7-$E$7)+$E16 -> 0 | S47: =($F16-$E16)*(S$38-$E$7)/($F$7-$E$7)+$E16 -> 0 | T47: =($F16-$E16)*(T$38-$E$7)/($F$7-$E$7)+$E16 -> 0 | U47: =($F16-$E16)*(U$38-$E$7)/($F$7-$E$7)+$E16 -> 0 | ... AB47: =($F16-$E16)*(AB$38-$E$7)/($F$7-$E$7)+$E16 -> 0 | AD47: Impact on quantity produced (% of yearly output) | AF47: =($L16-$K16)*(AF$38-$K$7)/($L$7-$K$7)+$K16 -> -0.49315068 | AG47: =($L16-$K16)*(AG$38-$K$7)/($L$7-$K$7)+$K16 -> -0.49315068 | AH47: =($L16-$K16)*(AH$38-$K$7)/($L$7-$K$7)+$K16 -> -0.49315068 | AI47: =($L16-$K16)*(AI$38-$K$7)/($L$7-$K$7)+$K16 -> -0.49315068 | AJ47: =($L16-$K16)*(AJ$38-$K$7)/($L$7-$K$7)+$K16 -> -0.49315068 | AK47: =($L16-$K16)*(AK$38-$K$7)/($L$7-$K$7)+$K16 -> -0.49315068 | AL47: =($L16-$K16)*(AL$38-$K$7)/($L$7-$K$7)+$K16 -> -0.49315068 | AM47: =($L16-$K16)*(AM$38-$K$7)/($L$7-$K$7)+$K16 -> -0.49315068 | ... BD47: =($L16-$K16)*(BD$38-$K$7)/($L$7-$K$7)+$K16 -> -0.49315068 | BF47: Impact on quantity produced (% of yearly output) | BH47: =($S16-$R16)*(BH$38-$R$7)/($S$7-$R$7)+$R16 -> -0.73972603 | BI47: =($S16-$R16)*(BI$38-$R$7)/($S$7-$R$7)+$R16 -> -0.73972603 | BJ47: =($S16-$R16)*(BJ$38-$R$7)/($S$7-$R$7)+$R16 -> -0.73972603 | BK47: =($S16-$R16)*(BK$38-$R$7)/($S$7-$R$7)+$R16 -> -0.73972603 | BL47: =($S16-$R16)*(BL$38-$R$7)/($S$7-$R$7)+$R16 -> -0.73972603 | BM47: =($S16-$R16)*(BM$38-$R$7)/($S$7-$R$7)+$R16 -> -0.73972603 | BN47: =($S16-$R16)*(BN$38-$R$7)/($S$7-$R$7)+$R16 -> -0.73972603 | BO47: =($S16-$R16)*(BO$38-$R$7)/($S$7-$R$7)+$R16 -> -0.73972603 | ... BQ47: =($S16-$R16)*(BQ$38-$R$7)/($S$7-$R$7)+$R16 -> -0.73972603 | BR47: =($T16-$S16)*(BR$38-$S$7)/($T$7-$S$7)+$S16 -> -0.73972603 | BS47: =($T16-$S16)*(BS$38-$S$7)/($T$7-$S$7)+$S16 -> -0.73972603 | BT47: =($T16-$S16)*(BT$38-$S$7)/($T$7-$S$7)+$S16 -> -0.73972603 | BU47: =($T16-$S16)*(BU$38-$S$7)/($T$7-$S$7)+$S16 -> -0.73972603 | BV47: =($T16-$S16)*(BV$38-$S$7)/($T$7-$S$7)+$S16 -> -0.73972603 | BW47: =($T16-$S16)*(BW$38-$S$7)/($T$7-$S$7)+$S16 -> -0.73972603 | BX47: =($T16-$S16)*(BX$38-$S$7)/($T$7-$S$7)+$S16 -> -0.73972603 | BY47: =($T16-$S16)*(BY$38-$S$7)/($T$7-$S$7)+$S16 -> -0.73972603 | ... CF47: =($T16-$S16)*(CF$38-$S$7)/($T$7-$S$7)+$S16 -> -0.73972603
B48: Impact on quantity produced (% of yearly output) without project | D48: =($E17-$D17)*(D$38-$D$7)/($E$7-$D$7)+$D17 -> 0 | E48: =($E17-$D17)*(E$38-$D$7)/($E$7-$D$7)+$D17 -> 0 | F48: =($E17-$D17)*(F$38-$D$7)/($E$7-$D$7)+$D17 -> 0 | G48: =($E17-$D17)*(G$38-$D$7)/($E$7-$D$7)+$D17 -> 0 | H48: =($E17-$D17)*(H$38-$D$7)/($E$7-$D$7)+$D17 -> 0 | I48: =($E17-$D17)*(I$38-$D$7)/($E$7-$D$7)+$D17 -> 0 | J48: =($E17-$D17)*(J$38-$D$7)/($E$7-$D$7)+$D17 -> 0 | K48: =($E17-$D17)*(K$38-$D$7)/($E$7-$D$7)+$D17 -> 0 | ... M48: =($E17-$D17)*(M$38-$D$7)/($E$7-$D$7)+$D17 -> 0 | N48: =($F17-$E17)*(N$38-$E$7)/($F$7-$E$7)+$E17 -> 0 | O48: =($F17-$E17)*(O$38-$E$7)/($F$7-$E$7)+$E17 -> 0 | P48: =($F17-$E17)*(P$38-$E$7)/($F$7-$E$7)+$E17 -> 0 | Q48: =($F17-$E17)*(Q$38-$E$7)/($F$7-$E$7)+$E17 -> 0 | R48: =($F17-$E17)*(R$38-$E$7)/($F$7-$E$7)+$E17 -> 0 | S48: =($F17-$E17)*(S$38-$E$7)/($F$7-$E$7)+$E17 -> 0 | T48: =($F17-$E17)*(T$38-$E$7)/($F$7-$E$7)+$E17 -> 0 | U48: =($F17-$E17)*(U$38-$E$7)/($F$7-$E$7)+$E17 -> 0 | ... AB48: =($F17-$E17)*(AB$38-$E$7)/($F$7-$E$7)+$E17 -> 0 | AD48: Impact on quantity produced (% of yearly output) without project | AF48: =($L17-$K17)*(AF$38-$K$7)/($L$7-$K$7)+$K17 -> -0.73972603 | AG48: =($L17-$K17)*(AG$38-$K$7)/($L$7-$K$7)+$K17 -> -0.73972603 | AH48: =($L17-$K17)*(AH$38-$K$7)/($L$7-$K$7)+$K17 -> -0.73972603 | AI48: =($L17-$K17)*(AI$38-$K$7)/($L$7-$K$7)+$K17 -> -0.73972603 | AJ48: =($L17-$K17)*(AJ$38-$K$7)/($L$7-$K$7)+$K17 -> -0.73972603 | AK48: =($L17-$K17)*(AK$38-$K$7)/($L$7-$K$7)+$K17 -> -0.73972603 | AL48: =($L17-$K17)*(AL$38-$K$7)/($L$7-$K$7)+$K17 -> -0.73972603 | AM48: =($L17-$K17)*(AM$38-$K$7)/($L$7-$K$7)+$K17 -> -0.73972603 | ... BD48: =($L17-$K17)*(BD$38-$K$7)/($L$7-$K$7)+$K17 -> -0.73972603 | BF48: Impact on quantity produced (% of yearly output) without project | BH48: =($S17-$R17)*(BH$38-$R$7)/($S$7-$R$7)+$R17 -> -60.438396 | BI48: =($S17-$R17)*(BI$38-$R$7)/($S$7-$R$7)+$R17 -> -0.8630137 | BJ48: =($S17-$R17)*(BJ$38-$R$7)/($S$7-$R$7)+$R17 -> 58.712369 | BK48: =($S17-$R17)*(BK$38-$R$7)/($S$7-$R$7)+$R17 -> 118.28775 | BL48: =($S17-$R17)*(BL$38-$R$7)/($S$7-$R$7)+$R17 -> 177.86313 | BM48: =($S17-$R17)*(BM$38-$R$7)/($S$7-$R$7)+$R17 -> 237.43852 | BN48: =($S17-$R17)*(BN$38-$R$7)/($S$7-$R$7)+$R17 -> 297.0139 | BO48: =($S17-$R17)*(BO$38-$R$7)/($S$7-$R$7)+$R17 -> 356.58928 | ... BQ48: =($S17-$R17)*(BQ$38-$R$7)/($S$7-$R$7)+$R17 -> 475.74005 | BR48: =($T17-$S17)*(BR$38-$S$7)/($T$7-$S$7)+$S17 -> 594.89081 | BS48: =($T17-$S17)*(BS$38-$S$7)/($T$7-$S$7)+$S17 -> 594.89081 | BT48: =($T17-$S17)*(BT$38-$S$7)/($T$7-$S$7)+$S17 -> 594.89081 | BU48: =($T17-$S17)*(BU$38-$S$7)/($T$7-$S$7)+$S17 -> 594.89081 | BV48: =($T17-$S17)*(BV$38-$S$7)/($T$7-$S$7)+$S17 -> 594.89081 | BW48: =($T17-$S17)*(BW$38-$S$7)/($T$7-$S$7)+$S17 -> 594.89081 | BX48: =($T17-$S17)*(BX$38-$S$7)/($T$7-$S$7)+$S17 -> 594.89081 | BY48: =($T17-$S17)*(BY$38-$S$7)/($T$7-$S$7)+$S17 -> 594.89081 | ... CF48: =($T17-$S17)*(CF$38-$S$7)/($T$7-$S$7)+$S17 -> 594.89081
B49: Repair/Reconstruction cost (CAPEX) (in absolute terms) | D49: =($E18-$D18)*(D$38-$D$7)/($E$7-$D$7)+$D18 -> 0 | E49: =($E18-$D18)*(E$38-$D$7)/($E$7-$D$7)+$D18 -> 0 | F49: =($E18-$D18)*(F$38-$D$7)/($E$7-$D$7)+$D18 -> 0 | G49: =($E18-$D18)*(G$38-$D$7)/($E$7-$D$7)+$D18 -> 0 | H49: =($E18-$D18)*(H$38-$D$7)/($E$7-$D$7)+$D18 -> 0 | I49: =($E18-$D18)*(I$38-$D$7)/($E$7-$D$7)+$D18 -> 0 | J49: =($E18-$D18)*(J$38-$D$7)/($E$7-$D$7)+$D18 -> 0 | K49: =($E18-$D18)*(K$38-$D$7)/($E$7-$D$7)+$D18 -> 0 | ... M49: =($E18-$D18)*(M$38-$D$7)/($E$7-$D$7)+$D18 -> 0 | N49: =($F18-$E18)*(N$38-$E$7)/($F$7-$E$7)+$E18 -> 0 | O49: =($F18-$E18)*(O$38-$E$7)/($F$7-$E$7)+$E18 -> 0 | P49: =($F18-$E18)*(P$38-$E$7)/($F$7-$E$7)+$E18 -> 0 | Q49: =($F18-$E18)*(Q$38-$E$7)/($F$7-$E$7)+$E18 -> 0 | R49: =($F18-$E18)*(R$38-$E$7)/($F$7-$E$7)+$E18 -> 0 | S49: =($F18-$E18)*(S$38-$E$7)/($F$7-$E$7)+$E18 -> 0 | T49: =($F18-$E18)*(T$38-$E$7)/($F$7-$E$7)+$E18 -> 0 | U49: =($F18-$E18)*(U$38-$E$7)/($F$7-$E$7)+$E18 -> 0 | ... AB49: =($F18-$E18)*(AB$38-$E$7)/($F$7-$E$7)+$E18 -> 0 | AD49: Repair/Reconstruction cost (CAPEX) (in absolute terms) | AF49: =($L18-$K18)*(AF$38-$K$7)/($L$7-$K$7)+$K18 -> 594.89081 | AG49: =($L18-$K18)*(AG$38-$K$7)/($L$7-$K$7)+$K18 -> 594.89081 | AH49: =($L18-$K18)*(AH$38-$K$7)/($L$7-$K$7)+$K18 -> 594.89081 | AI49: =($L18-$K18)*(AI$38-$K$7)/($L$7-$K$7)+$K18 -> 594.89081 | AJ49: =($L18-$K18)*(AJ$38-$K$7)/($L$7-$K$7)+$K18 -> 594.89081 | AK49: =($L18-$K18)*(AK$38-$K$7)/($L$7-$K$7)+$K18 -> 594.89081 | AL49: =($L18-$K18)*(AL$38-$K$7)/($L$7-$K$7)+$K18 -> 594.89081 | AM49: =($L18-$K18)*(AM$38-$K$7)/($L$7-$K$7)+$K18 -> 594.89081 | ... BD49: =($L18-$K18)*(BD$38-$K$7)/($L$7-$K$7)+$K18 -> 594.89081 | BF49: Repair/Reconstruction cost (CAPEX) (in absolute terms) | BH49: =($S18-$R18)*(BH$38-$R$7)/($S$7-$R$7)+$R18 -> 594.89081 | BI49: =($S18-$R18)*(BI$38-$R$7)/($S$7-$R$7)+$R18 -> 594.89081 | BJ49: =($S18-$R18)*(BJ$38-$R$7)/($S$7-$R$7)+$R18 -> 594.89081 | BK49: =($S18-$R18)*(BK$38-$R$7)/($S$7-$R$7)+$R18 -> 594.89081 | BL49: =($S18-$R18)*(BL$38-$R$7)/($S$7-$R$7)+$R18 -> 594.89081 | BM49: =($S18-$R18)*(BM$38-$R$7)/($S$7-$R$7)+$R18 -> 594.89081 | BN49: =($S18-$R18)*(BN$38-$R$7)/($S$7-$R$7)+$R18 -> 594.89081 | BO49: =($S18-$R18)*(BO$38-$R$7)/($S$7-$R$7)+$R18 -> 594.89081 | ... BQ49: =($S18-$R18)*(BQ$38-$R$7)/($S$7-$R$7)+$R18 -> 594.89081 | BR49: =($T18-$S18)*(BR$38-$S$7)/($T$7-$S$7)+$S18 -> 594.89081 | BS49: =($T18-$S18)*(BS$38-$S$7)/($T$7-$S$7)+$S18 -> 594.89081 | BT49: =($T18-$S18)*(BT$38-$S$7)/($T$7-$S$7)+$S18 -> 594.89081 | BU49: =($T18-$S18)*(BU$38-$S$7)/($T$7-$S$7)+$S18 -> 594.89081 | BV49: =($T18-$S18)*(BV$38-$S$7)/($T$7-$S$7)+$S18 -> 594.89081 | BW49: =($T18-$S18)*(BW$38-$S$7)/($T$7-$S$7)+$S18 -> 594.89081 | BX49: =($T18-$S18)*(BX$38-$S$7)/($T$7-$S$7)+$S18 -> 594.89081 | BY49: =($T18-$S18)*(BY$38-$S$7)/($T$7-$S$7)+$S18 -> 594.89081 | ... CF49: =($T18-$S18)*(CF$38-$S$7)/($T$7-$S$7)+$S18 -> 594.89081
B50: Additional out-of-system impacts (in absolute terms) | D50: =($E19-$D19)*(D$38-$D$7)/($E$7-$D$7)+$D19 -> 0 | E50: =($E19-$D19)*(E$38-$D$7)/($E$7-$D$7)+$D19 -> 0 | F50: =($E19-$D19)*(F$38-$D$7)/($E$7-$D$7)+$D19 -> 0 | G50: =($E19-$D19)*(G$38-$D$7)/($E$7-$D$7)+$D19 -> 0 | H50: =($E19-$D19)*(H$38-$D$7)/($E$7-$D$7)+$D19 -> 0 | I50: =($E19-$D19)*(I$38-$D$7)/($E$7-$D$7)+$D19 -> 0 | J50: =($E19-$D19)*(J$38-$D$7)/($E$7-$D$7)+$D19 -> 0 | K50: =($E19-$D19)*(K$38-$D$7)/($E$7-$D$7)+$D19 -> 0 | ... M50: =($E19-$D19)*(M$38-$D$7)/($E$7-$D$7)+$D19 -> 0 | N50: =($F19-$E19)*(N$38-$E$7)/($F$7-$E$7)+$E19 -> 0 | O50: =($F19-$E19)*(O$38-$E$7)/($F$7-$E$7)+$E19 -> 0 | P50: =($F19-$E19)*(P$38-$E$7)/($F$7-$E$7)+$E19 -> 0 | Q50: =($F19-$E19)*(Q$38-$E$7)/($F$7-$E$7)+$E19 -> 0 | R50: =($F19-$E19)*(R$38-$E$7)/($F$7-$E$7)+$E19 -> 0 | S50: =($F19-$E19)*(S$38-$E$7)/($F$7-$E$7)+$E19 -> 0 | T50: =($F19-$E19)*(T$38-$E$7)/($F$7-$E$7)+$E19 -> 0 | U50: =($F19-$E19)*(U$38-$E$7)/($F$7-$E$7)+$E19 -> 0 | ... AB50: =($F19-$E19)*(AB$38-$E$7)/($F$7-$E$7)+$E19 -> 0 | AD50: Additional out-of-system impacts (in absolute terms) | AF50: =($L19-$K19)*(AF$38-$K$7)/($L$7-$K$7)+$K19 -> 0 | AG50: =($L19-$K19)*(AG$38-$K$7)/($L$7-$K$7)+$K19 -> 0 | AH50: =($L19-$K19)*(AH$38-$K$7)/($L$7-$K$7)+$K19 -> 0 | AI50: =($L19-$K19)*(AI$38-$K$7)/($L$7-$K$7)+$K19 -> 0 | AJ50: =($L19-$K19)*(AJ$38-$K$7)/($L$7-$K$7)+$K19 -> 0 | AK50: =($L19-$K19)*(AK$38-$K$7)/($L$7-$K$7)+$K19 -> 0 | AL50: =($L19-$K19)*(AL$38-$K$7)/($L$7-$K$7)+$K19 -> 0 | AM50: =($L19-$K19)*(AM$38-$K$7)/($L$7-$K$7)+$K19 -> 0 | ... BD50: =($L19-$K19)*(BD$38-$K$7)/($L$7-$K$7)+$K19 -> 0 | BF50: Additional out-of-system impacts (in absolute terms) | BH50: =($S19-$R19)*(BH$38-$R$7)/($S$7-$R$7)+$R19 -> 0 | BI50: =($S19-$R19)*(BI$38-$R$7)/($S$7-$R$7)+$R19 -> 0 | BJ50: =($S19-$R19)*(BJ$38-$R$7)/($S$7-$R$7)+$R19 -> 0 | BK50: =($S19-$R19)*(BK$38-$R$7)/($S$7-$R$7)+$R19 -> 0 | BL50: =($S19-$R19)*(BL$38-$R$7)/($S$7-$R$7)+$R19 -> 0 | BM50: =($S19-$R19)*(BM$38-$R$7)/($S$7-$R$7)+$R19 -> 0 | BN50: =($S19-$R19)*(BN$38-$R$7)/($S$7-$R$7)+$R19 -> 0 | BO50: =($S19-$R19)*(BO$38-$R$7)/($S$7-$R$7)+$R19 -> 0 | ... BQ50: =($S19-$R19)*(BQ$38-$R$7)/($S$7-$R$7)+$R19 -> 0 | BR50: =($T19-$S19)*(BR$38-$S$7)/($T$7-$S$7)+$S19 -> 0 | BS50: =($T19-$S19)*(BS$38-$S$7)/($T$7-$S$7)+$S19 -> 0 | BT50: =($T19-$S19)*(BT$38-$S$7)/($T$7-$S$7)+$S19 -> 0 | BU50: =($T19-$S19)*(BU$38-$S$7)/($T$7-$S$7)+$S19 -> 0 | BV50: =($T19-$S19)*(BV$38-$S$7)/($T$7-$S$7)+$S19 -> 0 | BW50: =($T19-$S19)*(BW$38-$S$7)/($T$7-$S$7)+$S19 -> 0 | BX50: =($T19-$S19)*(BX$38-$S$7)/($T$7-$S$7)+$S19 -> 0 | BY50: =($T19-$S19)*(BY$38-$S$7)/($T$7-$S$7)+$S19 -> 0 | ... CF50: =($T19-$S19)*(CF$38-$S$7)/($T$7-$S$7)+$S19 -> 0
B51: Once every 100 years | AD51: Once every 100 years | BF51: Once every 100 years
B52: Probability of occurence (in %) | D52: =(1/$E21-1/$D21)*(D$38-$D$7)/($E$7-$D$7)+1/$D21 -> 0.010833333 | E52: =(1/$E21-1/$D21)*(E$38-$D$7)/($E$7-$D$7)+1/$D21 -> 0.011666667 | F52: =(1/$E21-1/$D21)*(F$38-$D$7)/($E$7-$D$7)+1/$D21 -> 0.0125 | G52: =(1/$E21-1/$D21)*(G$38-$D$7)/($E$7-$D$7)+1/$D21 -> 0.013333333 | H52: =(1/$E21-1/$D21)*(H$38-$D$7)/($E$7-$D$7)+1/$D21 -> 0.014166667 | I52: =(1/$E21-1/$D21)*(I$38-$D$7)/($E$7-$D$7)+1/$D21 -> 0.015 | J52: =(1/$E21-1/$D21)*(J$38-$D$7)/($E$7-$D$7)+1/$D21 -> 0.015833333 | K52: =(1/$E21-1/$D21)*(K$38-$D$7)/($E$7-$D$7)+1/$D21 -> 0.016666667 | ... M52: =(1/$E21-1/$D21)*(M$38-$D$7)/($E$7-$D$7)+1/$D21 -> 0.018333333 | N52: =(1/$F21-1/$E21)*(N$38-$E$7)/($F$7-$E$7)+1/$E21 -> 0.02 | O52: =(1/$F21-1/$E21)*(O$38-$E$7)/($F$7-$E$7)+1/$E21 -> 0.02 | P52: =(1/$F21-1/$E21)*(P$38-$E$7)/($F$7-$E$7)+1/$E21 -> 0.02 | Q52: =(1/$F21-1/$E21)*(Q$38-$E$7)/($F$7-$E$7)+1/$E21 -> 0.02 | R52: =(1/$F21-1/$E21)*(R$38-$E$7)/($F$7-$E$7)+1/$E21 -> 0.02 | S52: =(1/$F21-1/$E21)*(S$38-$E$7)/($F$7-$E$7)+1/$E21 -> 0.02 | T52: =(1/$F21-1/$E21)*(T$38-$E$7)/($F$7-$E$7)+1/$E21 -> 0.02 | U52: =(1/$F21-1/$E21)*(U$38-$E$7)/($F$7-$E$7)+1/$E21 -> 0.02 | ... AB52: =(1/$F21-1/$E21)*(AB$38-$E$7)/($F$7-$E$7)+1/$E21 -> 0.02 | AD52: Probability of occurence (in %) | AF52: =(1/$L21-1/$K21)*(AF$38-$K$7)/($L$7-$K$7)+1/$K21 -> 0.009 | AG52: =(1/$L21-1/$K21)*(AG$38-$K$7)/($L$7-$K$7)+1/$K21 -> 0.01 | AH52: =(1/$L21-1/$K21)*(AH$38-$K$7)/($L$7-$K$7)+1/$K21 -> 0.011 | AI52: =(1/$L21-1/$K21)*(AI$38-$K$7)/($L$7-$K$7)+1/$K21 -> 0.012 | AJ52: =(1/$L21-1/$K21)*(AJ$38-$K$7)/($L$7-$K$7)+1/$K21 -> 0.013 | AK52: =(1/$L21-1/$K21)*(AK$38-$K$7)/($L$7-$K$7)+1/$K21 -> 0.014 | AL52: =(1/$L21-1/$K21)*(AL$38-$K$7)/($L$7-$K$7)+1/$K21 -> 0.015 | AM52: =(1/$L21-1/$K21)*(AM$38-$K$7)/($L$7-$K$7)+1/$K21 -> 0.016 | ... AO52: =(1/$L21-1/$K21)*(AO$38-$K$7)/($L$7-$K$7)+1/$K21 -> 0.018 | AP52: =(1/$M21-1/$L21)*(AP$38-$L$7)/($M$7-$L$7)+1/$L21 -> 0.02 | AQ52: =(1/$M21-1/$L21)*(AQ$38-$L$7)/($M$7-$L$7)+1/$L21 -> 0.02 | AR52: =(1/$M21-1/$L21)*(AR$38-$L$7)/($M$7-$L$7)+1/$L21 -> 0.02 | AS52: =(1/$M21-1/$L21)*(AS$38-$L$7)/($M$7-$L$7)+1/$L21 -> 0.02 | AT52: =(1/$M21-1/$L21)*(AT$38-$L$7)/($M$7-$L$7)+1/$L21 -> 0.02 | AU52: =(1/$M21-1/$L21)*(AU$38-$L$7)/($M$7-$L$7)+1/$L21 -> 0.02 | AV52: =(1/$M21-1/$L21)*(AV$38-$L$7)/($M$7-$L$7)+1/$L21 -> 0.02 | AW52: =(1/$M21-1/$L21)*(AW$38-$L$7)/($M$7-$L$7)+1/$L21 -> 0.02 | ... BD52: =(1/$M21-1/$L21)*(BD$38-$L$7)/($M$7-$L$7)+1/$L21 -> 0.02 | BF52: Probability of occurence (in %) | BH52: =(1/$S21-1/$R21)*(BH$38-$R$7)/($S$7-$R$7)+1/$R21 -> 0.009 | BI52: =(1/$S21-1/$R21)*(BI$38-$R$7)/($S$7-$R$7)+1/$R21 -> 0.01 | BJ52: =(1/$S21-1/$R21)*(BJ$38-$R$7)/($S$7-$R$7)+1/$R21 -> 0.011 | BK52: =(1/$S21-1/$R21)*(BK$38-$R$7)/($S$7-$R$7)+1/$R21 -> 0.012 | BL52: =(1/$S21-1/$R21)*(BL$38-$R$7)/($S$7-$R$7)+1/$R21 -> 0.013 | BM52: =(1/$S21-1/$R21)*(BM$38-$R$7)/($S$7-$R$7)+1/$R21 -> 0.014 | BN52: =(1/$S21-1/$R21)*(BN$38-$R$7)/($S$7-$R$7)+1/$R21 -> 0.015 | BO52: =(1/$S21-1/$R21)*(BO$38-$R$7)/($S$7-$R$7)+1/$R21 -> 0.016 | ... BQ52: =(1/$S21-1/$R21)*(BQ$38-$R$7)/($S$7-$R$7)+1/$R21 -> 0.018 | BR52: =(1/$T21-1/$S21)*(BR$38-$S$7)/($T$7-$S$7)+1/$S21 -> 0.02 | BS52: =(1/$T21-1/$S21)*(BS$38-$S$7)/($T$7-$S$7)+1/$S21 -> 0.02 | BT52: =(1/$T21-1/$S21)*(BT$38-$S$7)/($T$7-$S$7)+1/$S21 -> 0.02 | BU52: =(1/$T21-1/$S21)*(BU$38-$S$7)/($T$7-$S$7)+1/$S21 -> 0.02 | BV52: =(1/$T21-1/$S21)*(BV$38-$S$7)/($T$7-$S$7)+1/$S21 -> 0.02 | BW52: =(1/$T21-1/$S21)*(BW$38-$S$7)/($T$7-$S$7)+1/$S21 -> 0.02 | BX52: =(1/$T21-1/$S21)*(BX$38-$S$7)/($T$7-$S$7)+1/$S21 -> 0.02 | BY52: =(1/$T21-1/$S21)*(BY$38-$S$7)/($T$7-$S$7)+1/$S21 -> 0.02 | ... CF52: =(1/$T21-1/$S21)*(CF$38-$S$7)/($T$7-$S$7)+1/$S21 -> 0.02
B53: Impact on quantity produced (% of yearly output) | D53: =($E22-$D22)*(D$38-$D$7)/($E$7-$D$7)+$D22 -> 0 | E53: =($E22-$D22)*(E$38-$D$7)/($E$7-$D$7)+$D22 -> 0 | F53: =($E22-$D22)*(F$38-$D$7)/($E$7-$D$7)+$D22 -> 0 | G53: =($E22-$D22)*(G$38-$D$7)/($E$7-$D$7)+$D22 -> 0 | H53: =($E22-$D22)*(H$38-$D$7)/($E$7-$D$7)+$D22 -> 0 | I53: =($E22-$D22)*(I$38-$D$7)/($E$7-$D$7)+$D22 -> 0 | J53: =($E22-$D22)*(J$38-$D$7)/($E$7-$D$7)+$D22 -> 0 | K53: =($E22-$D22)*(K$38-$D$7)/($E$7-$D$7)+$D22 -> 0 | ... M53: =($E22-$D22)*(M$38-$D$7)/($E$7-$D$7)+$D22 -> 0 | N53: =($F22-$E22)*(N$38-$E$7)/($F$7-$E$7)+$E22 -> 0 | O53: =($F22-$E22)*(O$38-$E$7)/($F$7-$E$7)+$E22 -> 0 | P53: =($F22-$E22)*(P$38-$E$7)/($F$7-$E$7)+$E22 -> 0 | Q53: =($F22-$E22)*(Q$38-$E$7)/($F$7-$E$7)+$E22 -> 0 | R53: =($F22-$E22)*(R$38-$E$7)/($F$7-$E$7)+$E22 -> 0 | S53: =($F22-$E22)*(S$38-$E$7)/($F$7-$E$7)+$E22 -> 0 | T53: =($F22-$E22)*(T$38-$E$7)/($F$7-$E$7)+$E22 -> 0 | U53: =($F22-$E22)*(U$38-$E$7)/($F$7-$E$7)+$E22 -> 0 | ... AB53: =($F22-$E22)*(AB$38-$E$7)/($F$7-$E$7)+$E22 -> 0 | AD53: Impact on quantity produced (% of yearly output) | AF53: =($L22-$K22)*(AF$38-$K$7)/($L$7-$K$7)+$K22 -> -0.19726027 | AG53: =($L22-$K22)*(AG$38-$K$7)/($L$7-$K$7)+$K22 -> -0.19726027 | AH53: =($L22-$K22)*(AH$38-$K$7)/($L$7-$K$7)+$K22 -> -0.19726027 | AI53: =($L22-$K22)*(AI$38-$K$7)/($L$7-$K$7)+$K22 -> -0.19726027 | AJ53: =($L22-$K22)*(AJ$38-$K$7)/($L$7-$K$7)+$K22 -> -0.19726027 | AK53: =($L22-$K22)*(AK$38-$K$7)/($L$7-$K$7)+$K22 -> -0.19726027 | AL53: =($L22-$K22)*(AL$38-$K$7)/($L$7-$K$7)+$K22 -> -0.19726027 | AM53: =($L22-$K22)*(AM$38-$K$7)/($L$7-$K$7)+$K22 -> -0.19726027 | ... AO53: =($L22-$K22)*(AO$38-$K$7)/($L$7-$K$7)+$K22 -> -0.19726027 | AP53: =($M22-$L22)*(AP$38-$L$7)/($M$7-$L$7)+$L22 -> -0.19726027 | AQ53: =($M22-$L22)*(AQ$38-$L$7)/($M$7-$L$7)+$L22 -> -0.19726027 | AR53: =($M22-$L22)*(AR$38-$L$7)/($M$7-$L$7)+$L22 -> -0.19726027 | AS53: =($M22-$L22)*(AS$38-$L$7)/($M$7-$L$7)+$L22 -> -0.19726027 | AT53: =($M22-$L22)*(AT$38-$L$7)/($M$7-$L$7)+$L22 -> -0.19726027 | AU53: =($M22-$L22)*(AU$38-$L$7)/($M$7-$L$7)+$L22 -> -0.19726027 | AV53: =($M22-$L22)*(AV$38-$L$7)/($M$7-$L$7)+$L22 -> -0.19726027 | AW53: =($M22-$L22)*(AW$38-$L$7)/($M$7-$L$7)+$L22 -> -0.19726027 | ... BD53: =($M22-$L22)*(BD$38-$L$7)/($M$7-$L$7)+$L22 -> -0.19726027 | BF53: Impact on quantity produced (% of yearly output) | BH53: =($S22-$R22)*(BH$38-$R$7)/($S$7-$R$7)+$R22 -> -0.29589041 | BI53: =($S22-$R22)*(BI$38-$R$7)/($S$7-$R$7)+$R22 -> -0.29589041 | BJ53: =($S22-$R22)*(BJ$38-$R$7)/($S$7-$R$7)+$R22 -> -0.29589041 | BK53: =($S22-$R22)*(BK$38-$R$7)/($S$7-$R$7)+$R22 -> -0.29589041 | BL53: =($S22-$R22)*(BL$38-$R$7)/($S$7-$R$7)+$R22 -> -0.29589041 | BM53: =($S22-$R22)*(BM$38-$R$7)/($S$7-$R$7)+$R22 -> -0.29589041 | BN53: =($S22-$R22)*(BN$38-$R$7)/($S$7-$R$7)+$R22 -> -0.29589041 | BO53: =($S22-$R22)*(BO$38-$R$7)/($S$7-$R$7)+$R22 -> -0.29589041 | ... BQ53: =($S22-$R22)*(BQ$38-$R$7)/($S$7-$R$7)+$R22 -> -0.29589041 | BR53: =($T22-$S22)*(BR$38-$S$7)/($T$7-$S$7)+$S22 -> -0.29589041 | BS53: =($T22-$S22)*(BS$38-$S$7)/($T$7-$S$7)+$S22 -> -0.29589041 | BT53: =($T22-$S22)*(BT$38-$S$7)/($T$7-$S$7)+$S22 -> -0.29589041 | BU53: =($T22-$S22)*(BU$38-$S$7)/($T$7-$S$7)+$S22 -> -0.29589041 | BV53: =($T22-$S22)*(BV$38-$S$7)/($T$7-$S$7)+$S22 -> -0.29589041 | BW53: =($T22-$S22)*(BW$38-$S$7)/($T$7-$S$7)+$S22 -> -0.29589041 | BX53: =($T22-$S22)*(BX$38-$S$7)/($T$7-$S$7)+$S22 -> -0.29589041 | BY53: =($T22-$S22)*(BY$38-$S$7)/($T$7-$S$7)+$S22 -> -0.29589041 | ... CF53: =($T22-$S22)*(CF$38-$S$7)/($T$7-$S$7)+$S22 -> -0.29589041
B54: Impact on quantity produced (% of yearly output) without project | D54: =($E23-$D23)*(D$38-$D$7)/($E$7-$D$7)+$D23 -> 0 | E54: =($E23-$D23)*(E$38-$D$7)/($E$7-$D$7)+$D23 -> 0 | F54: =($E23-$D23)*(F$38-$D$7)/($E$7-$D$7)+$D23 -> 0 | G54: =($E23-$D23)*(G$38-$D$7)/($E$7-$D$7)+$D23 -> 0 | H54: =($E23-$D23)*(H$38-$D$7)/($E$7-$D$7)+$D23 -> 0 | I54: =($E23-$D23)*(I$38-$D$7)/($E$7-$D$7)+$D23 -> 0 | J54: =($E23-$D23)*(J$38-$D$7)/($E$7-$D$7)+$D23 -> 0 | K54: =($E23-$D23)*(K$38-$D$7)/($E$7-$D$7)+$D23 -> 0 | ... M54: =($E23-$D23)*(M$38-$D$7)/($E$7-$D$7)+$D23 -> 0 | N54: =($F23-$E23)*(N$38-$E$7)/($F$7-$E$7)+$E23 -> 0 | O54: =($F23-$E23)*(O$38-$E$7)/($F$7-$E$7)+$E23 -> 0 | P54: =($F23-$E23)*(P$38-$E$7)/($F$7-$E$7)+$E23 -> 0 | Q54: =($F23-$E23)*(Q$38-$E$7)/($F$7-$E$7)+$E23 -> 0 | R54: =($F23-$E23)*(R$38-$E$7)/($F$7-$E$7)+$E23 -> 0 | S54: =($F23-$E23)*(S$38-$E$7)/($F$7-$E$7)+$E23 -> 0 | T54: =($F23-$E23)*(T$38-$E$7)/($F$7-$E$7)+$E23 -> 0 | U54: =($F23-$E23)*(U$38-$E$7)/($F$7-$E$7)+$E23 -> 0 | ... AB54: =($F23-$E23)*(AB$38-$E$7)/($F$7-$E$7)+$E23 -> 0 | AD54: Impact on quantity produced (% of yearly output) without project | AF54: =($L23-$K23)*(AF$38-$K$7)/($L$7-$K$7)+$K23 -> -0.29589041 | AG54: =($L23-$K23)*(AG$38-$K$7)/($L$7-$K$7)+$K23 -> -0.29589041 | AH54: =($L23-$K23)*(AH$38-$K$7)/($L$7-$K$7)+$K23 -> -0.29589041 | AI54: =($L23-$K23)*(AI$38-$K$7)/($L$7-$K$7)+$K23 -> -0.29589041 | AJ54: =($L23-$K23)*(AJ$38-$K$7)/($L$7-$K$7)+$K23 -> -0.29589041 | AK54: =($L23-$K23)*(AK$38-$K$7)/($L$7-$K$7)+$K23 -> -0.29589041 | AL54: =($L23-$K23)*(AL$38-$K$7)/($L$7-$K$7)+$K23 -> -0.29589041 | AM54: =($L23-$K23)*(AM$38-$K$7)/($L$7-$K$7)+$K23 -> -0.29589041 | ... AO54: =($L23-$K23)*(AO$38-$K$7)/($L$7-$K$7)+$K23 -> -0.29589041 | AP54: =($M23-$L23)*(AP$38-$L$7)/($M$7-$L$7)+$L23 -> -0.29589041 | AQ54: =($M23-$L23)*(AQ$38-$L$7)/($M$7-$L$7)+$L23 -> -0.29589041 | AR54: =($M23-$L23)*(AR$38-$L$7)/($M$7-$L$7)+$L23 -> -0.29589041 | AS54: =($M23-$L23)*(AS$38-$L$7)/($M$7-$L$7)+$L23 -> -0.29589041 | AT54: =($M23-$L23)*(AT$38-$L$7)/($M$7-$L$7)+$L23 -> -0.29589041 | AU54: =($M23-$L23)*(AU$38-$L$7)/($M$7-$L$7)+$L23 -> -0.29589041 | AV54: =($M23-$L23)*(AV$38-$L$7)/($M$7-$L$7)+$L23 -> -0.29589041 | AW54: =($M23-$L23)*(AW$38-$L$7)/($M$7-$L$7)+$L23 -> -0.29589041 | ... BD54: =($M23-$L23)*(BD$38-$L$7)/($M$7-$L$7)+$L23 -> -0.29589041 | BF54: Impact on quantity produced (% of yearly output) without project | BH54: =($S23-$R23)*(BH$38-$R$7)/($S$7-$R$7)+$R23 -> -104.4585 | BI54: =($S23-$R23)*(BI$38-$R$7)/($S$7-$R$7)+$R23 -> -0.32054795 | BJ54: =($S23-$R23)*(BJ$38-$R$7)/($S$7-$R$7)+$R23 -> 103.8174 | BK54: =($S23-$R23)*(BK$38-$R$7)/($S$7-$R$7)+$R23 -> 207.95535 | BL54: =($S23-$R23)*(BL$38-$R$7)/($S$7-$R$7)+$R23 -> 312.09329 | BM54: =($S23-$R23)*(BM$38-$R$7)/($S$7-$R$7)+$R23 -> 416.23124 | BN54: =($S23-$R23)*(BN$38-$R$7)/($S$7-$R$7)+$R23 -> 520.36919 | BO54: =($S23-$R23)*(BO$38-$R$7)/($S$7-$R$7)+$R23 -> 624.50714 | ... BQ54: =($S23-$R23)*(BQ$38-$R$7)/($S$7-$R$7)+$R23 -> 832.78303 | BR54: =($T23-$S23)*(BR$38-$S$7)/($T$7-$S$7)+$S23 -> 1041.0589 | BS54: =($T23-$S23)*(BS$38-$S$7)/($T$7-$S$7)+$S23 -> 1041.0589 | BT54: =($T23-$S23)*(BT$38-$S$7)/($T$7-$S$7)+$S23 -> 1041.0589 | BU54: =($T23-$S23)*(BU$38-$S$7)/($T$7-$S$7)+$S23 -> 1041.0589 | BV54: =($T23-$S23)*(BV$38-$S$7)/($T$7-$S$7)+$S23 -> 1041.0589 | BW54: =($T23-$S23)*(BW$38-$S$7)/($T$7-$S$7)+$S23 -> 1041.0589 | BX54: =($T23-$S23)*(BX$38-$S$7)/($T$7-$S$7)+$S23 -> 1041.0589 | BY54: =($T23-$S23)*(BY$38-$S$7)/($T$7-$S$7)+$S23 -> 1041.0589 | ... CF54: =($T23-$S23)*(CF$38-$S$7)/($T$7-$S$7)+$S23 -> 1041.0589
B55: Repair/Reconstruction cost (CAPEX) (in absolute terms) | D55: =($E24-$D24)*(D$38-$D$7)/($E$7-$D$7)+$D24 -> 0 | E55: =($E24-$D24)*(E$38-$D$7)/($E$7-$D$7)+$D24 -> 0 | F55: =($E24-$D24)*(F$38-$D$7)/($E$7-$D$7)+$D24 -> 0 | G55: =($E24-$D24)*(G$38-$D$7)/($E$7-$D$7)+$D24 -> 0 | H55: =($E24-$D24)*(H$38-$D$7)/($E$7-$D$7)+$D24 -> 0 | I55: =($E24-$D24)*(I$38-$D$7)/($E$7-$D$7)+$D24 -> 0 | J55: =($E24-$D24)*(J$38-$D$7)/($E$7-$D$7)+$D24 -> 0 | K55: =($E24-$D24)*(K$38-$D$7)/($E$7-$D$7)+$D24 -> 0 | ... M55: =($E24-$D24)*(M$38-$D$7)/($E$7-$D$7)+$D24 -> 0 | N55: =($F24-$E24)*(N$38-$E$7)/($F$7-$E$7)+$E24 -> 0 | O55: =($F24-$E24)*(O$38-$E$7)/($F$7-$E$7)+$E24 -> 0 | P55: =($F24-$E24)*(P$38-$E$7)/($F$7-$E$7)+$E24 -> 0 | Q55: =($F24-$E24)*(Q$38-$E$7)/($F$7-$E$7)+$E24 -> 0 | R55: =($F24-$E24)*(R$38-$E$7)/($F$7-$E$7)+$E24 -> 0 | S55: =($F24-$E24)*(S$38-$E$7)/($F$7-$E$7)+$E24 -> 0 | T55: =($F24-$E24)*(T$38-$E$7)/($F$7-$E$7)+$E24 -> 0 | U55: =($F24-$E24)*(U$38-$E$7)/($F$7-$E$7)+$E24 -> 0 | ... AB55: =($F24-$E24)*(AB$38-$E$7)/($F$7-$E$7)+$E24 -> 0 | AD55: Repair/Reconstruction cost (CAPEX) (in absolute terms) | AF55: =($L24-$K24)*(AF$38-$K$7)/($L$7-$K$7)+$K24 -> 1041.0589 | AG55: =($L24-$K24)*(AG$38-$K$7)/($L$7-$K$7)+$K24 -> 1041.0589 | AH55: =($L24-$K24)*(AH$38-$K$7)/($L$7-$K$7)+$K24 -> 1041.0589 | AI55: =($L24-$K24)*(AI$38-$K$7)/($L$7-$K$7)+$K24 -> 1041.0589 | AJ55: =($L24-$K24)*(AJ$38-$K$7)/($L$7-$K$7)+$K24 -> 1041.0589 | AK55: =($L24-$K24)*(AK$38-$K$7)/($L$7-$K$7)+$K24 -> 1041.0589 | AL55: =($L24-$K24)*(AL$38-$K$7)/($L$7-$K$7)+$K24 -> 1041.0589 | AM55: =($L24-$K24)*(AM$38-$K$7)/($L$7-$K$7)+$K24 -> 1041.0589 | ... AO55: =($L24-$K24)*(AO$38-$K$7)/($L$7-$K$7)+$K24 -> 1041.0589 | AP55: =($M24-$L24)*(AP$38-$L$7)/($M$7-$L$7)+$L24 -> 1041.0589 | AQ55: =($M24-$L24)*(AQ$38-$L$7)/($M$7-$L$7)+$L24 -> 1041.0589 | AR55: =($M24-$L24)*(AR$38-$L$7)/($M$7-$L$7)+$L24 -> 1041.0589 | AS55: =($M24-$L24)*(AS$38-$L$7)/($M$7-$L$7)+$L24 -> 1041.0589 | AT55: =($M24-$L24)*(AT$38-$L$7)/($M$7-$L$7)+$L24 -> 1041.0589 | AU55: =($M24-$L24)*(AU$38-$L$7)/($M$7-$L$7)+$L24 -> 1041.0589 | AV55: =($M24-$L24)*(AV$38-$L$7)/($M$7-$L$7)+$L24 -> 1041.0589 | AW55: =($M24-$L24)*(AW$38-$L$7)/($M$7-$L$7)+$L24 -> 1041.0589 | ... BD55: =($M24-$L24)*(BD$38-$L$7)/($M$7-$L$7)+$L24 -> 1041.0589 | BF55: Repair/Reconstruction cost (CAPEX) (in absolute terms) | BH55: =($S24-$R24)*(BH$38-$R$7)/($S$7-$R$7)+$R24 -> 1041.0589 | BI55: =($S24-$R24)*(BI$38-$R$7)/($S$7-$R$7)+$R24 -> 1041.0589 | BJ55: =($S24-$R24)*(BJ$38-$R$7)/($S$7-$R$7)+$R24 -> 1041.0589 | BK55: =($S24-$R24)*(BK$38-$R$7)/($S$7-$R$7)+$R24 -> 1041.0589 | BL55: =($S24-$R24)*(BL$38-$R$7)/($S$7-$R$7)+$R24 -> 1041.0589 | BM55: =($S24-$R24)*(BM$38-$R$7)/($S$7-$R$7)+$R24 -> 1041.0589 | BN55: =($S24-$R24)*(BN$38-$R$7)/($S$7-$R$7)+$R24 -> 1041.0589 | BO55: =($S24-$R24)*(BO$38-$R$7)/($S$7-$R$7)+$R24 -> 1041.0589 | ... BQ55: =($S24-$R24)*(BQ$38-$R$7)/($S$7-$R$7)+$R24 -> 1041.0589 | BR55: =($T24-$S24)*(BR$38-$S$7)/($T$7-$S$7)+$S24 -> 1041.0589 | BS55: =($T24-$S24)*(BS$38-$S$7)/($T$7-$S$7)+$S24 -> 1041.0589 | BT55: =($T24-$S24)*(BT$38-$S$7)/($T$7-$S$7)+$S24 -> 1041.0589 | BU55: =($T24-$S24)*(BU$38-$S$7)/($T$7-$S$7)+$S24 -> 1041.0589 | BV55: =($T24-$S24)*(BV$38-$S$7)/($T$7-$S$7)+$S24 -> 1041.0589 | BW55: =($T24-$S24)*(BW$38-$S$7)/($T$7-$S$7)+$S24 -> 1041.0589 | BX55: =($T24-$S24)*(BX$38-$S$7)/($T$7-$S$7)+$S24 -> 1041.0589 | BY55: =($T24-$S24)*(BY$38-$S$7)/($T$7-$S$7)+$S24 -> 1041.0589 | ... CF55: =($T24-$S24)*(CF$38-$S$7)/($T$7-$S$7)+$S24 -> 1041.0589
B56: Additional out-of-system impacts (in absolute terms) | D56: =($E25-$D25)*(D$38-$D$7)/($E$7-$D$7)+$D25 -> 0 | E56: =($E25-$D25)*(E$38-$D$7)/($E$7-$D$7)+$D25 -> 0 | F56: =($E25-$D25)*(F$38-$D$7)/($E$7-$D$7)+$D25 -> 0 | G56: =($E25-$D25)*(G$38-$D$7)/($E$7-$D$7)+$D25 -> 0 | H56: =($E25-$D25)*(H$38-$D$7)/($E$7-$D$7)+$D25 -> 0 | I56: =($E25-$D25)*(I$38-$D$7)/($E$7-$D$7)+$D25 -> 0 | J56: =($E25-$D25)*(J$38-$D$7)/($E$7-$D$7)+$D25 -> 0 | K56: =($E25-$D25)*(K$38-$D$7)/($E$7-$D$7)+$D25 -> 0 | ... M56: =($E25-$D25)*(M$38-$D$7)/($E$7-$D$7)+$D25 -> 0 | N56: =($F25-$E25)*(N$38-$E$7)/($F$7-$E$7)+$E25 -> 0 | O56: =($F25-$E25)*(O$38-$E$7)/($F$7-$E$7)+$E25 -> 0 | P56: =($F25-$E25)*(P$38-$E$7)/($F$7-$E$7)+$E25 -> 0 | Q56: =($F25-$E25)*(Q$38-$E$7)/($F$7-$E$7)+$E25 -> 0 | R56: =($F25-$E25)*(R$38-$E$7)/($F$7-$E$7)+$E25 -> 0 | S56: =($F25-$E25)*(S$38-$E$7)/($F$7-$E$7)+$E25 -> 0 | T56: =($F25-$E25)*(T$38-$E$7)/($F$7-$E$7)+$E25 -> 0 | U56: =($F25-$E25)*(U$38-$E$7)/($F$7-$E$7)+$E25 -> 0 | ... AB56: =($F25-$E25)*(AB$38-$E$7)/($F$7-$E$7)+$E25 -> 0 | AD56: Additional out-of-system impacts (in absolute terms) | AF56: =($L25-$K25)*(AF$38-$K$7)/($L$7-$K$7)+$K25 -> 0 | AG56: =($L25-$K25)*(AG$38-$K$7)/($L$7-$K$7)+$K25 -> 0 | AH56: =($L25-$K25)*(AH$38-$K$7)/($L$7-$K$7)+$K25 -> 0 | AI56: =($L25-$K25)*(AI$38-$K$7)/($L$7-$K$7)+$K25 -> 0 | AJ56: =($L25-$K25)*(AJ$38-$K$7)/($L$7-$K$7)+$K25 -> 0 | AK56: =($L25-$K25)*(AK$38-$K$7)/($L$7-$K$7)+$K25 -> 0 | AL56: =($L25-$K25)*(AL$38-$K$7)/($L$7-$K$7)+$K25 -> 0 | AM56: =($L25-$K25)*(AM$38-$K$7)/($L$7-$K$7)+$K25 -> 0 | ... AO56: =($L25-$K25)*(AO$38-$K$7)/($L$7-$K$7)+$K25 -> 0 | AP56: =($M25-$L25)*(AP$38-$L$7)/($M$7-$L$7)+$L25 -> 0 | AQ56: =($M25-$L25)*(AQ$38-$L$7)/($M$7-$L$7)+$L25 -> 0 | AR56: =($M25-$L25)*(AR$38-$L$7)/($M$7-$L$7)+$L25 -> 0 | AS56: =($M25-$L25)*(AS$38-$L$7)/($M$7-$L$7)+$L25 -> 0 | AT56: =($M25-$L25)*(AT$38-$L$7)/($M$7-$L$7)+$L25 -> 0 | AU56: =($M25-$L25)*(AU$38-$L$7)/($M$7-$L$7)+$L25 -> 0 | AV56: =($M25-$L25)*(AV$38-$L$7)/($M$7-$L$7)+$L25 -> 0 | AW56: =($M25-$L25)*(AW$38-$L$7)/($M$7-$L$7)+$L25 -> 0 | ... BD56: =($M25-$L25)*(BD$38-$L$7)/($M$7-$L$7)+$L25 -> 0 | BF56: Additional out-of-system impacts (in absolute terms) | BH56: =($S25-$R25)*(BH$38-$R$7)/($S$7-$R$7)+$R25 -> 0 | BI56: =($S25-$R25)*(BI$38-$R$7)/($S$7-$R$7)+$R25 -> 0 | BJ56: =($S25-$R25)*(BJ$38-$R$7)/($S$7-$R$7)+$R25 -> 0 | BK56: =($S25-$R25)*(BK$38-$R$7)/($S$7-$R$7)+$R25 -> 0 | BL56: =($S25-$R25)*(BL$38-$R$7)/($S$7-$R$7)+$R25 -> 0 | BM56: =($S25-$R25)*(BM$38-$R$7)/($S$7-$R$7)+$R25 -> 0 | BN56: =($S25-$R25)*(BN$38-$R$7)/($S$7-$R$7)+$R25 -> 0 | BO56: =($S25-$R25)*(BO$38-$R$7)/($S$7-$R$7)+$R25 -> 0 | ... BQ56: =($S25-$R25)*(BQ$38-$R$7)/($S$7-$R$7)+$R25 -> 0 | BR56: =($T25-$S25)*(BR$38-$S$7)/($T$7-$S$7)+$S25 -> 0 | BS56: =($T25-$S25)*(BS$38-$S$7)/($T$7-$S$7)+$S25 -> 0 | BT56: =($T25-$S25)*(BT$38-$S$7)/($T$7-$S$7)+$S25 -> 0 | BU56: =($T25-$S25)*(BU$38-$S$7)/($T$7-$S$7)+$S25 -> 0 | BV56: =($T25-$S25)*(BV$38-$S$7)/($T$7-$S$7)+$S25 -> 0 | BW56: =($T25-$S25)*(BW$38-$S$7)/($T$7-$S$7)+$S25 -> 0 | BX56: =($T25-$S25)*(BX$38-$S$7)/($T$7-$S$7)+$S25 -> 0 | BY56: =($T25-$S25)*(BY$38-$S$7)/($T$7-$S$7)+$S25 -> 0 | ... CF56: =($T25-$S25)*(CF$38-$S$7)/($T$7-$S$7)+$S25 -> 0
B57: Once every 1000 years | AD57: Once every 1000 years | BF57: Once every 1000 years
B58: Probability of occurence (in %) | D58: =(1/$E27-1/$D27)*(D$38-$D$7)/($E$7-$D$7)+1/$D27 -> 0.0010833333 | E58: =(1/$E27-1/$D27)*(E$38-$D$7)/($E$7-$D$7)+1/$D27 -> 0.0011666667 | F58: =(1/$E27-1/$D27)*(F$38-$D$7)/($E$7-$D$7)+1/$D27 -> 0.00125 | G58: =(1/$E27-1/$D27)*(G$38-$D$7)/($E$7-$D$7)+1/$D27 -> 0.0013333333 | H58: =(1/$E27-1/$D27)*(H$38-$D$7)/($E$7-$D$7)+1/$D27 -> 0.0014166667 | I58: =(1/$E27-1/$D27)*(I$38-$D$7)/($E$7-$D$7)+1/$D27 -> 0.0015 | J58: =(1/$E27-1/$D27)*(J$38-$D$7)/($E$7-$D$7)+1/$D27 -> 0.0015833333 | K58: =(1/$E27-1/$D27)*(K$38-$D$7)/($E$7-$D$7)+1/$D27 -> 0.0016666667 | ... M58: =(1/$E27-1/$D27)*(M$38-$D$7)/($E$7-$D$7)+1/$D27 -> 0.0018333333 | N58: =(1/$F27-1/$E27)*(N$38-$E$7)/($F$7-$E$7)+1/$E27 -> 0.002 | O58: =(1/$F27-1/$E27)*(O$38-$E$7)/($F$7-$E$7)+1/$E27 -> 0.002 | P58: =(1/$F27-1/$E27)*(P$38-$E$7)/($F$7-$E$7)+1/$E27 -> 0.002 | Q58: =(1/$F27-1/$E27)*(Q$38-$E$7)/($F$7-$E$7)+1/$E27 -> 0.002 | R58: =(1/$F27-1/$E27)*(R$38-$E$7)/($F$7-$E$7)+1/$E27 -> 0.002 | S58: =(1/$F27-1/$E27)*(S$38-$E$7)/($F$7-$E$7)+1/$E27 -> 0.002 | T58: =(1/$F27-1/$E27)*(T$38-$E$7)/($F$7-$E$7)+1/$E27 -> 0.002 | U58: =(1/$F27-1/$E27)*(U$38-$E$7)/($F$7-$E$7)+1/$E27 -> 0.002 | ... AB58: =(1/$F27-1/$E27)*(AB$38-$E$7)/($F$7-$E$7)+1/$E27 -> 0.002 | AD58: Probability of occurence (in %) | AF58: =(1/$L27-1/$K27)*(AF$38-$K$7)/($L$7-$K$7)+1/$K27 -> 0.0009 | AG58: =(1/$L27-1/$K27)*(AG$38-$K$7)/($L$7-$K$7)+1/$K27 -> 0.001 | AH58: =(1/$L27-1/$K27)*(AH$38-$K$7)/($L$7-$K$7)+1/$K27 -> 0.0011 | AI58: =(1/$L27-1/$K27)*(AI$38-$K$7)/($L$7-$K$7)+1/$K27 -> 0.0012 | AJ58: =(1/$L27-1/$K27)*(AJ$38-$K$7)/($L$7-$K$7)+1/$K27 -> 0.0013 | AK58: =(1/$L27-1/$K27)*(AK$38-$K$7)/($L$7-$K$7)+1/$K27 -> 0.0014 | AL58: =(1/$L27-1/$K27)*(AL$38-$K$7)/($L$7-$K$7)+1/$K27 -> 0.0015 | AM58: =(1/$L27-1/$K27)*(AM$38-$K$7)/($L$7-$K$7)+1/$K27 -> 0.0016 | ... AO58: =(1/$L27-1/$K27)*(AO$38-$K$7)/($L$7-$K$7)+1/$K27 -> 0.0018 | AP58: =(1/$M27-1/$L27)*(AP$38-$L$7)/($M$7-$L$7)+1/$L27 -> 0.002 | AQ58: =(1/$M27-1/$L27)*(AQ$38-$L$7)/($M$7-$L$7)+1/$L27 -> 0.002 | AR58: =(1/$M27-1/$L27)*(AR$38-$L$7)/($M$7-$L$7)+1/$L27 -> 0.002 | AS58: =(1/$M27-1/$L27)*(AS$38-$L$7)/($M$7-$L$7)+1/$L27 -> 0.002 | AT58: =(1/$M27-1/$L27)*(AT$38-$L$7)/($M$7-$L$7)+1/$L27 -> 0.002 | AU58: =(1/$M27-1/$L27)*(AU$38-$L$7)/($M$7-$L$7)+1/$L27 -> 0.002 | AV58: =(1/$M27-1/$L27)*(AV$38-$L$7)/($M$7-$L$7)+1/$L27 -> 0.002 | AW58: =(1/$M27-1/$L27)*(AW$38-$L$7)/($M$7-$L$7)+1/$L27 -> 0.002 | ... BD58: =(1/$M27-1/$L27)*(BD$38-$L$7)/($M$7-$L$7)+1/$L27 -> 0.002 | BF58: Probability of occurence (in %) | BH58: =(1/$S27-1/$R27)*(R$38-$R$7)/($S$7-$R$7)+1/$R27 -> 0.0023 | BI58: =(1/$S27-1/$R27)*(S$38-$R$7)/($S$7-$R$7)+1/$R27 -> 0.0024 | BJ58: =(1/$S27-1/$R27)*(T$38-$R$7)/($S$7-$R$7)+1/$R27 -> 0.0025 | BK58: =(1/$S27-1/$R27)*(U$38-$R$7)/($S$7-$R$7)+1/$R27 -> 0.0026 | BL58: =(1/$S27-1/$R27)*(V$38-$R$7)/($S$7-$R$7)+1/$R27 -> 0.0027 | BM58: =(1/$S27-1/$R27)*(W$38-$R$7)/($S$7-$R$7)+1/$R27 -> 0.0028 | BN58: =(1/$S27-1/$R27)*(X$38-$R$7)/($S$7-$R$7)+1/$R27 -> 0.0029 | BO58: =(1/$S27-1/$R27)*(Y$38-$R$7)/($S$7-$R$7)+1/$R27 -> 0.003 | ... BQ58: =(1/$S27-1/$R27)*(AA$38-$R$7)/($S$7-$R$7)+1/$R27 -> 0.0032 | BR58: =(1/$T27-1/$S27)*(BR$38-$S$7)/($T$7-$S$7)+1/$S27 -> 0.002 | BS58: =(1/$T27-1/$S27)*(BS$38-$S$7)/($T$7-$S$7)+1/$S27 -> 0.002 | BT58: =(1/$T27-1/$S27)*(BT$38-$S$7)/($T$7-$S$7)+1/$S27 -> 0.002 | BU58: =(1/$T27-1/$S27)*(BU$38-$S$7)/($T$7-$S$7)+1/$S27 -> 0.002 | BV58: =(1/$T27-1/$S27)*(BV$38-$S$7)/($T$7-$S$7)+1/$S27 -> 0.002 | BW58: =(1/$T27-1/$S27)*(BW$38-$S$7)/($T$7-$S$7)+1/$S27 -> 0.002 | BX58: =(1/$T27-1/$S27)*(BX$38-$S$7)/($T$7-$S$7)+1/$S27 -> 0.002 | BY58: =(1/$T27-1/$S27)*(BY$38-$S$7)/($T$7-$S$7)+1/$S27 -> 0.002 | ... CF58: =(1/$T27-1/$S27)*(CF$38-$S$7)/($T$7-$S$7)+1/$S27 -> 0.002
B59: Impact on quantity produced (% of yearly output) | D59: =($E28-$D28)*(D$38-$D$7)/($E$7-$D$7)+$D28 -> 0 | E59: =($E28-$D28)*(E$38-$D$7)/($E$7-$D$7)+$D28 -> 0 | F59: =($E28-$D28)*(F$38-$D$7)/($E$7-$D$7)+$D28 -> 0 | G59: =($E28-$D28)*(G$38-$D$7)/($E$7-$D$7)+$D28 -> 0 | H59: =($E28-$D28)*(H$38-$D$7)/($E$7-$D$7)+$D28 -> 0 | I59: =($E28-$D28)*(I$38-$D$7)/($E$7-$D$7)+$D28 -> 0 | J59: =($E28-$D28)*(J$38-$D$7)/($E$7-$D$7)+$D28 -> 0 | K59: =($E28-$D28)*(K$38-$D$7)/($E$7-$D$7)+$D28 -> 0 | ... M59: =($E28-$D28)*(M$38-$D$7)/($E$7-$D$7)+$D28 -> 0 | N59: =($F28-$E28)*(N$38-$E$7)/($F$7-$E$7)+$E28 -> 0 | O59: =($F28-$E28)*(O$38-$E$7)/($F$7-$E$7)+$E28 -> 0 | P59: =($F28-$E28)*(P$38-$E$7)/($F$7-$E$7)+$E28 -> 0 | Q59: =($F28-$E28)*(Q$38-$E$7)/($F$7-$E$7)+$E28 -> 0 | R59: =($F28-$E28)*(R$38-$E$7)/($F$7-$E$7)+$E28 -> 0 | S59: =($F28-$E28)*(S$38-$E$7)/($F$7-$E$7)+$E28 -> 0 | T59: =($F28-$E28)*(T$38-$E$7)/($F$7-$E$7)+$E28 -> 0 | U59: =($F28-$E28)*(U$38-$E$7)/($F$7-$E$7)+$E28 -> 0 | ... AB59: =($F28-$E28)*(AB$38-$E$7)/($F$7-$E$7)+$E28 -> 0 | AD59: Impact on quantity produced (% of yearly output) | AF59: =($L28-$K28)*(AF$38-$K$7)/($L$7-$K$7)+$K28 -> -0.051780822 | AG59: =($L28-$K28)*(AG$38-$K$7)/($L$7-$K$7)+$K28 -> -0.051780822 | AH59: =($L28-$K28)*(AH$38-$K$7)/($L$7-$K$7)+$K28 -> -0.051780822 | AI59: =($L28-$K28)*(AI$38-$K$7)/($L$7-$K$7)+$K28 -> -0.051780822 | AJ59: =($L28-$K28)*(AJ$38-$K$7)/($L$7-$K$7)+$K28 -> -0.051780822 | AK59: =($L28-$K28)*(AK$38-$K$7)/($L$7-$K$7)+$K28 -> -0.051780822 | AL59: =($L28-$K28)*(AL$38-$K$7)/($L$7-$K$7)+$K28 -> -0.051780822 | AM59: =($L28-$K28)*(AM$38-$K$7)/($L$7-$K$7)+$K28 -> -0.051780822 | ... AO59: =($L28-$K28)*(AO$38-$K$7)/($L$7-$K$7)+$K28 -> -0.051780822 | AP59: =($M28-$L28)*(AP$38-$L$7)/($M$7-$L$7)+$L28 -> -0.051780822 | AQ59: =($M28-$L28)*(AQ$38-$L$7)/($M$7-$L$7)+$L28 -> -0.051780822 | AR59: =($M28-$L28)*(AR$38-$L$7)/($M$7-$L$7)+$L28 -> -0.051780822 | AS59: =($M28-$L28)*(AS$38-$L$7)/($M$7-$L$7)+$L28 -> -0.051780822 | AT59: =($M28-$L28)*(AT$38-$L$7)/($M$7-$L$7)+$L28 -> -0.051780822 | AU59: =($M28-$L28)*(AU$38-$L$7)/($M$7-$L$7)+$L28 -> -0.051780822 | AV59: =($M28-$L28)*(AV$38-$L$7)/($M$7-$L$7)+$L28 -> -0.051780822 | AW59: =($M28-$L28)*(AW$38-$L$7)/($M$7-$L$7)+$L28 -> -0.051780822 | ... BD59: =($M28-$L28)*(BD$38-$L$7)/($M$7-$L$7)+$L28 -> -0.051780822 | BF59: Impact on quantity produced (% of yearly output) | BH59: =($S28-$R28)*(BH$38-$R$7)/($S$7-$R$7)+$R28 -> -0.073972603 | BI59: =($S28-$R28)*(BI$38-$R$7)/($S$7-$R$7)+$R28 -> -0.073972603 | BJ59: =($S28-$R28)*(BJ$38-$R$7)/($S$7-$R$7)+$R28 -> -0.073972603 | BK59: =($S28-$R28)*(BK$38-$R$7)/($S$7-$R$7)+$R28 -> -0.073972603 | BL59: =($S28-$R28)*(BL$38-$R$7)/($S$7-$R$7)+$R28 -> -0.073972603 | BM59: =($S28-$R28)*(BM$38-$R$7)/($S$7-$R$7)+$R28 -> -0.073972603 | BN59: =($S28-$R28)*(BN$38-$R$7)/($S$7-$R$7)+$R28 -> -0.073972603 | BO59: =($S28-$R28)*(BO$38-$R$7)/($S$7-$R$7)+$R28 -> -0.073972603 | ... BQ59: =($S28-$R28)*(BQ$38-$R$7)/($S$7-$R$7)+$R28 -> -0.073972603 | BR59: =($T28-$S28)*(BR$38-$S$7)/($T$7-$S$7)+$S28 -> -0.073972603 | BS59: =($T28-$S28)*(BS$38-$S$7)/($T$7-$S$7)+$S28 -> -0.073972603 | BT59: =($T28-$S28)*(BT$38-$S$7)/($T$7-$S$7)+$S28 -> -0.073972603 | BU59: =($T28-$S28)*(BU$38-$S$7)/($T$7-$S$7)+$S28 -> -0.073972603 | BV59: =($T28-$S28)*(BV$38-$S$7)/($T$7-$S$7)+$S28 -> -0.073972603 | BW59: =($T28-$S28)*(BW$38-$S$7)/($T$7-$S$7)+$S28 -> -0.073972603 | BX59: =($T28-$S28)*(BX$38-$S$7)/($T$7-$S$7)+$S28 -> -0.073972603 | BY59: =($T28-$S28)*(BY$38-$S$7)/($T$7-$S$7)+$S28 -> -0.073972603 | ... CF59: =($T28-$S28)*(CF$38-$S$7)/($T$7-$S$7)+$S28 -> -0.073972603
B60: Impact on quantity produced (% of yearly output) without project | D60: =($E29-$D29)*(D$38-$D$7)/($E$7-$D$7)+$D29 -> 0 | E60: =($E29-$D29)*(E$38-$D$7)/($E$7-$D$7)+$D29 -> 0 | F60: =($E29-$D29)*(F$38-$D$7)/($E$7-$D$7)+$D29 -> 0 | G60: =($E29-$D29)*(G$38-$D$7)/($E$7-$D$7)+$D29 -> 0 | H60: =($E29-$D29)*(H$38-$D$7)/($E$7-$D$7)+$D29 -> 0 | I60: =($E29-$D29)*(I$38-$D$7)/($E$7-$D$7)+$D29 -> 0 | J60: =($E29-$D29)*(J$38-$D$7)/($E$7-$D$7)+$D29 -> 0 | K60: =($E29-$D29)*(K$38-$D$7)/($E$7-$D$7)+$D29 -> 0 | ... M60: =($E29-$D29)*(M$38-$D$7)/($E$7-$D$7)+$D29 -> 0 | N60: =($F29-$E29)*(N$38-$E$7)/($F$7-$E$7)+$E29 -> 0 | O60: =($F29-$E29)*(O$38-$E$7)/($F$7-$E$7)+$E29 -> 0 | P60: =($F29-$E29)*(P$38-$E$7)/($F$7-$E$7)+$E29 -> 0 | Q60: =($F29-$E29)*(Q$38-$E$7)/($F$7-$E$7)+$E29 -> 0 | R60: =($F29-$E29)*(R$38-$E$7)/($F$7-$E$7)+$E29 -> 0 | S60: =($F29-$E29)*(S$38-$E$7)/($F$7-$E$7)+$E29 -> 0 | T60: =($F29-$E29)*(T$38-$E$7)/($F$7-$E$7)+$E29 -> 0 | U60: =($F29-$E29)*(U$38-$E$7)/($F$7-$E$7)+$E29 -> 0 | ... AB60: =($F29-$E29)*(AB$38-$E$7)/($F$7-$E$7)+$E29 -> 0 | AD60: Impact on quantity produced (% of yearly output) without project | AF60: =($L29-$K29)*(AF$38-$K$7)/($L$7-$K$7)+$K29 -> -0.073972603 | AG60: =($L29-$K29)*(AG$38-$K$7)/($L$7-$K$7)+$K29 -> -0.073972603 | AH60: =($L29-$K29)*(AH$38-$K$7)/($L$7-$K$7)+$K29 -> -0.073972603 | AI60: =($L29-$K29)*(AI$38-$K$7)/($L$7-$K$7)+$K29 -> -0.073972603 | AJ60: =($L29-$K29)*(AJ$38-$K$7)/($L$7-$K$7)+$K29 -> -0.073972603 | AK60: =($L29-$K29)*(AK$38-$K$7)/($L$7-$K$7)+$K29 -> -0.073972603 | AL60: =($L29-$K29)*(AL$38-$K$7)/($L$7-$K$7)+$K29 -> -0.073972603 | AM60: =($L29-$K29)*(AM$38-$K$7)/($L$7-$K$7)+$K29 -> -0.073972603 | ... AO60: =($L29-$K29)*(AO$38-$K$7)/($L$7-$K$7)+$K29 -> -0.073972603 | AP60: =($M29-$L29)*(AP$38-$L$7)/($M$7-$L$7)+$L29 -> -0.073972603 | AQ60: =($M29-$L29)*(AQ$38-$L$7)/($M$7-$L$7)+$L29 -> -0.073972603 | AR60: =($M29-$L29)*(AR$38-$L$7)/($M$7-$L$7)+$L29 -> -0.073972603 | AS60: =($M29-$L29)*(AS$38-$L$7)/($M$7-$L$7)+$L29 -> -0.073972603 | AT60: =($M29-$L29)*(AT$38-$L$7)/($M$7-$L$7)+$L29 -> -0.073972603 | AU60: =($M29-$L29)*(AU$38-$L$7)/($M$7-$L$7)+$L29 -> -0.073972603 | AV60: =($M29-$L29)*(AV$38-$L$7)/($M$7-$L$7)+$L29 -> -0.073972603 | AW60: =($M29-$L29)*(AW$38-$L$7)/($M$7-$L$7)+$L29 -> -0.073972603 | ... BD60: =($M29-$L29)*(BD$38-$L$7)/($M$7-$L$7)+$L29 -> -0.073972603 | BF60: Impact on quantity produced (% of yearly output) without project | BH60: =($S29-$R29)*(BH$38-$R$7)/($S$7-$R$7)+$R29 -> -163.68041 | BI60: =($S29-$R29)*(BI$38-$R$7)/($S$7-$R$7)+$R29 -> -0.077671233 | BJ60: =($S29-$R29)*(BJ$38-$R$7)/($S$7-$R$7)+$R29 -> 163.52507 | BK60: =($S29-$R29)*(BK$38-$R$7)/($S$7-$R$7)+$R29 -> 327.12781 | BL60: =($S29-$R29)*(BL$38-$R$7)/($S$7-$R$7)+$R29 -> 490.73055 | BM60: =($S29-$R29)*(BM$38-$R$7)/($S$7-$R$7)+$R29 -> 654.33329 | BN60: =($S29-$R29)*(BN$38-$R$7)/($S$7-$R$7)+$R29 -> 817.93603 | BO60: =($S29-$R29)*(BO$38-$R$7)/($S$7-$R$7)+$R29 -> 981.53877 | ... BQ60: =($S29-$R29)*(BQ$38-$R$7)/($S$7-$R$7)+$R29 -> 1308.7443 | BR60: =($T29-$S29)*(BR$38-$S$7)/($T$7-$S$7)+$S29 -> 1635.9497 | BS60: =($T29-$S29)*(BS$38-$S$7)/($T$7-$S$7)+$S29 -> 1635.9497 | BT60: =($T29-$S29)*(BT$38-$S$7)/($T$7-$S$7)+$S29 -> 1635.9497 | BU60: =($T29-$S29)*(BU$38-$S$7)/($T$7-$S$7)+$S29 -> 1635.9497 | BV60: =($T29-$S29)*(BV$38-$S$7)/($T$7-$S$7)+$S29 -> 1635.9497 | BW60: =($T29-$S29)*(BW$38-$S$7)/($T$7-$S$7)+$S29 -> 1635.9497 | BX60: =($T29-$S29)*(BX$38-$S$7)/($T$7-$S$7)+$S29 -> 1635.9497 | BY60: =($T29-$S29)*(BY$38-$S$7)/($T$7-$S$7)+$S29 -> 1635.9497 | ... CF60: =($T29-$S29)*(CF$38-$S$7)/($T$7-$S$7)+$S29 -> 1635.9497
B61: Repair/Reconstruction cost (CAPEX) (in absolute terms) | D61: =($E30-$D30)*(D$38-$D$7)/($E$7-$D$7)+$D30 -> 0 | E61: =($E30-$D30)*(E$38-$D$7)/($E$7-$D$7)+$D30 -> 0 | F61: =($E30-$D30)*(F$38-$D$7)/($E$7-$D$7)+$D30 -> 0 | G61: =($E30-$D30)*(G$38-$D$7)/($E$7-$D$7)+$D30 -> 0 | H61: =($E30-$D30)*(H$38-$D$7)/($E$7-$D$7)+$D30 -> 0 | I61: =($E30-$D30)*(I$38-$D$7)/($E$7-$D$7)+$D30 -> 0 | J61: =($E30-$D30)*(J$38-$D$7)/($E$7-$D$7)+$D30 -> 0 | K61: =($E30-$D30)*(K$38-$D$7)/($E$7-$D$7)+$D30 -> 0 | ... M61: =($E30-$D30)*(M$38-$D$7)/($E$7-$D$7)+$D30 -> 0 | N61: =($F30-$E30)*(N$38-$E$7)/($F$7-$E$7)+$E30 -> 0 | O61: =($F30-$E30)*(O$38-$E$7)/($F$7-$E$7)+$E30 -> 0 | P61: =($F30-$E30)*(P$38-$E$7)/($F$7-$E$7)+$E30 -> 0 | Q61: =($F30-$E30)*(Q$38-$E$7)/($F$7-$E$7)+$E30 -> 0 | R61: =($F30-$E30)*(R$38-$E$7)/($F$7-$E$7)+$E30 -> 0 | S61: =($F30-$E30)*(S$38-$E$7)/($F$7-$E$7)+$E30 -> 0 | T61: =($F30-$E30)*(T$38-$E$7)/($F$7-$E$7)+$E30 -> 0 | U61: =($F30-$E30)*(U$38-$E$7)/($F$7-$E$7)+$E30 -> 0 | ... AB61: =($F30-$E30)*(AB$38-$E$7)/($F$7-$E$7)+$E30 -> 0 | AD61: Repair/Reconstruction cost (CAPEX) (in absolute terms) | AF61: =($L30-$K30)*(AF$38-$K$7)/($L$7-$K$7)+$K30 -> 1635.9497 | AG61: =($L30-$K30)*(AG$38-$K$7)/($L$7-$K$7)+$K30 -> 1635.9497 | AH61: =($L30-$K30)*(AH$38-$K$7)/($L$7-$K$7)+$K30 -> 1635.9497 | AI61: =($L30-$K30)*(AI$38-$K$7)/($L$7-$K$7)+$K30 -> 1635.9497 | AJ61: =($L30-$K30)*(AJ$38-$K$7)/($L$7-$K$7)+$K30 -> 1635.9497 | AK61: =($L30-$K30)*(AK$38-$K$7)/($L$7-$K$7)+$K30 -> 1635.9497 | AL61: =($L30-$K30)*(AL$38-$K$7)/($L$7-$K$7)+$K30 -> 1635.9497 | AM61: =($L30-$K30)*(AM$38-$K$7)/($L$7-$K$7)+$K30 -> 1635.9497 | ... AO61: =($L30-$K30)*(AO$38-$K$7)/($L$7-$K$7)+$K30 -> 1635.9497 | AP61: =($M30-$L30)*(AP$38-$L$7)/($M$7-$L$7)+$L30 -> 1635.9497 | AQ61: =($M30-$L30)*(AQ$38-$L$7)/($M$7-$L$7)+$L30 -> 1635.9497 | AR61: =($M30-$L30)*(AR$38-$L$7)/($M$7-$L$7)+$L30 -> 1635.9497 | AS61: =($M30-$L30)*(AS$38-$L$7)/($M$7-$L$7)+$L30 -> 1635.9497 | AT61: =($M30-$L30)*(AT$38-$L$7)/($M$7-$L$7)+$L30 -> 1635.9497 | AU61: =($M30-$L30)*(AU$38-$L$7)/($M$7-$L$7)+$L30 -> 1635.9497 | AV61: =($M30-$L30)*(AV$38-$L$7)/($M$7-$L$7)+$L30 -> 1635.9497 | AW61: =($M30-$L30)*(AW$38-$L$7)/($M$7-$L$7)+$L30 -> 1635.9497 | ... BD61: =($M30-$L30)*(BD$38-$L$7)/($M$7-$L$7)+$L30 -> 1635.9497 | BF61: Repair/Reconstruction cost (CAPEX) (in absolute terms) | BH61: =($S30-$R30)*(BH$38-$R$7)/($S$7-$R$7)+$R30 -> 1635.9497 | BI61: =($S30-$R30)*(BI$38-$R$7)/($S$7-$R$7)+$R30 -> 1635.9497 | BJ61: =($S30-$R30)*(BJ$38-$R$7)/($S$7-$R$7)+$R30 -> 1635.9497 | BK61: =($S30-$R30)*(BK$38-$R$7)/($S$7-$R$7)+$R30 -> 1635.9497 | BL61: =($S30-$R30)*(BL$38-$R$7)/($S$7-$R$7)+$R30 -> 1635.9497 | BM61: =($S30-$R30)*(BM$38-$R$7)/($S$7-$R$7)+$R30 -> 1635.9497 | BN61: =($S30-$R30)*(BN$38-$R$7)/($S$7-$R$7)+$R30 -> 1635.9497 | BO61: =($S30-$R30)*(BO$38-$R$7)/($S$7-$R$7)+$R30 -> 1635.9497 | ... BQ61: =($S30-$R30)*(BQ$38-$R$7)/($S$7-$R$7)+$R30 -> 1635.9497 | BR61: =($T30-$S30)*(BR$38-$S$7)/($T$7-$S$7)+$S30 -> 1635.9497 | BS61: =($T30-$S30)*(BS$38-$S$7)/($T$7-$S$7)+$S30 -> 1635.9497 | BT61: =($T30-$S30)*(BT$38-$S$7)/($T$7-$S$7)+$S30 -> 1635.9497 | BU61: =($T30-$S30)*(BU$38-$S$7)/($T$7-$S$7)+$S30 -> 1635.9497 | BV61: =($T30-$S30)*(BV$38-$S$7)/($T$7-$S$7)+$S30 -> 1635.9497 | BW61: =($T30-$S30)*(BW$38-$S$7)/($T$7-$S$7)+$S30 -> 1635.9497 | BX61: =($T30-$S30)*(BX$38-$S$7)/($T$7-$S$7)+$S30 -> 1635.9497 | BY61: =($T30-$S30)*(BY$38-$S$7)/($T$7-$S$7)+$S30 -> 1635.9497 | ... CF61: =($T30-$S30)*(CF$38-$S$7)/($T$7-$S$7)+$S30 -> 1635.9497
B62: Additional out-of-system impacts (in absolute terms) | D62: =($E31-$D31)*(D$38-$D$7)/($E$7-$D$7)+$D31 -> 0 | E62: =($E31-$D31)*(E$38-$D$7)/($E$7-$D$7)+$D31 -> 0 | F62: =($E31-$D31)*(F$38-$D$7)/($E$7-$D$7)+$D31 -> 0 | G62: =($E31-$D31)*(G$38-$D$7)/($E$7-$D$7)+$D31 -> 0 | H62: =($E31-$D31)*(H$38-$D$7)/($E$7-$D$7)+$D31 -> 0 | I62: =($E31-$D31)*(I$38-$D$7)/($E$7-$D$7)+$D31 -> 0 | J62: =($E31-$D31)*(J$38-$D$7)/($E$7-$D$7)+$D31 -> 0 | K62: =($E31-$D31)*(K$38-$D$7)/($E$7-$D$7)+$D31 -> 0 | ... M62: =($E31-$D31)*(M$38-$D$7)/($E$7-$D$7)+$D31 -> 0 | N62: =($F31-$E31)*(N$38-$E$7)/($F$7-$E$7)+$E31 -> 0 | O62: =($F31-$E31)*(O$38-$E$7)/($F$7-$E$7)+$E31 -> 0 | P62: =($F31-$E31)*(P$38-$E$7)/($F$7-$E$7)+$E31 -> 0 | Q62: =($F31-$E31)*(Q$38-$E$7)/($F$7-$E$7)+$E31 -> 0 | R62: =($F31-$E31)*(R$38-$E$7)/($F$7-$E$7)+$E31 -> 0 | S62: =($F31-$E31)*(S$38-$E$7)/($F$7-$E$7)+$E31 -> 0 | T62: =($F31-$E31)*(T$38-$E$7)/($F$7-$E$7)+$E31 -> 0 | U62: =($F31-$E31)*(U$38-$E$7)/($F$7-$E$7)+$E31 -> 0 | ... AB62: =($F31-$E31)*(AB$38-$E$7)/($F$7-$E$7)+$E31 -> 0 | AD62: Additional out-of-system impacts (in absolute terms) | AF62: =($L31-$K31)*(AF$38-$K$7)/($L$7-$K$7)+$K31 -> 0 | AG62: =($L31-$K31)*(AG$38-$K$7)/($L$7-$K$7)+$K31 -> 0 | AH62: =($L31-$K31)*(AH$38-$K$7)/($L$7-$K$7)+$K31 -> 0 | AI62: =($L31-$K31)*(AI$38-$K$7)/($L$7-$K$7)+$K31 -> 0 | AJ62: =($L31-$K31)*(AJ$38-$K$7)/($L$7-$K$7)+$K31 -> 0 | AK62: =($L31-$K31)*(AK$38-$K$7)/($L$7-$K$7)+$K31 -> 0 | AL62: =($L31-$K31)*(AL$38-$K$7)/($L$7-$K$7)+$K31 -> 0 | AM62: =($L31-$K31)*(AM$38-$K$7)/($L$7-$K$7)+$K31 -> 0 | ... AO62: =($L31-$K31)*(AO$38-$K$7)/($L$7-$K$7)+$K31 -> 0 | AP62: =($M31-$L31)*(AP$38-$L$7)/($M$7-$L$7)+$L31 -> 0 | AQ62: =($M31-$L31)*(AQ$38-$L$7)/($M$7-$L$7)+$L31 -> 0 | AR62: =($M31-$L31)*(AR$38-$L$7)/($M$7-$L$7)+$L31 -> 0 | AS62: =($M31-$L31)*(AS$38-$L$7)/($M$7-$L$7)+$L31 -> 0 | AT62: =($M31-$L31)*(AT$38-$L$7)/($M$7-$L$7)+$L31 -> 0 | AU62: =($M31-$L31)*(AU$38-$L$7)/($M$7-$L$7)+$L31 -> 0 | AV62: =($M31-$L31)*(AV$38-$L$7)/($M$7-$L$7)+$L31 -> 0 | AW62: =($M31-$L31)*(AW$38-$L$7)/($M$7-$L$7)+$L31 -> 0 | ... BD62: =($M31-$L31)*(BD$38-$L$7)/($M$7-$L$7)+$L31 -> 0 | BF62: Additional out-of-system impacts (in absolute terms) | BH62: =($S31-$R31)*(BH$38-$R$7)/($S$7-$R$7)+$R31 -> 0 | BI62: =($S31-$R31)*(BI$38-$R$7)/($S$7-$R$7)+$R31 -> 0 | BJ62: =($S31-$R31)*(BJ$38-$R$7)/($S$7-$R$7)+$R31 -> 0 | BK62: =($S31-$R31)*(BK$38-$R$7)/($S$7-$R$7)+$R31 -> 0 | BL62: =($S31-$R31)*(BL$38-$R$7)/($S$7-$R$7)+$R31 -> 0 | BM62: =($S31-$R31)*(BM$38-$R$7)/($S$7-$R$7)+$R31 -> 0 | BN62: =($S31-$R31)*(BN$38-$R$7)/($S$7-$R$7)+$R31 -> 0 | BO62: =($S31-$R31)*(BO$38-$R$7)/($S$7-$R$7)+$R31 -> 0 | ... BQ62: =($S31-$R31)*(BQ$38-$R$7)/($S$7-$R$7)+$R31 -> 0 | BR62: =($T31-$S31)*(BR$38-$S$7)/($T$7-$S$7)+$S31 -> 0 | BS62: =($T31-$S31)*(BS$38-$S$7)/($T$7-$S$7)+$S31 -> 0 | BT62: =($T31-$S31)*(BT$38-$S$7)/($T$7-$S$7)+$S31 -> 0 | BU62: =($T31-$S31)*(BU$38-$S$7)/($T$7-$S$7)+$S31 -> 0 | BV62: =($T31-$S31)*(BV$38-$S$7)/($T$7-$S$7)+$S31 -> 0 | BW62: =($T31-$S31)*(BW$38-$S$7)/($T$7-$S$7)+$S31 -> 0 | BX62: =($T31-$S31)*(BX$38-$S$7)/($T$7-$S$7)+$S31 -> 0 | BY62: =($T31-$S31)*(BY$38-$S$7)/($T$7-$S$7)+$S31 -> 0 | ... CF62: =($T31-$S31)*(CF$38-$S$7)/($T$7-$S$7)+$S31 -> 0
B65: Calculation: | AD65: Calculation: | BF65: Calculation:
B66: Expected annual figures based on "frequencies" | AD66: Expected annual figures based on "frequencies" | BF66: Expected annual figures based on "frequencies"
B67: Input: All this sheet (table above) | AD67: Input: All this sheet (table above) | BF67: Input: All this sheet (table above)
B69: ExpectedShockServiceLoss: Expected impact on quantity produced with project (% of yearly output) | D69: =D$58*D59+(D$52-D$58)*D53+(D$46-D$52)*D47+(D$40-D$46)*D41 -> 0 | E69: =E$58*E59+(E$52-E$58)*E53+(E$46-E$52)*E47+(E$40-E$46)*E41 -> 0 | F69: =F$58*F59+(F$52-F$58)*F53+(F$46-F$52)*F47+(F$40-F$46)*F41 -> 0 | G69: =G$58*G59+(G$52-G$58)*G53+(G$46-G$52)*G47+(G$40-G$46)*G41 -> 0 | H69: =H$58*H59+(H$52-H$58)*H53+(H$46-H$52)*H47+(H$40-H$46)*H41 -> 0 | I69: =I$58*I59+(I$52-I$58)*I53+(I$46-I$52)*I47+(I$40-I$46)*I41 -> 0 | J69: =J$58*J59+(J$52-J$58)*J53+(J$46-J$52)*J47+(J$40-J$46)*J41 -> 0 | K69: =K$58*K59+(K$52-K$58)*K53+(K$46-K$52)*K47+(K$40-K$46)*K41 -> 0 | ... AB69: =AB$58*AB59+(AB$52-AB$58)*AB53+(AB$46-AB$52)*AB47+(AB$40-AB$46)*AB41 -> 0 | AD69: ExpectedShockServiceLoss: Expected impact on quantity produced (% of yearly output) | AF69: =AF$58*AF59+(AF$52-AF$58)*AF53+(AF$46-AF$52)*AF47+(AF$40-AF$46)*AF41 -> -0.041589616 | AG69: =AG$58*AG59+(AG$52-AG$58)*AG53+(AG$46-AG$52)*AG47+(AG$40-AG$46)*AG41 -> -0.046210685 | AH69: =AH$58*AH59+(AH$52-AH$58)*AH53+(AH$46-AH$52)*AH47+(AH$40-AH$46)*AH41 -> -0.050831753 | AI69: =AI$58*AI59+(AI$52-AI$58)*AI53+(AI$46-AI$52)*AI47+(AI$40-AI$46)*AI41 -> -0.055452822 | AJ69: =AJ$58*AJ59+(AJ$52-AJ$58)*AJ53+(AJ$46-AJ$52)*AJ47+(AJ$40-AJ$46)*AJ41 -> -0.06007389 | AK69: =AK$58*AK59+(AK$52-AK$58)*AK53+(AK$46-AK$52)*AK47+(AK$40-AK$46)*AK41 -> -0.064694959 | AL69: =AL$58*AL59+(AL$52-AL$58)*AL53+(AL$46-AL$52)*AL47+(AL$40-AL$46)*AL41 -> -0.069316027 | AM69: =AM$58*AM59+(AM$52-AM$58)*AM53+(AM$46-AM$52)*AM47+(AM$40-AM$46)*AM41 -> -0.073937096 | ... BD69: =BD$58*BD59+(BD$52-BD$58)*BD53+(BD$46-BD$52)*BD47+(BD$40-BD$46)*BD41 -> -0.09242137 | BF69: ExpectedShockServiceLoss: Expected impact on quantity produced (% of yearly output) | BH69: =BH$58*BH59+(BH$52-BH$58)*BH53+(BH$46-BH$52)*BH47+(BH$40-BH$46)*BH41 -> -0.062070411 | BI69: =BI$58*BI59+(BI$52-BI$58)*BI53+(BI$46-BI$52)*BI47+(BI$40-BI$46)*BI41 -> -0.069001644 | BJ69: =BJ$58*BJ59+(BJ$52-BJ$58)*BJ53+(BJ$46-BJ$52)*BJ47+(BJ$40-BJ$46)*BJ41 -> -0.075932877 | BK69: =BK$58*BK59+(BK$52-BK$58)*BK53+(BK$46-BK$52)*BK47+(BK$40-BK$46)*BK41 -> -0.08286411 | BL69: =BL$58*BL59+(BL$52-BL$58)*BL53+(BL$46-BL$52)*BL47+(BL$40-BL$46)*BL41 -> -0.089795342 | BM69: =BM$58*BM59+(BM$52-BM$58)*BM53+(BM$46-BM$52)*BM47+(BM$40-BM$46)*BM41 -> -0.096726575 | BN69: =BN$58*BN59+(BN$52-BN$58)*BN53+(BN$46-BN$52)*BN47+(BN$40-BN$46)*BN41 -> -0.10365781 | BO69: =BO$58*BO59+(BO$52-BO$58)*BO53+(BO$46-BO$52)*BO47+(BO$40-BO$46)*BO41 -> -0.11058904 | ... CF69: =CF$58*CF59+(CF$52-CF$58)*CF53+(CF$46-CF$52)*CF47+(CF$40-CF$46)*CF41 -> -0.13862466
B70: ExpectedShockServiceLoss: Expected impact on quantity produced without project (% of yearly output) | D70: =D$58*D60+(D$52-D$58)*D54+(D$46-D$52)*D48+(D$40-D$46)*D42 -> 0 | E70: =E$58*E60+(E$52-E$58)*E54+(E$46-E$52)*E48+(E$40-E$46)*E42 -> 0 | F70: =F$58*F60+(F$52-F$58)*F54+(F$46-F$52)*F48+(F$40-F$46)*F42 -> 0 | G70: =G$58*G60+(G$52-G$58)*G54+(G$46-G$52)*G48+(G$40-G$46)*G42 -> 0 | H70: =H$58*H60+(H$52-H$58)*H54+(H$46-H$52)*H48+(H$40-H$46)*H42 -> 0 | I70: =I$58*I60+(I$52-I$58)*I54+(I$46-I$52)*I48+(I$40-I$46)*I42 -> 0 | J70: =J$58*J60+(J$52-J$58)*J54+(J$46-J$52)*J48+(J$40-J$46)*J42 -> 0 | K70: =K$58*K60+(K$52-K$58)*K54+(K$46-K$52)*K48+(K$40-K$46)*K42 -> 0 | ... AB70: =AB$58*AB60+(AB$52-AB$58)*AB54+(AB$46-AB$52)*AB48+(AB$40-AB$46)*AB42 -> 0 | AD70: ExpectedShockServiceLoss: Expected impact on quantity produced without project (% of yearly output) | AF70: =AF$58*AF60+(AF$52-AF$58)*AF54+(AF$46-AF$52)*AF48+(AF$40-AF$46)*AF42 -> -0.062381096 | AG70: =AG$58*AG60+(AG$52-AG$58)*AG54+(AG$46-AG$52)*AG48+(AG$40-AG$46)*AG42 -> -0.069312329 | AH70: =AH$58*AH60+(AH$52-AH$58)*AH54+(AH$46-AH$52)*AH48+(AH$40-AH$46)*AH42 -> -0.076243562 | AI70: =AI$58*AI60+(AI$52-AI$58)*AI54+(AI$46-AI$52)*AI48+(AI$40-AI$46)*AI42 -> -0.083174795 | AJ70: =AJ$58*AJ60+(AJ$52-AJ$58)*AJ54+(AJ$46-AJ$52)*AJ48+(AJ$40-AJ$46)*AJ42 -> -0.090106027 | AK70: =AK$58*AK60+(AK$52-AK$58)*AK54+(AK$46-AK$52)*AK48+(AK$40-AK$46)*AK42 -> -0.09703726 | AL70: =AL$58*AL60+(AL$52-AL$58)*AL54+(AL$46-AL$52)*AL48+(AL$40-AL$46)*AL42 -> -0.10396849 | AM70: =AM$58*AM60+(AM$52-AM$58)*AM54+(AM$46-AM$52)*AM48+(AM$40-AM$46)*AM42 -> -0.11089973 | ... BD70: =BD$58*BD60+(BD$52-BD$58)*BD54+(BD$46-BD$52)*BD48+(BD$40-BD$46)*BD42 -> -0.13862466 | BF70: ExpectedShockServiceLoss: Expected impact on quantity produced without project (% of yearly output) | BH70: =BH$58*BH60+(BH$52-BH$58)*BH54+(BH$46-BH$52)*BH48+(BH$40-BH$46)*BH42 -> -5.971847 | BI70: =BI$58*BI60+(BI$52-BI$58)*BI54+(BI$46-BI$52)*BI48+(BI$40-BI$46)*BI42 -> -0.080293808 | BJ70: =BJ$58*BJ60+(BJ$52-BJ$58)*BJ54+(BJ$46-BJ$52)*BJ48+(BJ$40-BJ$46)*BJ42 -> 7.1037851 | BK70: =BK$58*BK60+(BK$52-BK$58)*BK54+(BK$46-BK$52)*BK48+(BK$40-BK$46)*BK42 -> 15.58039 | BL70: =BL$58*BL60+(BL$52-BL$58)*BL54+(BL$46-BL$52)*BL48+(BL$40-BL$46)*BL42 -> 25.34952 | BM70: =BM$58*BM60+(BM$52-BM$58)*BM54+(BM$46-BM$52)*BM48+(BM$40-BM$46)*BM42 -> 36.411176 | BN70: =BN$58*BN60+(BN$52-BN$58)*BN54+(BN$46-BN$52)*BN48+(BN$40-BN$46)*BN42 -> 48.765358 | BO70: =BO$58*BO60+(BO$52-BO$58)*BO54+(BO$46-BO$52)*BO48+(BO$40-BO$46)*BO42 -> 62.412066 | ... CF70: =CF$58*CF60+(CF$52-CF$58)*CF54+(CF$46-CF$52)*CF48+(CF$40-CF$46)*CF42 -> 129.09131
B71: ExpectedShockRepair: Expected repair/Reconstruction cost (CAPEX) | D71: =D$58*D61+(D$52-D$58)*D55+(D$46-D$52)*D49+(D$40-D$46)*D43 -> 0 | E71: =E$58*E61+(E$52-E$58)*E55+(E$46-E$52)*E49+(E$40-E$46)*E43 -> 0 | F71: =F$58*F61+(F$52-F$58)*F55+(F$46-F$52)*F49+(F$40-F$46)*F43 -> 0 | G71: =G$58*G61+(G$52-G$58)*G55+(G$46-G$52)*G49+(G$40-G$46)*G43 -> 0 | H71: =H$58*H61+(H$52-H$58)*H55+(H$46-H$52)*H49+(H$40-H$46)*H43 -> 0 | I71: =I$58*I61+(I$52-I$58)*I55+(I$46-I$52)*I49+(I$40-I$46)*I43 -> 0 | J71: =J$58*J61+(J$52-J$58)*J55+(J$46-J$52)*J49+(J$40-J$46)*J43 -> 0 | K71: =K$58*K61+(K$52-K$58)*K55+(K$46-K$52)*K49+(K$40-K$46)*K43 -> 0 | ... AB71: =AB$58*AB61+(AB$52-AB$58)*AB55+(AB$46-AB$52)*AB49+(AB$40-AB$46)*AB43 -> 0 | AD71: ExpectedShockRepair: Expected repair/Reconstruction cost (CAPEX) | AF71: =AF$58*AF61+(AF$52-AF$58)*AF55+(AF$46-AF$52)*AF49+(AF$40-AF$46)*AF43 -> 58.091088 | AG71: =AG$58*AG61+(AG$52-AG$58)*AG55+(AG$46-AG$52)*AG49+(AG$40-AG$46)*AG43 -> 64.545653 | AH71: =AH$58*AH61+(AH$52-AH$58)*AH55+(AH$46-AH$52)*AH49+(AH$40-AH$46)*AH43 -> 71.000219 | AI71: =AI$58*AI61+(AI$52-AI$58)*AI55+(AI$46-AI$52)*AI49+(AI$40-AI$46)*AI43 -> 77.454784 | AJ71: =AJ$58*AJ61+(AJ$52-AJ$58)*AJ55+(AJ$46-AJ$52)*AJ49+(AJ$40-AJ$46)*AJ43 -> 83.909349 | AK71: =AK$58*AK61+(AK$52-AK$58)*AK55+(AK$46-AK$52)*AK49+(AK$40-AK$46)*AK43 -> 90.363915 | AL71: =AL$58*AL61+(AL$52-AL$58)*AL55+(AL$46-AL$52)*AL49+(AL$40-AL$46)*AL43 -> 96.81848 | AM71: =AM$58*AM61+(AM$52-AM$58)*AM55+(AM$46-AM$52)*AM49+(AM$40-AM$46)*AM43 -> 103.27305 | ... BD71: =BD$58*BD61+(BD$52-BD$58)*BD55+(BD$46-BD$52)*BD49+(BD$40-BD$46)*BD43 -> 129.09131 | BF71: ExpectedShockRepair: Expected repair/Reconstruction cost (CAPEX) | BH71: =BH$58*BH61+(BH$52-BH$58)*BH55+(BH$46-BH$52)*BH49+(BH$40-BH$46)*BH43 -> 58.923935 | BI71: =BI$58*BI61+(BI$52-BI$58)*BI55+(BI$46-BI$52)*BI49+(BI$40-BI$46)*BI43 -> 65.3785 | BJ71: =BJ$58*BJ61+(BJ$52-BJ$58)*BJ55+(BJ$46-BJ$52)*BJ49+(BJ$40-BJ$46)*BJ43 -> 71.833066 | BK71: =BK$58*BK61+(BK$52-BK$58)*BK55+(BK$46-BK$52)*BK49+(BK$40-BK$46)*BK43 -> 78.287631 | BL71: =BL$58*BL61+(BL$52-BL$58)*BL55+(BL$46-BL$52)*BL49+(BL$40-BL$46)*BL43 -> 84.742196 | BM71: =BM$58*BM61+(BM$52-BM$58)*BM55+(BM$46-BM$52)*BM49+(BM$40-BM$46)*BM43 -> 91.196762 | BN71: =BN$58*BN61+(BN$52-BN$58)*BN55+(BN$46-BN$52)*BN49+(BN$40-BN$46)*BN43 -> 97.651327 | BO71: =BO$58*BO61+(BO$52-BO$58)*BO55+(BO$46-BO$52)*BO49+(BO$40-BO$46)*BO43 -> 104.10589 | ... CF71: =CF$58*CF61+(CF$52-CF$58)*CF55+(CF$46-CF$52)*CF49+(CF$40-CF$46)*CF43 -> 129.09131
B72: ExpectedShockOutofSystemLoss: Expected additional out-of-system impacts | D72: =D$58*D62+(D$52-D$58)*D56+(D$46-D$52)*D50+(D$40-D$46)*D44 -> 0 | E72: =E$58*E62+(E$52-E$58)*E56+(E$46-E$52)*E50+(E$40-E$46)*E44 -> 0 | F72: =F$58*F62+(F$52-F$58)*F56+(F$46-F$52)*F50+(F$40-F$46)*F44 -> 0 | G72: =G$58*G62+(G$52-G$58)*G56+(G$46-G$52)*G50+(G$40-G$46)*G44 -> 0 | H72: =H$58*H62+(H$52-H$58)*H56+(H$46-H$52)*H50+(H$40-H$46)*H44 -> 0 | I72: =I$58*I62+(I$52-I$58)*I56+(I$46-I$52)*I50+(I$40-I$46)*I44 -> 0 | J72: =J$58*J62+(J$52-J$58)*J56+(J$46-J$52)*J50+(J$40-J$46)*J44 -> 0 | K72: =K$58*K62+(K$52-K$58)*K56+(K$46-K$52)*K50+(K$40-K$46)*K44 -> 0 | ... AB72: =AB$58*AB62+(AB$52-AB$58)*AB56+(AB$46-AB$52)*AB50+(AB$40-AB$46)*AB44 -> 0 | AD72: ExpectedShockOutofSystemLoss: Expected additional out-of-system impacts | AF72: =AF$58*AF62+(AF$52-AF$58)*AF56+(AF$46-AF$52)*AF50+(AF$40-AF$46)*AF44 -> 0 | AG72: =AG$58*AG62+(AG$52-AG$58)*AG56+(AG$46-AG$52)*AG50+(AG$40-AG$46)*AG44 -> 0 | AH72: =AH$58*AH62+(AH$52-AH$58)*AH56+(AH$46-AH$52)*AH50+(AH$40-AH$46)*AH44 -> 0 | AI72: =AI$58*AI62+(AI$52-AI$58)*AI56+(AI$46-AI$52)*AI50+(AI$40-AI$46)*AI44 -> 0 | AJ72: =AJ$58*AJ62+(AJ$52-AJ$58)*AJ56+(AJ$46-AJ$52)*AJ50+(AJ$40-AJ$46)*AJ44 -> 0 | AK72: =AK$58*AK62+(AK$52-AK$58)*AK56+(AK$46-AK$52)*AK50+(AK$40-AK$46)*AK44 -> 0 | AL72: =AL$58*AL62+(AL$52-AL$58)*AL56+(AL$46-AL$52)*AL50+(AL$40-AL$46)*AL44 -> 0 | AM72: =AM$58*AM62+(AM$52-AM$58)*AM56+(AM$46-AM$52)*AM50+(AM$40-AM$46)*AM44 -> 0 | ... BD72: =BD$58*BD62+(BD$52-BD$58)*BD56+(BD$46-BD$52)*BD50+(BD$40-BD$46)*BD44 -> 0 | BF72: ExpectedShockOutofSystemLoss: Expected additional out-of-system impacts | BH72: =BH$58*BH62+(BH$52-BH$58)*BH56+(BH$46-BH$52)*BH50+(BH$40-BH$46)*BH44 -> 0 | BI72: =BI$58*BI62+(BI$52-BI$58)*BI56+(BI$46-BI$52)*BI50+(BI$40-BI$46)*BI44 -> 0 | BJ72: =BJ$58*BJ62+(BJ$52-BJ$58)*BJ56+(BJ$46-BJ$52)*BJ50+(BJ$40-BJ$46)*BJ44 -> 0 | BK72: =BK$58*BK62+(BK$52-BK$58)*BK56+(BK$46-BK$52)*BK50+(BK$40-BK$46)*BK44 -> 0 | BL72: =BL$58*BL62+(BL$52-BL$58)*BL56+(BL$46-BL$52)*BL50+(BL$40-BL$46)*BL44 -> 0 | BM72: =BM$58*BM62+(BM$52-BM$58)*BM56+(BM$46-BM$52)*BM50+(BM$40-BM$46)*BM44 -> 0 | BN72: =BN$58*BN62+(BN$52-BN$58)*BN56+(BN$46-BN$52)*BN50+(BN$40-BN$46)*BN44 -> 0 | BO72: =BO$58*BO62+(BO$52-BO$58)*BO56+(BO$46-BO$52)*BO50+(BO$40-BO$46)*BO44 -> 0 | ... CF72: =CF$58*CF62+(CF$52-CF$58)*CF56+(CF$46-CF$52)*CF50+(CF$40-CF$46)*CF44 -> 0
B75: ='Climate impacts'!B21 -> Disaster 1 - | AD75: ='Climate impacts'!G21 -> Disaster 2 - Floods | BF75: ='Climate impacts'!L21 -> Disaster 3 - [Landslides]

Sheet Extrapolation average con.
A1: SIMULATION
C2: 2030 | D2: 2050 | E2: 2100
A3: Expected change in quantity produced (e.g., corn yield) | B3: User Costs With Project | C3: =Parameters_Results!$D$16*'Climate impacts'!G11+(1-Parameters_Results!$D$16)*'Climate impacts'!F11 -> -0.004 | D3: =Parameters_Results!$D$16*'Climate impacts'!I11+(1-Parameters_Results!$D$16)*'Climate impacts'!H11 -> -0.008 | E3: =Parameters_Results!$D$16*'Climate impacts'!K11+(1-Parameters_Results!$D$16)*'Climate impacts'!J11 -> 0
B4: User Costs Without Project | C4: =Parameters_Results!$D$16*'Climate impacts'!G12+(1-Parameters_Results!$D$16)*'Climate impacts'!F12 -> -0.012 | D4: =Parameters_Results!$D$16*'Climate impacts'!I12+(1-Parameters_Results!$D$16)*'Climate impacts'!H12 -> -0.041 | E4: =Parameters_Results!$D$16*'Climate impacts'!K12+(1-Parameters_Results!$D$16)*'Climate impacts'!J12 -> 0
C5: =Parameters_Results!$D$16*'Climate impacts'!G13+(1-Parameters_Results!$D$16)*'Climate impacts'!F13 -> 0 | D5: =Parameters_Results!$D$16*'Climate impacts'!I13+(1-Parameters_Results!$D$16)*'Climate impacts'!H13 -> 0 | E5: =Parameters_Results!$D$16*'Climate impacts'!K13+(1-Parameters_Results!$D$16)*'Climate impacts'!J13 -> 0
A6: Expected change in price of supply (e.g., unit corn price) | B6: User Costs With Project | C6: =Parameters_Results!$D$17*'Climate impacts'!G14+(1-Parameters_Results!$D$17)*'Climate impacts'!F14 -> 0 | D6: =Parameters_Results!$D$17*'Climate impacts'!I14+(1-Parameters_Results!$D$17)*'Climate impacts'!H14 -> 0 | E6: =Parameters_Results!$D$17*'Climate impacts'!K14+(1-Parameters_Results!$D$17)*'Climate impacts'!J14 -> 0
B7: User Costs Without Project | C7: =Parameters_Results!$D$17*'Climate impacts'!G15+(1-Parameters_Results!$D$17)*'Climate impacts'!F15 -> 0 | D7: =Parameters_Results!$D$17*'Climate impacts'!I15+(1-Parameters_Results!$D$17)*'Climate impacts'!H15 -> 0 | E7: =Parameters_Results!$D$17*'Climate impacts'!K15+(1-Parameters_Results!$D$17)*'Climate impacts'!J15 -> 0
C8: =Parameters_Results!$D$17*'Climate impacts'!G16+(1-Parameters_Results!$D$17)*'Climate impacts'!F16 -> 0 | D8: =Parameters_Results!$D$17*'Climate impacts'!I16+(1-Parameters_Results!$D$17)*'Climate impacts'!H16 -> 0 | E8: =Parameters_Results!$D$17*'Climate impacts'!K16+(1-Parameters_Results!$D$17)*'Climate impacts'!J16 -> 0
A9: Expected change in operational or production costs | B9: CAPEX | C9: =Parameters_Results!$D$18*'Climate impacts'!G17+(1-Parameters_Results!$D$18)*'Climate impacts'!F17 -> 0 | D9: =Parameters_Results!$D$18*'Climate impacts'!I17+(1-Parameters_Results!$D$18)*'Climate impacts'!H17 -> 0 | E9: =Parameters_Results!$D$18*'Climate impacts'!K17+(1-Parameters_Results!$D$18)*'Climate impacts'!J17 -> 0
B10: OPEX With Project | C10: =Parameters_Results!$D$18*'Climate impacts'!G18+(1-Parameters_Results!$D$18)*'Climate impacts'!F18 -> 0.02 | D10: =Parameters_Results!$D$18*'Climate impacts'!I18+(1-Parameters_Results!$D$18)*'Climate impacts'!H18 -> 0.04 | E10: =Parameters_Results!$D$18*'Climate impacts'!K18+(1-Parameters_Results!$D$18)*'Climate impacts'!J18 -> 0
B11: OPEX Without Project | C11: =Parameters_Results!$D$18*'Climate impacts'!G19+(1-Parameters_Results!$D$18)*'Climate impacts'!F19 -> 0.06 | D11: =Parameters_Results!$D$18*'Climate impacts'!I19+(1-Parameters_Results!$D$18)*'Climate impacts'!H19 -> 0.1 | E11: =Parameters_Results!$D$18*'Climate impacts'!K19+(1-Parameters_Results!$D$18)*'Climate impacts'!J19 -> 0
A15: Year | C15: =Parameters_Results!$D$10+COLUMN()-2 -> 2019 | D15: =Parameters_Results!$D$10+COLUMN()-2 -> 2020 | E15: =Parameters_Results!$D$10+COLUMN()-2 -> 2021 | F15: =Parameters_Results!$D$10+COLUMN()-2 -> 2022 | G15: =Parameters_Results!$D$10+COLUMN()-2 -> 2023 | H15: =Parameters_Results!$D$10+COLUMN()-2 -> 2024 | I15: =Parameters_Results!$D$10+COLUMN()-2 -> 2025 | J15: =Parameters_Results!$D$10+COLUMN()-2 -> 2026 | ... CD15: =Parameters_Results!$D$10+COLUMN()-2 -> 2098
A16: Expected change in quantity produced (e.g., corn yield) | B16: User Costs With Project | C16: =$C3*('Extrapolation average con.'!C$15-Parameters_Results!$D$10)/($C$2-Parameters_Results!$D$10) -> -0.00033333333 | D16: =$C3*('Extrapolation average con.'!D$15-Parameters_Results!$D$10)/($C$2-Parameters_Results!$D$10) -> -0.00066666667 | E16: =$C3*('Extrapolation average con.'!E$15-Parameters_Results!$D$10)/($C$2-Parameters_Results!$D$10) -> -0.001 | F16: =$C3*('Extrapolation average con.'!F$15-Parameters_Results!$D$10)/($C$2-Parameters_Results!$D$10) -> -0.0013333333 | G16: =$C3*('Extrapolation average con.'!G$15-Parameters_Results!$D$10)/($C$2-Parameters_Results!$D$10) -> -0.0016666667 | H16: =$C3*('Extrapolation average con.'!H$15-Parameters_Results!$D$10)/($C$2-Parameters_Results!$D$10) -> -0.002 | I16: =$C3*('Extrapolation average con.'!I$15-Parameters_Results!$D$10)/($C$2-Parameters_Results!$D$10) -> -0.0023333333 | J16: =$C3*('Extrapolation average con.'!J$15-Parameters_Results!$D$10)/($C$2-Parameters_Results!$D$10) -> -0.0026666667 | ... L16: =$C3*('Extrapolation average con.'!L$15-Parameters_Results!$D$10)/($C$2-Parameters_Results!$D$10) -> -0.0033333333 | M16: =($D3-$C3)*('Extrapolation average con.'!M$15-$C$2)/($D$2-$C$2)+$L16 -> -0.0031333333 | N16: =($D3-$C3)*('Extrapolation average con.'!N$15-$C$2)/($D$2-$C$2)+$L16 -> -0.0033333333 | O16: =($D3-$C3)*('Extrapolation average con.'!O$15-$C$2)/($D$2-$C$2)+$L16 -> -0.0035333333 | P16: =($D3-$C3)*('Extrapolation average con.'!P$15-$C$2)/($D$2-$C$2)+$L16 -> -0.0037333333 | Q16: =($D3-$C3)*('Extrapolation average con.'!Q$15-$C$2)/($D$2-$C$2)+$L16 -> -0.0039333333 | R16: =($D3-$C3)*('Extrapolation average con.'!R$15-$C$2)/($D$2-$C$2)+$L16 -> -0.0041333333 | S16: =($D3-$C3)*('Extrapolation average con.'!S$15-$C$2)/($D$2-$C$2)+$L16 -> -0.0043333333 | T16: =($D3-$C3)*('Extrapolation average con.'!T$15-$C$2)/($D$2-$C$2)+$L16 -> -0.0045333333 | ... AF16: =($D3-$C3)*('Extrapolation average con.'!AF$15-$C$2)/($D$2-$C$2)+$L16 -> -0.0069333333 | AG16: =($E3-$D3)*('Extrapolation average con.'!AG$15-$D$2)/($E$2-$D$2)+$AF16 -> -0.0070933333 | AH16: =($E3-$D3)*('Extrapolation average con.'!AH$15-$D$2)/($E$2-$D$2)+$AF16 -> -0.0069333333 | AI16: =($E3-$D3)*('Extrapolation average con.'!AI$15-$D$2)/($E$2-$D$2)+$AF16 -> -0.0067733333 | AJ16: =($E3-$D3)*('Extrapolation average con.'!AJ$15-$D$2)/($E$2-$D$2)+$AF16 -> -0.0066133333 | AK16: =($E3-$D3)*('Extrapolation average con.'!AK$15-$D$2)/($E$2-$D$2)+$AF16 -> -0.0064533333 | AL16: =($E3-$D3)*('Extrapolation average con.'!AL$15-$D$2)/($E$2-$D$2)+$AF16 -> -0.0062933333 | AM16: =($E3-$D3)*('Extrapolation average con.'!AM$15-$D$2)/($E$2-$D$2)+$AF16 -> -0.0061333333 | AN16: =($E3-$D3)*('Extrapolation average con.'!AN$15-$D$2)/($E$2-$D$2)+$AF16 -> -0.0059733333 | ... CD16: =($E3-$D3)*('Extrapolation average con.'!CD$15-$D$2)/($E$2-$D$2)+$AF16 -> 0.00074666667
B17: User Costs Without Project | C17: =$C4*('Extrapolation average con.'!C$15-Parameters_Results!$D$10)/($C$2-Parameters_Results!$D$10) -> -0.001 | D17: =$C4*('Extrapolation average con.'!D$15-Parameters_Results!$D$10)/($C$2-Parameters_Results!$D$10) -> -0.002 | E17: =$C4*('Extrapolation average con.'!E$15-Parameters_Results!$D$10)/($C$2-Parameters_Results!$D$10) -> -0.003 | F17: =$C4*('Extrapolation average con.'!F$15-Parameters_Results!$D$10)/($C$2-Parameters_Results!$D$10) -> -0.004 | G17: =$C4*('Extrapolation average con.'!G$15-Parameters_Results!$D$10)/($C$2-Parameters_Results!$D$10) -> -0.005 | H17: =$C4*('Extrapolation average con.'!H$15-Parameters_Results!$D$10)/($C$2-Parameters_Results!$D$10) -> -0.006 | I17: =$C4*('Extrapolation average con.'!I$15-Parameters_Results!$D$10)/($C$2-Parameters_Results!$D$10) -> -0.007 | J17: =$C4*('Extrapolation average con.'!J$15-Parameters_Results!$D$10)/($C$2-Parameters_Results!$D$10) -> -0.008 | ... L17: =$C4*('Extrapolation average con.'!L$15-Parameters_Results!$D$10)/($C$2-Parameters_Results!$D$10) -> -0.01 | M17: =($D4-$C4)*('Extrapolation average con.'!M$15-$C$2)/($D$2-$C$2)+$L17 -> -0.00855 | N17: =($D4-$C4)*('Extrapolation average con.'!N$15-$C$2)/($D$2-$C$2)+$L17 -> -0.01 | O17: =($D4-$C4)*('Extrapolation average con.'!O$15-$C$2)/($D$2-$C$2)+$L17 -> -0.01145 | P17: =($D4-$C4)*('Extrapolation average con.'!P$15-$C$2)/($D$2-$C$2)+$L17 -> -0.0129 | Q17: =($D4-$C4)*('Extrapolation average con.'!Q$15-$C$2)/($D$2-$C$2)+$L17 -> -0.01435 | R17: =($D4-$C4)*('Extrapolation average con.'!R$15-$C$2)/($D$2-$C$2)+$L17 -> -0.0158 | S17: =($D4-$C4)*('Extrapolation average con.'!S$15-$C$2)/($D$2-$C$2)+$L17 -> -0.01725 | T17: =($D4-$C4)*('Extrapolation average con.'!T$15-$C$2)/($D$2-$C$2)+$L17 -> -0.0187 | ... AF17: =($D4-$C4)*('Extrapolation average con.'!AF$15-$C$2)/($D$2-$C$2)+$L17 -> -0.0361 | AG17: =($E4-$D4)*('Extrapolation average con.'!AG$15-$D$2)/($E$2-$D$2)+$AF17 -> -0.03692 | AH17: =($E4-$D4)*('Extrapolation average con.'!AH$15-$D$2)/($E$2-$D$2)+$AF17 -> -0.0361 | AI17: =($E4-$D4)*('Extrapolation average con.'!AI$15-$D$2)/($E$2-$D$2)+$AF17 -> -0.03528 | AJ17: =($E4-$D4)*('Extrapolation average con.'!AJ$15-$D$2)/($E$2-$D$2)+$AF17 -> -0.03446 | AK17: =($E4-$D4)*('Extrapolation average con.'!AK$15-$D$2)/($E$2-$D$2)+$AF17 -> -0.03364 | AL17: =($E4-$D4)*('Extrapolation average con.'!AL$15-$D$2)/($E$2-$D$2)+$AF17 -> -0.03282 | AM17: =($E4-$D4)*('Extrapolation average con.'!AM$15-$D$2)/($E$2-$D$2)+$AF17 -> -0.032 | AN17: =($E4-$D4)*('Extrapolation average con.'!AN$15-$D$2)/($E$2-$D$2)+$AF17 -> -0.03118 | ... CD17: =($E4-$D4)*('Extrapolation average con.'!CD$15-$D$2)/($E$2-$D$2)+$AF17 -> 0.00326
