Workbook
Name cce: Translation!$C$256
Name Country: Country_data!$B$2:$B$197
Name Country: Country_data!$B$2:$B$197
Name cr: Translation!$C$254
Name Eqpt_list: PQEquipment!$D$6:$D$97
Name filtr: Translation!$C$325:$C$327
Name Formulation: Vaccine_database!$D$10:$D$278
Name fr: Translation!$C$255
Name freez: Translation!$C$258
Name Icepack_Freezers: Supplies!$C$51:$C$60
Name Icepacks: Supplies!$E$50:$G$50
Name Langues: Translation!$D$9:$I$9
Name Langues: Translation!$D$9:$I$9
Name max: Translation!$C$326
Name min: Translation!$C$325
Name Passive_contain: Supplies!$C$64:$C$71
Name per_individual_vaccine: Translation!$C$21:$C$24
Name refr: Translation!$C$257
Name Schedule: Vaccine_Selection!$M$16:$Q$16
Name SIAs: Vaccine_Selection!$S$16:$U$16
Name smax: Abacus_Tables!$F$4:$F$7
Name target: Translation!XFC$314:XFC$315
Name target1: Translation!$C$314
Name target2: Translation!$C$315
Name Vaccines: OFFSET([1]Vaccine_database!$B$11,0,0,COUNTA([1]Vaccine_database!$B$1:$B$65536)-1,1)
Name Vaccines: Vaccine_database!$C$10:$C$278
Name Vaccines1: OFFSET([2]Vaccine_database!$B$221,0,0,COUNTA([2]Vaccine_database!$B1048574:$B36)-1,1)
Name Vaccines1: Vaccine_database!$B$283:$B$325
Name WICR: Supplies!$B$36:$B$46
Name WICR_list: Supplies!$C$36:$C$46
Name WIFR: Supplies!$N$36:$N$46

Sheet Cover
C3: =Translation!C90 -> V A C C I N E V O L U M E C A L C U L A T O R
C10: =Translation!C91 -> Country: | D10: Erehwonia
C12: =Translation!C92 -> Language: | D12: English
C14: =Translation!C93 -> Date: | D14: 40919
D18: =Translation!C94 -> Click to index page
D20: =Translation!C95 -> v 2012.1 - January 2012
E27: Contact: kones@who.int

Sheet Index
B2: =Translation!C96 -> Index and instructions
B3: =Translation!C104 -> 1) The Vaccine Volume Calculator is used to estimate the net volume of vaccines and related supplies at each level in the supply chain. It can also be used to estimate the type of cold chain equipment needed for a specific target population. The effect of new vaccine introductions can be tested by comparing one or more of these against the current schedule.
B4: =Translation!C105 -> 2) How to use the tool:
B5: =Translation!C106 -> STEP 1: Estimate net storage volume per recipient using the Vaccine_Selection worksheet.
B6: =Translation!C107 -> STEP 2: Use the Abacus_Tables worksheet to enter the data needed to generate graphs covering the range of target populations at each supply level.
B7: =Translation!C108 -> STEP 3: Use the graphs to read off the net storage volumes for a specific catchment population. Then use these data to select appropriate cold chain equipment.
B8: =Translation!C99 -> Data input sheets:
B9: =MID(D9,FIND("]",D9)+1,256) -> Vaccine_Selection | C9: =Vaccine_Selection!B2 -> Vaccine storage volumes | D9: =CELL("filename",Vaccine_Selection!A$1) -> C:\Users\WHO\Downloads\[vaccine_volume_calculator_2012.xlsx]Vaccine_Selection
B10: =MID(D10,FIND("]",D10)+1,256) -> Abacus_Tables | C10: =Abacus_Tables!B1 -> Analysis of national and sub-national storage | D10: =CELL("filename",Abacus_Tables!A$1) -> C:\Users\WHO\Downloads\[vaccine_volume_calculator_2012.xlsx]Abacus_Tables
B11: =Translation!C101 -> Data output sheets: results of assessment of requirements per recipient
B12: =MID(D12,FIND("]",D12)+1,256) -> Volume_Inject | C12: =Volume_Inject!$B$2 -> Volume of diluents and safe injection equipment per recipient | D12: =CELL("filename",Volume_Inject!A$1) -> C:\Users\WHO\Downloads\[vaccine_volume_calculator_2012.xlsx]Volume_Inject
B13: =MID(D13,FIND("]",D13)+1,256) -> Weight_Inject | C13: =Weight_Inject!$B$2 -> Weight of safe injection equipment per recipient | D13: =CELL("filename",Weight_Inject!A$1) -> C:\Users\WHO\Downloads\[vaccine_volume_calculator_2012.xlsx]Weight_Inject
B14: =MID(D14,FIND("]",D14)+1,256) -> Qty_Waste | C14: =Qty_Waste!$B$2 -> Estimate of the amount of injection waste generated per recipient | D14: =CELL("filename",Qty_Waste!A$1) -> C:\Users\WHO\Downloads\[vaccine_volume_calculator_2012.xlsx]Qty_Waste
B15: =MID(D15,FIND("]",D15)+1,256) -> Cost_Supplies | C15: =Cost_Supplies!$B$2 -> Cost of vaccines and safe injection equipment per recipient | D15: =CELL("filename",Cost_Supplies!A$1) -> C:\Users\WHO\Downloads\[vaccine_volume_calculator_2012.xlsx]Cost_Supplies
B16: =Translation!C100 -> Data output sheets: graphical illustration of results
B17: =MID(D17,FIND("]",D17)+1,256) -> Routine_illustration | C17: =Routine_illustration!B2 -> Illustration of results from analysis of vaccines used in routine vaccination | D17: =CELL("filename",Routine_illustration!A$1) -> C:\Users\WHO\Downloads\[vaccine_volume_calculator_2012.xlsx]Routine_illustration
B18: =MID(D18,FIND("]",D18)+1,256) -> SIAs_illustration | C18: =SIAs_illustration!B2 -> Illustration of results from analysis of vaccines planned for vaccination campaign | D18: =CELL("filename",SIAs_illustration!A$1) -> C:\Users\WHO\Downloads\[vaccine_volume_calculator_2012.xlsx]SIAs_illustration
B19: =Translation!C102 -> Graphs
B20: Abacus_NatStore_1 | C20: =Translation!D30 -> Graph for cold storage capacity at national and sub-national stores - @ +5°C: (different schedules with same Maximum Stock)
B21: Abacus_NatStore_2 | C21: =Translation!D32 -> Graph for cold storage capacity at national and sub-national stores - @ +5°C: (same schedule with different Maximum Stocks)
B22: Abacus_Dist_1 | C22: =Translation!D48 -> Graph for cold storage capacity at district stores - @ +5°C: (different schedules with same Maximum Stock)
B23: Abacus_Dist_2 | C23: =Translation!D50 -> Graph for cold storage capacity at district stores - @ +5°C: (same schedule with different Maximum Stocks)
B24: Abacus_SP_1 | C24: =Translation!D58 -> Graph for cold storage capacity at service points - @ +5°C: (different schedules with same Maximum Stock)
B25: Abacus_SP_2 | C25: =Translation!D60 -> Graph for cold storage capacity at service points - @ +5°C: (same schedule with different Maximum Stocks)
B26: ds_Abacus_NatStore_1 | C26: =Translation!D34 -> Graph for dry storage capacity at national and sub-national stores: (different schedules with same Maximum Stock)
B27: ds_Abacus_NatStore_2 | C27: =Translation!D36 -> Graph for dry storage capacity at national and sub-national stores: (same schedule with different Maximum Stocks)
B28: ds_Abacus_Dist_1 | C28: =Translation!D52 -> Graph for dry storage capacity at district stores: (different schedules with same Maximum Stock)
B29: ds_Abacus_Dist_2 | C29: =Translation!D54 -> Graph for dry storage capacity at district stores: (same schedule with different Maximum Stocks)
B30: ds_Abacus_SP_1 | C30: =Translation!D62 -> Graph for dry storage capacity at service points (different schedules with same Maximum Stock)
B31: ds_Abacus_SP_2 | C31: =Translation!D64 -> Graph for dry storage capacity at service points: (same schedule with different Maximum Stocks)
B32: =Translation!C103 -> Sheets with reference data:
B33: =MID(D33,FIND("]",D33)+1,256) -> Vaccine_database | C33: =Vaccine_database!B1 -> Vaccine database | D33: =CELL("filename",Vaccine_database!B$1) -> C:\Users\WHO\Downloads\[vaccine_volume_calculator_2012.xlsx]Vaccine_database
B34: =MID(D34,FIND("]",D34)+1,256) -> Supplies | C34: =Supplies!B2 -> Safe injection supplies and cold chain equipment | D34: =CELL("filename",Supplies!A$1) -> C:\Users\WHO\Downloads\[vaccine_volume_calculator_2012.xlsx]Supplies
B35: PQEquipment | C35: =PQEquipment!B1 -> Refrigerator and freezer database
B36: =MID(D36,FIND("]",D36)+1,256) -> Passive_containers | C36: =Passive_containers!B1 -> Passive container database | D36: =CELL("filename",Passive_containers!B2) -> C:\Users\WHO\Downloads\[vaccine_volume_calculator_2012.xlsx]Passive_containers
B37: =MID(D37,FIND("]",D37)+1,256) -> Translation | C37: =Translation!B1 -> Translation | D37: =CELL("filename",Translation!A1) -> C:\Users\WHO\Downloads\[vaccine_volume_calculator_2012.xlsx]Translation

Sheet Vaccine_Selection
B2: =Translation!C311 -> Vaccine storage volumes | V2: =Translation!C109 -> Index
B5: =Translation!C317 -> STEP 1: Choose vaccine filter: | D5: Average | E5: =Translation!C328 -> WARNING: The packed volume for each vaccine presentation differs between manufacturers. Select 'Min/Max/Average' depending upon whether you want to use the minimum, maximum or average packed volume per vaccine presentation from the vaccine database.
B6: =Translation!C318 -> STEP 2: Choose applicable vaccine types and presentations from the vaccine database. Optionally, enter volume/dose data for vaccine types that are not in the database.
B7: =Translation!C319 -> STEP 3: Indicate country-specific wastage rates for each vaccine. If there no national data, WHO/GAVI indicative rates will apply.
B8: =Translation!C320 -> STEP 4: Choose target group type: | E8: Unit of Population | G8: =Translation!C316 -> Choose 'FIC' (Fully Immunized Child) or choose 'Unit of Population' (UP) for an analysis based on percentage of total population receiving each vaccine. | AC8: =IF(E8=target1,target1,"")
B9: =Translation!C321 -> STEP 5: If you chosen 'Unit of Population' in step 5, enter the Unit of Population % for each vaccine in cells L18 to L37. Otherwise go to STEP 6.
B10: =Translation!C322 -> STEP 6: In column M, enter the number of doses per recipient for vaccines in the current schedule. Optionally use columns N to Q for alternative schedules. In cells N17 to Q17 enter a title for each schedule.
B11: =Translation!C323 -> STEP 7: Use columns S to U to enter the number of doses per recipient for planned mass vaccination campaigns. In cells S17 to U17 enter a title for each schedule.
B12: =Translation!C324 -> STEP 8: For each vaccine, enter the maximum supply interval and the safety stock level at the primary store.
B14: =Translation!C329 -> Characteristics of vaccines selected for use | I14: =Translation!C340 -> Vaccine wastage | L14: =Translation!C344 -> UP data | M14: =Translation!C346 -> National immunization schedule | S14: =Translation!C349 -> Supplementary | V14: =Translation!C351 -> Primary store | Y14: =M14 -> National immunization schedule
B15: =Translation!C330 -> Vaccine | C15: =Translation!C331 -> Presentation | D15: =Translation!C333 -> National figures | F15: =Translation!C335 -> from data base | H15: =Translation!C338 -> Price | M15: =Translation!C347 -> (Routine vaccinations) | S15: =Translation!C350 -> activities (SIAs) | V15: =Translation!C352 -> supply parameters (months) | Y15: =Translation!C355 -> (based on individual vaccine shipments)
B16: =Translation!C332 -> Choose from dropdown list | C16: =B16 -> Choose from dropdown list | D16: =Translation!C336 -> Vaccine volume (cm³/dose) | E16: =Translation!C337 -> Diluent volume (cm³/dose) | F16: =D16 -> Vaccine volume (cm³/dose) | G16: =E16 -> Diluent volume (cm³/dose) | H16: =Translation!C339 -> (US$/ dose) | I16: =Translation!C341 -> National wastage rates (%) | J16: =Translation!C342 -> WHO/GAVI indicative rates (%) | K16: =Translation!C343 -> Wastage factor | L16: =Translation!C345 -> Enter as % of total population | M16: =Translation!C348 -> Current schedule | N16: Current schedule with penta 1d | O16: Current schedule with penta CAD | S16: H1N1 campaign | V16: =Translation!C353 -> Maxi supply interval | W16: =Translation!C354 -> Safety stock | Y16: =M16 -> Current schedule | Z16: =IF(N16="","",N16) -> Current schedule with penta 1d | AA16: =IF(O16="","",O16) -> Current schedule with penta CAD | AB16: =IF(P16="","",P16) | AC16: =IF(Q16="","",Q16)
B17: BCG | C17: 20 | F17: {=IF(B17="",0,IF($D$5=min,MIN(IF(Vaccines=$B17,IF(Formulation=Volume_Inject!$C13,IF(Vaccine_database!$E$10:$E$278=Volume_Inject!$D13,IF(Vaccine_database!$J$10:$J$278=$C17,Vaccine_database!K$10:K$278))))),IF($D$5=max,MAX(IF(Vaccines=$B17,IF(Formulation=Volume_Inject!$C13,IF(Vaccine_database!$E$10:$E$278=Volume_Inject!$D13,IF(Vaccine_database!$J$10:$J$278=$C17,Vaccine_database!K$10:K$278))))),AVERAGE(IF(Vaccines=$B17,IF(Formulation=Volume_Inject!$C13,IF(Vaccine_database!$E$10:$E$278=Volume_Inject!$D13,IF(Vaccine_database!$J$10:$J$278=$C17,Vaccine_database!K$10:K$278))))))))} -> 1.2102 | G17: {=IF(C17="",0,IF($D$5=min,MIN(IF(Vaccines=$B17,IF(Formulation=Volume_Inject!$C13,IF(Vaccine_database!$E$10:$E$278=Volume_Inject!$D13,IF(Vaccine_database!$J$10:$J$278=$C17,Vaccine_database!L$10:L$278))))),IF($D$5=max,MAX(IF(Vaccines=$B17,IF(Formulation=Volume_Inject!$C13,IF(Vaccine_database!$E$10:$E$278=Volume_Inject!$D13,IF(Vaccine_database!$J$10:$J$278=$C17,Vaccine_database!L$10:L$278))))),AVERAGE(IF(Vaccines=$B17,IF(Formulation=Volume_Inject!$C13,IF(Vaccine_database!$E$10:$E$278=Volume_Inject!$D13,IF(Vaccine_database!$J$10:$J$278=$C17,Vaccine_database!L$10:L$278))))))))} -> 1.1256667 | J17: =IF(B17="","",IF(OR(ISTEXT(C17),C17=1),5,IF(Volume_Inject!$C13<>"liquid",IF(C17>=20,50,IF(C17=10,40,10)),IF(C17>=10,25,10)))) -> 50 | K17: =IF(I17="",IF($J17="",0,100/(100-$J17)),100/(100-$I17)) -> 2 | L17: 0.019 | M17: 1 | N17: 1 | O17: 1 | V17: 4 | W17: 1 | Y17: =IF($V17="",0,Volume_Inject!$F13*$K17*M17*($V17+$W17)/12) -> 1.0085 | Z17: =IF($V17="",0,Volume_Inject!$F13*$K17*N17*($V17+$W17)/12) -> 1.0085 | AA17: =IF($V17="",0,Volume_Inject!$F13*$K17*O17*($V17+$W17)/12) -> 1.0085 | AB17: =IF($V17="",0,Volume_Inject!$F13*$K17*P17*($V17+$W17)/12) -> 0 | AC17: =IF($V17="",0,Volume_Inject!$F13*$K17*Q17*($V17+$W17)/12) -> 0
B18: OPV | C18: 10 | F18: {=IF(B18="",0,IF($D$5=min,MIN(IF(Vaccines=$B18,IF(Formulation=Volume_Inject!$C14,IF(Vaccine_database!$E$10:$E$278=Volume_Inject!$D14,IF(Vaccine_database!$J$10:$J$278=$C18,Vaccine_database!K$10:K$278))))),IF($D$5=max,MAX(IF(Vaccines=$B18,IF(Formulation=Volume_Inject!$C14,IF(Vaccine_database!$E$10:$E$278=Volume_Inject!$D14,IF(Vaccine_database!$J$10:$J$278=$C18,Vaccine_database!K$10:K$278))))),AVERAGE(IF(Vaccines=$B18,IF(Formulation=Volume_Inject!$C14,IF(Vaccine_database!$E$10:$E$278=Volume_Inject!$D14,IF(Vaccine_database!$J$10:$J$278=$C18,Vaccine_database!K$10:K$278))))))))} -> 2 | G18: {=IF(C18="",0,IF($D$5=min,MIN(IF(Vaccines=$B18,IF(Formulation=Volume_Inject!$C14,IF(Vaccine_database!$E$10:$E$278=Volume_Inject!$D14,IF(Vaccine_database!$J$10:$J$278=$C18,Vaccine_database!L$10:L$278))))),IF($D$5=max,MAX(IF(Vaccines=$B18,IF(Formulation=Volume_Inject!$C14,IF(Vaccine_database!$E$10:$E$278=Volume_Inject!$D14,IF(Vaccine_database!$J$10:$J$278=$C18,Vaccine_database!L$10:L$278))))),AVERAGE(IF(Vaccines=$B18,IF(Formulation=Volume_Inject!$C14,IF(Vaccine_database!$E$10:$E$278=Volume_Inject!$D14,IF(Vaccine_database!$J$10:$J$278=$C18,Vaccine_database!L$10:L$278))))))))} -> 0 | J18: =IF(B18="","",IF(OR(ISTEXT(C18),C18=1),5,IF(Volume_Inject!$C14<>"liquid",IF(C18>=20,50,IF(C18=10,40,10)),IF(C18>=10,25,10)))) -> 25 | K18: =IF(I18="",IF($J18="",0,100/(100-$J18)),100/(100-$I18)) -> 1.3333333 | L18: 0.019 | M18: 4 | N18: 4 | O18: 4 | V18: 4 | W18: 1 | Y18: =IF($V18="",0,Volume_Inject!$F14*$K18*M18*($V18+$W18)/12) -> 4.4444444 | Z18: =IF($V18="",0,Volume_Inject!$F14*$K18*N18*($V18+$W18)/12) -> 4.4444444 | AA18: =IF($V18="",0,Volume_Inject!$F14*$K18*O18*($V18+$W18)/12) -> 4.4444444 | AB18: =IF($V18="",0,Volume_Inject!$F14*$K18*P18*($V18+$W18)/12) -> 0 | AC18: =IF($V18="",0,Volume_Inject!$F14*$K18*Q18*($V18+$W18)/12) -> 0
B19: DTP-HepB-Hib | C19: 10 | F19: {=IF(B19="",0,IF($D$5=min,MIN(IF(Vaccines=$B19,IF(Formulation=Volume_Inject!$C15,IF(Vaccine_database!$E$10:$E$278=Volume_Inject!$D15,IF(Vaccine_database!$J$10:$J$278=$C19,Vaccine_database!K$10:K$278))))),IF($D$5=max,MAX(IF(Vaccines=$B19,IF(Formulation=Volume_Inject!$C15,IF(Vaccine_database!$E$10:$E$278=Volume_Inject!$D15,IF(Vaccine_database!$J$10:$J$278=$C19,Vaccine_database!K$10:K$278))))),AVERAGE(IF(Vaccines=$B19,IF(Formulation=Volume_Inject!$C15,IF(Vaccine_database!$E$10:$E$278=Volume_Inject!$D15,IF(Vaccine_database!$J$10:$J$278=$C19,Vaccine_database!K$10:K$278))))))))} -> 2.75 | G19: {=IF(C19="",0,IF($D$5=min,MIN(IF(Vaccines=$B19,IF(Formulation=Volume_Inject!$C15,IF(Vaccine_database!$E$10:$E$278=Volume_Inject!$D15,IF(Vaccine_database!$J$10:$J$278=$C19,Vaccine_database!L$10:L$278))))),IF($D$5=max,MAX(IF(Vaccines=$B19,IF(Formulation=Volume_Inject!$C15,IF(Vaccine_database!$E$10:$E$278=Volume_Inject!$D15,IF(Vaccine_database!$J$10:$J$278=$C19,Vaccine_database!L$10:L$278))))),AVERAGE(IF(Vaccines=$B19,IF(Formulation=Volume_Inject!$C15,IF(Vaccine_database!$E$10:$E$278=Volume_Inject!$D15,IF(Vaccine_database!$J$10:$J$278=$C19,Vaccine_database!L$10:L$278))))))))} -> 0 | J19: =IF(B19="","",IF(OR(ISTEXT(C19),C19=1),5,IF(Volume_Inject!$C15<>"liquid",IF(C19>=20,50,IF(C19=10,40,10)),IF(C19>=10,25,10)))) -> 25 | K19: =IF(I19="",IF($J19="",0,100/(100-$J19)),100/(100-$I19)) -> 1.3333333 | L19: 0.019 | M19: 3 | V19: 4 | W19: 1 | Y19: =IF($V19="",0,Volume_Inject!$F15*$K19*M19*($V19+$W19)/12) -> 4.5833333 | Z19: =IF($V19="",0,Volume_Inject!$F15*$K19*N19*($V19+$W19)/12) -> 0 | AA19: =IF($V19="",0,Volume_Inject!$F15*$K19*O19*($V19+$W19)/12) -> 0 | AB19: =IF($V19="",0,Volume_Inject!$F15*$K19*P19*($V19+$W19)/12) -> 0 | AC19: =IF($V19="",0,Volume_Inject!$F15*$K19*Q19*($V19+$W19)/12) -> 0
B20: DTP-HepB-Hib | C20: 1 | F20: {=IF(B20="",0,IF($D$5=min,MIN(IF(Vaccines=$B20,IF(Formulation=Volume_Inject!$C16,IF(Vaccine_database!$E$10:$E$278=Volume_Inject!$D16,IF(Vaccine_database!$J$10:$J$278=$C20,Vaccine_database!K$10:K$278))))),IF($D$5=max,MAX(IF(Vaccines=$B20,IF(Formulation=Volume_Inject!$C16,IF(Vaccine_database!$E$10:$E$278=Volume_Inject!$D16,IF(Vaccine_database!$J$10:$J$278=$C20,Vaccine_database!K$10:K$278))))),AVERAGE(IF(Vaccines=$B20,IF(Formulation=Volume_Inject!$C16,IF(Vaccine_database!$E$10:$E$278=Volume_Inject!$D16,IF(Vaccine_database!$J$10:$J$278=$C20,Vaccine_database!K$10:K$278))))))))} -> 16.66384 | G20: {=IF(C20="",0,IF($D$5=min,MIN(IF(Vaccines=$B20,IF(Formulation=Volume_Inject!$C16,IF(Vaccine_database!$E$10:$E$278=Volume_Inject!$D16,IF(Vaccine_database!$J$10:$J$278=$C20,Vaccine_database!L$10:L$278))))),IF($D$5=max,MAX(IF(Vaccines=$B20,IF(Formulation=Volume_Inject!$C16,IF(Vaccine_database!$E$10:$E$278=Volume_Inject!$D16,IF(Vaccine_database!$J$10:$J$278=$C20,Vaccine_database!L$10:L$278))))),AVERAGE(IF(Vaccines=$B20,IF(Formulation=Volume_Inject!$C16,IF(Vaccine_database!$E$10:$E$278=Volume_Inject!$D16,IF(Vaccine_database!$J$10:$J$278=$C20,Vaccine_database!L$10:L$278))))))))} -> 0 | J20: =IF(B20="","",IF(OR(ISTEXT(C20),C20=1),5,IF(Volume_Inject!$C16<>"liquid",IF(C20>=20,50,IF(C20=10,40,10)),IF(C20>=10,25,10)))) -> 5 | K20: =IF(I20="",IF($J20="",0,100/(100-$J20)),100/(100-$I20)) -> 1.0526316 | L20: 0.019 | N20: 3 | V20: 3 | W20: 1 | Y20: =IF($V20="",0,Volume_Inject!$F16*$K20*M20*($V20+$W20)/12) -> 0 | Z20: =IF($V20="",0,Volume_Inject!$F16*$K20*N20*($V20+$W20)/12) -> 17.540884 | AA20: =IF($V20="",0,Volume_Inject!$F16*$K20*O20*($V20+$W20)/12) -> 0 | AB20: =IF($V20="",0,Volume_Inject!$F16*$K20*P20*($V20+$W20)/12) -> 0 | AC20: =IF($V20="",0,Volume_Inject!$F16*$K20*Q20*($V20+$W20)/12) -> 0
B21: DTP-HepB-Hib | C21: Uniject | D21: 12 | F21: {=IF(B21="",0,IF($D$5=min,MIN(IF(Vaccines=$B21,IF(Formulation=Volume_Inject!$C17,IF(Vaccine_database!$E$10:$E$278=Volume_Inject!$D17,IF(Vaccine_database!$J$10:$J$278=$C21,Vaccine_database!K$10:K$278))))),IF($D$5=max,MAX(IF(Vaccines=$B21,IF(Formulation=Volume_Inject!$C17,IF(Vaccine_database!$E$10:$E$278=Volume_Inject!$D17,IF(Vaccine_database!$J$10:$J$278=$C21,Vaccine_database!K$10:K$278))))),AVERAGE(IF(Vaccines=$B21,IF(Formulation=Volume_Inject!$C17,IF(Vaccine_database!$E$10:$E$278=Volume_Inject!$D17,IF(Vaccine_database!$J$10:$J$278=$C21,Vaccine_database!K$10:K$278))))))))} -> #DIV/0! | G21: {=IF(C21="",0,IF($D$5=min,MIN(IF(Vaccines=$B21,IF(Formulation=Volume_Inject!$C17,IF(Vaccine_database!$E$10:$E$278=Volume_Inject!$D17,IF(Vaccine_database!$J$10:$J$278=$C21,Vaccine_database!L$10:L$278))))),IF($D$5=max,MAX(IF(Vaccines=$B21,IF(Formulation=Volume_Inject!$C17,IF(Vaccine_database!$E$10:$E$278=Volume_Inject!$D17,IF(Vaccine_database!$J$10:$J$278=$C21,Vaccine_database!L$10:L$278))))),AVERAGE(IF(Vaccines=$B21,IF(Formulation=Volume_Inject!$C17,IF(Vaccine_database!$E$10:$E$278=Volume_Inject!$D17,IF(Vaccine_database!$J$10:$J$278=$C21,Vaccine_database!L$10:L$278))))))))} -> #DIV/0! | J21: =IF(B21="","",IF(OR(ISTEXT(C21),C21=1),5,IF(Volume_Inject!$C17<>"liquid",IF(C21>=20,50,IF(C21=10,40,10)),IF(C21>=10,25,10)))) -> 5 | K21: =IF(I21="",IF($J21="",0,100/(100-$J21)),100/(100-$I21)) -> 1.0526316 | L21: 0.019 | O21: 3 | V21: 4 | W21: 1 | Y21: =IF($V21="",0,Volume_Inject!$F17*$K21*M21*($V21+$W21)/12) -> 0 | Z21: =IF($V21="",0,Volume_Inject!$F17*$K21*N21*($V21+$W21)/12) -> 0 | AA21: =IF($V21="",0,Volume_Inject!$F17*$K21*O21*($V21+$W21)/12) -> 15.789474 | AB21: =IF($V21="",0,Volume_Inject!$F17*$K21*P21*($V21+$W21)/12) -> 0 | AC21: =IF($V21="",0,Volume_Inject!$F17*$K21*Q21*($V21+$W21)/12) -> 0
B22: Measles | C22: 10 | F22: {=IF(B22="",0,IF($D$5=min,MIN(IF(Vaccines=$B22,IF(Formulation=Volume_Inject!$C18,IF(Vaccine_database!$E$10:$E$278=Volume_Inject!$D18,IF(Vaccine_database!$J$10:$J$278=$C22,Vaccine_database!K$10:K$278))))),IF($D$5=max,MAX(IF(Vaccines=$B22,IF(Formulation=Volume_Inject!$C18,IF(Vaccine_database!$E$10:$E$278=Volume_Inject!$D18,IF(Vaccine_database!$J$10:$J$278=$C22,Vaccine_database!K$10:K$278))))),AVERAGE(IF(Vaccines=$B22,IF(Formulation=Volume_Inject!$C18,IF(Vaccine_database!$E$10:$E$278=Volume_Inject!$D18,IF(Vaccine_database!$J$10:$J$278=$C22,Vaccine_database!K$10:K$278))))))))} -> 2.4002 | G22: {=IF(C22="",0,IF($D$5=min,MIN(IF(Vaccines=$B22,IF(Formulation=Volume_Inject!$C18,IF(Vaccine_database!$E$10:$E$278=Volume_Inject!$D18,IF(Vaccine_database!$J$10:$J$278=$C22,Vaccine_database!L$10:L$278))))),IF($D$5=max,MAX(IF(Vaccines=$B22,IF(Formulation=Volume_Inject!$C18,IF(Vaccine_database!$E$10:$E$278=Volume_Inject!$D18,IF(Vaccine_database!$J$10:$J$278=$C22,Vaccine_database!L$10:L$278))))),AVERAGE(IF(Vaccines=$B22,IF(Formulation=Volume_Inject!$C18,IF(Vaccine_database!$E$10:$E$278=Volume_Inject!$D18,IF(Vaccine_database!$J$10:$J$278=$C22,Vaccine_database!L$10:L$278))))))))} -> 3.2 | J22: =IF(B22="","",IF(OR(ISTEXT(C22),C22=1),5,IF(Volume_Inject!$C18<>"liquid",IF(C22>=20,50,IF(C22=10,40,10)),IF(C22>=10,25,10)))) -> 40 | K22: =IF(I22="",IF($J22="",0,100/(100-$J22)),100/(100-$I22)) -> 1.6666667 | L22: 0.018 | M22: 1 | N22: 1 | O22: 1 | V22: 4 | W22: 1 | Y22: =IF($V22="",0,Volume_Inject!$F18*$K22*M22*($V22+$W22)/12) -> 1.6668056 | Z22: =IF($V22="",0,Volume_Inject!$F18*$K22*N22*($V22+$W22)/12) -> 1.6668056 | AA22: =IF($V22="",0,Volume_Inject!$F18*$K22*O22*($V22+$W22)/12) -> 1.6668056 | AB22: =IF($V22="",0,Volume_Inject!$F18*$K22*P22*($V22+$W22)/12) -> 0 | AC22: =IF($V22="",0,Volume_Inject!$F18*$K22*Q22*($V22+$W22)/12) -> 0
B23: YF | C23: 5 | F23: {=IF(B23="",0,IF($D$5=min,MIN(IF(Vaccines=$B23,IF(Formulation=Volume_Inject!$C19,IF(Vaccine_database!$E$10:$E$278=Volume_Inject!$D19,IF(Vaccine_database!$J$10:$J$278=$C23,Vaccine_database!K$10:K$278))))),IF($D$5=max,MAX(IF(Vaccines=$B23,IF(Formulation=Volume_Inject!$C19,IF(Vaccine_database!$E$10:$E$278=Volume_Inject!$D19,IF(Vaccine_database!$J$10:$J$278=$C23,Vaccine_database!K$10:K$278))))),AVERAGE(IF(Vaccines=$B23,IF(Formulation=Volume_Inject!$C19,IF(Vaccine_database!$E$10:$E$278=Volume_Inject!$D19,IF(Vaccine_database!$J$10:$J$278=$C23,Vaccine_database!K$10:K$278))))))))} -> 5.4025 | G23: {=IF(C23="",0,IF($D$5=min,MIN(IF(Vaccines=$B23,IF(Formulation=Volume_Inject!$C19,IF(Vaccine_database!$E$10:$E$278=Volume_Inject!$D19,IF(Vaccine_database!$J$10:$J$278=$C23,Vaccine_database!L$10:L$278))))),IF($D$5=max,MAX(IF(Vaccines=$B23,IF(Formulation=Volume_Inject!$C19,IF(Vaccine_database!$E$10:$E$278=Volume_Inject!$D19,IF(Vaccine_database!$J$10:$J$278=$C23,Vaccine_database!L$10:L$278))))),AVERAGE(IF(Vaccines=$B23,IF(Formulation=Volume_Inject!$C19,IF(Vaccine_database!$E$10:$E$278=Volume_Inject!$D19,IF(Vaccine_database!$J$10:$J$278=$C23,Vaccine_database!L$10:L$278))))))))} -> 6.75 | J23: =IF(B23="","",IF(OR(ISTEXT(C23),C23=1),5,IF(Volume_Inject!$C19<>"liquid",IF(C23>=20,50,IF(C23=10,40,10)),IF(C23>=10,25,10)))) -> 10 | K23: =IF(I23="",IF($J23="",0,100/(100-$J23)),100/(100-$I23)) -> 1.1111111 | L23: 0.018 | M23: 1 | N23: 1 | O23: 1 | V23: 4 | W23: 1 | Y23: =IF($V23="",0,Volume_Inject!$F19*$K23*M23*($V23+$W23)/12) -> 2.5011574 | Z23: =IF($V23="",0,Volume_Inject!$F19*$K23*N23*($V23+$W23)/12) -> 2.5011574 | AA23: =IF($V23="",0,Volume_Inject!$F19*$K23*O23*($V23+$W23)/12) -> 2.5011574 | AB23: =IF($V23="",0,Volume_Inject!$F19*$K23*P23*($V23+$W23)/12) -> 0 | AC23: =IF($V23="",0,Volume_Inject!$F19*$K23*Q23*($V23+$W23)/12) -> 0
B24: TT | C24: 10 | F24: {=IF(B24="",0,IF($D$5=min,MIN(IF(Vaccines=$B24,IF(Formulation=Volume_Inject!$C20,IF(Vaccine_database!$E$10:$E$278=Volume_Inject!$D20,IF(Vaccine_database!$J$10:$J$278=$C24,Vaccine_database!K$10:K$278))))),IF($D$5=max,MAX(IF(Vaccines=$B24,IF(Formulation=Volume_Inject!$C20,IF(Vaccine_database!$E$10:$E$278=Volume_Inject!$D20,IF(Vaccine_database!$J$10:$J$278=$C24,Vaccine_database!K$10:K$278))))),AVERAGE(IF(Vaccines=$B24,IF(Formulation=Volume_Inject!$C20,IF(Vaccine_database!$E$10:$E$278=Volume_Inject!$D20,IF(Vaccine_database!$J$10:$J$278=$C24,Vaccine_database!K$10:K$278))))))))} -> 3.1093333 | G24: {=IF(C24="",0,IF($D$5=min,MIN(IF(Vaccines=$B24,IF(Formulation=Volume_Inject!$C20,IF(Vaccine_database!$E$10:$E$278=Volume_Inject!$D20,IF(Vaccine_database!$J$10:$J$278=$C24,Vaccine_database!L$10:L$278))))),IF($D$5=max,MAX(IF(Vaccines=$B24,IF(Formulation=Volume_Inject!$C20,IF(Vaccine_database!$E$10:$E$278=Volume_Inject!$D20,IF(Vaccine_database!$J$10:$J$278=$C24,Vaccine_database!L$10:L$278))))),AVERAGE(IF(Vaccines=$B24,IF(Formulation=Volume_Inject!$C20,IF(Vaccine_database!$E$10:$E$278=Volume_Inject!$D20,IF(Vaccine_database!$J$10:$J$278=$C24,Vaccine_database!L$10:L$278))))))))} -> 0 | J24: =IF(B24="","",IF(OR(ISTEXT(C24),C24=1),5,IF(Volume_Inject!$C20<>"liquid",IF(C24>=20,50,IF(C24=10,40,10)),IF(C24>=10,25,10)))) -> 25 | K24: =IF(I24="",IF($J24="",0,100/(100-$J24)),100/(100-$I24)) -> 1.3333333 | L24: 0.02 | M24: 2 | N24: 2 | O24: 2 | V24: 3 | W24: 1 | Y24: =IF($V24="",0,Volume_Inject!$F20*$K24*M24*($V24+$W24)/12) -> 2.7638519 | Z24: =IF($V24="",0,Volume_Inject!$F20*$K24*N24*($V24+$W24)/12) -> 2.7638519 | AA24: =IF($V24="",0,Volume_Inject!$F20*$K24*O24*($V24+$W24)/12) -> 2.7638519 | AB24: =IF($V24="",0,Volume_Inject!$F20*$K24*P24*($V24+$W24)/12) -> 0 | AC24: =IF($V24="",0,Volume_Inject!$F20*$K24*Q24*($V24+$W24)/12) -> 0
B25: PCV-13 | C25: 1 | F25: {=IF(B25="",0,IF($D$5=min,MIN(IF(Vaccines=$B25,IF(Formulation=Volume_Inject!$C21,IF(Vaccine_database!$E$10:$E$278=Volume_Inject!$D21,IF(Vaccine_database!$J$10:$J$278=$C25,Vaccine_database!K$10:K$278))))),IF($D$5=max,MAX(IF(Vaccines=$B25,IF(Formulation=Volume_Inject!$C21,IF(Vaccine_database!$E$10:$E$278=Volume_Inject!$D21,IF(Vaccine_database!$J$10:$J$278=$C25,Vaccine_database!K$10:K$278))))),AVERAGE(IF(Vaccines=$B25,IF(Formulation=Volume_Inject!$C21,IF(Vaccine_database!$E$10:$E$278=Volume_Inject!$D21,IF(Vaccine_database!$J$10:$J$278=$C25,Vaccine_database!K$10:K$278))))))))} -> 13.825247 | G25: {=IF(C25="",0,IF($D$5=min,MIN(IF(Vaccines=$B25,IF(Formulation=Volume_Inject!$C21,IF(Vaccine_database!$E$10:$E$278=Volume_Inject!$D21,IF(Vaccine_database!$J$10:$J$278=$C25,Vaccine_database!L$10:L$278))))),IF($D$5=max,MAX(IF(Vaccines=$B25,IF(Formulation=Volume_Inject!$C21,IF(Vaccine_database!$E$10:$E$278=Volume_Inject!$D21,IF(Vaccine_database!$J$10:$J$278=$C25,Vaccine_database!L$10:L$278))))),AVERAGE(IF(Vaccines=$B25,IF(Formulation=Volume_Inject!$C21,IF(Vaccine_database!$E$10:$E$278=Volume_Inject!$D21,IF(Vaccine_database!$J$10:$J$278=$C25,Vaccine_database!L$10:L$278))))))))} -> 0 | J25: =IF(B25="","",IF(OR(ISTEXT(C25),C25=1),5,IF(Volume_Inject!$C21<>"liquid",IF(C25>=20,50,IF(C25=10,40,10)),IF(C25>=10,25,10)))) -> 5 | K25: =IF(I25="",IF($J25="",0,100/(100-$J25)),100/(100-$I25)) -> 1.0526316 | L25: 0.01 | V25: 12 | W25: 0 | Y25: =IF($V25="",0,Volume_Inject!$F21*$K25*M25*($V25+$W25)/12) -> 0 | Z25: =IF($V25="",0,Volume_Inject!$F21*$K25*N25*($V25+$W25)/12) -> 0 | AA25: =IF($V25="",0,Volume_Inject!$F21*$K25*O25*($V25+$W25)/12) -> 0 | AB25: =IF($V25="",0,Volume_Inject!$F21*$K25*P25*($V25+$W25)/12) -> 0 | AC25: =IF($V25="",0,Volume_Inject!$F21*$K25*Q25*($V25+$W25)/12) -> 0
B26: Rota_liq | C26: 1 | D26: 17.1 | F26: {=IF(B26="",0,IF($D$5=min,MIN(IF(Vaccines=$B26,IF(Formulation=Volume_Inject!$C22,IF(Vaccine_database!$E$10:$E$278=Volume_Inject!$D22,IF(Vaccine_database!$J$10:$J$278=$C26,Vaccine_database!K$10:K$278))))),IF($D$5=max,MAX(IF(Vaccines=$B26,IF(Formulation=Volume_Inject!$C22,IF(Vaccine_database!$E$10:$E$278=Volume_Inject!$D22,IF(Vaccine_database!$J$10:$J$278=$C26,Vaccine_database!K$10:K$278))))),AVERAGE(IF(Vaccines=$B26,IF(Formulation=Volume_Inject!$C22,IF(Vaccine_database!$E$10:$E$278=Volume_Inject!$D22,IF(Vaccine_database!$J$10:$J$278=$C26,Vaccine_database!K$10:K$278))))))))} -> 17.1258 | G26: {=IF(C26="",0,IF($D$5=min,MIN(IF(Vaccines=$B26,IF(Formulation=Volume_Inject!$C22,IF(Vaccine_database!$E$10:$E$278=Volume_Inject!$D22,IF(Vaccine_database!$J$10:$J$278=$C26,Vaccine_database!L$10:L$278))))),IF($D$5=max,MAX(IF(Vaccines=$B26,IF(Formulation=Volume_Inject!$C22,IF(Vaccine_database!$E$10:$E$278=Volume_Inject!$D22,IF(Vaccine_database!$J$10:$J$278=$C26,Vaccine_database!L$10:L$278))))),AVERAGE(IF(Vaccines=$B26,IF(Formulation=Volume_Inject!$C22,IF(Vaccine_database!$E$10:$E$278=Volume_Inject!$D22,IF(Vaccine_database!$J$10:$J$278=$C26,Vaccine_database!L$10:L$278))))))))} -> 0 | J26: =IF(B26="","",IF(OR(ISTEXT(C26),C26=1),5,IF(Volume_Inject!$C22<>"liquid",IF(C26>=20,50,IF(C26=10,40,10)),IF(C26>=10,25,10)))) -> 5 | K26: =IF(I26="",IF($J26="",0,100/(100-$J26)),100/(100-$I26)) -> 1.0526316 | L26: 0.035 | S26: 1 | Y26: =IF($V26="",0,Volume_Inject!$F22*$K26*M26*($V26+$W26)/12) -> 0 | Z26: =IF($V26="",0,Volume_Inject!$F22*$K26*N26*($V26+$W26)/12) -> 0 | AA26: =IF($V26="",0,Volume_Inject!$F22*$K26*O26*($V26+$W26)/12) -> 0 | AB26: =IF($V26="",0,Volume_Inject!$F22*$K26*P26*($V26+$W26)/12) -> 0 | AC26: =IF($V26="",0,Volume_Inject!$F22*$K26*Q26*($V26+$W26)/12) -> 0
F27: {=IF(B27="",0,IF($D$5=min,MIN(IF(Vaccines=$B27,IF(Formulation=Volume_Inject!$C23,IF(Vaccine_database!$E$10:$E$278=Volume_Inject!$D23,IF(Vaccine_database!$J$10:$J$278=$C27,Vaccine_database!K$10:K$278))))),IF($D$5=max,MAX(IF(Vaccines=$B27,IF(Formulation=Volume_Inject!$C23,IF(Vaccine_database!$E$10:$E$278=Volume_Inject!$D23,IF(Vaccine_database!$J$10:$J$278=$C27,Vaccine_database!K$10:K$278))))),AVERAGE(IF(Vaccines=$B27,IF(Formulation=Volume_Inject!$C23,IF(Vaccine_database!$E$10:$E$278=Volume_Inject!$D23,IF(Vaccine_database!$J$10:$J$278=$C27,Vaccine_database!K$10:K$278))))))))} -> 0 | G27: {=IF(C27="",0,IF($D$5=min,MIN(IF(Vaccines=$B27,IF(Formulation=Volume_Inject!$C23,IF(Vaccine_database!$E$10:$E$278=Volume_Inject!$D23,IF(Vaccine_database!$J$10:$J$278=$C27,Vaccine_database!L$10:L$278))))),IF($D$5=max,MAX(IF(Vaccines=$B27,IF(Formulation=Volume_Inject!$C23,IF(Vaccine_database!$E$10:$E$278=Volume_Inject!$D23,IF(Vaccine_database!$J$10:$J$278=$C27,Vaccine_database!L$10:L$278))))),AVERAGE(IF(Vaccines=$B27,IF(Formulation=Volume_Inject!$C23,IF(Vaccine_database!$E$10:$E$278=Volume_Inject!$D23,IF(Vaccine_database!$J$10:$J$278=$C27,Vaccine_database!L$10:L$278))))))))} -> 0 | J27: =IF(B27="","",IF(OR(ISTEXT(C27),C27=1),5,IF(Volume_Inject!$C23<>"liquid",IF(C27>=20,50,IF(C27=10,40,10)),IF(C27>=10,25,10)))) | K27: =IF(I27="",IF($J27="",0,100/(100-$J27)),100/(100-$I27)) -> 0 | Y27: =IF($V27="",0,Volume_Inject!$F23*$K27*M27*($V27+$W27)/12) -> 0 | Z27: =IF($V27="",0,Volume_Inject!$F23*$K27*N27*($V27+$W27)/12) -> 0 | AA27: =IF($V27="",0,Volume_Inject!$F23*$K27*O27*($V27+$W27)/12) -> 0 | AB27: =IF($V27="",0,Volume_Inject!$F23*$K27*P27*($V27+$W27)/12) -> 0 | AC27: =IF($V27="",0,Volume_Inject!$F23*$K27*Q27*($V27+$W27)/12) -> 0
F28: {=IF(B28="",0,IF($D$5=min,MIN(IF(Vaccines=$B28,IF(Formulation=Volume_Inject!$C24,IF(Vaccine_database!$E$10:$E$278=Volume_Inject!$D24,IF(Vaccine_database!$J$10:$J$278=$C28,Vaccine_database!K$10:K$278))))),IF($D$5=max,MAX(IF(Vaccines=$B28,IF(Formulation=Volume_Inject!$C24,IF(Vaccine_database!$E$10:$E$278=Volume_Inject!$D24,IF(Vaccine_database!$J$10:$J$278=$C28,Vaccine_database!K$10:K$278))))),AVERAGE(IF(Vaccines=$B28,IF(Formulation=Volume_Inject!$C24,IF(Vaccine_database!$E$10:$E$278=Volume_Inject!$D24,IF(Vaccine_database!$J$10:$J$278=$C28,Vaccine_database!K$10:K$278))))))))} -> 0 | G28: {=IF(C28="",0,IF($D$5=min,MIN(IF(Vaccines=$B28,IF(Formulation=Volume_Inject!$C24,IF(Vaccine_database!$E$10:$E$278=Volume_Inject!$D24,IF(Vaccine_database!$J$10:$J$278=$C28,Vaccine_database!L$10:L$278))))),IF($D$5=max,MAX(IF(Vaccines=$B28,IF(Formulation=Volume_Inject!$C24,IF(Vaccine_database!$E$10:$E$278=Volume_Inject!$D24,IF(Vaccine_database!$J$10:$J$278=$C28,Vaccine_database!L$10:L$278))))),AVERAGE(IF(Vaccines=$B28,IF(Formulation=Volume_Inject!$C24,IF(Vaccine_database!$E$10:$E$278=Volume_Inject!$D24,IF(Vaccine_database!$J$10:$J$278=$C28,Vaccine_database!L$10:L$278))))))))} -> 0 | J28: =IF(B28="","",IF(OR(ISTEXT(C28),C28=1),5,IF(Volume_Inject!$C24<>"liquid",IF(C28>=20,50,IF(C28=10,40,10)),IF(C28>=10,25,10)))) | K28: =IF(I28="",IF($J28="",0,100/(100-$J28)),100/(100-$I28)) -> 0 | Y28: =IF($V28="",0,Volume_Inject!$F24*$K28*M28*($V28+$W28)/12) -> 0 | Z28: =IF($V28="",0,Volume_Inject!$F24*$K28*N28*($V28+$W28)/12) -> 0 | AA28: =IF($V28="",0,Volume_Inject!$F24*$K28*O28*($V28+$W28)/12) -> 0 | AB28: =IF($V28="",0,Volume_Inject!$F24*$K28*P28*($V28+$W28)/12) -> 0 | AC28: =IF($V28="",0,Volume_Inject!$F24*$K28*Q28*($V28+$W28)/12) -> 0
F29: {=IF(B29="",0,IF($D$5=min,MIN(IF(Vaccines=$B29,IF(Formulation=Volume_Inject!$C25,IF(Vaccine_database!$E$10:$E$278=Volume_Inject!$D25,IF(Vaccine_database!$J$10:$J$278=$C29,Vaccine_database!K$10:K$278))))),IF($D$5=max,MAX(IF(Vaccines=$B29,IF(Formulation=Volume_Inject!$C25,IF(Vaccine_database!$E$10:$E$278=Volume_Inject!$D25,IF(Vaccine_database!$J$10:$J$278=$C29,Vaccine_database!K$10:K$278))))),AVERAGE(IF(Vaccines=$B29,IF(Formulation=Volume_Inject!$C25,IF(Vaccine_database!$E$10:$E$278=Volume_Inject!$D25,IF(Vaccine_database!$J$10:$J$278=$C29,Vaccine_database!K$10:K$278))))))))} -> 0 | G29: {=IF(C29="",0,IF($D$5=min,MIN(IF(Vaccines=$B29,IF(Formulation=Volume_Inject!$C25,IF(Vaccine_database!$E$10:$E$278=Volume_Inject!$D25,IF(Vaccine_database!$J$10:$J$278=$C29,Vaccine_database!L$10:L$278))))),IF($D$5=max,MAX(IF(Vaccines=$B29,IF(Formulation=Volume_Inject!$C25,IF(Vaccine_database!$E$10:$E$278=Volume_Inject!$D25,IF(Vaccine_database!$J$10:$J$278=$C29,Vaccine_database!L$10:L$278))))),AVERAGE(IF(Vaccines=$B29,IF(Formulation=Volume_Inject!$C25,IF(Vaccine_database!$E$10:$E$278=Volume_Inject!$D25,IF(Vaccine_database!$J$10:$J$278=$C29,Vaccine_database!L$10:L$278))))))))} -> 0 | J29: =IF(B29="","",IF(OR(ISTEXT(C29),C29=1),5,IF(Volume_Inject!$C25<>"liquid",IF(C29>=20,50,IF(C29=10,40,10)),IF(C29>=10,25,10)))) | K29: =IF(I29="",IF($J29="",0,100/(100-$J29)),100/(100-$I29)) -> 0 | Y29: =IF($V29="",0,Volume_Inject!$F25*$K29*M29*($V29+$W29)/12) -> 0 | Z29: =IF($V29="",0,Volume_Inject!$F25*$K29*N29*($V29+$W29)/12) -> 0 | AA29: =IF($V29="",0,Volume_Inject!$F25*$K29*O29*($V29+$W29)/12) -> 0 | AB29: =IF($V29="",0,Volume_Inject!$F25*$K29*P29*($V29+$W29)/12) -> 0 | AC29: =IF($V29="",0,Volume_Inject!$F25*$K29*Q29*($V29+$W29)/12) -> 0
F30: {=IF(B30="",0,IF($D$5=min,MIN(IF(Vaccines=$B30,IF(Formulation=Volume_Inject!$C26,IF(Vaccine_database!$E$10:$E$278=Volume_Inject!$D26,IF(Vaccine_database!$J$10:$J$278=$C30,Vaccine_database!K$10:K$278))))),IF($D$5=max,MAX(IF(Vaccines=$B30,IF(Formulation=Volume_Inject!$C26,IF(Vaccine_database!$E$10:$E$278=Volume_Inject!$D26,IF(Vaccine_database!$J$10:$J$278=$C30,Vaccine_database!K$10:K$278))))),AVERAGE(IF(Vaccines=$B30,IF(Formulation=Volume_Inject!$C26,IF(Vaccine_database!$E$10:$E$278=Volume_Inject!$D26,IF(Vaccine_database!$J$10:$J$278=$C30,Vaccine_database!K$10:K$278))))))))} -> 0 | G30: {=IF(C30="",0,IF($D$5=min,MIN(IF(Vaccines=$B30,IF(Formulation=Volume_Inject!$C26,IF(Vaccine_database!$E$10:$E$278=Volume_Inject!$D26,IF(Vaccine_database!$J$10:$J$278=$C30,Vaccine_database!L$10:L$278))))),IF($D$5=max,MAX(IF(Vaccines=$B30,IF(Formulation=Volume_Inject!$C26,IF(Vaccine_database!$E$10:$E$278=Volume_Inject!$D26,IF(Vaccine_database!$J$10:$J$278=$C30,Vaccine_database!L$10:L$278))))),AVERAGE(IF(Vaccines=$B30,IF(Formulation=Volume_Inject!$C26,IF(Vaccine_database!$E$10:$E$278=Volume_Inject!$D26,IF(Vaccine_database!$J$10:$J$278=$C30,Vaccine_database!L$10:L$278))))))))} -> 0 | J30: =IF(B30="","",IF(OR(ISTEXT(C30),C30=1),5,IF(Volume_Inject!$C26<>"liquid",IF(C30>=20,50,IF(C30=10,40,10)),IF(C30>=10,25,10)))) | K30: =IF(I30="",IF($J30="",0,100/(100-$J30)),100/(100-$I30)) -> 0 | Y30: =IF($V30="",0,Volume_Inject!$F26*$K30*M30*($V30+$W30)/12) -> 0 | Z30: =IF($V30="",0,Volume_Inject!$F26*$K30*N30*($V30+$W30)/12) -> 0 | AA30: =IF($V30="",0,Volume_Inject!$F26*$K30*O30*($V30+$W30)/12) -> 0 | AB30: =IF($V30="",0,Volume_Inject!$F26*$K30*P30*($V30+$W30)/12) -> 0 | AC30: =IF($V30="",0,Volume_Inject!$F26*$K30*Q30*($V30+$W30)/12) -> 0
F31: {=IF(B31="",0,IF($D$5=min,MIN(IF(Vaccines=$B31,IF(Formulation=Volume_Inject!$C27,IF(Vaccine_database!$E$10:$E$278=Volume_Inject!$D27,IF(Vaccine_database!$J$10:$J$278=$C31,Vaccine_database!K$10:K$278))))),IF($D$5=max,MAX(IF(Vaccines=$B31,IF(Formulation=Volume_Inject!$C27,IF(Vaccine_database!$E$10:$E$278=Volume_Inject!$D27,IF(Vaccine_database!$J$10:$J$278=$C31,Vaccine_database!K$10:K$278))))),AVERAGE(IF(Vaccines=$B31,IF(Formulation=Volume_Inject!$C27,IF(Vaccine_database!$E$10:$E$278=Volume_Inject!$D27,IF(Vaccine_database!$J$10:$J$278=$C31,Vaccine_database!K$10:K$278))))))))} -> 0 | G31: {=IF(C31="",0,IF($D$5=min,MIN(IF(Vaccines=$B31,IF(Formulation=Volume_Inject!$C27,IF(Vaccine_database!$E$10:$E$278=Volume_Inject!$D27,IF(Vaccine_database!$J$10:$J$278=$C31,Vaccine_database!L$10:L$278))))),IF($D$5=max,MAX(IF(Vaccines=$B31,IF(Formulation=Volume_Inject!$C27,IF(Vaccine_database!$E$10:$E$278=Volume_Inject!$D27,IF(Vaccine_database!$J$10:$J$278=$C31,Vaccine_database!L$10:L$278))))),AVERAGE(IF(Vaccines=$B31,IF(Formulation=Volume_Inject!$C27,IF(Vaccine_database!$E$10:$E$278=Volume_Inject!$D27,IF(Vaccine_database!$J$10:$J$278=$C31,Vaccine_database!L$10:L$278))))))))} -> 0 | J31: =IF(B31="","",IF(OR(ISTEXT(C31),C31=1),5,IF(Volume_Inject!$C27<>"liquid",IF(C31>=20,50,IF(C31=10,40,10)),IF(C31>=10,25,10)))) | K31: =IF(I31="",IF($J31="",0,100/(100-$J31)),100/(100-$I31)) -> 0 | Y31: =IF($V31="",0,Volume_Inject!$F27*$K31*M31*($V31+$W31)/12) -> 0 | Z31: =IF($V31="",0,Volume_Inject!$F27*$K31*N31*($V31+$W31)/12) -> 0 | AA31: =IF($V31="",0,Volume_Inject!$F27*$K31*O31*($V31+$W31)/12) -> 0 | AB31: =IF($V31="",0,Volume_Inject!$F27*$K31*P31*($V31+$W31)/12) -> 0 | AC31: =IF($V31="",0,Volume_Inject!$F27*$K31*Q31*($V31+$W31)/12) -> 0
F32: {=IF(B32="",0,IF($D$5=min,MIN(IF(Vaccines=$B32,IF(Formulation=Volume_Inject!$C28,IF(Vaccine_database!$E$10:$E$278=Volume_Inject!$D28,IF(Vaccine_database!$J$10:$J$278=$C32,Vaccine_database!K$10:K$278))))),IF($D$5=max,MAX(IF(Vaccines=$B32,IF(Formulation=Volume_Inject!$C28,IF(Vaccine_database!$E$10:$E$278=Volume_Inject!$D28,IF(Vaccine_database!$J$10:$J$278=$C32,Vaccine_database!K$10:K$278))))),AVERAGE(IF(Vaccines=$B32,IF(Formulation=Volume_Inject!$C28,IF(Vaccine_database!$E$10:$E$278=Volume_Inject!$D28,IF(Vaccine_database!$J$10:$J$278=$C32,Vaccine_database!K$10:K$278))))))))} -> 0 | G32: {=IF(C32="",0,IF($D$5=min,MIN(IF(Vaccines=$B32,IF(Formulation=Volume_Inject!$C28,IF(Vaccine_database!$E$10:$E$278=Volume_Inject!$D28,IF(Vaccine_database!$J$10:$J$278=$C32,Vaccine_database!L$10:L$278))))),IF($D$5=max,MAX(IF(Vaccines=$B32,IF(Formulation=Volume_Inject!$C28,IF(Vaccine_database!$E$10:$E$278=Volume_Inject!$D28,IF(Vaccine_database!$J$10:$J$278=$C32,Vaccine_database!L$10:L$278))))),AVERAGE(IF(Vaccines=$B32,IF(Formulation=Volume_Inject!$C28,IF(Vaccine_database!$E$10:$E$278=Volume_Inject!$D28,IF(Vaccine_database!$J$10:$J$278=$C32,Vaccine_database!L$10:L$278))))))))} -> 0 | J32: =IF(B32="","",IF(OR(ISTEXT(C32),C32=1),5,IF(Volume_Inject!$C28<>"liquid",IF(C32>=20,50,IF(C32=10,40,10)),IF(C32>=10,25,10)))) | K32: =IF(I32="",IF($J32="",0,100/(100-$J32)),100/(100-$I32)) -> 0 | Y32: =IF($V32="",0,Volume_Inject!$F28*$K32*M32*($V32+$W32)/12) -> 0 | Z32: =IF($V32="",0,Volume_Inject!$F28*$K32*N32*($V32+$W32)/12) -> 0 | AA32: =IF($V32="",0,Volume_Inject!$F28*$K32*O32*($V32+$W32)/12) -> 0 | AB32: =IF($V32="",0,Volume_Inject!$F28*$K32*P32*($V32+$W32)/12) -> 0 | AC32: =IF($V32="",0,Volume_Inject!$F28*$K32*Q32*($V32+$W32)/12) -> 0
F33: {=IF(B33="",0,IF($D$5=min,MIN(IF(Vaccines=$B33,IF(Formulation=Volume_Inject!$C29,IF(Vaccine_database!$E$10:$E$278=Volume_Inject!$D29,IF(Vaccine_database!$J$10:$J$278=$C33,Vaccine_database!K$10:K$278))))),IF($D$5=max,MAX(IF(Vaccines=$B33,IF(Formulation=Volume_Inject!$C29,IF(Vaccine_database!$E$10:$E$278=Volume_Inject!$D29,IF(Vaccine_database!$J$10:$J$278=$C33,Vaccine_database!K$10:K$278))))),AVERAGE(IF(Vaccines=$B33,IF(Formulation=Volume_Inject!$C29,IF(Vaccine_database!$E$10:$E$278=Volume_Inject!$D29,IF(Vaccine_database!$J$10:$J$278=$C33,Vaccine_database!K$10:K$278))))))))} -> 0 | G33: {=IF(C33="",0,IF($D$5=min,MIN(IF(Vaccines=$B33,IF(Formulation=Volume_Inject!$C29,IF(Vaccine_database!$E$10:$E$278=Volume_Inject!$D29,IF(Vaccine_database!$J$10:$J$278=$C33,Vaccine_database!L$10:L$278))))),IF($D$5=max,MAX(IF(Vaccines=$B33,IF(Formulation=Volume_Inject!$C29,IF(Vaccine_database!$E$10:$E$278=Volume_Inject!$D29,IF(Vaccine_database!$J$10:$J$278=$C33,Vaccine_database!L$10:L$278))))),AVERAGE(IF(Vaccines=$B33,IF(Formulation=Volume_Inject!$C29,IF(Vaccine_database!$E$10:$E$278=Volume_Inject!$D29,IF(Vaccine_database!$J$10:$J$278=$C33,Vaccine_database!L$10:L$278))))))))} -> 0 | J33: =IF(B33="","",IF(OR(ISTEXT(C33),C33=1),5,IF(Volume_Inject!$C29<>"liquid",IF(C33>=20,50,IF(C33=10,40,10)),IF(C33>=10,25,10)))) | K33: =IF(I33="",IF($J33="",0,100/(100-$J33)),100/(100-$I33)) -> 0 | Y33: =IF($V33="",0,Volume_Inject!$F29*$K33*M33*($V33+$W33)/12) -> 0 | Z33: =IF($V33="",0,Volume_Inject!$F29*$K33*N33*($V33+$W33)/12) -> 0 | AA33: =IF($V33="",0,Volume_Inject!$F29*$K33*O33*($V33+$W33)/12) -> 0 | AB33: =IF($V33="",0,Volume_Inject!$F29*$K33*P33*($V33+$W33)/12) -> 0 | AC33: =IF($V33="",0,Volume_Inject!$F29*$K33*Q33*($V33+$W33)/12) -> 0
F34: {=IF(B34="",0,IF($D$5=min,MIN(IF(Vaccines=$B34,IF(Formulation=Volume_Inject!$C30,IF(Vaccine_database!$E$10:$E$278=Volume_Inject!$D30,IF(Vaccine_database!$J$10:$J$278=$C34,Vaccine_database!K$10:K$278))))),IF($D$5=max,MAX(IF(Vaccines=$B34,IF(Formulation=Volume_Inject!$C30,IF(Vaccine_database!$E$10:$E$278=Volume_Inject!$D30,IF(Vaccine_database!$J$10:$J$278=$C34,Vaccine_database!K$10:K$278))))),AVERAGE(IF(Vaccines=$B34,IF(Formulation=Volume_Inject!$C30,IF(Vaccine_database!$E$10:$E$278=Volume_Inject!$D30,IF(Vaccine_database!$J$10:$J$278=$C34,Vaccine_database!K$10:K$278))))))))} -> 0 | G34: {=IF(C34="",0,IF($D$5=min,MIN(IF(Vaccines=$B34,IF(Formulation=Volume_Inject!$C30,IF(Vaccine_database!$E$10:$E$278=Volume_Inject!$D30,IF(Vaccine_database!$J$10:$J$278=$C34,Vaccine_database!L$10:L$278))))),IF($D$5=max,MAX(IF(Vaccines=$B34,IF(Formulation=Volume_Inject!$C30,IF(Vaccine_database!$E$10:$E$278=Volume_Inject!$D30,IF(Vaccine_database!$J$10:$J$278=$C34,Vaccine_database!L$10:L$278))))),AVERAGE(IF(Vaccines=$B34,IF(Formulation=Volume_Inject!$C30,IF(Vaccine_database!$E$10:$E$278=Volume_Inject!$D30,IF(Vaccine_database!$J$10:$J$278=$C34,Vaccine_database!L$10:L$278))))))))} -> 0 | J34: =IF(B34="","",IF(OR(ISTEXT(C34),C34=1),5,IF(Volume_Inject!$C30<>"liquid",IF(C34>=20,50,IF(C34=10,40,10)),IF(C34>=10,25,10)))) | K34: =IF(I34="",IF($J34="",0,100/(100-$J34)),100/(100-$I34)) -> 0 | Y34: =IF($V34="",0,Volume_Inject!$F30*$K34*M34*($V34+$W34)/12) -> 0 | Z34: =IF($V34="",0,Volume_Inject!$F30*$K34*N34*($V34+$W34)/12) -> 0 | AA34: =IF($V34="",0,Volume_Inject!$F30*$K34*O34*($V34+$W34)/12) -> 0 | AB34: =IF($V34="",0,Volume_Inject!$F30*$K34*P34*($V34+$W34)/12) -> 0 | AC34: =IF($V34="",0,Volume_Inject!$F30*$K34*Q34*($V34+$W34)/12) -> 0
F35: {=IF(B35="",0,IF($D$5=min,MIN(IF(Vaccines=$B35,IF(Formulation=Volume_Inject!$C31,IF(Vaccine_database!$E$10:$E$278=Volume_Inject!$D31,IF(Vaccine_database!$J$10:$J$278=$C35,Vaccine_database!K$10:K$278))))),IF($D$5=max,MAX(IF(Vaccines=$B35,IF(Formulation=Volume_Inject!$C31,IF(Vaccine_database!$E$10:$E$278=Volume_Inject!$D31,IF(Vaccine_database!$J$10:$J$278=$C35,Vaccine_database!K$10:K$278))))),AVERAGE(IF(Vaccines=$B35,IF(Formulation=Volume_Inject!$C31,IF(Vaccine_database!$E$10:$E$278=Volume_Inject!$D31,IF(Vaccine_database!$J$10:$J$278=$C35,Vaccine_database!K$10:K$278))))))))} -> 0 | G35: {=IF(C35="",0,IF($D$5=min,MIN(IF(Vaccines=$B35,IF(Formulation=Volume_Inject!$C31,IF(Vaccine_database!$E$10:$E$278=Volume_Inject!$D31,IF(Vaccine_database!$J$10:$J$278=$C35,Vaccine_database!L$10:L$278))))),IF($D$5=max,MAX(IF(Vaccines=$B35,IF(Formulation=Volume_Inject!$C31,IF(Vaccine_database!$E$10:$E$278=Volume_Inject!$D31,IF(Vaccine_database!$J$10:$J$278=$C35,Vaccine_database!L$10:L$278))))),AVERAGE(IF(Vaccines=$B35,IF(Formulation=Volume_Inject!$C31,IF(Vaccine_database!$E$10:$E$278=Volume_Inject!$D31,IF(Vaccine_database!$J$10:$J$278=$C35,Vaccine_database!L$10:L$278))))))))} -> 0 | J35: =IF(B35="","",IF(OR(ISTEXT(C35),C35=1),5,IF(Volume_Inject!$C31<>"liquid",IF(C35>=20,50,IF(C35=10,40,10)),IF(C35>=10,25,10)))) | K35: =IF(I35="",IF($J35="",0,100/(100-$J35)),100/(100-$I35)) -> 0 | Y35: =IF($V35="",0,Volume_Inject!$F31*$K35*M35*($V35+$W35)/12) -> 0 | Z35: =IF($V35="",0,Volume_Inject!$F31*$K35*N35*($V35+$W35)/12) -> 0 | AA35: =IF($V35="",0,Volume_Inject!$F31*$K35*O35*($V35+$W35)/12) -> 0 | AB35: =IF($V35="",0,Volume_Inject!$F31*$K35*P35*($V35+$W35)/12) -> 0 | AC35: =IF($V35="",0,Volume_Inject!$F31*$K35*Q35*($V35+$W35)/12) -> 0
F36: {=IF(B36="",0,IF($D$5=min,MIN(IF(Vaccines=$B36,IF(Formulation=Volume_Inject!$C32,IF(Vaccine_database!$E$10:$E$278=Volume_Inject!$D32,IF(Vaccine_database!$J$10:$J$278=$C36,Vaccine_database!K$10:K$278))))),IF($D$5=max,MAX(IF(Vaccines=$B36,IF(Formulation=Volume_Inject!$C32,IF(Vaccine_database!$E$10:$E$278=Volume_Inject!$D32,IF(Vaccine_database!$J$10:$J$278=$C36,Vaccine_database!K$10:K$278))))),AVERAGE(IF(Vaccines=$B36,IF(Formulation=Volume_Inject!$C32,IF(Vaccine_database!$E$10:$E$278=Volume_Inject!$D32,IF(Vaccine_database!$J$10:$J$278=$C36,Vaccine_database!K$10:K$278))))))))} -> 0 | G36: {=IF(C36="",0,IF($D$5=min,MIN(IF(Vaccines=$B36,IF(Formulation=Volume_Inject!$C32,IF(Vaccine_database!$E$10:$E$278=Volume_Inject!$D32,IF(Vaccine_database!$J$10:$J$278=$C36,Vaccine_database!L$10:L$278))))),IF($D$5=max,MAX(IF(Vaccines=$B36,IF(Formulation=Volume_Inject!$C32,IF(Vaccine_database!$E$10:$E$278=Volume_Inject!$D32,IF(Vaccine_database!$J$10:$J$278=$C36,Vaccine_database!L$10:L$278))))),AVERAGE(IF(Vaccines=$B36,IF(Formulation=Volume_Inject!$C32,IF(Vaccine_database!$E$10:$E$278=Volume_Inject!$D32,IF(Vaccine_database!$J$10:$J$278=$C36,Vaccine_database!L$10:L$278))))))))} -> 0 | J36: =IF(B36="","",IF(OR(ISTEXT(C36),C36=1),5,IF(Volume_Inject!$C32<>"liquid",IF(C36>=20,50,IF(C36=10,40,10)),IF(C36>=10,25,10)))) | K36: =IF(I36="",IF($J36="",0,100/(100-$J36)),100/(100-$I36)) -> 0 | Y36: =IF($V36="",0,Volume_Inject!$F32*$K36*M36*($V36+$W36)/12) -> 0 | Z36: =IF($V36="",0,Volume_Inject!$F32*$K36*N36*($V36+$W36)/12) -> 0 | AA36: =IF($V36="",0,Volume_Inject!$F32*$K36*O36*($V36+$W36)/12) -> 0 | AB36: =IF($V36="",0,Volume_Inject!$F32*$K36*P36*($V36+$W36)/12) -> 0 | AC36: =IF($V36="",0,Volume_Inject!$F32*$K36*Q36*($V36+$W36)/12) -> 0
L38: =CONCATENATE(Translation!C356," ",E$8) -> Net volume of OPV at -20°C in higher level stores, per Unit of Population | M38: {=IF($E$8=target1,SUM(($B$17:$B$36="OPV")*(Volume_Inject!$F$13:$F$32)*($K$17:$K$36)*(M$17:M$36)),SUM(($B$17:$B$36="OPV")*(Volume_Inject!$F$13:$F$32)*($K$17:$K$36)*($L$17:$L$36)*(M$17:M$36)))} -> 0.20266667 | N38: {=IF($E$8=target1,SUM(($B$17:$B$36="OPV")*(Volume_Inject!$F$13:$F$32)*($K$17:$K$36)*(N$17:N$36)),SUM(($B$17:$B$36="OPV")*(Volume_Inject!$F$13:$F$32)*($K$17:$K$36)*($L$17:$L$36)*(N$17:N$36)))} -> 0.20266667 | O38: {=IF($E$8=target1,SUM(($B$17:$B$36="OPV")*(Volume_Inject!$F$13:$F$32)*($K$17:$K$36)*(O$17:O$36)),SUM(($B$17:$B$36="OPV")*(Volume_Inject!$F$13:$F$32)*($K$17:$K$36)*($L$17:$L$36)*(O$17:O$36)))} -> 0.20266667 | P38: {=IF($E$8=target1,SUM(($B$17:$B$36="OPV")*(Volume_Inject!$F$13:$F$32)*($K$17:$K$36)*(P$17:P$36)),SUM(($B$17:$B$36="OPV")*(Volume_Inject!$F$13:$F$32)*($K$17:$K$36)*($L$17:$L$36)*(P$17:P$36)))} -> 0 | Q38: {=IF($E$8=target1,SUM(($B$17:$B$36="OPV")*(Volume_Inject!$F$13:$F$32)*($K$17:$K$36)*(Q$17:Q$36)),SUM(($B$17:$B$36="OPV")*(Volume_Inject!$F$13:$F$32)*($K$17:$K$36)*($L$17:$L$36)*(Q$17:Q$36)))} -> 0 | Y38: {=IF($E$8=target1,SUMIF($B$17:$B$36,"OPV",Y$17:Y$36),SUM(($B$17:$B$36="OPV")*($L$17:$L$36)*(Y$17:Y$36)))} -> 0.084444444 | Z38: {=IF($E$8=target1,SUMIF($B$17:$B$36,"OPV",Z$17:Z$36),SUM(($B$17:$B$36="OPV")*($L$17:$L$36)*(Z$17:Z$36)))} -> 0.084444444 | AA38: {=IF($E$8=target1,SUMIF($B$17:$B$36,"OPV",AA$17:AA$36),SUM(($B$17:$B$36="OPV")*($L$17:$L$36)*(AA$17:AA$36)))} -> 0.084444444 | AB38: {=IF($E$8=target1,SUMIF($B$17:$B$36,"OPV",AB$17:AB$36),SUM(($B$17:$B$36="OPV")*($L$17:$L$36)*(AB$17:AB$36)))} -> 0 | AC38: {=IF($E$8=target1,SUMIF($B$17:$B$36,"OPV",AC$17:AC$36),SUM(($B$17:$B$36="OPV")*($L$17:$L$36)*(AC$17:AC$36)))} -> 0
L39: =CONCATENATE(Translation!C357," ",E$8) -> Net volume of all vaccines except OPV stored at +5°C in higher level stores, per Unit of Population | M39: {=IF($E$8=target1,SUMPRODUCT(Volume_Inject!$F$13:$F$32,$K$17:$K$36,M$17:M$36),SUMPRODUCT(Volume_Inject!$F$13:$F$32,$K$17:$K$36,$L$17:$L$36,M$17:M$36))-M38} -> 0.60087471 | N39: {=IF($E$8=target1,SUMPRODUCT(Volume_Inject!$F$13:$F$32,$K$17:$K$36,N$17:N$36),SUMPRODUCT(Volume_Inject!$F$13:$F$32,$K$17:$K$36,$L$17:$L$36,N$17:N$36))-N38} -> 1.3917051 | O39: {=IF($E$8=target1,SUMPRODUCT(Volume_Inject!$F$13:$F$32,$K$17:$K$36,O$17:O$36),SUMPRODUCT(Volume_Inject!$F$13:$F$32,$K$17:$K$36,$L$17:$L$36,O$17:O$36))-O38} -> 1.1118747 | P39: {=IF($E$8=target1,SUMPRODUCT(Volume_Inject!$F$13:$F$32,$K$17:$K$36,P$17:P$36),SUMPRODUCT(Volume_Inject!$F$13:$F$32,$K$17:$K$36,$L$17:$L$36,P$17:P$36))-P38} -> 0 | Q39: {=IF($E$8=target1,SUMPRODUCT(Volume_Inject!$F$13:$F$32,$K$17:$K$36,Q$17:Q$36),SUMPRODUCT(Volume_Inject!$F$13:$F$32,$K$17:$K$36,$L$17:$L$36,Q$17:Q$36))-Q38} -> 0 | Y39: =Y40-Y38 -> 0.2365452 | Z39: =Z40-Z38 -> 0.48273867 | AA39: =AA40-AA38 -> 0.44946187 | AB39: =AB40-AB38 -> 0 | AC39: =AC40-AC38 -> 0
L40: =CONCATENATE(Translation!C358," ",E$8) -> Net volume of all vaccines, including OPV, stored at +5°C in lower level stores, per Unit of Population | M40: {=IF($E$8=target1,SUMPRODUCT(Volume_Inject!$F$13:$F$32,$K$17:$K$36,M$17:M$36),SUMPRODUCT(Volume_Inject!$F$13:$F$32,$K$17:$K$36,$L$17:$L$36,M$17:M$36))} -> 0.80354138 | N40: {=IF($E$8=target1,SUMPRODUCT(Volume_Inject!$F$13:$F$32,$K$17:$K$36,N$17:N$36),SUMPRODUCT(Volume_Inject!$F$13:$F$32,$K$17:$K$36,$L$17:$L$36,N$17:N$36))} -> 1.5943718 | O40: {=IF($E$8=target1,SUMPRODUCT(Volume_Inject!$F$13:$F$32,$K$17:$K$36,O$17:O$36),SUMPRODUCT(Volume_Inject!$F$13:$F$32,$K$17:$K$36,$L$17:$L$36,O$17:O$36))} -> 1.3145414 | P40: {=IF($E$8=target1,SUMPRODUCT(Volume_Inject!$F$13:$F$32,$K$17:$K$36,P$17:P$36),SUMPRODUCT(Volume_Inject!$F$13:$F$32,$K$17:$K$36,$L$17:$L$36,P$17:P$36))} -> 0 | Q40: {=IF($E$8=target1,SUMPRODUCT(Volume_Inject!$F$13:$F$32,$K$17:$K$36,Q$17:Q$36),SUMPRODUCT(Volume_Inject!$F$13:$F$32,$K$17:$K$36,$L$17:$L$36,Q$17:Q$36))} -> 0 | R40: =Translation!C357 -> Net volume of all vaccines except OPV stored at +5°C in higher level stores, per | S40: =SUMPRODUCT(Volume_Inject!$F$13:$F$32,$K$17:$K$36,S$17:S$36) -> 18 | T40: =SUMPRODUCT(Volume_Inject!$F$13:$F$32,$K$17:$K$36,T$17:T$36) -> 0 | U40: =SUMPRODUCT(Volume_Inject!$F$13:$F$32,$K$17:$K$36,U$17:U$36) -> 0 | Y40: {=IF($E$8=target1,SUM(Y$17:Y$36),SUM(($L$17:$L$36)*(Y$17:Y$36)))} -> 0.32098965 | Z40: {=IF($E$8=target1,SUM(Z$17:Z$36),SUM(($L$17:$L$36)*(Z$17:Z$36)))} -> 0.56718311 | AA40: {=IF($E$8=target1,SUM(AA$17:AA$36),SUM(($L$17:$L$36)*(AA$17:AA$36)))} -> 0.53390631 | AB40: {=IF($E$8=target1,SUM(AB$17:AB$36),SUM(($L$17:$L$36)*(AB$17:AB$36)))} -> 0 | AC40: {=IF($E$8=target1,SUM(AC$17:AC$36),SUM(($L$17:$L$36)*(AC$17:AC$36)))} -> 0
L41: =CONCATENATE(Translation!C359," ",E$8) -> Net volume of vaccines and diluents, stored at +5°C at service points, per Unit of Population | M41: =IF($E$8=target1,SUMPRODUCT(Volume_Inject!$F$13:$F$32,$K$17:$K$36,M$17:M$36)+SUMPRODUCT(Volume_Inject!$G$13:$G$32,$K$17:$K$36,M$17:M$36),SUMPRODUCT(Volume_Inject!$F$13:$F$32,$K$17:$K$36,$L$17:$L$36,M$17:M$36)+SUMPRODUCT(Volume_Inject!$G$13:$G$32,$K$17:$K$36,$L$17:$L$36,M$17:M$36)) -> 1.0773167 | N41: =IF($E$8=target1,SUMPRODUCT(Volume_Inject!$F$13:$F$32,$K$17:$K$36,N$17:N$36)+SUMPRODUCT(Volume_Inject!$G$13:$G$32,$K$17:$K$36,N$17:N$36),SUMPRODUCT(Volume_Inject!$F$13:$F$32,$K$17:$K$36,$L$17:$L$36,N$17:N$36)+SUMPRODUCT(Volume_Inject!$G$13:$G$32,$K$17:$K$36,$L$17:$L$36,N$17:N$36)) -> 1.8681471 | O41: =IF($E$8=target1,SUMPRODUCT(Volume_Inject!$F$13:$F$32,$K$17:$K$36,O$17:O$36)+SUMPRODUCT(Volume_Inject!$G$13:$G$32,$K$17:$K$36,O$17:O$36),SUMPRODUCT(Volume_Inject!$F$13:$F$32,$K$17:$K$36,$L$17:$L$36,O$17:O$36)+SUMPRODUCT(Volume_Inject!$G$13:$G$32,$K$17:$K$36,$L$17:$L$36,O$17:O$36)) -> 1.5883167 | P41: =IF($E$8=target1,SUMPRODUCT(Volume_Inject!$F$13:$F$32,$K$17:$K$36,P$17:P$36)+SUMPRODUCT(Volume_Inject!$G$13:$G$32,$K$17:$K$36,P$17:P$36),SUMPRODUCT(Volume_Inject!$F$13:$F$32,$K$17:$K$36,$L$17:$L$36,P$17:P$36)+SUMPRODUCT(Volume_Inject!$G$13:$G$32,$K$17:$K$36,$L$17:$L$36,P$17:P$36)) -> 0 | Q41: =IF($E$8=target1,SUMPRODUCT(Volume_Inject!$F$13:$F$32,$K$17:$K$36,Q$17:Q$36)+SUMPRODUCT(Volume_Inject!$G$13:$G$32,$K$17:$K$36,Q$17:Q$36),SUMPRODUCT(Volume_Inject!$F$13:$F$32,$K$17:$K$36,$L$17:$L$36,Q$17:Q$36)+SUMPRODUCT(Volume_Inject!$G$13:$G$32,$K$17:$K$36,$L$17:$L$36,Q$17:Q$36)) -> 0 | R41: =Translation!C366 -> Total net storage volume of vaccines & diluents per recipient | S41: =SUMPRODUCT(Volume_Inject!$F$13:$F$32,$K$17:$K$36,S$17:S$36)+SUMPRODUCT(Volume_Inject!$G$13:$G$32,$K$17:$K$36,S$17:S$36) -> 18 | T41: =SUMPRODUCT(Volume_Inject!$F$13:$F$32,$K$17:$K$36,T$17:T$36)+SUMPRODUCT(Volume_Inject!$G$13:$G$32,$K$17:$K$36,T$17:T$36) -> 0 | U41: =SUMPRODUCT(Volume_Inject!$F$13:$F$32,$K$17:$K$36,U$17:U$36)+SUMPRODUCT(Volume_Inject!$G$13:$G$32,$K$17:$K$36,U$17:U$36) -> 0
L43: =CONCATENATE(Translation!C360," ",$E$8) -> No. of vaccine doses per Unit of Population | M43: =SUM(M$17:M$36) -> 12 | N43: =SUM(N$17:N$36) -> 12 | O43: =SUM(O$17:O$36) -> 12 | P43: =SUM(P$17:P$36) -> 0 | Q43: =SUM(Q$17:Q$36) -> 0 | S43: =SUMPRODUCT(S$17:S$36,$K$17:$K$36) -> 1.0526316 | T43: =SUMPRODUCT(T$17:T$36,$K$17:$K$36) -> 0 | U43: =SUMPRODUCT(U$17:U$36,$K$17:$K$36) -> 0
L45: =Translation!C361 -> Percent increase of the net vaccine volume compared to current schedule in store for -20°C | N45: =IF(OR($M$38=0,N38=0),"",(N38-$M$38)/$M$38) -> 0 | O45: =IF(OR($M$38=0,O38=0),"",(O38-$M$38)/$M$38) -> 0 | P45: =IF(OR($M$38=0,P38=0),"",(P38-$M$38)/$M$38) | Q45: =IF(OR($M$38=0,Q38=0),"",(Q38-$M$38)/$M$38) | Z45: =IF(OR($Y$38=0,Z38=0),"",(Z38-$Y$38)/$Y$38) -> 0 | AA45: =IF(OR($Y$38=0,AA38=0),"",(AA38-$Y$38)/$Y$38) -> 0 | AB45: =IF(OR($Y$38=0,AB38=0),"",(AB38-$Y$38)/$Y$38) | AC45: =IF(OR($Y$38=0,AC38=0),"",(AC38-$Y$38)/$Y$38)
L46: =Translation!C362 -> % increase of the net vaccine volume compared to current schedule in store w/o OPV @+5°C | N46: =IF(OR($M$39=0,N39=0),"",(N39-$M$39)/$M$39) -> 1.3161319 | O46: =IF(OR($M$39=0,O39=0),"",(O39-$M$39)/$M$39) -> 0.85042687 | P46: =IF(OR($M$39=0,P39=0),"",(P39-$M$39)/$M$39) | Q46: =IF(OR($M$39=0,Q39=0),"",(Q39-$M$39)/$M$39) | Z46: =IF(OR($Y$39=0,Z39=0),"",(Z39-$Y$39)/$Y$39) -> 1.0407882 | AA46: =IF(OR($Y$39=0,AA39=0),"",(AA39-$Y$39)/$Y$39) -> 0.90010985 | AB46: =IF(OR($Y$39=0,AB39=0),"",(AB39-$Y$39)/$Y$39) | AC46: =IF(OR($Y$39=0,AC39=0),"",(AC39-$Y$39)/$Y$39)
L47: =Translation!C363 -> % increase of the net vaccine volume compared to current schedule in store with OPV @+5°C | N47: =IF(OR($M$40=0,N40=0),"",(N40-$M$40)/$M$40) -> 0.9841813 | O47: =IF(OR($M$40=0,O40=0),"",(O40-$M$40)/$M$40) -> 0.63593489 | P47: =IF(OR($M$40=0,P40=0),"",(P40-$M$40)/$M$40) | Q47: =IF(OR($M$40=0,Q40=0),"",(Q40-$M$40)/$M$40) | T47: =IF(OR($S$40=0,T40=0),"",(T40-$S$40)/$S$40) | U47: =IF(OR($S$40=0,U40=0),"",(U40-$S$40)/$S$40) | Z47: =IF(OR($Y$40=0,Z40=0),"",(Z40-$Y$40)/$Y$40) -> 0.76698257 | AA47: =IF(OR($Y$40=0,AA40=0),"",(AA40-$Y$40)/$Y$40) -> 0.66331319 | AB47: =IF(OR($Y$40=0,AB40=0),"",(AB40-$Y$40)/$Y$40) | AC47: =IF(OR($Y$40=0,AC40=0),"",(AC40-$Y$40)/$Y$40)
L48: =Translation!C364 -> % increase of the net vaccine volume compared to current schedule at service delivery | N48: =IF(OR($M$41=0,N41=0),"",(N41-$M$41)/$M$41) -> 0.7340742 | O48: =IF(OR($M$41=0,O41=0),"",(O41-$M$41)/$M$41) -> 0.47432663 | P48: =IF(OR($M$41=0,P41=0),"",(P41-$M$41)/$M$41) | Q48: =IF(OR($M$41=0,Q41=0),"",(Q41-$M$41)/$M$41) | T48: =IF(OR($S$41=0,T41=0),"",(T41-$S$41)/$S$41) | U48: =IF(OR($S$41=0,U41=0),"",(U41-$S$41)/$S$41)

Sheet Abacus_Tables
B1: =Translation!C10 -> Analysis of national and sub-national storage | O1: =Translation!C109 -> Index
F2: =Translation!C19 -> Maximum stock levels (months)
F3: =Translation!C20 -> Vaccines | H3: =Translation!C25 -> Safe injection equipment
B4: =Translation!C11 -> Analysis per | C4: =Vaccine_Selection!$E$8 -> Unit of Population | F4: 4 | H4: 6
B5: =IF($C$4=target2,CONCATENATE(Translation!$C$12," ",Translation!$C$15),CONCATENATE(Translation!$C$13," ",Translation!$C$15)) -> Total population (minimum) | C5: 500000 | F5: 6 | H5: 9 | K5: =Translation!C26 -> Cold room cost equation | N5: 4.2 | O5: =Translation!C27 -> Indicative grossing factor
B6: =IF($C$4=target2,CONCATENATE(Translation!$C$12," ",Translation!$C$14),CONCATENATE(Translation!$C$13," ",Translation!$C$14)) -> Total population (maximum) | C6: 10000000 | F6: 9 | H6: 12 | K6: Y1 = | L6: 0.0403 | M6: -11.316 | N6: 2326.5 | O6: =Translation!C254 -> WICR
B7: =Translation!C18 -> MaxiStock | C7: per individual vaccine | E7: =Translation!C17 -> months | F7: par vaccin individuel | K7: Y2 = | L7: 0.0506 | M7: -14.207 | N7: 2944.4 | O7: =Translation!C255 -> WIFR
C8: =(C6-C5)/25 -> 380000 | D8: =IF(C8=0,0,ROUNDUP(C8,-(ROUND(LOG(C8),1)))) -> 400000
B10: =Translation!C28 -> Vaccine net volume for supply period and cold room capacities | F10: =IF($C$4=target2,Translation!$C$12,Translation!$C$13) -> Total population
B11: =CONCATENATE(F10,": ",) -> Total population: | C11: =$C$5 -> 500000 | D11: =C11+$D$8 -> 900000 | E11: =D11+$D$8 -> 1300000 | F11: =E11+$D$8 -> 1700000 | G11: =F11+$D$8 -> 2100000 | H11: =G11+$D$8 -> 2500000 | I11: =H11+$D$8 -> 2900000 | J11: =I11+$D$8 -> 3300000 | K11: =J11+$D$8 -> 3700000 | ... AB11: =AA11+$D$8 -> 10500000
B12: =Translation!C29 -> Estimate of cold-chain capacity per schedule (litres)
B13: =IF(Vaccine_Selection!$M$16="","",CONCATENATE(Vaccine_Selection!$M$16," @ ",$C$7,$E$7,"-MaxiStock")) -> Current schedule @ per individual vaccine months-MaxiStock | C13: =IF(ISTEXT($C$7),Vaccine_Selection!$Y$39,Vaccine_Selection!$M$39*$C$7/12)*C$11/1000 -> 118.2726 | D13: =IF(ISTEXT($C$7),Vaccine_Selection!$Y$39,Vaccine_Selection!$M$39*$C$7/12)*D$11/1000 -> 212.89068 | E13: =IF(ISTEXT($C$7),Vaccine_Selection!$Y$39,Vaccine_Selection!$M$39*$C$7/12)*E$11/1000 -> 307.50876 | F13: =IF(ISTEXT($C$7),Vaccine_Selection!$Y$39,Vaccine_Selection!$M$39*$C$7/12)*F$11/1000 -> 402.12685 | G13: =IF(ISTEXT($C$7),Vaccine_Selection!$Y$39,Vaccine_Selection!$M$39*$C$7/12)*G$11/1000 -> 496.74493 | H13: =IF(ISTEXT($C$7),Vaccine_Selection!$Y$39,Vaccine_Selection!$M$39*$C$7/12)*H$11/1000 -> 591.36301 | I13: =IF(ISTEXT($C$7),Vaccine_Selection!$Y$39,Vaccine_Selection!$M$39*$C$7/12)*I$11/1000 -> 685.98109 | J13: =IF(ISTEXT($C$7),Vaccine_Selection!$Y$39,Vaccine_Selection!$M$39*$C$7/12)*J$11/1000 -> 780.59917 | ... AB13: =IF(ISTEXT($C$7),Vaccine_Selection!$Y$39,Vaccine_Selection!$M$39*$C$7/12)*AB$11/1000 -> 2483.7246
B14: =IF(Vaccine_Selection!$N$16="","",CONCATENATE(Vaccine_Selection!$N$16," @ ",$C$7,$E$7,"-MaxiStock")) -> Current schedule with penta 1d @ per individual vaccine months-MaxiStock | C14: =IF(ISTEXT($C$7),Vaccine_Selection!$Z$39,Vaccine_Selection!$N$39*$C$7/12)*C$11/1000 -> 241.36934 | D14: =IF(ISTEXT($C$7),Vaccine_Selection!$Z$39,Vaccine_Selection!$N$39*$C$7/12)*D$11/1000 -> 434.4648 | E14: =IF(ISTEXT($C$7),Vaccine_Selection!$Z$39,Vaccine_Selection!$N$39*$C$7/12)*E$11/1000 -> 627.56027 | F14: =IF(ISTEXT($C$7),Vaccine_Selection!$Z$39,Vaccine_Selection!$N$39*$C$7/12)*F$11/1000 -> 820.65574 | G14: =IF(ISTEXT($C$7),Vaccine_Selection!$Z$39,Vaccine_Selection!$N$39*$C$7/12)*G$11/1000 -> 1013.7512 | H14: =IF(ISTEXT($C$7),Vaccine_Selection!$Z$39,Vaccine_Selection!$N$39*$C$7/12)*H$11/1000 -> 1206.8467 | I14: =IF(ISTEXT($C$7),Vaccine_Selection!$Z$39,Vaccine_Selection!$N$39*$C$7/12)*I$11/1000 -> 1399.9421 | J14: =IF(ISTEXT($C$7),Vaccine_Selection!$Z$39,Vaccine_Selection!$N$39*$C$7/12)*J$11/1000 -> 1593.0376 | ... AB14: =IF(ISTEXT($C$7),Vaccine_Selection!$Z$39,Vaccine_Selection!$N$39*$C$7/12)*AB$11/1000 -> 5068.756
B15: =IF(Vaccine_Selection!$O$16="","",CONCATENATE(Vaccine_Selection!$O$16," @ ",$C$7,$E$7,"-MaxiStock")) -> Current schedule with penta CAD @ per individual vaccine months-MaxiStock | C15: =IF(ISTEXT($C$7),Vaccine_Selection!$AA$39,Vaccine_Selection!$O$39*$C$7/12)*C$11/1000 -> 224.73094 | D15: =IF(ISTEXT($C$7),Vaccine_Selection!$AA$39,Vaccine_Selection!$O$39*$C$7/12)*D$11/1000 -> 404.51568 | E15: =IF(ISTEXT($C$7),Vaccine_Selection!$AA$39,Vaccine_Selection!$O$39*$C$7/12)*E$11/1000 -> 584.30043 | F15: =IF(ISTEXT($C$7),Vaccine_Selection!$AA$39,Vaccine_Selection!$O$39*$C$7/12)*F$11/1000 -> 764.08518 | G15: =IF(ISTEXT($C$7),Vaccine_Selection!$AA$39,Vaccine_Selection!$O$39*$C$7/12)*G$11/1000 -> 943.86993 | H15: =IF(ISTEXT($C$7),Vaccine_Selection!$AA$39,Vaccine_Selection!$O$39*$C$7/12)*H$11/1000 -> 1123.6547 | I15: =IF(ISTEXT($C$7),Vaccine_Selection!$AA$39,Vaccine_Selection!$O$39*$C$7/12)*I$11/1000 -> 1303.4394 | J15: =IF(ISTEXT($C$7),Vaccine_Selection!$AA$39,Vaccine_Selection!$O$39*$C$7/12)*J$11/1000 -> 1483.2242 | ... AB15: =IF(ISTEXT($C$7),Vaccine_Selection!$AA$39,Vaccine_Selection!$O$39*$C$7/12)*AB$11/1000 -> 4719.3496
B16: =IF(Vaccine_Selection!$P$16="","",CONCATENATE(Vaccine_Selection!$P$16," @ ",$C$7,$E$7,"-MaxiStock")) | C16: =IF(ISTEXT($C$7),Vaccine_Selection!$AB$39,Vaccine_Selection!$P$39*$C$7/12)*C$11/1000 -> 0 | D16: =IF(ISTEXT($C$7),Vaccine_Selection!$AB$39,Vaccine_Selection!$P$39*$C$7/12)*D$11/1000 -> 0 | E16: =IF(ISTEXT($C$7),Vaccine_Selection!$AB$39,Vaccine_Selection!$P$39*$C$7/12)*E$11/1000 -> 0 | F16: =IF(ISTEXT($C$7),Vaccine_Selection!$AB$39,Vaccine_Selection!$P$39*$C$7/12)*F$11/1000 -> 0 | G16: =IF(ISTEXT($C$7),Vaccine_Selection!$AB$39,Vaccine_Selection!$P$39*$C$7/12)*G$11/1000 -> 0 | H16: =IF(ISTEXT($C$7),Vaccine_Selection!$AB$39,Vaccine_Selection!$P$39*$C$7/12)*H$11/1000 -> 0 | I16: =IF(ISTEXT($C$7),Vaccine_Selection!$AB$39,Vaccine_Selection!$P$39*$C$7/12)*I$11/1000 -> 0 | J16: =IF(ISTEXT($C$7),Vaccine_Selection!$AB$39,Vaccine_Selection!$P$39*$C$7/12)*J$11/1000 -> 0 | ... AB16: =IF(ISTEXT($C$7),Vaccine_Selection!$AB$39,Vaccine_Selection!$P$39*$C$7/12)*AB$11/1000 -> 0
B17: =IF(Vaccine_Selection!$Q$16="","",CONCATENATE(Vaccine_Selection!$Q$16," @ ",$C$7,$E$7,"-MaxiStock")) | C17: =IF(ISTEXT($C$7),Vaccine_Selection!$AC$39,Vaccine_Selection!$Q$39*$C$7/12)*C$11/1000 -> 0 | D17: =IF(ISTEXT($C$7),Vaccine_Selection!$AC$39,Vaccine_Selection!$Q$39*$C$7/12)*D$11/1000 -> 0 | E17: =IF(ISTEXT($C$7),Vaccine_Selection!$AC$39,Vaccine_Selection!$Q$39*$C$7/12)*E$11/1000 -> 0 | F17: =IF(ISTEXT($C$7),Vaccine_Selection!$AC$39,Vaccine_Selection!$Q$39*$C$7/12)*F$11/1000 -> 0 | G17: =IF(ISTEXT($C$7),Vaccine_Selection!$AC$39,Vaccine_Selection!$Q$39*$C$7/12)*G$11/1000 -> 0 | H17: =IF(ISTEXT($C$7),Vaccine_Selection!$AC$39,Vaccine_Selection!$Q$39*$C$7/12)*H$11/1000 -> 0 | I17: =IF(ISTEXT($C$7),Vaccine_Selection!$AC$39,Vaccine_Selection!$Q$39*$C$7/12)*I$11/1000 -> 0 | J17: =IF(ISTEXT($C$7),Vaccine_Selection!$AC$39,Vaccine_Selection!$Q$39*$C$7/12)*J$11/1000 -> 0 | ... AB17: =IF(ISTEXT($C$7),Vaccine_Selection!$AC$39,Vaccine_Selection!$Q$39*$C$7/12)*AB$11/1000 -> 0
B18: =Translation!C38 -> Estimate of equipment requirements per schedule | E18: =Translation!C40 -> Equipment utilization factor (%) | F18: 0.65
B19: WICR-10m3 | C19: =SUMIF(WICR,$B$19,Supplies!$E$36:$E$46) -> 3030.303 | D19: =C19 -> 3030.303 | E19: =D19 -> 3030.303 | F19: =E19 -> 3030.303 | G19: =F19 -> 3030.303 | H19: =G19 -> 3030.303 | I19: =H19 -> 3030.303 | J19: =I19 -> 3030.303 | K19: =J19 -> 3030.303 | ... AB19: =AA19 -> 3030.303
B20: =IF(Vaccine_Selection!$M$16="","",CONCATENATE(Vaccine_Selection!$M$16," @ ",$C$7,$E$7,"-MaxiStock: ",$B$19)) -> Current schedule @ per individual vaccine months-MaxiStock: WICR-10m3 | C20: =IF(C$19=0,0,ROUND(C13/(C$19*$F$18),0)) -> 0 | D20: =IF(D$19=0,0,ROUND(D13/(D$19*$F$18),0)) -> 0 | E20: =IF(E$19=0,0,ROUND(E13/(E$19*$F$18),0)) -> 0 | F20: =IF(F$19=0,0,ROUND(F13/(F$19*$F$18),0)) -> 0 | G20: =IF(G$19=0,0,ROUND(G13/(G$19*$F$18),0)) -> 0 | H20: =IF(H$19=0,0,ROUND(H13/(H$19*$F$18),0)) -> 0 | I20: =IF(I$19=0,0,ROUND(I13/(I$19*$F$18),0)) -> 0 | J20: =IF(J$19=0,0,ROUND(J13/(J$19*$F$18),0)) -> 0 | ... AB20: =IF(AB$19=0,0,ROUND(AB13/(AB$19*$F$18),0)) -> 1
B21: =IF(Vaccine_Selection!$N$16="","",CONCATENATE(Vaccine_Selection!$N$16," @ ",$C$7,$E$7,"-MaxiStock: ",$B$19)) -> Current schedule with penta 1d @ per individual vaccine months-MaxiStock: WICR-10m3 | C21: =IF(C$19=0,0,ROUND(C14/(C$19*$F$18),0)) -> 0 | D21: =IF(D$19=0,0,ROUND(D14/(D$19*$F$18),0)) -> 0 | E21: =IF(E$19=0,0,ROUND(E14/(E$19*$F$18),0)) -> 0 | F21: =IF(F$19=0,0,ROUND(F14/(F$19*$F$18),0)) -> 0 | G21: =IF(G$19=0,0,ROUND(G14/(G$19*$F$18),0)) -> 1 | H21: =IF(H$19=0,0,ROUND(H14/(H$19*$F$18),0)) -> 1 | I21: =IF(I$19=0,0,ROUND(I14/(I$19*$F$18),0)) -> 1 | J21: =IF(J$19=0,0,ROUND(J14/(J$19*$F$18),0)) -> 1 | ... AB21: =IF(AB$19=0,0,ROUND(AB14/(AB$19*$F$18),0)) -> 3
B22: =IF(Vaccine_Selection!$O$16="","",CONCATENATE(Vaccine_Selection!$O$16," @ ",$C$7,$E$7,"-MaxiStock: ",$B$19)) -> Current schedule with penta CAD @ per individual vaccine months-MaxiStock: WICR-10m3 | C22: =IF(C$19=0,0,ROUND(C15/(C$19*$F$18),0)) -> 0 | D22: =IF(D$19=0,0,ROUND(D15/(D$19*$F$18),0)) -> 0 | E22: =IF(E$19=0,0,ROUND(E15/(E$19*$F$18),0)) -> 0 | F22: =IF(F$19=0,0,ROUND(F15/(F$19*$F$18),0)) -> 0 | G22: =IF(G$19=0,0,ROUND(G15/(G$19*$F$18),0)) -> 0 | H22: =IF(H$19=0,0,ROUND(H15/(H$19*$F$18),0)) -> 1 | I22: =IF(I$19=0,0,ROUND(I15/(I$19*$F$18),0)) -> 1 | J22: =IF(J$19=0,0,ROUND(J15/(J$19*$F$18),0)) -> 1 | ... AB22: =IF(AB$19=0,0,ROUND(AB15/(AB$19*$F$18),0)) -> 2
B23: =IF(Vaccine_Selection!$P$16="","",CONCATENATE(Vaccine_Selection!$P$16," @ ",$C$7,$E$7,"-MaxiStock: ",$B$19)) | C23: =IF(C$19=0,0,ROUND(C16/(C$19*$F$18),0)) -> 0 | D23: =IF(D$19=0,0,ROUND(D16/(D$19*$F$18),0)) -> 0 | E23: =IF(E$19=0,0,ROUND(E16/(E$19*$F$18),0)) -> 0 | F23: =IF(F$19=0,0,ROUND(F16/(F$19*$F$18),0)) -> 0 | G23: =IF(G$19=0,0,ROUND(G16/(G$19*$F$18),0)) -> 0 | H23: =IF(H$19=0,0,ROUND(H16/(H$19*$F$18),0)) -> 0 | I23: =IF(I$19=0,0,ROUND(I16/(I$19*$F$18),0)) -> 0 | J23: =IF(J$19=0,0,ROUND(J16/(J$19*$F$18),0)) -> 0 | ... AB23: =IF(AB$19=0,0,ROUND(AB16/(AB$19*$F$18),0)) -> 0
B24: =IF(Vaccine_Selection!$Q$16="","",CONCATENATE(Vaccine_Selection!$Q$16," @ ",$C$7,$E$7,"-MaxiStock: ",$B$19)) | C24: =IF(C$19=0,0,ROUND(C17/(C$19*$F$18),0)) -> 0 | D24: =IF(D$19=0,0,ROUND(D17/(D$19*$F$18),0)) -> 0 | E24: =IF(E$19=0,0,ROUND(E17/(E$19*$F$18),0)) -> 0 | F24: =IF(F$19=0,0,ROUND(F17/(F$19*$F$18),0)) -> 0 | G24: =IF(G$19=0,0,ROUND(G17/(G$19*$F$18),0)) -> 0 | H24: =IF(H$19=0,0,ROUND(H17/(H$19*$F$18),0)) -> 0 | I24: =IF(I$19=0,0,ROUND(I17/(I$19*$F$18),0)) -> 0 | J24: =IF(J$19=0,0,ROUND(J17/(J$19*$F$18),0)) -> 0 | ... AB24: =IF(AB$19=0,0,ROUND(AB17/(AB$19*$F$18),0)) -> 0
B25: =Translation!C42 -> Estimate of cold-chain capacity per MaxiStock (litres) | E25: =Translation!C45 -> Select schedule | F25: Current schedule
B26: =IF(F4="","",IF(ISTEXT($F4),CONCATENATE($F$25," @ ",$F4," MaxiStock"),CONCATENATE($F$25," @ ",$F4,$E$7," MaxiStock"))) -> Current schedule @ 4 months MaxiStock | C26: {=IF(ISTEXT($F4),SUMIF(Schedule,$F$25,Vaccine_Selection!$Y$39:$AC$39),SUMIF(Schedule,$F$25,Vaccine_Selection!$M$39:$Q$39)*$F4/12)*C$11/1000} -> 100.14579 | D26: {=IF(ISTEXT($F4),SUMIF(Schedule,$F$25,Vaccine_Selection!$Y$39:$AC$39),SUMIF(Schedule,$F$25,Vaccine_Selection!$M$39:$Q$39)*$F4/12)*D$11/1000} -> 180.26241 | E26: {=IF(ISTEXT($F4),SUMIF(Schedule,$F$25,Vaccine_Selection!$Y$39:$AC$39),SUMIF(Schedule,$F$25,Vaccine_Selection!$M$39:$Q$39)*$F4/12)*E$11/1000} -> 260.37904 | F26: {=IF(ISTEXT($F4),SUMIF(Schedule,$F$25,Vaccine_Selection!$Y$39:$AC$39),SUMIF(Schedule,$F$25,Vaccine_Selection!$M$39:$Q$39)*$F4/12)*F$11/1000} -> 340.49567 | G26: {=IF(ISTEXT($F4),SUMIF(Schedule,$F$25,Vaccine_Selection!$Y$39:$AC$39),SUMIF(Schedule,$F$25,Vaccine_Selection!$M$39:$Q$39)*$F4/12)*G$11/1000} -> 420.6123 | H26: {=IF(ISTEXT($F4),SUMIF(Schedule,$F$25,Vaccine_Selection!$Y$39:$AC$39),SUMIF(Schedule,$F$25,Vaccine_Selection!$M$39:$Q$39)*$F4/12)*H$11/1000} -> 500.72893 | I26: {=IF(ISTEXT($F4),SUMIF(Schedule,$F$25,Vaccine_Selection!$Y$39:$AC$39),SUMIF(Schedule,$F$25,Vaccine_Selection!$M$39:$Q$39)*$F4/12)*I$11/1000} -> 580.84555 | J26: {=IF(ISTEXT($F4),SUMIF(Schedule,$F$25,Vaccine_Selection!$Y$39:$AC$39),SUMIF(Schedule,$F$25,Vaccine_Selection!$M$39:$Q$39)*$F4/12)*J$11/1000} -> 660.96218 | ... AB26: {=IF(ISTEXT($F4),SUMIF(Schedule,$F$25,Vaccine_Selection!$Y$39:$AC$39),SUMIF(Schedule,$F$25,Vaccine_Selection!$M$39:$Q$39)*$F4/12)*AB$11/1000} -> 2103.0615
B27: =IF(F5="","",IF(ISTEXT($F5),CONCATENATE($F$25," @ ",$F5," MaxiStock"),CONCATENATE($F$25," @ ",$F5,$E$7," MaxiStock"))) -> Current schedule @ 6 months MaxiStock | C27: {=IF(ISTEXT($F5),SUMIF(Schedule,$F$25,Vaccine_Selection!$Y$39:$AC$39),SUMIF(Schedule,$F$25,Vaccine_Selection!$M$39:$Q$39)*$F5/12)*C$11/1000} -> 150.21868 | D27: {=IF(ISTEXT($F5),SUMIF(Schedule,$F$25,Vaccine_Selection!$Y$39:$AC$39),SUMIF(Schedule,$F$25,Vaccine_Selection!$M$39:$Q$39)*$F5/12)*D$11/1000} -> 270.39362 | E27: {=IF(ISTEXT($F5),SUMIF(Schedule,$F$25,Vaccine_Selection!$Y$39:$AC$39),SUMIF(Schedule,$F$25,Vaccine_Selection!$M$39:$Q$39)*$F5/12)*E$11/1000} -> 390.56856 | F27: {=IF(ISTEXT($F5),SUMIF(Schedule,$F$25,Vaccine_Selection!$Y$39:$AC$39),SUMIF(Schedule,$F$25,Vaccine_Selection!$M$39:$Q$39)*$F5/12)*F$11/1000} -> 510.7435 | G27: {=IF(ISTEXT($F5),SUMIF(Schedule,$F$25,Vaccine_Selection!$Y$39:$AC$39),SUMIF(Schedule,$F$25,Vaccine_Selection!$M$39:$Q$39)*$F5/12)*G$11/1000} -> 630.91845 | H27: {=IF(ISTEXT($F5),SUMIF(Schedule,$F$25,Vaccine_Selection!$Y$39:$AC$39),SUMIF(Schedule,$F$25,Vaccine_Selection!$M$39:$Q$39)*$F5/12)*H$11/1000} -> 751.09339 | I27: {=IF(ISTEXT($F5),SUMIF(Schedule,$F$25,Vaccine_Selection!$Y$39:$AC$39),SUMIF(Schedule,$F$25,Vaccine_Selection!$M$39:$Q$39)*$F5/12)*I$11/1000} -> 871.26833 | J27: {=IF(ISTEXT($F5),SUMIF(Schedule,$F$25,Vaccine_Selection!$Y$39:$AC$39),SUMIF(Schedule,$F$25,Vaccine_Selection!$M$39:$Q$39)*$F5/12)*J$11/1000} -> 991.44327 | ... AB27: {=IF(ISTEXT($F5),SUMIF(Schedule,$F$25,Vaccine_Selection!$Y$39:$AC$39),SUMIF(Schedule,$F$25,Vaccine_Selection!$M$39:$Q$39)*$F5/12)*AB$11/1000} -> 3154.5922
B28: =IF(F6="","",IF(ISTEXT($F6),CONCATENATE($F$25," @ ",$F6," MaxiStock"),CONCATENATE($F$25," @ ",$F6,$E$7," MaxiStock"))) -> Current schedule @ 9 months MaxiStock | C28: {=IF(ISTEXT($F6),SUMIF(Schedule,$F$25,Vaccine_Selection!$Y$39:$AC$39),SUMIF(Schedule,$F$25,Vaccine_Selection!$M$39:$Q$39)*$F6/12)*C$11/1000} -> 225.32802 | D28: {=IF(ISTEXT($F6),SUMIF(Schedule,$F$25,Vaccine_Selection!$Y$39:$AC$39),SUMIF(Schedule,$F$25,Vaccine_Selection!$M$39:$Q$39)*$F6/12)*D$11/1000} -> 405.59043 | E28: {=IF(ISTEXT($F6),SUMIF(Schedule,$F$25,Vaccine_Selection!$Y$39:$AC$39),SUMIF(Schedule,$F$25,Vaccine_Selection!$M$39:$Q$39)*$F6/12)*E$11/1000} -> 585.85284 | F28: {=IF(ISTEXT($F6),SUMIF(Schedule,$F$25,Vaccine_Selection!$Y$39:$AC$39),SUMIF(Schedule,$F$25,Vaccine_Selection!$M$39:$Q$39)*$F6/12)*F$11/1000} -> 766.11526 | G28: {=IF(ISTEXT($F6),SUMIF(Schedule,$F$25,Vaccine_Selection!$Y$39:$AC$39),SUMIF(Schedule,$F$25,Vaccine_Selection!$M$39:$Q$39)*$F6/12)*G$11/1000} -> 946.37767 | H28: {=IF(ISTEXT($F6),SUMIF(Schedule,$F$25,Vaccine_Selection!$Y$39:$AC$39),SUMIF(Schedule,$F$25,Vaccine_Selection!$M$39:$Q$39)*$F6/12)*H$11/1000} -> 1126.6401 | I28: {=IF(ISTEXT($F6),SUMIF(Schedule,$F$25,Vaccine_Selection!$Y$39:$AC$39),SUMIF(Schedule,$F$25,Vaccine_Selection!$M$39:$Q$39)*$F6/12)*I$11/1000} -> 1306.9025 | J28: {=IF(ISTEXT($F6),SUMIF(Schedule,$F$25,Vaccine_Selection!$Y$39:$AC$39),SUMIF(Schedule,$F$25,Vaccine_Selection!$M$39:$Q$39)*$F6/12)*J$11/1000} -> 1487.1649 | ... AB28: {=IF(ISTEXT($F6),SUMIF(Schedule,$F$25,Vaccine_Selection!$Y$39:$AC$39),SUMIF(Schedule,$F$25,Vaccine_Selection!$M$39:$Q$39)*$F6/12)*AB$11/1000} -> 4731.8884
B29: =IF(F7="","",IF(ISTEXT($F7),CONCATENATE($F$25," @ ",$F7," MaxiStock"),CONCATENATE($F$25," @ ",$F7,$E$7,"MaxiStock"))) -> Current schedule @ par vaccin individuel MaxiStock | C29: {=IF(ISTEXT($F7),SUMIF(Schedule,$F$25,Vaccine_Selection!$Y$39:$AC$39),SUMIF(Schedule,$F$25,Vaccine_Selection!$M$39:$Q$39)*$F7/12)*C$11/1000} -> 118.2726 | D29: {=IF(ISTEXT($F7),SUMIF(Schedule,$F$25,Vaccine_Selection!$Y$39:$AC$39),SUMIF(Schedule,$F$25,Vaccine_Selection!$M$39:$Q$39)*$F7/12)*D$11/1000} -> 212.89068 | E29: {=IF(ISTEXT($F7),SUMIF(Schedule,$F$25,Vaccine_Selection!$Y$39:$AC$39),SUMIF(Schedule,$F$25,Vaccine_Selection!$M$39:$Q$39)*$F7/12)*E$11/1000} -> 307.50876 | F29: {=IF(ISTEXT($F7),SUMIF(Schedule,$F$25,Vaccine_Selection!$Y$39:$AC$39),SUMIF(Schedule,$F$25,Vaccine_Selection!$M$39:$Q$39)*$F7/12)*F$11/1000} -> 402.12685 | G29: {=IF(ISTEXT($F7),SUMIF(Schedule,$F$25,Vaccine_Selection!$Y$39:$AC$39),SUMIF(Schedule,$F$25,Vaccine_Selection!$M$39:$Q$39)*$F7/12)*G$11/1000} -> 496.74493 | H29: {=IF(ISTEXT($F7),SUMIF(Schedule,$F$25,Vaccine_Selection!$Y$39:$AC$39),SUMIF(Schedule,$F$25,Vaccine_Selection!$M$39:$Q$39)*$F7/12)*H$11/1000} -> 591.36301 | I29: {=IF(ISTEXT($F7),SUMIF(Schedule,$F$25,Vaccine_Selection!$Y$39:$AC$39),SUMIF(Schedule,$F$25,Vaccine_Selection!$M$39:$Q$39)*$F7/12)*I$11/1000} -> 685.98109 | J29: {=IF(ISTEXT($F7),SUMIF(Schedule,$F$25,Vaccine_Selection!$Y$39:$AC$39),SUMIF(Schedule,$F$25,Vaccine_Selection!$M$39:$Q$39)*$F7/12)*J$11/1000} -> 780.59917 | ... AB29: {=IF(ISTEXT($F7),SUMIF(Schedule,$F$25,Vaccine_Selection!$Y$39:$AC$39),SUMIF(Schedule,$F$25,Vaccine_Selection!$M$39:$Q$39)*$F7/12)*AB$11/1000} -> 2483.7246
B30: =Translation!C39 -> Estimate of equipment requirements per MaxiStock | E30: =Translation!C40 -> Equipment utilization factor (%) | F30: 0.65
B31: WICR-10m3 | C31: =SUMIF(WICR,$B$31,Supplies!$E$36:$E$46) -> 3030.303 | D31: =C31 -> 3030.303 | E31: =D31 -> 3030.303 | F31: =E31 -> 3030.303 | G31: =F31 -> 3030.303 | H31: =G31 -> 3030.303 | I31: =H31 -> 3030.303 | J31: =I31 -> 3030.303 | K31: =J31 -> 3030.303 | ... AB31: =AA31 -> 3030.303
B32: =IF(F4="","",CONCATENATE(B26," - ",$B$31)) -> Current schedule @ 4 months MaxiStock - WICR-10m3 | C32: =IF(C$31=0,0,ROUND(C26/(C$31*$F$30),0)) -> 0 | D32: =IF(D$31=0,0,ROUND(D26/(D$31*$F$30),0)) -> 0 | E32: =IF(E$31=0,0,ROUND(E26/(E$31*$F$30),0)) -> 0 | F32: =IF(F$31=0,0,ROUND(F26/(F$31*$F$30),0)) -> 0 | G32: =IF(G$31=0,0,ROUND(G26/(G$31*$F$30),0)) -> 0 | H32: =IF(H$31=0,0,ROUND(H26/(H$31*$F$30),0)) -> 0 | I32: =IF(I$31=0,0,ROUND(I26/(I$31*$F$30),0)) -> 0 | J32: =IF(J$31=0,0,ROUND(J26/(J$31*$F$30),0)) -> 0 | ... AB32: =IF(AB$31=0,0,ROUND(AB26/(AB$31*$F$30),0)) -> 1
B33: =IF(F5="","",CONCATENATE(B27," - ",$B$31)) -> Current schedule @ 6 months MaxiStock - WICR-10m3 | C33: =IF(C$31=0,0,ROUND(C27/(C$31*$F$30),0)) -> 0 | D33: =IF(D$31=0,0,ROUND(D27/(D$31*$F$30),0)) -> 0 | E33: =IF(E$31=0,0,ROUND(E27/(E$31*$F$30),0)) -> 0 | F33: =IF(F$31=0,0,ROUND(F27/(F$31*$F$30),0)) -> 0 | G33: =IF(G$31=0,0,ROUND(G27/(G$31*$F$30),0)) -> 0 | H33: =IF(H$31=0,0,ROUND(H27/(H$31*$F$30),0)) -> 0 | I33: =IF(I$31=0,0,ROUND(I27/(I$31*$F$30),0)) -> 0 | J33: =IF(J$31=0,0,ROUND(J27/(J$31*$F$30),0)) -> 1 | ... AB33: =IF(AB$31=0,0,ROUND(AB27/(AB$31*$F$30),0)) -> 2
B34: =IF(F6="","",CONCATENATE(B28," - ",$B$31)) -> Current schedule @ 9 months MaxiStock - WICR-10m3 | C34: =IF(C$31=0,0,ROUND(C28/(C$31*$F$30),0)) -> 0 | D34: =IF(D$31=0,0,ROUND(D28/(D$31*$F$30),0)) -> 0 | E34: =IF(E$31=0,0,ROUND(E28/(E$31*$F$30),0)) -> 0 | F34: =IF(F$31=0,0,ROUND(F28/(F$31*$F$30),0)) -> 0 | G34: =IF(G$31=0,0,ROUND(G28/(G$31*$F$30),0)) -> 0 | H34: =IF(H$31=0,0,ROUND(H28/(H$31*$F$30),0)) -> 1 | I34: =IF(I$31=0,0,ROUND(I28/(I$31*$F$30),0)) -> 1 | J34: =IF(J$31=0,0,ROUND(J28/(J$31*$F$30),0)) -> 1 | ... AB34: =IF(AB$31=0,0,ROUND(AB28/(AB$31*$F$30),0)) -> 2
B35: =IF(F7="","",CONCATENATE(B29," - ",$B$31)) -> Current schedule @ par vaccin individuel MaxiStock - WICR-10m3 | C35: =IF(C$31=0,0,ROUND(C29/(C$31*$F$30),0)) -> 0 | D35: =IF(D$31=0,0,ROUND(D29/(D$31*$F$30),0)) -> 0 | E35: =IF(E$31=0,0,ROUND(E29/(E$31*$F$30),0)) -> 0 | F35: =IF(F$31=0,0,ROUND(F29/(F$31*$F$30),0)) -> 0 | G35: =IF(G$31=0,0,ROUND(G29/(G$31*$F$30),0)) -> 0 | H35: =IF(H$31=0,0,ROUND(H29/(H$31*$F$30),0)) -> 0 | I35: =IF(I$31=0,0,ROUND(I29/(I$31*$F$30),0)) -> 0 | J35: =IF(J$31=0,0,ROUND(J29/(J$31*$F$30),0)) -> 0 | ... AB35: =IF(AB$31=0,0,ROUND(AB29/(AB$31*$F$30),0)) -> 1
B36: =Translation!C43 -> Estimate of net dry storage per schedule (m³)
B37: =B13 -> Current schedule @ per individual vaccine months-MaxiStock | C37: =IF(ISTEXT($C$7),MAX(Vaccine_Selection!$V$17:$V$36)+MAX(Vaccine_Selection!$W$17:$W$36),$C$7)*C$11*Volume_Inject!$M$38/12000000 -> 6.1949646 | D37: =IF(ISTEXT($C$7),MAX(Vaccine_Selection!$V$17:$V$36)+MAX(Vaccine_Selection!$W$17:$W$36),$C$7)*D$11*Volume_Inject!$M$38/12000000 -> 11.150936 | E37: =IF(ISTEXT($C$7),MAX(Vaccine_Selection!$V$17:$V$36)+MAX(Vaccine_Selection!$W$17:$W$36),$C$7)*E$11*Volume_Inject!$M$38/12000000 -> 16.106908 | F37: =IF(ISTEXT($C$7),MAX(Vaccine_Selection!$V$17:$V$36)+MAX(Vaccine_Selection!$W$17:$W$36),$C$7)*F$11*Volume_Inject!$M$38/12000000 -> 21.06288 | G37: =IF(ISTEXT($C$7),MAX(Vaccine_Selection!$V$17:$V$36)+MAX(Vaccine_Selection!$W$17:$W$36),$C$7)*G$11*Volume_Inject!$M$38/12000000 -> 26.018851 | H37: =IF(ISTEXT($C$7),MAX(Vaccine_Selection!$V$17:$V$36)+MAX(Vaccine_Selection!$W$17:$W$36),$C$7)*H$11*Volume_Inject!$M$38/12000000 -> 30.974823 | I37: =IF(ISTEXT($C$7),MAX(Vaccine_Selection!$V$17:$V$36)+MAX(Vaccine_Selection!$W$17:$W$36),$C$7)*I$11*Volume_Inject!$M$38/12000000 -> 35.930794 | J37: =IF(ISTEXT($C$7),MAX(Vaccine_Selection!$V$17:$V$36)+MAX(Vaccine_Selection!$W$17:$W$36),$C$7)*J$11*Volume_Inject!$M$38/12000000 -> 40.886766 | ... AB37: =IF(ISTEXT($C$7),MAX(Vaccine_Selection!$V$17:$V$36)+MAX(Vaccine_Selection!$W$17:$W$36),$C$7)*AB$11*Volume_Inject!$M$38/12000000 -> 130.09426
B38: =B14 -> Current schedule with penta 1d @ per individual vaccine months-MaxiStock | C38: =IF(ISTEXT($C$7),MAX(Vaccine_Selection!$V$17:$V$36)+MAX(Vaccine_Selection!$W$17:$W$36),$C$7)*C$11*Volume_Inject!$N$38/12000000 -> 6.1949646 | D38: =IF(ISTEXT($C$7),MAX(Vaccine_Selection!$V$17:$V$36)+MAX(Vaccine_Selection!$W$17:$W$36),$C$7)*D$11*Volume_Inject!$N$38/12000000 -> 11.150936 | E38: =IF(ISTEXT($C$7),MAX(Vaccine_Selection!$V$17:$V$36)+MAX(Vaccine_Selection!$W$17:$W$36),$C$7)*E$11*Volume_Inject!$N$38/12000000 -> 16.106908 | F38: =IF(ISTEXT($C$7),MAX(Vaccine_Selection!$V$17:$V$36)+MAX(Vaccine_Selection!$W$17:$W$36),$C$7)*F$11*Volume_Inject!$N$38/12000000 -> 21.06288 | G38: =IF(ISTEXT($C$7),MAX(Vaccine_Selection!$V$17:$V$36)+MAX(Vaccine_Selection!$W$17:$W$36),$C$7)*G$11*Volume_Inject!$N$38/12000000 -> 26.018851 | H38: =IF(ISTEXT($C$7),MAX(Vaccine_Selection!$V$17:$V$36)+MAX(Vaccine_Selection!$W$17:$W$36),$C$7)*H$11*Volume_Inject!$N$38/12000000 -> 30.974823 | I38: =IF(ISTEXT($C$7),MAX(Vaccine_Selection!$V$17:$V$36)+MAX(Vaccine_Selection!$W$17:$W$36),$C$7)*I$11*Volume_Inject!$N$38/12000000 -> 35.930794 | J38: =IF(ISTEXT($C$7),MAX(Vaccine_Selection!$V$17:$V$36)+MAX(Vaccine_Selection!$W$17:$W$36),$C$7)*J$11*Volume_Inject!$N$38/12000000 -> 40.886766 | ... AB38: =IF(ISTEXT($C$7),MAX(Vaccine_Selection!$V$17:$V$36)+MAX(Vaccine_Selection!$W$17:$W$36),$C$7)*AB$11*Volume_Inject!$N$38/12000000 -> 130.09426
B39: =B15 -> Current schedule with penta CAD @ per individual vaccine months-MaxiStock | C39: =IF(ISTEXT($C$7),MAX(Vaccine_Selection!$V$17:$V$36)+MAX(Vaccine_Selection!$W$17:$W$36),$C$7)*C$11*Volume_Inject!$O$38/12000000 -> 4.2704229 | D39: =IF(ISTEXT($C$7),MAX(Vaccine_Selection!$V$17:$V$36)+MAX(Vaccine_Selection!$W$17:$W$36),$C$7)*D$11*Volume_Inject!$O$38/12000000 -> 7.6867612 | E39: =IF(ISTEXT($C$7),MAX(Vaccine_Selection!$V$17:$V$36)+MAX(Vaccine_Selection!$W$17:$W$36),$C$7)*E$11*Volume_Inject!$O$38/12000000 -> 11.1031 | F39: =IF(ISTEXT($C$7),MAX(Vaccine_Selection!$V$17:$V$36)+MAX(Vaccine_Selection!$W$17:$W$36),$C$7)*F$11*Volume_Inject!$O$38/12000000 -> 14.519438 | G39: =IF(ISTEXT($C$7),MAX(Vaccine_Selection!$V$17:$V$36)+MAX(Vaccine_Selection!$W$17:$W$36),$C$7)*G$11*Volume_Inject!$O$38/12000000 -> 17.935776 | H39: =IF(ISTEXT($C$7),MAX(Vaccine_Selection!$V$17:$V$36)+MAX(Vaccine_Selection!$W$17:$W$36),$C$7)*H$11*Volume_Inject!$O$38/12000000 -> 21.352114 | I39: =IF(ISTEXT($C$7),MAX(Vaccine_Selection!$V$17:$V$36)+MAX(Vaccine_Selection!$W$17:$W$36),$C$7)*I$11*Volume_Inject!$O$38/12000000 -> 24.768453 | J39: =IF(ISTEXT($C$7),MAX(Vaccine_Selection!$V$17:$V$36)+MAX(Vaccine_Selection!$W$17:$W$36),$C$7)*J$11*Volume_Inject!$O$38/12000000 -> 28.184791 | ... AB39: =IF(ISTEXT($C$7),MAX(Vaccine_Selection!$V$17:$V$36)+MAX(Vaccine_Selection!$W$17:$W$36),$C$7)*AB$11*Volume_Inject!$O$38/12000000 -> 89.678881
B40: =B16 | C40: =IF(ISTEXT($C$7),MAX(Vaccine_Selection!$V$17:$V$36)+MAX(Vaccine_Selection!$W$17:$W$36),$C$7)*C$11*Volume_Inject!$P$38/12000000 -> 0 | D40: =IF(ISTEXT($C$7),MAX(Vaccine_Selection!$V$17:$V$36)+MAX(Vaccine_Selection!$W$17:$W$36),$C$7)*D$11*Volume_Inject!$P$38/12000000 -> 0 | E40: =IF(ISTEXT($C$7),MAX(Vaccine_Selection!$V$17:$V$36)+MAX(Vaccine_Selection!$W$17:$W$36),$C$7)*E$11*Volume_Inject!$P$38/12000000 -> 0 | F40: =IF(ISTEXT($C$7),MAX(Vaccine_Selection!$V$17:$V$36)+MAX(Vaccine_Selection!$W$17:$W$36),$C$7)*F$11*Volume_Inject!$P$38/12000000 -> 0 | G40: =IF(ISTEXT($C$7),MAX(Vaccine_Selection!$V$17:$V$36)+MAX(Vaccine_Selection!$W$17:$W$36),$C$7)*G$11*Volume_Inject!$P$38/12000000 -> 0 | H40: =IF(ISTEXT($C$7),MAX(Vaccine_Selection!$V$17:$V$36)+MAX(Vaccine_Selection!$W$17:$W$36),$C$7)*H$11*Volume_Inject!$P$38/12000000 -> 0 | I40: =IF(ISTEXT($C$7),MAX(Vaccine_Selection!$V$17:$V$36)+MAX(Vaccine_Selection!$W$17:$W$36),$C$7)*I$11*Volume_Inject!$P$38/12000000 -> 0 | J40: =IF(ISTEXT($C$7),MAX(Vaccine_Selection!$V$17:$V$36)+MAX(Vaccine_Selection!$W$17:$W$36),$C$7)*J$11*Volume_Inject!$P$38/12000000 -> 0 | ... AB40: =IF(ISTEXT($C$7),MAX(Vaccine_Selection!$V$17:$V$36)+MAX(Vaccine_Selection!$W$17:$W$36),$C$7)*AB$11*Volume_Inject!$P$38/12000000 -> 0
B41: =B17 | C41: =IF(ISTEXT($C$7),MAX(Vaccine_Selection!$V$17:$V$36)+MAX(Vaccine_Selection!$W$17:$W$36),$C$7)*C$11*Volume_Inject!$Q$38/12000000 -> 0 | D41: =IF(ISTEXT($C$7),MAX(Vaccine_Selection!$V$17:$V$36)+MAX(Vaccine_Selection!$W$17:$W$36),$C$7)*D$11*Volume_Inject!$Q$38/12000000 -> 0 | E41: =IF(ISTEXT($C$7),MAX(Vaccine_Selection!$V$17:$V$36)+MAX(Vaccine_Selection!$W$17:$W$36),$C$7)*E$11*Volume_Inject!$Q$38/12000000 -> 0 | F41: =IF(ISTEXT($C$7),MAX(Vaccine_Selection!$V$17:$V$36)+MAX(Vaccine_Selection!$W$17:$W$36),$C$7)*F$11*Volume_Inject!$Q$38/12000000 -> 0 | G41: =IF(ISTEXT($C$7),MAX(Vaccine_Selection!$V$17:$V$36)+MAX(Vaccine_Selection!$W$17:$W$36),$C$7)*G$11*Volume_Inject!$Q$38/12000000 -> 0 | H41: =IF(ISTEXT($C$7),MAX(Vaccine_Selection!$V$17:$V$36)+MAX(Vaccine_Selection!$W$17:$W$36),$C$7)*H$11*Volume_Inject!$Q$38/12000000 -> 0 | I41: =IF(ISTEXT($C$7),MAX(Vaccine_Selection!$V$17:$V$36)+MAX(Vaccine_Selection!$W$17:$W$36),$C$7)*I$11*Volume_Inject!$Q$38/12000000 -> 0 | J41: =IF(ISTEXT($C$7),MAX(Vaccine_Selection!$V$17:$V$36)+MAX(Vaccine_Selection!$W$17:$W$36),$C$7)*J$11*Volume_Inject!$Q$38/12000000 -> 0 | ... AB41: =IF(ISTEXT($C$7),MAX(Vaccine_Selection!$V$17:$V$36)+MAX(Vaccine_Selection!$W$17:$W$36),$C$7)*AB$11*Volume_Inject!$Q$38/12000000 -> 0
B42: =Translation!C44 -> Estimate of net dry storage per MaxiStock (m³) | E42: =Translation!C45 -> Select schedule | F42: Current schedule
B43: =CONCATENATE($F$42," @ ",$H4,$E$7," ",$B$7) -> Current schedule @ 6 months MaxiStock | C43: =C$11*SUMIF(Volume_Inject!$M$12:$Q$12,$F$42,Volume_Inject!$M$38:$Q$38)*$H4/12000000 -> 2.8592144 | D43: =D$11*SUMIF(Volume_Inject!$M$12:$Q$12,$F$42,Volume_Inject!$M$38:$Q$38)*$H4/12000000 -> 5.1465859 | E43: =E$11*SUMIF(Volume_Inject!$M$12:$Q$12,$F$42,Volume_Inject!$M$38:$Q$38)*$H4/12000000 -> 7.4339575 | F43: =F$11*SUMIF(Volume_Inject!$M$12:$Q$12,$F$42,Volume_Inject!$M$38:$Q$38)*$H4/12000000 -> 9.721329 | G43: =G$11*SUMIF(Volume_Inject!$M$12:$Q$12,$F$42,Volume_Inject!$M$38:$Q$38)*$H4/12000000 -> 12.008701 | H43: =H$11*SUMIF(Volume_Inject!$M$12:$Q$12,$F$42,Volume_Inject!$M$38:$Q$38)*$H4/12000000 -> 14.296072 | I43: =I$11*SUMIF(Volume_Inject!$M$12:$Q$12,$F$42,Volume_Inject!$M$38:$Q$38)*$H4/12000000 -> 16.583444 | J43: =J$11*SUMIF(Volume_Inject!$M$12:$Q$12,$F$42,Volume_Inject!$M$38:$Q$38)*$H4/12000000 -> 18.870815 | ... AB43: =AB$11*SUMIF(Volume_Inject!$M$12:$Q$12,$F$42,Volume_Inject!$M$38:$Q$38)*$H4/12000000 -> 60.043503
B44: =CONCATENATE($F$42," @ ",$H5,$E$7," ",$B$7) -> Current schedule @ 9 months MaxiStock | C44: =C$11*SUMIF(Volume_Inject!$M$12:$Q$12,$F$42,Volume_Inject!$M$38:$Q$38)*$H5/12000000 -> 4.2888216 | D44: =D$11*SUMIF(Volume_Inject!$M$12:$Q$12,$F$42,Volume_Inject!$M$38:$Q$38)*$H5/12000000 -> 7.7198789 | E44: =E$11*SUMIF(Volume_Inject!$M$12:$Q$12,$F$42,Volume_Inject!$M$38:$Q$38)*$H5/12000000 -> 11.150936 | F44: =F$11*SUMIF(Volume_Inject!$M$12:$Q$12,$F$42,Volume_Inject!$M$38:$Q$38)*$H5/12000000 -> 14.581994 | G44: =G$11*SUMIF(Volume_Inject!$M$12:$Q$12,$F$42,Volume_Inject!$M$38:$Q$38)*$H5/12000000 -> 18.013051 | H44: =H$11*SUMIF(Volume_Inject!$M$12:$Q$12,$F$42,Volume_Inject!$M$38:$Q$38)*$H5/12000000 -> 21.444108 | I44: =I$11*SUMIF(Volume_Inject!$M$12:$Q$12,$F$42,Volume_Inject!$M$38:$Q$38)*$H5/12000000 -> 24.875165 | J44: =J$11*SUMIF(Volume_Inject!$M$12:$Q$12,$F$42,Volume_Inject!$M$38:$Q$38)*$H5/12000000 -> 28.306223 | ... AB44: =AB$11*SUMIF(Volume_Inject!$M$12:$Q$12,$F$42,Volume_Inject!$M$38:$Q$38)*$H5/12000000 -> 90.065254
B45: =CONCATENATE($F$42," @ ",$H6,$E$7," ",$B$7) -> Current schedule @ 12 months MaxiStock | C45: =C$11*SUMIF(Volume_Inject!$M$12:$Q$12,$F$42,Volume_Inject!$M$38:$Q$38)*$H6/12000000 -> 5.7184288 | D45: =D$11*SUMIF(Volume_Inject!$M$12:$Q$12,$F$42,Volume_Inject!$M$38:$Q$38)*$H6/12000000 -> 10.293172 | E45: =E$11*SUMIF(Volume_Inject!$M$12:$Q$12,$F$42,Volume_Inject!$M$38:$Q$38)*$H6/12000000 -> 14.867915 | F45: =F$11*SUMIF(Volume_Inject!$M$12:$Q$12,$F$42,Volume_Inject!$M$38:$Q$38)*$H6/12000000 -> 19.442658 | G45: =G$11*SUMIF(Volume_Inject!$M$12:$Q$12,$F$42,Volume_Inject!$M$38:$Q$38)*$H6/12000000 -> 24.017401 | H45: =H$11*SUMIF(Volume_Inject!$M$12:$Q$12,$F$42,Volume_Inject!$M$38:$Q$38)*$H6/12000000 -> 28.592144 | I45: =I$11*SUMIF(Volume_Inject!$M$12:$Q$12,$F$42,Volume_Inject!$M$38:$Q$38)*$H6/12000000 -> 33.166887 | J45: =J$11*SUMIF(Volume_Inject!$M$12:$Q$12,$F$42,Volume_Inject!$M$38:$Q$38)*$H6/12000000 -> 37.74163 | ... AB45: =AB$11*SUMIF(Volume_Inject!$M$12:$Q$12,$F$42,Volume_Inject!$M$38:$Q$38)*$H6/12000000 -> 120.08701
B46: =CONCATENATE($F$42," @ ",$H7,$E$7," ",$B$7) -> Current schedule @ months MaxiStock | C46: =C$11*SUMIF(Volume_Inject!$M$12:$Q$12,$F$42,Volume_Inject!$M$38:$Q$38)*$H7/12000000 -> 0 | D46: =D$11*SUMIF(Volume_Inject!$M$12:$Q$12,$F$42,Volume_Inject!$M$38:$Q$38)*$H7/12000000 -> 0 | E46: =E$11*SUMIF(Volume_Inject!$M$12:$Q$12,$F$42,Volume_Inject!$M$38:$Q$38)*$H7/12000000 -> 0 | F46: =F$11*SUMIF(Volume_Inject!$M$12:$Q$12,$F$42,Volume_Inject!$M$38:$Q$38)*$H7/12000000 -> 0 | G46: =G$11*SUMIF(Volume_Inject!$M$12:$Q$12,$F$42,Volume_Inject!$M$38:$Q$38)*$H7/12000000 -> 0 | H46: =H$11*SUMIF(Volume_Inject!$M$12:$Q$12,$F$42,Volume_Inject!$M$38:$Q$38)*$H7/12000000 -> 0 | I46: =I$11*SUMIF(Volume_Inject!$M$12:$Q$12,$F$42,Volume_Inject!$M$38:$Q$38)*$H7/12000000 -> 0 | J46: =J$11*SUMIF(Volume_Inject!$M$12:$Q$12,$F$42,Volume_Inject!$M$38:$Q$38)*$H7/12000000 -> 0 | ... AB46: =AB$11*SUMIF(Volume_Inject!$M$12:$Q$12,$F$42,Volume_Inject!$M$38:$Q$38)*$H7/12000000 -> 0
B48: =Translation!C46 -> Analysis of district level storage
F49: =F2 -> Maximum stock levels (months)
F50: =$F$3 -> Vaccines | G50: =$H$3 -> Safe injection equipment
B51: =B4 -> Analysis per | C51: =C4 -> Unit of Population | F51: 1.5 | G51: 2
B52: =B5 -> Total population (minimum) | C52: 100000 | D52: =E5 -> 0 | F52: 2 | G52: 3
B53: =B6 -> Total population (maximum) | C53: 300000 | D53: =E6 -> 0 | F53: 3 | G53: 4
B54: =B7 -> MaxiStock | C54: 3 | D54: =E7 -> months
C55: =(C53-C52)/25 -> 8000 | D55: =IF(C55=0,0,ROUNDUP(C55,-(ROUND(LOG(C55),1)))) -> 8000
B57: =Translation!C47 -> Vaccine net volume for supply period and cold equipment capacities (litres) | F57: =IF($C$4=target2,Translation!$C$12,Translation!$C$13) -> Total population
B58: =B11 -> Total population: | C58: =$C$52 -> 100000 | D58: =C58+$D$55 -> 108000 | E58: =D58+$D$55 -> 116000 | F58: =E58+$D$55 -> 124000 | G58: =F58+$D$55 -> 132000 | H58: =G58+$D$55 -> 140000 | I58: =H58+$D$55 -> 148000 | J58: =I58+$D$55 -> 156000 | K58: =J58+$D$55 -> 164000 | ... AB58: =AA58+$D$55 -> 300000
B59: =Translation!C29 -> Estimate of cold-chain capacity per schedule (litres)
B60: =IF(Vaccine_Selection!$M$16="","",CONCATENATE(Vaccine_Selection!$M$16," @ ",$C$54,$D$54," MaxiStock")) -> Current schedule @ 3 months MaxiStock | C60: =Vaccine_Selection!$M$40*$C$54*C$58/12000 -> 20.088534 | D60: =Vaccine_Selection!$M$40*$C$54*D$58/12000 -> 21.695617 | E60: =Vaccine_Selection!$M$40*$C$54*E$58/12000 -> 23.3027 | F60: =Vaccine_Selection!$M$40*$C$54*F$58/12000 -> 24.909783 | G60: =Vaccine_Selection!$M$40*$C$54*G$58/12000 -> 26.516865 | H60: =Vaccine_Selection!$M$40*$C$54*H$58/12000 -> 28.123948 | I60: =Vaccine_Selection!$M$40*$C$54*I$58/12000 -> 29.731031 | J60: =Vaccine_Selection!$M$40*$C$54*J$58/12000 -> 31.338114 | ... AB60: =Vaccine_Selection!$M$40*$C$54*AB$58/12000 -> 60.265603
B61: =IF(Vaccine_Selection!$N$16="","",CONCATENATE(Vaccine_Selection!$N$16," @ ",$C$54,$D$54," MaxiStock")) -> Current schedule with penta 1d @ 3 months MaxiStock | C61: =Vaccine_Selection!$N$40*$C$54*C$58/12000 -> 39.859294 | D61: =Vaccine_Selection!$N$40*$C$54*D$58/12000 -> 43.048038 | E61: =Vaccine_Selection!$N$40*$C$54*E$58/12000 -> 46.236782 | F61: =Vaccine_Selection!$N$40*$C$54*F$58/12000 -> 49.425525 | G61: =Vaccine_Selection!$N$40*$C$54*G$58/12000 -> 52.614269 | H61: =Vaccine_Selection!$N$40*$C$54*H$58/12000 -> 55.803012 | I61: =Vaccine_Selection!$N$40*$C$54*I$58/12000 -> 58.991756 | J61: =Vaccine_Selection!$N$40*$C$54*J$58/12000 -> 62.180499 | ... AB61: =Vaccine_Selection!$N$40*$C$54*AB$58/12000 -> 119.57788
B62: =IF(Vaccine_Selection!$O$16="","",CONCATENATE(Vaccine_Selection!$O$16," @ ",$C$54,$D$54," MaxiStock")) -> Current schedule with penta CAD @ 3 months MaxiStock | C62: =Vaccine_Selection!$O$40*$C$54*C$58/12000 -> 32.863534 | D62: =Vaccine_Selection!$O$40*$C$54*D$58/12000 -> 35.492617 | E62: =Vaccine_Selection!$O$40*$C$54*E$58/12000 -> 38.1217 | F62: =Vaccine_Selection!$O$40*$C$54*F$58/12000 -> 40.750783 | G62: =Vaccine_Selection!$O$40*$C$54*G$58/12000 -> 43.379865 | H62: =Vaccine_Selection!$O$40*$C$54*H$58/12000 -> 46.008948 | I62: =Vaccine_Selection!$O$40*$C$54*I$58/12000 -> 48.638031 | J62: =Vaccine_Selection!$O$40*$C$54*J$58/12000 -> 51.267114 | ... AB62: =Vaccine_Selection!$O$40*$C$54*AB$58/12000 -> 98.590603
B63: =IF(Vaccine_Selection!$P$16="","",CONCATENATE(Vaccine_Selection!$P$16," @ ",$C$54,$D$54," MaxiStock")) | C63: =Vaccine_Selection!$P$40*$C$54*C$58/12000 -> 0 | D63: =Vaccine_Selection!$P$40*$C$54*D$58/12000 -> 0 | E63: =Vaccine_Selection!$P$40*$C$54*E$58/12000 -> 0 | F63: =Vaccine_Selection!$P$40*$C$54*F$58/12000 -> 0 | G63: =Vaccine_Selection!$P$40*$C$54*G$58/12000 -> 0 | H63: =Vaccine_Selection!$P$40*$C$54*H$58/12000 -> 0 | I63: =Vaccine_Selection!$P$40*$C$54*I$58/12000 -> 0 | J63: =Vaccine_Selection!$P$40*$C$54*J$58/12000 -> 0 | ... AB63: =Vaccine_Selection!$P$40*$C$54*AB$58/12000 -> 0
B64: =IF(Vaccine_Selection!$Q$16="","",CONCATENATE(Vaccine_Selection!$Q$16," @ ",$C$54,$D$54," MaxiStock")) | C64: =Vaccine_Selection!$Q$40*$C$54*C$58/12000 -> 0 | D64: =Vaccine_Selection!$Q$40*$C$54*D$58/12000 -> 0 | E64: =Vaccine_Selection!$Q$40*$C$54*E$58/12000 -> 0 | F64: =Vaccine_Selection!$Q$40*$C$54*F$58/12000 -> 0 | G64: =Vaccine_Selection!$Q$40*$C$54*G$58/12000 -> 0 | H64: =Vaccine_Selection!$Q$40*$C$54*H$58/12000 -> 0 | I64: =Vaccine_Selection!$Q$40*$C$54*I$58/12000 -> 0 | J64: =Vaccine_Selection!$Q$40*$C$54*J$58/12000 -> 0 | ... AB64: =Vaccine_Selection!$Q$40*$C$54*AB$58/12000 -> 0
B65: =Translation!C38 -> Estimate of equipment requirements per schedule | E65: =Translation!C40 -> Equipment utilization factor (%) | F65: 0.8
B66: HBC-340 | C66: =SUMIF(Eqpt_list,$B66,PQEquipment!$I$6:$I$97) -> 200 | D66: =C66 -> 200 | E66: =D66 -> 200 | F66: =E66 -> 200 | G66: =F66 -> 200 | H66: =G66 -> 200 | I66: =H66 -> 200 | J66: =I66 -> 200 | K66: =J66 -> 200 | ... AB66: =AA66 -> 200
B67: =IF(Vaccine_Selection!$M$16="","",CONCATENATE($B60," - ",$B$66)) -> Current schedule @ 3 months MaxiStock - HBC-340 | C67: =IF(C$66=0,0,ROUND(C60/(C$66*$F$65),0)) -> 0 | D67: =IF(D$66=0,0,ROUND(D60/(D$66*$F$65),0)) -> 0 | E67: =IF(E$66=0,0,ROUND(E60/(E$66*$F$65),0)) -> 0 | F67: =IF(F$66=0,0,ROUND(F60/(F$66*$F$65),0)) -> 0 | G67: =IF(G$66=0,0,ROUND(G60/(G$66*$F$65),0)) -> 0 | H67: =IF(H$66=0,0,ROUND(H60/(H$66*$F$65),0)) -> 0 | I67: =IF(I$66=0,0,ROUND(I60/(I$66*$F$65),0)) -> 0 | J67: =IF(J$66=0,0,ROUND(J60/(J$66*$F$65),0)) -> 0 | ... AB67: =IF(AB$66=0,0,ROUND(AB60/(AB$66*$F$65),0)) -> 0
B68: =IF(Vaccine_Selection!$N$16="","",CONCATENATE($B61," - ",$B$66)) -> Current schedule with penta 1d @ 3 months MaxiStock - HBC-340 | C68: =IF(C$66=0,0,ROUND(C61/(C$66*$F$65),0)) -> 0 | D68: =IF(D$66=0,0,ROUND(D61/(D$66*$F$65),0)) -> 0 | E68: =IF(E$66=0,0,ROUND(E61/(E$66*$F$65),0)) -> 0 | F68: =IF(F$66=0,0,ROUND(F61/(F$66*$F$65),0)) -> 0 | G68: =IF(G$66=0,0,ROUND(G61/(G$66*$F$65),0)) -> 0 | H68: =IF(H$66=0,0,ROUND(H61/(H$66*$F$65),0)) -> 0 | I68: =IF(I$66=0,0,ROUND(I61/(I$66*$F$65),0)) -> 0 | J68: =IF(J$66=0,0,ROUND(J61/(J$66*$F$65),0)) -> 0 | ... AB68: =IF(AB$66=0,0,ROUND(AB61/(AB$66*$F$65),0)) -> 1
B69: =IF(Vaccine_Selection!$O$16="","",CONCATENATE($B62," - ",$B$66)) -> Current schedule with penta CAD @ 3 months MaxiStock - HBC-340 | C69: =IF(C$66=0,0,ROUND(C62/(C$66*$F$65),0)) -> 0 | D69: =IF(D$66=0,0,ROUND(D62/(D$66*$F$65),0)) -> 0 | E69: =IF(E$66=0,0,ROUND(E62/(E$66*$F$65),0)) -> 0 | F69: =IF(F$66=0,0,ROUND(F62/(F$66*$F$65),0)) -> 0 | G69: =IF(G$66=0,0,ROUND(G62/(G$66*$F$65),0)) -> 0 | H69: =IF(H$66=0,0,ROUND(H62/(H$66*$F$65),0)) -> 0 | I69: =IF(I$66=0,0,ROUND(I62/(I$66*$F$65),0)) -> 0 | J69: =IF(J$66=0,0,ROUND(J62/(J$66*$F$65),0)) -> 0 | ... AB69: =IF(AB$66=0,0,ROUND(AB62/(AB$66*$F$65),0)) -> 1
B70: =IF(Vaccine_Selection!$P$16="","",CONCATENATE($B63," - ",$B$66)) | C70: =IF(C$66=0,0,ROUND(C63/(C$66*$F$65),0)) -> 0 | D70: =IF(D$66=0,0,ROUND(D63/(D$66*$F$65),0)) -> 0 | E70: =IF(E$66=0,0,ROUND(E63/(E$66*$F$65),0)) -> 0 | F70: =IF(F$66=0,0,ROUND(F63/(F$66*$F$65),0)) -> 0 | G70: =IF(G$66=0,0,ROUND(G63/(G$66*$F$65),0)) -> 0 | H70: =IF(H$66=0,0,ROUND(H63/(H$66*$F$65),0)) -> 0 | I70: =IF(I$66=0,0,ROUND(I63/(I$66*$F$65),0)) -> 0 | J70: =IF(J$66=0,0,ROUND(J63/(J$66*$F$65),0)) -> 0 | ... AB70: =IF(AB$66=0,0,ROUND(AB63/(AB$66*$F$65),0)) -> 0
B71: =IF(Vaccine_Selection!$Q$16="","",CONCATENATE($B64," - ",$B$66)) | C71: =IF(C$66=0,0,ROUND(C64/(C$66*$F$65),0)) -> 0 | D71: =IF(D$66=0,0,ROUND(D64/(D$66*$F$65),0)) -> 0 | E71: =IF(E$66=0,0,ROUND(E64/(E$66*$F$65),0)) -> 0 | F71: =IF(F$66=0,0,ROUND(F64/(F$66*$F$65),0)) -> 0 | G71: =IF(G$66=0,0,ROUND(G64/(G$66*$F$65),0)) -> 0 | H71: =IF(H$66=0,0,ROUND(H64/(H$66*$F$65),0)) -> 0 | I71: =IF(I$66=0,0,ROUND(I64/(I$66*$F$65),0)) -> 0 | J71: =IF(J$66=0,0,ROUND(J64/(J$66*$F$65),0)) -> 0 | ... AB71: =IF(AB$66=0,0,ROUND(AB64/(AB$66*$F$65),0)) -> 0
B72: =Translation!C42 -> Estimate of cold-chain capacity per MaxiStock (litres) | E72: =Translation!C45 -> Select schedule | F72: Current schedule
B73: =IF(F51="","",CONCATENATE($F$72," @ ",$F51,$D$54," MaxiStock")) -> Current schedule @ 1.5 months MaxiStock | C73: =SUMIF(Schedule,$F$72,Vaccine_Selection!$M$40:$Q$40)*$F51*C$58/12000 -> 10.044267 | D73: =SUMIF(Schedule,$F$72,Vaccine_Selection!$M$40:$Q$40)*$F51*D$58/12000 -> 10.847809 | E73: =SUMIF(Schedule,$F$72,Vaccine_Selection!$M$40:$Q$40)*$F51*E$58/12000 -> 11.65135 | F73: =SUMIF(Schedule,$F$72,Vaccine_Selection!$M$40:$Q$40)*$F51*F$58/12000 -> 12.454891 | G73: =SUMIF(Schedule,$F$72,Vaccine_Selection!$M$40:$Q$40)*$F51*G$58/12000 -> 13.258433 | H73: =SUMIF(Schedule,$F$72,Vaccine_Selection!$M$40:$Q$40)*$F51*H$58/12000 -> 14.061974 | I73: =SUMIF(Schedule,$F$72,Vaccine_Selection!$M$40:$Q$40)*$F51*I$58/12000 -> 14.865515 | J73: =SUMIF(Schedule,$F$72,Vaccine_Selection!$M$40:$Q$40)*$F51*J$58/12000 -> 15.669057 | ... AB73: =SUMIF(Schedule,$F$72,Vaccine_Selection!$M$40:$Q$40)*$F51*AB$58/12000 -> 30.132802
B74: =IF(F52="","",CONCATENATE($F$72," @ ",$F52,$D$54," MaxiStock")) -> Current schedule @ 2 months MaxiStock | C74: =SUMIF(Schedule,$F$72,Vaccine_Selection!$M$40:$Q$40)*$F52*C$58/12000 -> 13.392356 | D74: =SUMIF(Schedule,$F$72,Vaccine_Selection!$M$40:$Q$40)*$F52*D$58/12000 -> 14.463745 | E74: =SUMIF(Schedule,$F$72,Vaccine_Selection!$M$40:$Q$40)*$F52*E$58/12000 -> 15.535133 | F74: =SUMIF(Schedule,$F$72,Vaccine_Selection!$M$40:$Q$40)*$F52*F$58/12000 -> 16.606522 | G74: =SUMIF(Schedule,$F$72,Vaccine_Selection!$M$40:$Q$40)*$F52*G$58/12000 -> 17.67791 | H74: =SUMIF(Schedule,$F$72,Vaccine_Selection!$M$40:$Q$40)*$F52*H$58/12000 -> 18.749299 | I74: =SUMIF(Schedule,$F$72,Vaccine_Selection!$M$40:$Q$40)*$F52*I$58/12000 -> 19.820687 | J74: =SUMIF(Schedule,$F$72,Vaccine_Selection!$M$40:$Q$40)*$F52*J$58/12000 -> 20.892076 | ... AB74: =SUMIF(Schedule,$F$72,Vaccine_Selection!$M$40:$Q$40)*$F52*AB$58/12000 -> 40.177069
B75: =IF(F53="","",CONCATENATE($F$72," @ ",$F53,$D$54," MaxiStock")) -> Current schedule @ 3 months MaxiStock | C75: =SUMIF(Schedule,$F$72,Vaccine_Selection!$M$40:$Q$40)*$F53*C$58/12000 -> 20.088534 | D75: =SUMIF(Schedule,$F$72,Vaccine_Selection!$M$40:$Q$40)*$F53*D$58/12000 -> 21.695617 | E75: =SUMIF(Schedule,$F$72,Vaccine_Selection!$M$40:$Q$40)*$F53*E$58/12000 -> 23.3027 | F75: =SUMIF(Schedule,$F$72,Vaccine_Selection!$M$40:$Q$40)*$F53*F$58/12000 -> 24.909783 | G75: =SUMIF(Schedule,$F$72,Vaccine_Selection!$M$40:$Q$40)*$F53*G$58/12000 -> 26.516865 | H75: =SUMIF(Schedule,$F$72,Vaccine_Selection!$M$40:$Q$40)*$F53*H$58/12000 -> 28.123948 | I75: =SUMIF(Schedule,$F$72,Vaccine_Selection!$M$40:$Q$40)*$F53*I$58/12000 -> 29.731031 | J75: =SUMIF(Schedule,$F$72,Vaccine_Selection!$M$40:$Q$40)*$F53*J$58/12000 -> 31.338114 | ... AB75: =SUMIF(Schedule,$F$72,Vaccine_Selection!$M$40:$Q$40)*$F53*AB$58/12000 -> 60.265603
B76: =IF(F54="","",CONCATENATE($F$72," @ ",$F54,$D$54," MaxiStock")) | C76: =SUMIF(Schedule,$F$72,Vaccine_Selection!$M$40:$Q$40)*$F54*C$58/12000 -> 0 | D76: =SUMIF(Schedule,$F$72,Vaccine_Selection!$M$40:$Q$40)*$F54*D$58/12000 -> 0 | E76: =SUMIF(Schedule,$F$72,Vaccine_Selection!$M$40:$Q$40)*$F54*E$58/12000 -> 0 | F76: =SUMIF(Schedule,$F$72,Vaccine_Selection!$M$40:$Q$40)*$F54*F$58/12000 -> 0 | G76: =SUMIF(Schedule,$F$72,Vaccine_Selection!$M$40:$Q$40)*$F54*G$58/12000 -> 0 | H76: =SUMIF(Schedule,$F$72,Vaccine_Selection!$M$40:$Q$40)*$F54*H$58/12000 -> 0 | I76: =SUMIF(Schedule,$F$72,Vaccine_Selection!$M$40:$Q$40)*$F54*I$58/12000 -> 0 | J76: =SUMIF(Schedule,$F$72,Vaccine_Selection!$M$40:$Q$40)*$F54*J$58/12000 -> 0 | ... AB76: =SUMIF(Schedule,$F$72,Vaccine_Selection!$M$40:$Q$40)*$F54*AB$58/12000 -> 0
B77: =Translation!C39 -> Estimate of equipment requirements per MaxiStock | E77: =Translation!C40 -> Equipment utilization factor (%) | F77: 0.8
B78: BLF100AC | C78: =SUMIF(Eqpt_list,$B78,PQEquipment!$I$6:$I$97) -> 103 | D78: =C78 -> 103 | E78: =D78 -> 103 | F78: =E78 -> 103 | G78: =F78 -> 103 | H78: =G78 -> 103 | I78: =H78 -> 103 | J78: =I78 -> 103 | K78: =J78 -> 103 | ... AB78: =AA78 -> 103
B79: =IF(F51="","",CONCATENATE(B73," - ",$B$78)) -> Current schedule @ 1.5 months MaxiStock - BLF100AC | C79: =IF(C$78=0,0,ROUND(C73/(C$78*$F$77),0)) -> 0 | D79: =IF(D$78=0,0,ROUND(D73/(D$78*$F$77),0)) -> 0 | E79: =IF(E$78=0,0,ROUND(E73/(E$78*$F$77),0)) -> 0 | F79: =IF(F$78=0,0,ROUND(F73/(F$78*$F$77),0)) -> 0 | G79: =IF(G$78=0,0,ROUND(G73/(G$78*$F$77),0)) -> 0 | H79: =IF(H$78=0,0,ROUND(H73/(H$78*$F$77),0)) -> 0 | I79: =IF(I$78=0,0,ROUND(I73/(I$78*$F$77),0)) -> 0 | J79: =IF(J$78=0,0,ROUND(J73/(J$78*$F$77),0)) -> 0 | ... AB79: =IF(AB$78=0,0,ROUND(AB73/(AB$78*$F$77),0)) -> 0
B80: =IF(F52="","",CONCATENATE(B74," - ",$B$78)) -> Current schedule @ 2 months MaxiStock - BLF100AC | C80: =IF(C$78=0,0,ROUND(C74/(C$78*$F$77),0)) -> 0 | D80: =IF(D$78=0,0,ROUND(D74/(D$78*$F$77),0)) -> 0 | E80: =IF(E$78=0,0,ROUND(E74/(E$78*$F$77),0)) -> 0 | F80: =IF(F$78=0,0,ROUND(F74/(F$78*$F$77),0)) -> 0 | G80: =IF(G$78=0,0,ROUND(G74/(G$78*$F$77),0)) -> 0 | H80: =IF(H$78=0,0,ROUND(H74/(H$78*$F$77),0)) -> 0 | I80: =IF(I$78=0,0,ROUND(I74/(I$78*$F$77),0)) -> 0 | J80: =IF(J$78=0,0,ROUND(J74/(J$78*$F$77),0)) -> 0 | ... AB80: =IF(AB$78=0,0,ROUND(AB74/(AB$78*$F$77),0)) -> 0
B81: =IF(F53="","",CONCATENATE(B75," - ",$B$78)) -> Current schedule @ 3 months MaxiStock - BLF100AC | C81: =IF(C$78=0,0,ROUND(C75/(C$78*$F$77),0)) -> 0 | D81: =IF(D$78=0,0,ROUND(D75/(D$78*$F$77),0)) -> 0 | E81: =IF(E$78=0,0,ROUND(E75/(E$78*$F$77),0)) -> 0 | F81: =IF(F$78=0,0,ROUND(F75/(F$78*$F$77),0)) -> 0 | G81: =IF(G$78=0,0,ROUND(G75/(G$78*$F$77),0)) -> 0 | H81: =IF(H$78=0,0,ROUND(H75/(H$78*$F$77),0)) -> 0 | I81: =IF(I$78=0,0,ROUND(I75/(I$78*$F$77),0)) -> 0 | J81: =IF(J$78=0,0,ROUND(J75/(J$78*$F$77),0)) -> 0 | ... AB81: =IF(AB$78=0,0,ROUND(AB75/(AB$78*$F$77),0)) -> 1
B82: =IF(F54="","",CONCATENATE(B76," - ",$B$78)) | C82: =IF(C$78=0,0,ROUND(C76/(C$78*$F$77),0)) -> 0 | D82: =IF(D$78=0,0,ROUND(D76/(D$78*$F$77),0)) -> 0 | E82: =IF(E$78=0,0,ROUND(E76/(E$78*$F$77),0)) -> 0 | F82: =IF(F$78=0,0,ROUND(F76/(F$78*$F$77),0)) -> 0 | G82: =IF(G$78=0,0,ROUND(G76/(G$78*$F$77),0)) -> 0 | H82: =IF(H$78=0,0,ROUND(H76/(H$78*$F$77),0)) -> 0 | I82: =IF(I$78=0,0,ROUND(I76/(I$78*$F$77),0)) -> 0 | J82: =IF(J$78=0,0,ROUND(J76/(J$78*$F$77),0)) -> 0 | ... AB82: =IF(AB$78=0,0,ROUND(AB76/(AB$78*$F$77),0)) -> 0
B83: =Translation!C43 -> Estimate of net dry storage per schedule (m³)
B84: =B60 -> Current schedule @ 3 months MaxiStock | C84: =C$58*Volume_Inject!$M$38*$C$54/12000000 -> 0.28592144 | D84: =D$58*Volume_Inject!$M$38*$C$54/12000000 -> 0.30879516 | E84: =E$58*Volume_Inject!$M$38*$C$54/12000000 -> 0.33166887 | F84: =F$58*Volume_Inject!$M$38*$C$54/12000000 -> 0.35454259 | G84: =G$58*Volume_Inject!$M$38*$C$54/12000000 -> 0.3774163 | H84: =H$58*Volume_Inject!$M$38*$C$54/12000000 -> 0.40029002 | I84: =I$58*Volume_Inject!$M$38*$C$54/12000000 -> 0.42316373 | J84: =J$58*Volume_Inject!$M$38*$C$54/12000000 -> 0.44603745 | ... AB84: =AB$58*Volume_Inject!$M$38*$C$54/12000000 -> 0.85776432
B85: =B61 -> Current schedule with penta 1d @ 3 months MaxiStock | C85: =C$58*Volume_Inject!$N$38*$C$54/12000000 -> 0.28592144 | D85: =D$58*Volume_Inject!$N$38*$C$54/12000000 -> 0.30879516 | E85: =E$58*Volume_Inject!$N$38*$C$54/12000000 -> 0.33166887 | F85: =F$58*Volume_Inject!$N$38*$C$54/12000000 -> 0.35454259 | G85: =G$58*Volume_Inject!$N$38*$C$54/12000000 -> 0.3774163 | H85: =H$58*Volume_Inject!$N$38*$C$54/12000000 -> 0.40029002 | I85: =I$58*Volume_Inject!$N$38*$C$54/12000000 -> 0.42316373 | J85: =J$58*Volume_Inject!$N$38*$C$54/12000000 -> 0.44603745 | ... AB85: =AB$58*Volume_Inject!$N$38*$C$54/12000000 -> 0.85776432
B86: =B62 -> Current schedule with penta CAD @ 3 months MaxiStock | C86: =C$58*Volume_Inject!$O$38*$C$54/12000000 -> 0.19709644 | D86: =D$58*Volume_Inject!$O$38*$C$54/12000000 -> 0.21286416 | E86: =E$58*Volume_Inject!$O$38*$C$54/12000000 -> 0.22863187 | F86: =F$58*Volume_Inject!$O$38*$C$54/12000000 -> 0.24439959 | G86: =G$58*Volume_Inject!$O$38*$C$54/12000000 -> 0.2601673 | H86: =H$58*Volume_Inject!$O$38*$C$54/12000000 -> 0.27593502 | I86: =I$58*Volume_Inject!$O$38*$C$54/12000000 -> 0.29170273 | J86: =J$58*Volume_Inject!$O$38*$C$54/12000000 -> 0.30747045 | ... AB86: =AB$58*Volume_Inject!$O$38*$C$54/12000000 -> 0.59128932
B87: =B63 | C87: =C$58*Volume_Inject!$P$38*$C$54/12000000 -> 0 | D87: =D$58*Volume_Inject!$P$38*$C$54/12000000 -> 0 | E87: =E$58*Volume_Inject!$P$38*$C$54/12000000 -> 0 | F87: =F$58*Volume_Inject!$P$38*$C$54/12000000 -> 0 | G87: =G$58*Volume_Inject!$P$38*$C$54/12000000 -> 0 | H87: =H$58*Volume_Inject!$P$38*$C$54/12000000 -> 0 | I87: =I$58*Volume_Inject!$P$38*$C$54/12000000 -> 0 | J87: =J$58*Volume_Inject!$P$38*$C$54/12000000 -> 0 | ... AB87: =AB$58*Volume_Inject!$P$38*$C$54/12000000 -> 0
B88: =B64 | C88: =C$58*Volume_Inject!$Q$38*$C$54/12000000 -> 0 | D88: =D$58*Volume_Inject!$Q$38*$C$54/12000000 -> 0 | E88: =E$58*Volume_Inject!$Q$38*$C$54/12000000 -> 0 | F88: =F$58*Volume_Inject!$Q$38*$C$54/12000000 -> 0 | G88: =G$58*Volume_Inject!$Q$38*$C$54/12000000 -> 0 | H88: =H$58*Volume_Inject!$Q$38*$C$54/12000000 -> 0 | I88: =I$58*Volume_Inject!$Q$38*$C$54/12000000 -> 0 | J88: =J$58*Volume_Inject!$Q$38*$C$54/12000000 -> 0 | ... AB88: =AB$58*Volume_Inject!$Q$38*$C$54/12000000 -> 0
B89: =Translation!C44 -> Estimate of net dry storage per MaxiStock (m³) | E89: =Translation!C45 -> Select schedule | F89: Current schedule
B90: =IF(G51="","",CONCATENATE($F$89," @ ",$G51,$D$54,"_",$B$54)) -> Current schedule @ 2 months_MaxiStock | C90: =C$58*SUMIF(Volume_Inject!$M$12:$Q$12,$F$89,Volume_Inject!$M$38:$Q$38)*$G51/12000000 -> 0.19061429 | D90: =D$58*SUMIF(Volume_Inject!$M$12:$Q$12,$F$89,Volume_Inject!$M$38:$Q$38)*$G51/12000000 -> 0.20586344 | E90: =E$58*SUMIF(Volume_Inject!$M$12:$Q$12,$F$89,Volume_Inject!$M$38:$Q$38)*$G51/12000000 -> 0.22111258 | F90: =F$58*SUMIF(Volume_Inject!$M$12:$Q$12,$F$89,Volume_Inject!$M$38:$Q$38)*$G51/12000000 -> 0.23636172 | G90: =G$58*SUMIF(Volume_Inject!$M$12:$Q$12,$F$89,Volume_Inject!$M$38:$Q$38)*$G51/12000000 -> 0.25161087 | H90: =H$58*SUMIF(Volume_Inject!$M$12:$Q$12,$F$89,Volume_Inject!$M$38:$Q$38)*$G51/12000000 -> 0.26686001 | I90: =I$58*SUMIF(Volume_Inject!$M$12:$Q$12,$F$89,Volume_Inject!$M$38:$Q$38)*$G51/12000000 -> 0.28210916 | J90: =J$58*SUMIF(Volume_Inject!$M$12:$Q$12,$F$89,Volume_Inject!$M$38:$Q$38)*$G51/12000000 -> 0.2973583 | ... AB90: =AB$58*SUMIF(Volume_Inject!$M$12:$Q$12,$F$89,Volume_Inject!$M$38:$Q$38)*$G51/12000000 -> 0.57184288
B91: =IF(G52="","",CONCATENATE($F$89," @ ",$G52,$D$54,"_",$B$54)) -> Current schedule @ 3 months_MaxiStock | C91: =C$58*SUMIF(Volume_Inject!$M$12:$Q$12,$F$89,Volume_Inject!$M$38:$Q$38)*$G52/12000000 -> 0.28592144 | D91: =D$58*SUMIF(Volume_Inject!$M$12:$Q$12,$F$89,Volume_Inject!$M$38:$Q$38)*$G52/12000000 -> 0.30879516 | E91: =E$58*SUMIF(Volume_Inject!$M$12:$Q$12,$F$89,Volume_Inject!$M$38:$Q$38)*$G52/12000000 -> 0.33166887 | F91: =F$58*SUMIF(Volume_Inject!$M$12:$Q$12,$F$89,Volume_Inject!$M$38:$Q$38)*$G52/12000000 -> 0.35454259 | G91: =G$58*SUMIF(Volume_Inject!$M$12:$Q$12,$F$89,Volume_Inject!$M$38:$Q$38)*$G52/12000000 -> 0.3774163 | H91: =H$58*SUMIF(Volume_Inject!$M$12:$Q$12,$F$89,Volume_Inject!$M$38:$Q$38)*$G52/12000000 -> 0.40029002 | I91: =I$58*SUMIF(Volume_Inject!$M$12:$Q$12,$F$89,Volume_Inject!$M$38:$Q$38)*$G52/12000000 -> 0.42316373 | J91: =J$58*SUMIF(Volume_Inject!$M$12:$Q$12,$F$89,Volume_Inject!$M$38:$Q$38)*$G52/12000000 -> 0.44603745 | ... AB91: =AB$58*SUMIF(Volume_Inject!$M$12:$Q$12,$F$89,Volume_Inject!$M$38:$Q$38)*$G52/12000000 -> 0.85776432
B92: =IF(G53="","",CONCATENATE($F$89," @ ",$G53,$D$54,"_",$B$54)) -> Current schedule @ 4 months_MaxiStock | C92: =C$58*SUMIF(Volume_Inject!$M$12:$Q$12,$F$89,Volume_Inject!$M$38:$Q$38)*$G53/12000000 -> 0.38122859 | D92: =D$58*SUMIF(Volume_Inject!$M$12:$Q$12,$F$89,Volume_Inject!$M$38:$Q$38)*$G53/12000000 -> 0.41172688 | E92: =E$58*SUMIF(Volume_Inject!$M$12:$Q$12,$F$89,Volume_Inject!$M$38:$Q$38)*$G53/12000000 -> 0.44222516 | F92: =F$58*SUMIF(Volume_Inject!$M$12:$Q$12,$F$89,Volume_Inject!$M$38:$Q$38)*$G53/12000000 -> 0.47272345 | G92: =G$58*SUMIF(Volume_Inject!$M$12:$Q$12,$F$89,Volume_Inject!$M$38:$Q$38)*$G53/12000000 -> 0.50322174 | H92: =H$58*SUMIF(Volume_Inject!$M$12:$Q$12,$F$89,Volume_Inject!$M$38:$Q$38)*$G53/12000000 -> 0.53372002 | I92: =I$58*SUMIF(Volume_Inject!$M$12:$Q$12,$F$89,Volume_Inject!$M$38:$Q$38)*$G53/12000000 -> 0.56421831 | J92: =J$58*SUMIF(Volume_Inject!$M$12:$Q$12,$F$89,Volume_Inject!$M$38:$Q$38)*$G53/12000000 -> 0.5947166 | ... AB92: =AB$58*SUMIF(Volume_Inject!$M$12:$Q$12,$F$89,Volume_Inject!$M$38:$Q$38)*$G53/12000000 -> 1.1436858
B93: =IF(G54="","",CONCATENATE($F$89," @ ",$G54,$D$54,"_",$B$54)) | C93: =C$58*SUMIF(Volume_Inject!$M$12:$Q$12,$F$89,Volume_Inject!$M$38:$Q$38)*$G54/12000000 -> 0 | D93: =D$58*SUMIF(Volume_Inject!$M$12:$Q$12,$F$89,Volume_Inject!$M$38:$Q$38)*$G54/12000000 -> 0 | E93: =E$58*SUMIF(Volume_Inject!$M$12:$Q$12,$F$89,Volume_Inject!$M$38:$Q$38)*$G54/12000000 -> 0 | F93: =F$58*SUMIF(Volume_Inject!$M$12:$Q$12,$F$89,Volume_Inject!$M$38:$Q$38)*$G54/12000000 -> 0 | G93: =G$58*SUMIF(Volume_Inject!$M$12:$Q$12,$F$89,Volume_Inject!$M$38:$Q$38)*$G54/12000000 -> 0 | H93: =H$58*SUMIF(Volume_Inject!$M$12:$Q$12,$F$89,Volume_Inject!$M$38:$Q$38)*$G54/12000000 -> 0 | I93: =I$58*SUMIF(Volume_Inject!$M$12:$Q$12,$F$89,Volume_Inject!$M$38:$Q$38)*$G54/12000000 -> 0 | J93: =J$58*SUMIF(Volume_Inject!$M$12:$Q$12,$F$89,Volume_Inject!$M$38:$Q$38)*$G54/12000000 -> 0 | ... AB93: =AB$58*SUMIF(Volume_Inject!$M$12:$Q$12,$F$89,Volume_Inject!$M$38:$Q$38)*$G54/12000000 -> 0
B95: =Translation!C56 -> Analysis of service delivery level storage
F96: =F49 -> Maximum stock levels (months)
F97: =$F$50 -> Vaccines | G97: =$G$50 -> Safe injection equipment
B98: =B51 -> Analysis per | C98: =C51 -> Unit of Population | F98: 1 | G98: 2
B99: =B52 -> Total population (minimum) | C99: 1000 | D99: =D52 -> 0 | F99: 1.5 | G99: 3
B100: =B53 -> Total population (maximum) | C100: 40000 | D100: =D53 -> 0 | F100: 2 | G100: 4
B101: =B54 -> MaxiStock | C101: 2 | D101: =D54 -> months
C102: =(C100-C99)/25 -> 1560 | D102: =IF(C102=0,0,ROUNDUP(C102,-(ROUND(LOG(C102),1)))) -> 2000
B104: =B57 -> Vaccine net volume for supply period and cold equipment capacities (litres) | F104: =IF($C$4=target2,Translation!$C$12,Translation!$C$13) -> Total population
B105: =B58 -> Total population: | C105: =$C$99 -> 1000 | D105: =C105+$D$102 -> 3000 | E105: =D105+$D$102 -> 5000 | F105: =E105+$D$102 -> 7000 | G105: =F105+$D$102 -> 9000 | H105: =G105+$D$102 -> 11000 | I105: =H105+$D$102 -> 13000 | J105: =I105+$D$102 -> 15000 | K105: =J105+$D$102 -> 17000 | ... AB105: =AA105+$D$102 -> 51000
...

Sheet Volume_Inject
B2: =Translation!C368 -> Volume of diluents and safe injection equipment per recipient | O2: =Translation!C369 -> Optional data entry only | U2: =Translation!C109 -> Index
B5: =Translation!C370 -> OPTION: Over-ride default AD syringe packed volume, cm³/unit: | K5: =IF(I5<>"",I5,0.102*1000000/1800) -> 56.666667 | M5: cm³
B6: =Translation!C371 -> OPTION: Over-ride default reconstitution syringe packed volume, cm³/unit: | K6: =IF(I6<>"",I6,0.106*1000000/1600) -> 66.25 | M6: cm³
B7: =Translation!C372 -> OPTION: Over-ride default safety box packed volume, cm³/unit: | K7: =IF(I7<>"",I7,60*25.7*0.45) -> 693.9 | M7: cm³
B10: =Vaccine_Selection!B14 -> Characteristics of vaccines selected for use | I10: =Translation!C379 -> Net storage volume | M10: =Vaccine_Selection!M14 -> National immunization schedule | S10: =Vaccine_Selection!$S$14 -> Supplementary
F11: =Translation!C378 -> Volume data used | I11: =Translation!C380 -> per injection (cm³) | M11: =Vaccine_Selection!M15 -> (Routine vaccinations) | S11: =Vaccine_Selection!$S$15 -> activities (SIAs)
B12: =Translation!C374 -> Vaccine type | C12: =Translation!C375 -> Formulation | D12: =Translation!C376 -> Administration | E12: =Translation!C377 -> Presentation (doses/vial) | F12: =Vaccine_Selection!F16 -> Vaccine volume (cm³/dose) | G12: =Vaccine_Selection!G16 -> Diluent volume (cm³/dose) | I12: =Translation!C381 -> Injection syringe | J12: =Translation!C382 -> Mixing syringe | K12: =Translation!C383 -> Safety boxes | M12: =IF(Vaccine_Selection!M16="","",Vaccine_Selection!M16) -> Current schedule | N12: =IF(Vaccine_Selection!N16="","",Vaccine_Selection!N16) -> Current schedule with penta 1d | O12: =IF(Vaccine_Selection!O16="","",Vaccine_Selection!O16) -> Current schedule with penta CAD | P12: =IF(Vaccine_Selection!P16="","",Vaccine_Selection!P16) | Q12: =IF(Vaccine_Selection!Q16="","",Vaccine_Selection!Q16) | S12: =IF(Vaccine_Selection!S16="","",Vaccine_Selection!S16) -> H1N1 campaign | T12: =IF(Vaccine_Selection!T16="","",Vaccine_Selection!T16) | U12: =IF(Vaccine_Selection!U16="","",Vaccine_Selection!U16)
B13: =IF(Vaccine_Selection!B17="","",Vaccine_Selection!B17) -> BCG | C13: {=IF($B13="","",INDEX(Vaccine_database!$C$10:$D$278,MATCH($B13,Vaccines,0),2))} -> freeze-dried | D13: {=IF($B13="","",INDEX(Vaccine_database!$C$10:$E$278,MATCH($B13,Vaccines,0),3))} -> ID | E13: =Vaccine_Selection!C17 -> 20 | F13: =IF(Vaccine_Selection!D17="",Vaccine_Selection!F17,Vaccine_Selection!D17) -> 1.2102 | G13: =IF(Vaccine_Selection!D17="",Vaccine_Selection!G17,Vaccine_Selection!E17) -> 1.1256667 | I13: =IF(OR(B13="",D13="Oral",D13="Nasal"),"",IF(ISTEXT(E13),0,$K$5*1.1)) -> 62.333333 | J13: =IF(OR(B13="",C13="liquid",D13="Oral",D13="Nasal",ISTEXT(E13)),"",$K$6*Vaccine_Selection!K17/E13) -> 6.625 | K13: =IF(B13="",0,(COUNT($I13:$I13)+COUNT($J13:$J13)/IF(ISTEXT($E13),1,$E13))*$K$7/100) -> 7.28595 | L13: =Vaccine_Selection!L17 -> 0.019 | M13: =IF(Vaccine_Selection!M17="","",Vaccine_Selection!M17) -> 1 | N13: =IF(Vaccine_Selection!N17="","",Vaccine_Selection!N17) -> 1 | O13: =IF(Vaccine_Selection!O17="","",Vaccine_Selection!O17) -> 1 | P13: =IF(Vaccine_Selection!P17="","",Vaccine_Selection!P17) | Q13: =IF(Vaccine_Selection!Q17="","",Vaccine_Selection!Q17) | S13: =IF(Vaccine_Selection!S17="","",Vaccine_Selection!S17) | T13: =IF(Vaccine_Selection!T17="","",Vaccine_Selection!T17) | U13: =IF(Vaccine_Selection!U17="","",Vaccine_Selection!U17)
B14: =IF(Vaccine_Selection!B18="","",Vaccine_Selection!B18) -> OPV | C14: {=IF($B14="","",INDEX(Vaccine_database!$C$10:$D$278,MATCH($B14,Vaccines,0),2))} -> liquid | D14: {=IF($B14="","",INDEX(Vaccine_database!$C$10:$E$278,MATCH($B14,Vaccines,0),3))} -> Oral | E14: =Vaccine_Selection!C18 -> 10 | F14: =IF(Vaccine_Selection!D18="",Vaccine_Selection!F18,Vaccine_Selection!D18) -> 2 | G14: =IF(Vaccine_Selection!D18="",Vaccine_Selection!G18,Vaccine_Selection!E18) -> 0 | I14: =IF(OR(B14="",D14="Oral",D14="Nasal"),"",IF(ISTEXT(E14),0,$K$5*1.1)) | J14: =IF(OR(B14="",C14="liquid",D14="Oral",D14="Nasal",ISTEXT(E14)),"",$K$6*Vaccine_Selection!K18/E14) | K14: =IF(B14="",0,(COUNT($I14:$I14)+COUNT($J14:$J14)/IF(ISTEXT($E14),1,$E14))*$K$7/100) -> 0 | L14: =Vaccine_Selection!L18 -> 0.019 | M14: =IF(Vaccine_Selection!M18="","",Vaccine_Selection!M18) -> 4 | N14: =IF(Vaccine_Selection!N18="","",Vaccine_Selection!N18) -> 4 | O14: =IF(Vaccine_Selection!O18="","",Vaccine_Selection!O18) -> 4 | P14: =IF(Vaccine_Selection!P18="","",Vaccine_Selection!P18) | Q14: =IF(Vaccine_Selection!Q18="","",Vaccine_Selection!Q18) | S14: =IF(Vaccine_Selection!S18="","",Vaccine_Selection!S18) | T14: =IF(Vaccine_Selection!T18="","",Vaccine_Selection!T18) | U14: =IF(Vaccine_Selection!U18="","",Vaccine_Selection!U18)
B15: =IF(Vaccine_Selection!B19="","",Vaccine_Selection!B19) -> DTP-HepB-Hib | C15: {=IF($B15="","",INDEX(Vaccine_database!$C$10:$D$278,MATCH($B15,Vaccines,0),2))} -> liquid | D15: {=IF($B15="","",INDEX(Vaccine_database!$C$10:$E$278,MATCH($B15,Vaccines,0),3))} -> IM | E15: =Vaccine_Selection!C19 -> 10 | F15: =IF(Vaccine_Selection!D19="",Vaccine_Selection!F19,Vaccine_Selection!D19) -> 2.75 | G15: =IF(Vaccine_Selection!D19="",Vaccine_Selection!G19,Vaccine_Selection!E19) -> 0 | I15: =IF(OR(B15="",D15="Oral",D15="Nasal"),"",IF(ISTEXT(E15),0,$K$5*1.1)) -> 62.333333 | J15: =IF(OR(B15="",C15="liquid",D15="Oral",D15="Nasal",ISTEXT(E15)),"",$K$6*Vaccine_Selection!K19/E15) | K15: =IF(B15="",0,(COUNT($I15:$I15)+COUNT($J15:$J15)/IF(ISTEXT($E15),1,$E15))*$K$7/100) -> 6.939 | L15: =Vaccine_Selection!L19 -> 0.019 | M15: =IF(Vaccine_Selection!M19="","",Vaccine_Selection!M19) -> 3 | N15: =IF(Vaccine_Selection!N19="","",Vaccine_Selection!N19) | O15: =IF(Vaccine_Selection!O19="","",Vaccine_Selection!O19) | P15: =IF(Vaccine_Selection!P19="","",Vaccine_Selection!P19) | Q15: =IF(Vaccine_Selection!Q19="","",Vaccine_Selection!Q19) | S15: =IF(Vaccine_Selection!S19="","",Vaccine_Selection!S19) | T15: =IF(Vaccine_Selection!T19="","",Vaccine_Selection!T19) | U15: =IF(Vaccine_Selection!U19="","",Vaccine_Selection!U19)
B16: =IF(Vaccine_Selection!B20="","",Vaccine_Selection!B20) -> DTP-HepB-Hib | C16: {=IF($B16="","",INDEX(Vaccine_database!$C$10:$D$278,MATCH($B16,Vaccines,0),2))} -> liquid | D16: {=IF($B16="","",INDEX(Vaccine_database!$C$10:$E$278,MATCH($B16,Vaccines,0),3))} -> IM | E16: =Vaccine_Selection!C20 -> 1 | F16: =IF(Vaccine_Selection!D20="",Vaccine_Selection!F20,Vaccine_Selection!D20) -> 16.66384 | G16: =IF(Vaccine_Selection!D20="",Vaccine_Selection!G20,Vaccine_Selection!E20) -> 0 | I16: =IF(OR(B16="",D16="Oral",D16="Nasal"),"",IF(ISTEXT(E16),0,$K$5*1.1)) -> 62.333333 | J16: =IF(OR(B16="",C16="liquid",D16="Oral",D16="Nasal",ISTEXT(E16)),"",$K$6*Vaccine_Selection!K20/E16) | K16: =IF(B16="",0,(COUNT($I16:$I16)+COUNT($J16:$J16)/IF(ISTEXT($E16),1,$E16))*$K$7/100) -> 6.939 | L16: =Vaccine_Selection!L20 -> 0.019 | M16: =IF(Vaccine_Selection!M20="","",Vaccine_Selection!M20) | N16: =IF(Vaccine_Selection!N20="","",Vaccine_Selection!N20) -> 3 | O16: =IF(Vaccine_Selection!O20="","",Vaccine_Selection!O20) | P16: =IF(Vaccine_Selection!P20="","",Vaccine_Selection!P20) | Q16: =IF(Vaccine_Selection!Q20="","",Vaccine_Selection!Q20) | S16: =IF(Vaccine_Selection!S20="","",Vaccine_Selection!S20) | T16: =IF(Vaccine_Selection!T20="","",Vaccine_Selection!T20) | U16: =IF(Vaccine_Selection!U20="","",Vaccine_Selection!U20)
B17: =IF(Vaccine_Selection!B21="","",Vaccine_Selection!B21) -> DTP-HepB-Hib | C17: {=IF($B17="","",INDEX(Vaccine_database!$C$10:$D$278,MATCH($B17,Vaccines,0),2))} -> liquid | D17: {=IF($B17="","",INDEX(Vaccine_database!$C$10:$E$278,MATCH($B17,Vaccines,0),3))} -> IM | E17: =Vaccine_Selection!C21 -> Uniject | F17: =IF(Vaccine_Selection!D21="",Vaccine_Selection!F21,Vaccine_Selection!D21) -> 12 | G17: =IF(Vaccine_Selection!D21="",Vaccine_Selection!G21,Vaccine_Selection!E21) -> 0 | I17: =IF(OR(B17="",D17="Oral",D17="Nasal"),"",IF(ISTEXT(E17),0,$K$5*1.1)) -> 0 | J17: =IF(OR(B17="",C17="liquid",D17="Oral",D17="Nasal",ISTEXT(E17)),"",$K$6*Vaccine_Selection!K21/E17) | K17: =IF(B17="",0,(COUNT($I17:$I17)+COUNT($J17:$J17)/IF(ISTEXT($E17),1,$E17))*$K$7/100) -> 6.939 | L17: =Vaccine_Selection!L21 -> 0.019 | M17: =IF(Vaccine_Selection!M21="","",Vaccine_Selection!M21) | N17: =IF(Vaccine_Selection!N21="","",Vaccine_Selection!N21) | O17: =IF(Vaccine_Selection!O21="","",Vaccine_Selection!O21) -> 3 | P17: =IF(Vaccine_Selection!P21="","",Vaccine_Selection!P21) | Q17: =IF(Vaccine_Selection!Q21="","",Vaccine_Selection!Q21) | S17: =IF(Vaccine_Selection!S21="","",Vaccine_Selection!S21) | T17: =IF(Vaccine_Selection!T21="","",Vaccine_Selection!T21) | U17: =IF(Vaccine_Selection!U21="","",Vaccine_Selection!U21)
B18: =IF(Vaccine_Selection!B22="","",Vaccine_Selection!B22) -> Measles | C18: {=IF($B18="","",INDEX(Vaccine_database!$C$10:$D$278,MATCH($B18,Vaccines,0),2))} -> freeze-dried | D18: {=IF($B18="","",INDEX(Vaccine_database!$C$10:$E$278,MATCH($B18,Vaccines,0),3))} -> SC | E18: =Vaccine_Selection!C22 -> 10 | F18: =IF(Vaccine_Selection!D22="",Vaccine_Selection!F22,Vaccine_Selection!D22) -> 2.4002 | G18: =IF(Vaccine_Selection!D22="",Vaccine_Selection!G22,Vaccine_Selection!E22) -> 3.2 | I18: =IF(OR(B18="",D18="Oral",D18="Nasal"),"",IF(ISTEXT(E18),0,$K$5*1.1)) -> 62.333333 | J18: =IF(OR(B18="",C18="liquid",D18="Oral",D18="Nasal",ISTEXT(E18)),"",$K$6*Vaccine_Selection!K22/E18) -> 11.041667 | K18: =IF(B18="",0,(COUNT($I18:$I18)+COUNT($J18:$J18)/IF(ISTEXT($E18),1,$E18))*$K$7/100) -> 7.6329 | L18: =Vaccine_Selection!L22 -> 0.018 | M18: =IF(Vaccine_Selection!M22="","",Vaccine_Selection!M22) -> 1 | N18: =IF(Vaccine_Selection!N22="","",Vaccine_Selection!N22) -> 1 | O18: =IF(Vaccine_Selection!O22="","",Vaccine_Selection!O22) -> 1 | P18: =IF(Vaccine_Selection!P22="","",Vaccine_Selection!P22) | Q18: =IF(Vaccine_Selection!Q22="","",Vaccine_Selection!Q22) | S18: =IF(Vaccine_Selection!S22="","",Vaccine_Selection!S22) | T18: =IF(Vaccine_Selection!T22="","",Vaccine_Selection!T22) | U18: =IF(Vaccine_Selection!U22="","",Vaccine_Selection!U22)
B19: =IF(Vaccine_Selection!B23="","",Vaccine_Selection!B23) -> YF | C19: {=IF($B19="","",INDEX(Vaccine_database!$C$10:$D$278,MATCH($B19,Vaccines,0),2))} -> freeze-dried | D19: {=IF($B19="","",INDEX(Vaccine_database!$C$10:$E$278,MATCH($B19,Vaccines,0),3))} -> SC | E19: =Vaccine_Selection!C23 -> 5 | F19: =IF(Vaccine_Selection!D23="",Vaccine_Selection!F23,Vaccine_Selection!D23) -> 5.4025 | G19: =IF(Vaccine_Selection!D23="",Vaccine_Selection!G23,Vaccine_Selection!E23) -> 6.75 | I19: =IF(OR(B19="",D19="Oral",D19="Nasal"),"",IF(ISTEXT(E19),0,$K$5*1.1)) -> 62.333333 | J19: =IF(OR(B19="",C19="liquid",D19="Oral",D19="Nasal",ISTEXT(E19)),"",$K$6*Vaccine_Selection!K23/E19) -> 14.722222 | K19: =IF(B19="",0,(COUNT($I19:$I19)+COUNT($J19:$J19)/IF(ISTEXT($E19),1,$E19))*$K$7/100) -> 8.3268 | L19: =Vaccine_Selection!L23 -> 0.018 | M19: =IF(Vaccine_Selection!M23="","",Vaccine_Selection!M23) -> 1 | N19: =IF(Vaccine_Selection!N23="","",Vaccine_Selection!N23) -> 1 | O19: =IF(Vaccine_Selection!O23="","",Vaccine_Selection!O23) -> 1 | P19: =IF(Vaccine_Selection!P23="","",Vaccine_Selection!P23) | Q19: =IF(Vaccine_Selection!Q23="","",Vaccine_Selection!Q23) | S19: =IF(Vaccine_Selection!S23="","",Vaccine_Selection!S23) | T19: =IF(Vaccine_Selection!T23="","",Vaccine_Selection!T23) | U19: =IF(Vaccine_Selection!U23="","",Vaccine_Selection!U23)
B20: =IF(Vaccine_Selection!B24="","",Vaccine_Selection!B24) -> TT | C20: {=IF($B20="","",INDEX(Vaccine_database!$C$10:$D$278,MATCH($B20,Vaccines,0),2))} -> liquid | D20: {=IF($B20="","",INDEX(Vaccine_database!$C$10:$E$278,MATCH($B20,Vaccines,0),3))} -> IM | E20: =Vaccine_Selection!C24 -> 10 | F20: =IF(Vaccine_Selection!D24="",Vaccine_Selection!F24,Vaccine_Selection!D24) -> 3.1093333 | G20: =IF(Vaccine_Selection!D24="",Vaccine_Selection!G24,Vaccine_Selection!E24) -> 0 | I20: =IF(OR(B20="",D20="Oral",D20="Nasal"),"",IF(ISTEXT(E20),0,$K$5*1.1)) -> 62.333333 | J20: =IF(OR(B20="",C20="liquid",D20="Oral",D20="Nasal",ISTEXT(E20)),"",$K$6*Vaccine_Selection!K24/E20) | K20: =IF(B20="",0,(COUNT($I20:$I20)+COUNT($J20:$J20)/IF(ISTEXT($E20),1,$E20))*$K$7/100) -> 6.939 | L20: =Vaccine_Selection!L24 -> 0.02 | M20: =IF(Vaccine_Selection!M24="","",Vaccine_Selection!M24) -> 2 | N20: =IF(Vaccine_Selection!N24="","",Vaccine_Selection!N24) -> 2 | O20: =IF(Vaccine_Selection!O24="","",Vaccine_Selection!O24) -> 2 | P20: =IF(Vaccine_Selection!P24="","",Vaccine_Selection!P24) | Q20: =IF(Vaccine_Selection!Q24="","",Vaccine_Selection!Q24) | S20: =IF(Vaccine_Selection!S24="","",Vaccine_Selection!S24) | T20: =IF(Vaccine_Selection!T24="","",Vaccine_Selection!T24) | U20: =IF(Vaccine_Selection!U24="","",Vaccine_Selection!U24)
B21: =IF(Vaccine_Selection!B25="","",Vaccine_Selection!B25) -> PCV-13 | C21: {=IF($B21="","",INDEX(Vaccine_database!$C$10:$D$278,MATCH($B21,Vaccines,0),2))} -> liquid | D21: {=IF($B21="","",INDEX(Vaccine_database!$C$10:$E$278,MATCH($B21,Vaccines,0),3))} -> IM | E21: =Vaccine_Selection!C25 -> 1 | F21: =IF(Vaccine_Selection!D25="",Vaccine_Selection!F25,Vaccine_Selection!D25) -> 13.825247 | G21: =IF(Vaccine_Selection!D25="",Vaccine_Selection!G25,Vaccine_Selection!E25) -> 0 | I21: =IF(OR(B21="",D21="Oral",D21="Nasal"),"",IF(ISTEXT(E21),0,$K$5*1.1)) -> 62.333333 | J21: =IF(OR(B21="",C21="liquid",D21="Oral",D21="Nasal",ISTEXT(E21)),"",$K$6*Vaccine_Selection!K25/E21) | K21: =IF(B21="",0,(COUNT($I21:$I21)+COUNT($J21:$J21)/IF(ISTEXT($E21),1,$E21))*$K$7/100) -> 6.939 | L21: =Vaccine_Selection!L25 -> 0.01 | M21: =IF(Vaccine_Selection!M25="","",Vaccine_Selection!M25) | N21: =IF(Vaccine_Selection!N25="","",Vaccine_Selection!N25) | O21: =IF(Vaccine_Selection!O25="","",Vaccine_Selection!O25) | P21: =IF(Vaccine_Selection!P25="","",Vaccine_Selection!P25) | Q21: =IF(Vaccine_Selection!Q25="","",Vaccine_Selection!Q25) | S21: =IF(Vaccine_Selection!S25="","",Vaccine_Selection!S25) | T21: =IF(Vaccine_Selection!T25="","",Vaccine_Selection!T25) | U21: =IF(Vaccine_Selection!U25="","",Vaccine_Selection!U25)
B22: =IF(Vaccine_Selection!B26="","",Vaccine_Selection!B26) -> Rota_liq | C22: {=IF($B22="","",INDEX(Vaccine_database!$C$10:$D$278,MATCH($B22,Vaccines,0),2))} -> liquid | D22: {=IF($B22="","",INDEX(Vaccine_database!$C$10:$E$278,MATCH($B22,Vaccines,0),3))} -> Oral | E22: =Vaccine_Selection!C26 -> 1 | F22: =IF(Vaccine_Selection!D26="",Vaccine_Selection!F26,Vaccine_Selection!D26) -> 17.1 | G22: =IF(Vaccine_Selection!D26="",Vaccine_Selection!G26,Vaccine_Selection!E26) -> 0 | I22: =IF(OR(B22="",D22="Oral",D22="Nasal"),"",IF(ISTEXT(E22),0,$K$5*1.1)) | J22: =IF(OR(B22="",C22="liquid",D22="Oral",D22="Nasal",ISTEXT(E22)),"",$K$6*Vaccine_Selection!K26/E22) | K22: =IF(B22="",0,(COUNT($I22:$I22)+COUNT($J22:$J22)/IF(ISTEXT($E22),1,$E22))*$K$7/100) -> 0 | L22: =Vaccine_Selection!L26 -> 0.035 | M22: =IF(Vaccine_Selection!M26="","",Vaccine_Selection!M26) | N22: =IF(Vaccine_Selection!N26="","",Vaccine_Selection!N26) | O22: =IF(Vaccine_Selection!O26="","",Vaccine_Selection!O26) | P22: =IF(Vaccine_Selection!P26="","",Vaccine_Selection!P26) | Q22: =IF(Vaccine_Selection!Q26="","",Vaccine_Selection!Q26) | S22: =IF(Vaccine_Selection!S26="","",Vaccine_Selection!S26) -> 1 | U22: =IF(Vaccine_Selection!U26="","",Vaccine_Selection!U26)
B23: =IF(Vaccine_Selection!B27="","",Vaccine_Selection!B27) | C23: {=IF($B23="","",INDEX(Vaccine_database!$C$10:$D$278,MATCH($B23,Vaccines,0),2))} | D23: {=IF($B23="","",INDEX(Vaccine_database!$C$10:$E$278,MATCH($B23,Vaccines,0),3))} | E23: =Vaccine_Selection!C27 -> 0 | F23: =IF(Vaccine_Selection!D27="",Vaccine_Selection!F27,Vaccine_Selection!D27) -> 0 | G23: =IF(Vaccine_Selection!D27="",Vaccine_Selection!G27,Vaccine_Selection!E27) -> 0 | I23: =IF(OR(B23="",D23="Oral",D23="Nasal"),"",IF(ISTEXT(E23),0,$K$5*1.1)) | J23: =IF(OR(B23="",C23="liquid",D23="Oral",D23="Nasal",ISTEXT(E23)),"",$K$6*Vaccine_Selection!K27/E23) | K23: =IF(B23="",0,(COUNT($I23:$I23)+COUNT($J23:$J23)/IF(ISTEXT($E23),1,$E23))*$K$7/100) -> 0 | L23: =Vaccine_Selection!L27 -> 0 | M23: =IF(Vaccine_Selection!M27="","",Vaccine_Selection!M27) | N23: =IF(Vaccine_Selection!N27="","",Vaccine_Selection!N27) | O23: =IF(Vaccine_Selection!O27="","",Vaccine_Selection!O27) | P23: =IF(Vaccine_Selection!P27="","",Vaccine_Selection!P27) | Q23: =IF(Vaccine_Selection!Q27="","",Vaccine_Selection!Q27) | S23: =IF(Vaccine_Selection!S27="","",Vaccine_Selection!S27) | T23: =IF(Vaccine_Selection!T27="","",Vaccine_Selection!T27) | U23: =IF(Vaccine_Selection!U27="","",Vaccine_Selection!U27)
B24: =IF(Vaccine_Selection!B28="","",Vaccine_Selection!B28) | C24: {=IF($B24="","",INDEX(Vaccine_database!$C$10:$D$278,MATCH($B24,Vaccines,0),2))} | D24: {=IF($B24="","",INDEX(Vaccine_database!$C$10:$E$278,MATCH($B24,Vaccines,0),3))} | E24: =Vaccine_Selection!C28 -> 0 | F24: =IF(Vaccine_Selection!D28="",Vaccine_Selection!F28,Vaccine_Selection!D28) -> 0 | G24: =IF(Vaccine_Selection!D28="",Vaccine_Selection!G28,Vaccine_Selection!E28) -> 0 | I24: =IF(OR(B24="",D24="Oral",D24="Nasal"),"",IF(ISTEXT(E24),0,$K$5*1.1)) | J24: =IF(OR(B24="",C24="liquid",D24="Oral",D24="Nasal",ISTEXT(E24)),"",$K$6*Vaccine_Selection!K28/E24) | K24: =IF(B24="",0,(COUNT($I24:$I24)+COUNT($J24:$J24)/IF(ISTEXT($E24),1,$E24))*$K$7/100) -> 0 | L24: =Vaccine_Selection!L28 -> 0 | M24: =IF(Vaccine_Selection!M28="","",Vaccine_Selection!M28) | N24: =IF(Vaccine_Selection!N28="","",Vaccine_Selection!N28) | O24: =IF(Vaccine_Selection!O28="","",Vaccine_Selection!O28) | P24: =IF(Vaccine_Selection!P28="","",Vaccine_Selection!P28) | Q24: =IF(Vaccine_Selection!Q28="","",Vaccine_Selection!Q28) | S24: =IF(Vaccine_Selection!S28="","",Vaccine_Selection!S28) | T24: =IF(Vaccine_Selection!T28="","",Vaccine_Selection!T28) | U24: =IF(Vaccine_Selection!U28="","",Vaccine_Selection!U28)
B25: =IF(Vaccine_Selection!B29="","",Vaccine_Selection!B29) | C25: {=IF($B25="","",INDEX(Vaccine_database!$C$10:$D$278,MATCH($B25,Vaccines,0),2))} | D25: {=IF($B25="","",INDEX(Vaccine_database!$C$10:$E$278,MATCH($B25,Vaccines,0),3))} | E25: =Vaccine_Selection!C29 -> 0 | F25: =IF(Vaccine_Selection!D29="",Vaccine_Selection!F29,Vaccine_Selection!D29) -> 0 | G25: =IF(Vaccine_Selection!D29="",Vaccine_Selection!G29,Vaccine_Selection!E29) -> 0 | I25: =IF(OR(B25="",D25="Oral",D25="Nasal"),"",IF(ISTEXT(E25),0,$K$5*1.1)) | J25: =IF(OR(B25="",C25="liquid",D25="Oral",D25="Nasal",ISTEXT(E25)),"",$K$6*Vaccine_Selection!K29/E25) | K25: =IF(B25="",0,(COUNT($I25:$I25)+COUNT($J25:$J25)/IF(ISTEXT($E25),1,$E25))*$K$7/100) -> 0 | L25: =Vaccine_Selection!L29 -> 0 | M25: =IF(Vaccine_Selection!M29="","",Vaccine_Selection!M29) | N25: =IF(Vaccine_Selection!N29="","",Vaccine_Selection!N29) | O25: =IF(Vaccine_Selection!O29="","",Vaccine_Selection!O29) | P25: =IF(Vaccine_Selection!P29="","",Vaccine_Selection!P29) | Q25: =IF(Vaccine_Selection!Q29="","",Vaccine_Selection!Q29) | S25: =IF(Vaccine_Selection!S29="","",Vaccine_Selection!S29) | T25: =IF(Vaccine_Selection!T29="","",Vaccine_Selection!T29) | U25: =IF(Vaccine_Selection!U29="","",Vaccine_Selection!U29)
B26: =IF(Vaccine_Selection!B30="","",Vaccine_Selection!B30) | C26: {=IF($B26="","",INDEX(Vaccine_database!$C$10:$D$278,MATCH($B26,Vaccines,0),2))} | D26: {=IF($B26="","",INDEX(Vaccine_database!$C$10:$E$278,MATCH($B26,Vaccines,0),3))} | E26: =Vaccine_Selection!C30 -> 0 | F26: =IF(Vaccine_Selection!D30="",Vaccine_Selection!F30,Vaccine_Selection!D30) -> 0 | G26: =IF(Vaccine_Selection!D30="",Vaccine_Selection!G30,Vaccine_Selection!E30) -> 0 | I26: =IF(OR(B26="",D26="Oral",D26="Nasal"),"",IF(ISTEXT(E26),0,$K$5*1.1)) | J26: =IF(OR(B26="",C26="liquid",D26="Oral",D26="Nasal",ISTEXT(E26)),"",$K$6*Vaccine_Selection!K30/E26) | K26: =IF(B26="",0,(COUNT($I26:$I26)+COUNT($J26:$J26)/IF(ISTEXT($E26),1,$E26))*$K$7/100) -> 0 | L26: =Vaccine_Selection!L30 -> 0 | M26: =IF(Vaccine_Selection!M30="","",Vaccine_Selection!M30) | N26: =IF(Vaccine_Selection!N30="","",Vaccine_Selection!N30) | O26: =IF(Vaccine_Selection!O30="","",Vaccine_Selection!O30) | P26: =IF(Vaccine_Selection!P30="","",Vaccine_Selection!P30) | Q26: =IF(Vaccine_Selection!Q30="","",Vaccine_Selection!Q30) | S26: =IF(Vaccine_Selection!S30="","",Vaccine_Selection!S30) | T26: =IF(Vaccine_Selection!T30="","",Vaccine_Selection!T30) | U26: =IF(Vaccine_Selection!U30="","",Vaccine_Selection!U30)
B27: =IF(Vaccine_Selection!B31="","",Vaccine_Selection!B31) | C27: {=IF($B27="","",INDEX(Vaccine_database!$C$10:$D$278,MATCH($B27,Vaccines,0),2))} | D27: {=IF($B27="","",INDEX(Vaccine_database!$C$10:$E$278,MATCH($B27,Vaccines,0),3))} | E27: =Vaccine_Selection!C31 -> 0 | F27: =IF(Vaccine_Selection!D31="",Vaccine_Selection!F31,Vaccine_Selection!D31) -> 0 | G27: =IF(Vaccine_Selection!D31="",Vaccine_Selection!G31,Vaccine_Selection!E31) -> 0 | I27: =IF(OR(B27="",D27="Oral",D27="Nasal"),"",IF(ISTEXT(E27),0,$K$5*1.1)) | J27: =IF(OR(B27="",C27="liquid",D27="Oral",D27="Nasal",ISTEXT(E27)),"",$K$6*Vaccine_Selection!K31/E27) | K27: =IF(B27="",0,(COUNT($I27:$I27)+COUNT($J27:$J27)/IF(ISTEXT($E27),1,$E27))*$K$7/100) -> 0 | L27: =Vaccine_Selection!L31 -> 0 | M27: =IF(Vaccine_Selection!M31="","",Vaccine_Selection!M31) | N27: =IF(Vaccine_Selection!N31="","",Vaccine_Selection!N31) | O27: =IF(Vaccine_Selection!O31="","",Vaccine_Selection!O31) | P27: =IF(Vaccine_Selection!P31="","",Vaccine_Selection!P31) | Q27: =IF(Vaccine_Selection!Q31="","",Vaccine_Selection!Q31) | S27: =IF(Vaccine_Selection!S31="","",Vaccine_Selection!S31) | T27: =IF(Vaccine_Selection!T31="","",Vaccine_Selection!T31) | U27: =IF(Vaccine_Selection!U31="","",Vaccine_Selection!U31)
B28: =IF(Vaccine_Selection!B32="","",Vaccine_Selection!B32) | C28: {=IF($B28="","",INDEX(Vaccine_database!$C$10:$D$278,MATCH($B28,Vaccines,0),2))} | D28: {=IF($B28="","",INDEX(Vaccine_database!$C$10:$E$278,MATCH($B28,Vaccines,0),3))} | E28: =Vaccine_Selection!C32 -> 0 | F28: =IF(Vaccine_Selection!D32="",Vaccine_Selection!F32,Vaccine_Selection!D32) -> 0 | G28: =IF(Vaccine_Selection!D32="",Vaccine_Selection!G32,Vaccine_Selection!E32) -> 0 | I28: =IF(OR(B28="",D28="Oral",D28="Nasal"),"",IF(ISTEXT(E28),0,$K$5*1.1)) | J28: =IF(OR(B28="",C28="liquid",D28="Oral",D28="Nasal",ISTEXT(E28)),"",$K$6*Vaccine_Selection!K32/E28) | K28: =IF(B28="",0,(COUNT($I28:$I28)+COUNT($J28:$J28)/IF(ISTEXT($E28),1,$E28))*$K$7/100) -> 0 | L28: =Vaccine_Selection!L32 -> 0 | M28: =IF(Vaccine_Selection!M32="","",Vaccine_Selection!M32) | N28: =IF(Vaccine_Selection!N32="","",Vaccine_Selection!N32) | O28: =IF(Vaccine_Selection!O32="","",Vaccine_Selection!O32) | P28: =IF(Vaccine_Selection!P32="","",Vaccine_Selection!P32) | Q28: =IF(Vaccine_Selection!Q32="","",Vaccine_Selection!Q32) | S28: =IF(Vaccine_Selection!S32="","",Vaccine_Selection!S32) | T28: =IF(Vaccine_Selection!T32="","",Vaccine_Selection!T32) | U28: =IF(Vaccine_Selection!U32="","",Vaccine_Selection!U32)
B29: =IF(Vaccine_Selection!B33="","",Vaccine_Selection!B33) | C29: {=IF($B29="","",INDEX(Vaccine_database!$C$10:$D$278,MATCH($B29,Vaccines,0),2))} | D29: {=IF($B29="","",INDEX(Vaccine_database!$C$10:$E$278,MATCH($B29,Vaccines,0),3))} | E29: =Vaccine_Selection!C33 -> 0 | F29: =IF(Vaccine_Selection!D33="",Vaccine_Selection!F33,Vaccine_Selection!D33) -> 0 | G29: =IF(Vaccine_Selection!D33="",Vaccine_Selection!G33,Vaccine_Selection!E33) -> 0 | I29: =IF(OR(B29="",D29="Oral",D29="Nasal"),"",IF(ISTEXT(E29),0,$K$5*1.1)) | J29: =IF(OR(B29="",C29="liquid",D29="Oral",D29="Nasal",ISTEXT(E29)),"",$K$6*Vaccine_Selection!K33/E29) | K29: =IF(B29="",0,(COUNT($I29:$I29)+COUNT($J29:$J29)/IF(ISTEXT($E29),1,$E29))*$K$7/100) -> 0 | L29: =Vaccine_Selection!L33 -> 0 | M29: =IF(Vaccine_Selection!M33="","",Vaccine_Selection!M33) | N29: =IF(Vaccine_Selection!N33="","",Vaccine_Selection!N33) | O29: =IF(Vaccine_Selection!O33="","",Vaccine_Selection!O33) | P29: =IF(Vaccine_Selection!P33="","",Vaccine_Selection!P33) | Q29: =IF(Vaccine_Selection!Q33="","",Vaccine_Selection!Q33) | S29: =IF(Vaccine_Selection!S33="","",Vaccine_Selection!S33) | T29: =IF(Vaccine_Selection!T33="","",Vaccine_Selection!T33) | U29: =IF(Vaccine_Selection!U33="","",Vaccine_Selection!U33)
B30: =IF(Vaccine_Selection!B34="","",Vaccine_Selection!B34) | C30: {=IF($B30="","",INDEX(Vaccine_database!$C$10:$D$278,MATCH($B30,Vaccines,0),2))} | D30: {=IF($B30="","",INDEX(Vaccine_database!$C$10:$E$278,MATCH($B30,Vaccines,0),3))} | E30: =Vaccine_Selection!C34 -> 0 | F30: =IF(Vaccine_Selection!D34="",Vaccine_Selection!F34,Vaccine_Selection!D34) -> 0 | G30: =IF(Vaccine_Selection!D34="",Vaccine_Selection!G34,Vaccine_Selection!E34) -> 0 | I30: =IF(OR(B30="",D30="Oral",D30="Nasal"),"",IF(ISTEXT(E30),0,$K$5*1.1)) | J30: =IF(OR(B30="",C30="liquid",D30="Oral",D30="Nasal",ISTEXT(E30)),"",$K$6*Vaccine_Selection!K34/E30) | K30: =IF(B30="",0,(COUNT($I30:$I30)+COUNT($J30:$J30)/IF(ISTEXT($E30),1,$E30))*$K$7/100) -> 0 | L30: =Vaccine_Selection!L34 -> 0 | M30: =IF(Vaccine_Selection!M34="","",Vaccine_Selection!M34) | N30: =IF(Vaccine_Selection!N34="","",Vaccine_Selection!N34) | O30: =IF(Vaccine_Selection!O34="","",Vaccine_Selection!O34) | P30: =IF(Vaccine_Selection!P34="","",Vaccine_Selection!P34) | Q30: =IF(Vaccine_Selection!Q34="","",Vaccine_Selection!Q34) | S30: =IF(Vaccine_Selection!S34="","",Vaccine_Selection!S34) | T30: =IF(Vaccine_Selection!T34="","",Vaccine_Selection!T34) | U30: =IF(Vaccine_Selection!U34="","",Vaccine_Selection!U34)
B31: =IF(Vaccine_Selection!B35="","",Vaccine_Selection!B35) | C31: {=IF($B31="","",INDEX(Vaccine_database!$C$10:$D$278,MATCH($B31,Vaccines,0),2))} | D31: {=IF($B31="","",INDEX(Vaccine_database!$C$10:$E$278,MATCH($B31,Vaccines,0),3))} | E31: =Vaccine_Selection!C35 -> 0 | F31: =IF(Vaccine_Selection!D35="",Vaccine_Selection!F35,Vaccine_Selection!D35) -> 0 | G31: =IF(Vaccine_Selection!D35="",Vaccine_Selection!G35,Vaccine_Selection!E35) -> 0 | I31: =IF(OR(B31="",D31="Oral",D31="Nasal"),"",IF(ISTEXT(E31),0,$K$5*1.1)) | J31: =IF(OR(B31="",C31="liquid",D31="Oral",D31="Nasal",ISTEXT(E31)),"",$K$6*Vaccine_Selection!K35/E31) | K31: =IF(B31="",0,(COUNT($I31:$I31)+COUNT($J31:$J31)/IF(ISTEXT($E31),1,$E31))*$K$7/100) -> 0 | L31: =Vaccine_Selection!L35 -> 0 | M31: =IF(Vaccine_Selection!M35="","",Vaccine_Selection!M35) | N31: =IF(Vaccine_Selection!N35="","",Vaccine_Selection!N35) | O31: =IF(Vaccine_Selection!O35="","",Vaccine_Selection!O35) | P31: =IF(Vaccine_Selection!P35="","",Vaccine_Selection!P35) | Q31: =IF(Vaccine_Selection!Q35="","",Vaccine_Selection!Q35) | S31: =IF(Vaccine_Selection!S35="","",Vaccine_Selection!S35) | T31: =IF(Vaccine_Selection!T35="","",Vaccine_Selection!T35) | U31: =IF(Vaccine_Selection!U35="","",Vaccine_Selection!U35)
B32: =IF(Vaccine_Selection!B36="","",Vaccine_Selection!B36) | C32: {=IF($B32="","",INDEX(Vaccine_database!$C$10:$D$278,MATCH($B32,Vaccines,0),2))} | D32: {=IF($B32="","",INDEX(Vaccine_database!$C$10:$E$278,MATCH($B32,Vaccines,0),3))} | E32: =Vaccine_Selection!C36 -> 0 | F32: =IF(Vaccine_Selection!D36="",Vaccine_Selection!F36,Vaccine_Selection!D36) -> 0 | G32: =IF(Vaccine_Selection!D36="",Vaccine_Selection!G36,Vaccine_Selection!E36) -> 0 | I32: =IF(OR(B32="",D32="Oral",D32="Nasal"),"",IF(ISTEXT(E32),0,$K$5*1.1)) | J32: =IF(OR(B32="",C32="liquid",D32="Oral",D32="Nasal",ISTEXT(E32)),"",$K$6*Vaccine_Selection!K36/E32) | K32: =IF(B32="",0,(COUNT($I32:$I32)+COUNT($J32:$J32)/IF(ISTEXT($E32),1,$E32))*$K$7/100) -> 0 | L32: =Vaccine_Selection!L36 -> 0 | M32: =IF(Vaccine_Selection!M36="","",Vaccine_Selection!M36) | N32: =IF(Vaccine_Selection!N36="","",Vaccine_Selection!N36) | O32: =IF(Vaccine_Selection!O36="","",Vaccine_Selection!O36) | P32: =IF(Vaccine_Selection!P36="","",Vaccine_Selection!P36) | Q32: =IF(Vaccine_Selection!Q36="","",Vaccine_Selection!Q36) | S32: =IF(Vaccine_Selection!S36="","",Vaccine_Selection!S36) | T32: =IF(Vaccine_Selection!T36="","",Vaccine_Selection!T36) | U32: =IF(Vaccine_Selection!U36="","",Vaccine_Selection!U36)
K34: =CONCATENATE(Translation!C384," ",Vaccine_Selection!$E$8,", cm3") -> Total net storage volume of diluents per Unit of Population , cm3 | M34: =IF(Vaccine_Selection!$E$8=target1,SUMPRODUCT($G$13:$G$32,Vaccine_Selection!$K$17:$K$36,M$13:M$32),SUMPRODUCT($G$13:$G$32,Vaccine_Selection!$K$17:$K$36,Vaccine_Selection!$L$17:$L$36,M$13:M$32)) -> 0.27377533 | N34: =IF(Vaccine_Selection!$E$8=target1,SUMPRODUCT($G$13:$G$32,Vaccine_Selection!$K$17:$K$36,N$13:N$32),SUMPRODUCT($G$13:$G$32,Vaccine_Selection!$K$17:$K$36,Vaccine_Selection!$L$17:$L$36,N$13:N$32)) -> 0.27377533 | O34: =IF(Vaccine_Selection!$E$8=target1,SUMPRODUCT($G$13:$G$32,Vaccine_Selection!$K$17:$K$36,O$13:O$32),SUMPRODUCT($G$13:$G$32,Vaccine_Selection!$K$17:$K$36,Vaccine_Selection!$L$17:$L$36,O$13:O$32)) -> 0.27377533 | P34: =IF(Vaccine_Selection!$E$8=target1,SUMPRODUCT($G$13:$G$32,Vaccine_Selection!$K$17:$K$36,P$13:P$32),SUMPRODUCT($G$13:$G$32,Vaccine_Selection!$K$17:$K$36,Vaccine_Selection!$L$17:$L$36,P$13:P$32)) -> 0 | Q34: =IF(Vaccine_Selection!$E$8=target1,SUMPRODUCT($G$13:$G$32,Vaccine_Selection!$K$17:$K$36,Q$13:Q$32),SUMPRODUCT($G$13:$G$32,Vaccine_Selection!$K$17:$K$36,Vaccine_Selection!$L$17:$L$36,Q$13:Q$32)) -> 0 | R34: =Translation!C389 -> Total net storage volume of diluents per recipient | S34: =SUMPRODUCT(Vaccine_Selection!$K$17:$K$36,$G$13:$G$32,S$13:S$32) -> 0 | T34: =SUMPRODUCT(Vaccine_Selection!$K$17:$K$36,$G$13:$G$32,T$13:T$32) -> 0 | U34: =SUMPRODUCT(Vaccine_Selection!$K$17:$K$36,$G$13:$G$32,U$13:U$32) -> 0
K35: =CONCATENATE(Translation!C385," ",Vaccine_Selection!$E$8,", cm3") -> Total net storage volume of syringes per Unit of Population , cm3 | M35: =IF(Vaccine_Selection!$E$8=target1,SUMPRODUCT($I$13:$I$32,M$13:M$32)+SUMPRODUCT($J$13:$J$32,M$13:M$32),SUMPRODUCT(Vaccine_Selection!$L$17:$L$36,$I$13:$I$32,M$13:M$32)+SUMPRODUCT(Vaccine_Selection!$L$17:$L$36,$J$13:$J$32,M$13:M$32)) -> 10.064292 | N35: =IF(Vaccine_Selection!$E$8=target1,SUMPRODUCT($I$13:$I$32,N$13:N$32)+SUMPRODUCT($J$13:$J$32,N$13:N$32),SUMPRODUCT(Vaccine_Selection!$L$17:$L$36,$I$13:$I$32,N$13:N$32)+SUMPRODUCT(Vaccine_Selection!$L$17:$L$36,$J$13:$J$32,N$13:N$32)) -> 10.064292 | O35: =IF(Vaccine_Selection!$E$8=target1,SUMPRODUCT($I$13:$I$32,O$13:O$32)+SUMPRODUCT($J$13:$J$32,O$13:O$32),SUMPRODUCT(Vaccine_Selection!$L$17:$L$36,$I$13:$I$32,O$13:O$32)+SUMPRODUCT(Vaccine_Selection!$L$17:$L$36,$J$13:$J$32,O$13:O$32)) -> 6.5112917 | P35: =IF(Vaccine_Selection!$E$8=target1,SUMPRODUCT($I$13:$I$32,P$13:P$32)+SUMPRODUCT($J$13:$J$32,P$13:P$32),SUMPRODUCT(Vaccine_Selection!$L$17:$L$36,$I$13:$I$32,P$13:P$32)+SUMPRODUCT(Vaccine_Selection!$L$17:$L$36,$J$13:$J$32,P$13:P$32)) -> 0 | Q35: =IF(Vaccine_Selection!$E$8=target1,SUMPRODUCT($I$13:$I$32,Q$13:Q$32)+SUMPRODUCT($J$13:$J$32,Q$13:Q$32),SUMPRODUCT(Vaccine_Selection!$L$17:$L$36,$I$13:$I$32,Q$13:Q$32)+SUMPRODUCT(Vaccine_Selection!$L$17:$L$36,$J$13:$J$32,Q$13:Q$32)) -> 0 | R35: =Translation!C390 -> Total net storage volume of syringes per recipient | S35: =SUMPRODUCT($I$13:$I$32,S$13:S$32)+SUMPRODUCT($J$13:$J$32,S$13:S$32) -> 0 | T35: =SUMPRODUCT($I$13:$I$32,T$13:T$32)+SUMPRODUCT($J$13:$J$32,T$13:T$32) -> 0 | U35: =SUMPRODUCT($I$13:$I$32,U$13:U$32)+SUMPRODUCT($J$13:$J$32,U$13:U$32) -> 0
K36: =CONCATENATE(Translation!C386," ",Vaccine_Selection!$E$8,", cm3") -> Total net storage volume of safety boxes per Unit of Population , cm3 | M36: =IF(Vaccine_Selection!$E$8=target1,SUMPRODUCT($K$13:$K$32,M$13:M$32),SUMPRODUCT(Vaccine_Selection!$L$17:$L$36,$K$13:$K$32,M$13:M$32)) -> 1.0987907 | N36: =IF(Vaccine_Selection!$E$8=target1,SUMPRODUCT($K$13:$K$32,N$13:N$32),SUMPRODUCT(Vaccine_Selection!$L$17:$L$36,$K$13:$K$32,N$13:N$32)) -> 1.0987907 | O36: =IF(Vaccine_Selection!$E$8=target1,SUMPRODUCT($K$13:$K$32,O$13:O$32),SUMPRODUCT(Vaccine_Selection!$L$17:$L$36,$K$13:$K$32,O$13:O$32)) -> 1.0987907 | P36: =IF(Vaccine_Selection!$E$8=target1,SUMPRODUCT($K$13:$K$32,P$13:P$32),SUMPRODUCT(Vaccine_Selection!$L$17:$L$36,$K$13:$K$32,P$13:P$32)) -> 0 | Q36: =IF(Vaccine_Selection!$E$8=target1,SUMPRODUCT($K$13:$K$32,Q$13:Q$32),SUMPRODUCT(Vaccine_Selection!$L$17:$L$36,$K$13:$K$32,Q$13:Q$32)) -> 0 | R36: =Translation!C391 -> Total net storage volume of safety boxes per target | S36: =SUMPRODUCT($K$13:$K$32,S$13:S$32) -> 0 | T36: =SUMPRODUCT($K$13:$K$32,T$13:T$32) -> 0 | U36: =SUMPRODUCT($K$13:$K$32,U$13:U$32) -> 0
K38: =CONCATENATE(Translation!C387," ",Vaccine_Selection!$E$8,", cm3") -> Total net storage volume of injection supplies per Unit of Population , cm3 | M38: =SUM(M34:M36) -> 11.436858 | N38: =SUM(N34:N36) -> 11.436858 | O38: =SUM(O34:O36) -> 7.8838576 | P38: =SUM(P34:P36) -> 0 | Q38: =SUM(Q34:Q36) -> 0 | R38: =Translation!C392 -> Total net storage volume of injection supplies per recipient | S38: =SUM(S34:S36) -> 0 | T38: =SUM(T34:T36) -> 0 | U38: =SUM(U34:U36) -> 0
K39: =Translation!C388 -> Increase of net storage volume compared to current schedule | N39: =IF(OR($M$38=0,N38=0),"",(N38-$M$38)/$M$38) -> 0 | O39: =IF(OR($M$38=0,O38=0),"",(O38-$M$38)/$M$38) -> -0.31066226 | P39: =IF(OR($M$38=0,P38=0),"",(P38-$M$38)/$M$38) | Q39: =IF(OR($M$38=0,Q38=0),"",(Q38-$M$38)/$M$38) | T39: =IF(OR($S$38=0,T38=0),"",(T38-$S$38)/$S$38) | U39: =IF(OR($S$38=0,U38=0),"",(U38-$S$38)/$S$38)

Sheet Weight_Inject
B2: =Translation!C393 -> Weight of safe injection equipment per recipient | O2: =Translation!C394 -> Optional data entry only | U2: =Translation!C109 -> Index
B5: =Translation!C395 -> OPTION: Over-ride weight of AD syringe, g/unit: | K5: =IF(I5<>"",I5,AVERAGE(3.75,3.75,5.67)) -> 4.39 | M5: gram
B6: =Translation!C396 -> OPTION: Over-ride weight of reconstitution syringe, g/unit: | K6: =IF(I6<>"",I6,6.625) -> 6.625 | M6: gram
B7: =Translation!C397 -> OPTION: Over-ride weight of safety box, g/unit: | K7: =IF(I7<>"",I7,AVERAGE(205,390,237,270,300,505,290,292,328,485,840)) -> 376.54545 | M7: gram
B10: =Volume_Inject!B10 -> Characteristics of vaccines selected for use | I10: =Translation!C398 -> Weight of supplies | M10: =Vaccine_Selection!M14 -> National immunization schedule | S10: =Vaccine_Selection!$S$14 -> Supplementary
F11: =Volume_Inject!F11 -> Volume data used | I11: =Translation!C399 -> per injection (g) | M11: =Vaccine_Selection!M15 -> (Routine vaccinations) | S11: =Vaccine_Selection!$S$15 -> activities (SIAs)
B12: =Volume_Inject!B12 -> Vaccine type | C12: =Volume_Inject!C12 -> Formulation | D12: =Volume_Inject!D12 -> Administration | E12: =Volume_Inject!E12 -> Presentation (doses/vial) | F12: =Volume_Inject!F12 -> Vaccine volume (cm³/dose) | G12: =Volume_Inject!G12 -> Diluent volume (cm³/dose) | I12: =Volume_Inject!I12 -> Injection syringe | J12: =Volume_Inject!J12 -> Mixing syringe | K12: =Volume_Inject!K12 -> Safety boxes | M12: =IF(Vaccine_Selection!M16="","",Vaccine_Selection!M16) -> Current schedule | N12: =IF(Vaccine_Selection!N16="","",Vaccine_Selection!N16) -> Current schedule with penta 1d | O12: =IF(Vaccine_Selection!O16="","",Vaccine_Selection!O16) -> Current schedule with penta CAD | P12: =IF(Vaccine_Selection!P16="","",Vaccine_Selection!P16) | Q12: =IF(Vaccine_Selection!Q16="","",Vaccine_Selection!Q16) | S12: =IF(Vaccine_Selection!S16="","",Vaccine_Selection!S16) -> H1N1 campaign | T12: =IF(Vaccine_Selection!T16="","",Vaccine_Selection!T16) | U12: =IF(Vaccine_Selection!U16="","",Vaccine_Selection!U16)
B13: =Volume_Inject!B13 -> BCG | C13: =Volume_Inject!C13 -> freeze-dried | D13: =Volume_Inject!D13 -> ID | E13: =Volume_Inject!E13 -> 20 | F13: =Volume_Inject!F13 -> 1.2102 | G13: =Volume_Inject!G13 -> 1.1256667 | I13: =IF(B13="","",IF(OR(D13="Oral",D13="Nasal"),"",IF(ISTEXT(E13),0,$K$5*1.1))) -> 4.829 | J13: =IF(OR(B13="",C13="liquid",D13="Oral",D13="Nasal",ISTEXT(E13)),"",$K$6*Vaccine_Selection!K17/E13) -> 0.6625 | K13: =IF(B13="",0,(COUNT($I13:$I13)+COUNT($J13:$J13)/IF(ISTEXT($E13),1,$E13))*$K$7/100) -> 3.9537273 | M13: =IF(Vaccine_Selection!M17="","",Vaccine_Selection!M17) -> 1 | N13: =IF(Vaccine_Selection!N17="","",Vaccine_Selection!N17) -> 1 | O13: =IF(Vaccine_Selection!O17="","",Vaccine_Selection!O17) -> 1 | P13: =IF(Vaccine_Selection!P17="","",Vaccine_Selection!P17) | Q13: =IF(Vaccine_Selection!Q17="","",Vaccine_Selection!Q17) | S13: =IF(Vaccine_Selection!S17="","",Vaccine_Selection!S17) | T13: =IF(Vaccine_Selection!T17="","",Vaccine_Selection!T17) | U13: =IF(Vaccine_Selection!U17="","",Vaccine_Selection!U17)
B14: =Volume_Inject!B14 -> OPV | C14: =Volume_Inject!C14 -> liquid | D14: =Volume_Inject!D14 -> Oral | E14: =Volume_Inject!E14 -> 10 | F14: =Volume_Inject!F14 -> 2 | G14: =Volume_Inject!G14 -> 0 | I14: =IF(B14="","",IF(OR(D14="Oral",D14="Nasal"),"",IF(ISTEXT(E14),0,$K$5*1.1))) | J14: =IF(OR(B14="",C14="liquid",D14="Oral",D14="Nasal",ISTEXT(E14)),"",$K$6*Vaccine_Selection!K18/E14) | K14: =IF(B14="",0,(COUNT($I14:$I14)+COUNT($J14:$J14)/IF(ISTEXT($E14),1,$E14))*$K$7/100) -> 0 | M14: =IF(Vaccine_Selection!M18="","",Vaccine_Selection!M18) -> 4 | N14: =IF(Vaccine_Selection!N18="","",Vaccine_Selection!N18) -> 4 | O14: =IF(Vaccine_Selection!O18="","",Vaccine_Selection!O18) -> 4 | P14: =IF(Vaccine_Selection!P18="","",Vaccine_Selection!P18) | Q14: =IF(Vaccine_Selection!Q18="","",Vaccine_Selection!Q18) | S14: =IF(Vaccine_Selection!S18="","",Vaccine_Selection!S18) | T14: =IF(Vaccine_Selection!T18="","",Vaccine_Selection!T18) | U14: =IF(Vaccine_Selection!U18="","",Vaccine_Selection!U18)
B15: =Volume_Inject!B15 -> DTP-HepB-Hib | C15: =Volume_Inject!C15 -> liquid | D15: =Volume_Inject!D15 -> IM | E15: =Volume_Inject!E15 -> 10 | F15: =Volume_Inject!F15 -> 2.75 | G15: =Volume_Inject!G15 -> 0 | I15: =IF(B15="","",IF(OR(D15="Oral",D15="Nasal"),"",IF(ISTEXT(E15),0,$K$5*1.1))) -> 4.829 | J15: =IF(OR(B15="",C15="liquid",D15="Oral",D15="Nasal",ISTEXT(E15)),"",$K$6*Vaccine_Selection!K19/E15) | K15: =IF(B15="",0,(COUNT($I15:$I15)+COUNT($J15:$J15)/IF(ISTEXT($E15),1,$E15))*$K$7/100) -> 3.7654545 | M15: =IF(Vaccine_Selection!M19="","",Vaccine_Selection!M19) -> 3 | N15: =IF(Vaccine_Selection!N19="","",Vaccine_Selection!N19) | O15: =IF(Vaccine_Selection!O19="","",Vaccine_Selection!O19) | P15: =IF(Vaccine_Selection!P19="","",Vaccine_Selection!P19) | Q15: =IF(Vaccine_Selection!Q19="","",Vaccine_Selection!Q19) | S15: =IF(Vaccine_Selection!S19="","",Vaccine_Selection!S19) | T15: =IF(Vaccine_Selection!T19="","",Vaccine_Selection!T19) | U15: =IF(Vaccine_Selection!U19="","",Vaccine_Selection!U19)
B16: =Volume_Inject!B16 -> DTP-HepB-Hib | C16: =Volume_Inject!C16 -> liquid | D16: =Volume_Inject!D16 -> IM | E16: =Volume_Inject!E16 -> 1 | F16: =Volume_Inject!F16 -> 16.66384 | G16: =Volume_Inject!G16 -> 0 | I16: =IF(B16="","",IF(OR(D16="Oral",D16="Nasal"),"",IF(ISTEXT(E16),0,$K$5*1.1))) -> 4.829 | J16: =IF(OR(B16="",C16="liquid",D16="Oral",D16="Nasal",ISTEXT(E16)),"",$K$6*Vaccine_Selection!K20/E16) | K16: =IF(B16="",0,(COUNT($I16:$I16)+COUNT($J16:$J16)/IF(ISTEXT($E16),1,$E16))*$K$7/100) -> 3.7654545 | M16: =IF(Vaccine_Selection!M20="","",Vaccine_Selection!M20) | N16: =IF(Vaccine_Selection!N20="","",Vaccine_Selection!N20) -> 3 | O16: =IF(Vaccine_Selection!O20="","",Vaccine_Selection!O20) | P16: =IF(Vaccine_Selection!P20="","",Vaccine_Selection!P20) | Q16: =IF(Vaccine_Selection!Q20="","",Vaccine_Selection!Q20) | S16: =IF(Vaccine_Selection!S20="","",Vaccine_Selection!S20) | T16: =IF(Vaccine_Selection!T20="","",Vaccine_Selection!T20) | U16: =IF(Vaccine_Selection!U20="","",Vaccine_Selection!U20)
B17: =Volume_Inject!B17 -> DTP-HepB-Hib | C17: =Volume_Inject!C17 -> liquid | D17: =Volume_Inject!D17 -> IM | E17: =Volume_Inject!E17 -> Uniject | F17: =Volume_Inject!F17 -> 12 | G17: =Volume_Inject!G17 -> 0 | I17: =IF(B17="","",IF(OR(D17="Oral",D17="Nasal"),"",IF(ISTEXT(E17),0,$K$5*1.1))) -> 0 | J17: =IF(OR(B17="",C17="liquid",D17="Oral",D17="Nasal",ISTEXT(E17)),"",$K$6*Vaccine_Selection!K21/E17) | K17: =IF(B17="",0,(COUNT($I17:$I17)+COUNT($J17:$J17)/IF(ISTEXT($E17),1,$E17))*$K$7/100) -> 3.7654545 | M17: =IF(Vaccine_Selection!M21="","",Vaccine_Selection!M21) | N17: =IF(Vaccine_Selection!N21="","",Vaccine_Selection!N21) | O17: =IF(Vaccine_Selection!O21="","",Vaccine_Selection!O21) -> 3 | P17: =IF(Vaccine_Selection!P21="","",Vaccine_Selection!P21) | Q17: =IF(Vaccine_Selection!Q21="","",Vaccine_Selection!Q21) | S17: =IF(Vaccine_Selection!S21="","",Vaccine_Selection!S21) | T17: =IF(Vaccine_Selection!T21="","",Vaccine_Selection!T21) | U17: =IF(Vaccine_Selection!U21="","",Vaccine_Selection!U21)
B18: =Volume_Inject!B18 -> Measles | C18: =Volume_Inject!C18 -> freeze-dried | D18: =Volume_Inject!D18 -> SC | E18: =Volume_Inject!E18 -> 10 | F18: =Volume_Inject!F18 -> 2.4002 | G18: =Volume_Inject!G18 -> 3.2 | I18: =IF(B18="","",IF(OR(D18="Oral",D18="Nasal"),"",IF(ISTEXT(E18),0,$K$5*1.1))) -> 4.829 | J18: =IF(OR(B18="",C18="liquid",D18="Oral",D18="Nasal",ISTEXT(E18)),"",$K$6*Vaccine_Selection!K22/E18) -> 1.1041667 | K18: =IF(B18="",0,(COUNT($I18:$I18)+COUNT($J18:$J18)/IF(ISTEXT($E18),1,$E18))*$K$7/100) -> 4.142 | M18: =IF(Vaccine_Selection!M22="","",Vaccine_Selection!M22) -> 1 | N18: =IF(Vaccine_Selection!N22="","",Vaccine_Selection!N22) -> 1 | O18: =IF(Vaccine_Selection!O22="","",Vaccine_Selection!O22) -> 1 | P18: =IF(Vaccine_Selection!P22="","",Vaccine_Selection!P22) | Q18: =IF(Vaccine_Selection!Q22="","",Vaccine_Selection!Q22) | S18: =IF(Vaccine_Selection!S22="","",Vaccine_Selection!S22) | T18: =IF(Vaccine_Selection!T22="","",Vaccine_Selection!T22) | U18: =IF(Vaccine_Selection!U22="","",Vaccine_Selection!U22)
B19: =Volume_Inject!B19 -> YF | C19: =Volume_Inject!C19 -> freeze-dried | D19: =Volume_Inject!D19 -> SC | E19: =Volume_Inject!E19 -> 5 | F19: =Volume_Inject!F19 -> 5.4025 | G19: =Volume_Inject!G19 -> 6.75 | I19: =IF(B19="","",IF(OR(D19="Oral",D19="Nasal"),"",IF(ISTEXT(E19),0,$K$5*1.1))) -> 4.829 | J19: =IF(OR(B19="",C19="liquid",D19="Oral",D19="Nasal",ISTEXT(E19)),"",$K$6*Vaccine_Selection!K23/E19) -> 1.4722222 | K19: =IF(B19="",0,(COUNT($I19:$I19)+COUNT($J19:$J19)/IF(ISTEXT($E19),1,$E19))*$K$7/100) -> 4.5185455 | M19: =IF(Vaccine_Selection!M23="","",Vaccine_Selection!M23) -> 1 | N19: =IF(Vaccine_Selection!N23="","",Vaccine_Selection!N23) -> 1 | O19: =IF(Vaccine_Selection!O23="","",Vaccine_Selection!O23) -> 1 | P19: =IF(Vaccine_Selection!P23="","",Vaccine_Selection!P23) | Q19: =IF(Vaccine_Selection!Q23="","",Vaccine_Selection!Q23) | S19: =IF(Vaccine_Selection!S23="","",Vaccine_Selection!S23) | T19: =IF(Vaccine_Selection!T23="","",Vaccine_Selection!T23) | U19: =IF(Vaccine_Selection!U23="","",Vaccine_Selection!U23)
B20: =Volume_Inject!B20 -> TT | C20: =Volume_Inject!C20 -> liquid | D20: =Volume_Inject!D20 -> IM | E20: =Volume_Inject!E20 -> 10 | F20: =Volume_Inject!F20 -> 3.1093333 | G20: =Volume_Inject!G20 -> 0 | I20: =IF(B20="","",IF(OR(D20="Oral",D20="Nasal"),"",IF(ISTEXT(E20),0,$K$5*1.1))) -> 4.829 | J20: =IF(OR(B20="",C20="liquid",D20="Oral",D20="Nasal",ISTEXT(E20)),"",$K$6*Vaccine_Selection!K24/E20) | K20: =IF(B20="",0,(COUNT($I20:$I20)+COUNT($J20:$J20)/IF(ISTEXT($E20),1,$E20))*$K$7/100) -> 3.7654545 | M20: =IF(Vaccine_Selection!M24="","",Vaccine_Selection!M24) -> 2 | N20: =IF(Vaccine_Selection!N24="","",Vaccine_Selection!N24) -> 2 | O20: =IF(Vaccine_Selection!O24="","",Vaccine_Selection!O24) -> 2 | P20: =IF(Vaccine_Selection!P24="","",Vaccine_Selection!P24) | Q20: =IF(Vaccine_Selection!Q24="","",Vaccine_Selection!Q24) | S20: =IF(Vaccine_Selection!S24="","",Vaccine_Selection!S24) | T20: =IF(Vaccine_Selection!T24="","",Vaccine_Selection!T24) | U20: =IF(Vaccine_Selection!U24="","",Vaccine_Selection!U24)
B21: =Volume_Inject!B21 -> PCV-13 | C21: =Volume_Inject!C21 -> liquid | D21: =Volume_Inject!D21 -> IM | E21: =Volume_Inject!E21 -> 1 | F21: =Volume_Inject!F21 -> 13.825247 | G21: =Volume_Inject!G21 -> 0 | I21: =IF(B21="","",IF(OR(D21="Oral",D21="Nasal"),"",IF(ISTEXT(E21),0,$K$5*1.1))) -> 4.829 | J21: =IF(OR(B21="",C21="liquid",D21="Oral",D21="Nasal",ISTEXT(E21)),"",$K$6*Vaccine_Selection!K25/E21) | K21: =IF(B21="",0,(COUNT($I21:$I21)+COUNT($J21:$J21)/IF(ISTEXT($E21),1,$E21))*$K$7/100) -> 3.7654545 | M21: =IF(Vaccine_Selection!M25="","",Vaccine_Selection!M25) | N21: =IF(Vaccine_Selection!N25="","",Vaccine_Selection!N25) | O21: =IF(Vaccine_Selection!O25="","",Vaccine_Selection!O25) | P21: =IF(Vaccine_Selection!P25="","",Vaccine_Selection!P25) | Q21: =IF(Vaccine_Selection!Q25="","",Vaccine_Selection!Q25) | S21: =IF(Vaccine_Selection!S25="","",Vaccine_Selection!S25) | T21: =IF(Vaccine_Selection!T25="","",Vaccine_Selection!T25) | U21: =IF(Vaccine_Selection!U25="","",Vaccine_Selection!U25)
B22: =Volume_Inject!B22 -> Rota_liq | C22: =Volume_Inject!C22 -> liquid | D22: =Volume_Inject!D22 -> Oral | E22: =Volume_Inject!E22 -> 1 | F22: =Volume_Inject!F22 -> 17.1 | G22: =Volume_Inject!G22 -> 0 | I22: =IF(B22="","",IF(OR(D22="Oral",D22="Nasal"),"",IF(ISTEXT(E22),0,$K$5*1.1))) | J22: =IF(OR(B22="",C22="liquid",D22="Oral",D22="Nasal",ISTEXT(E22)),"",$K$6*Vaccine_Selection!K26/E22) | K22: =IF(B22="",0,(COUNT($I22:$I22)+COUNT($J22:$J22)/IF(ISTEXT($E22),1,$E22))*$K$7/100) -> 0 | M22: =IF(Vaccine_Selection!M26="","",Vaccine_Selection!M26) | N22: =IF(Vaccine_Selection!N26="","",Vaccine_Selection!N26) | O22: =IF(Vaccine_Selection!O26="","",Vaccine_Selection!O26) | P22: =IF(Vaccine_Selection!P26="","",Vaccine_Selection!P26) | Q22: =IF(Vaccine_Selection!Q26="","",Vaccine_Selection!Q26) | S22: =IF(Vaccine_Selection!S26="","",Vaccine_Selection!S26) -> 1 | T22: =IF(Vaccine_Selection!T26="","",Vaccine_Selection!T26) | U22: =IF(Vaccine_Selection!U26="","",Vaccine_Selection!U26)
B23: =Volume_Inject!B23 | C23: =Volume_Inject!C23 | D23: =Volume_Inject!D23 | E23: =Volume_Inject!E23 -> 0 | F23: =Volume_Inject!F23 -> 0 | G23: =Volume_Inject!G23 -> 0 | I23: =IF(B23="","",IF(OR(D23="Oral",D23="Nasal"),"",IF(ISTEXT(E23),0,$K$5*1.1))) | J23: =IF(OR(B23="",C23="liquid",D23="Oral",D23="Nasal",ISTEXT(E23)),"",$K$6*Vaccine_Selection!K27/E23) | K23: =IF(B23="",0,(COUNT($I23:$I23)+COUNT($J23:$J23)/IF(ISTEXT($E23),1,$E23))*$K$7/100) -> 0 | M23: =IF(Vaccine_Selection!M27="","",Vaccine_Selection!M27) | N23: =IF(Vaccine_Selection!N27="","",Vaccine_Selection!N27) | O23: =IF(Vaccine_Selection!O27="","",Vaccine_Selection!O27) | P23: =IF(Vaccine_Selection!P27="","",Vaccine_Selection!P27) | Q23: =IF(Vaccine_Selection!Q27="","",Vaccine_Selection!Q27) | S23: =IF(Vaccine_Selection!S27="","",Vaccine_Selection!S27) | T23: =IF(Vaccine_Selection!T27="","",Vaccine_Selection!T27) | U23: =IF(Vaccine_Selection!U27="","",Vaccine_Selection!U27)
B24: =Volume_Inject!B24 | C24: =Volume_Inject!C24 | D24: =Volume_Inject!D24 | E24: =Volume_Inject!E24 -> 0 | F24: =Volume_Inject!F24 -> 0 | G24: =Volume_Inject!G24 -> 0 | I24: =IF(B24="","",IF(OR(D24="Oral",D24="Nasal"),"",IF(ISTEXT(E24),0,$K$5*1.1))) | J24: =IF(OR(B24="",C24="liquid",D24="Oral",D24="Nasal",ISTEXT(E24)),"",$K$6*Vaccine_Selection!K28/E24) | K24: =IF(B24="",0,(COUNT($I24:$I24)+COUNT($J24:$J24)/IF(ISTEXT($E24),1,$E24))*$K$7/100) -> 0 | M24: =IF(Vaccine_Selection!M28="","",Vaccine_Selection!M28) | N24: =IF(Vaccine_Selection!N28="","",Vaccine_Selection!N28) | O24: =IF(Vaccine_Selection!O28="","",Vaccine_Selection!O28) | P24: =IF(Vaccine_Selection!P28="","",Vaccine_Selection!P28) | Q24: =IF(Vaccine_Selection!Q28="","",Vaccine_Selection!Q28) | S24: =IF(Vaccine_Selection!S28="","",Vaccine_Selection!S28) | T24: =IF(Vaccine_Selection!T28="","",Vaccine_Selection!T28) | U24: =IF(Vaccine_Selection!U28="","",Vaccine_Selection!U28)
... B32: =Volume_Inject!B32 | C32: =Volume_Inject!C32 | D32: =Volume_Inject!D32 | E32: =Volume_Inject!E32 -> 0 | F32: =Volume_Inject!F32 -> 0 | G32: =Volume_Inject!G32 -> 0 | I32: =IF(B32="","",IF(OR(D32="Oral",D32="Nasal"),"",IF(ISTEXT(E32),0,$K$5*1.1))) | J32: =IF(OR(B32="",C32="liquid",D32="Oral",D32="Nasal",ISTEXT(E32)),"",$K$6*Vaccine_Selection!K36/E32) | K32: =IF(B32="",0,(COUNT($I32:$I32)+COUNT($J32:$J32)/IF(ISTEXT($E32),1,$E32))*$K$7/100) -> 0 | M32: =IF(Vaccine_Selection!M36="","",Vaccine_Selection!M36) | N32: =IF(Vaccine_Selection!N36="","",Vaccine_Selection!N36) | O32: =IF(Vaccine_Selection!O36="","",Vaccine_Selection!O36) | P32: =IF(Vaccine_Selection!P36="","",Vaccine_Selection!P36) | Q32: =IF(Vaccine_Selection!Q36="","",Vaccine_Selection!Q36) | S32: =IF(Vaccine_Selection!S36="","",Vaccine_Selection!S36) | T32: =IF(Vaccine_Selection!T36="","",Vaccine_Selection!T36) | U32: =IF(Vaccine_Selection!U36="","",Vaccine_Selection!U36)
K34: =CONCATENATE(Translation!C400," ",Vaccine_Selection!$E$8,", g") -> Total weight of dilution syringes per Unit of Population , g | M34: =IF(Vaccine_Selection!$E$8=target1,SUMPRODUCT($J$13:$J$32,M$13:M$32),SUMPRODUCT(Vaccine_Selection!$L$17:$L$36,$J$13:$J$32,M$13:M$32)) -> 0.0589625 | N34: =IF(Vaccine_Selection!$E$8=target1,SUMPRODUCT($J$13:$J$32,N$13:N$32),SUMPRODUCT(Vaccine_Selection!$L$17:$L$36,$J$13:$J$32,N$13:N$32)) -> 0.0589625 | O34: =IF(Vaccine_Selection!$E$8=target1,SUMPRODUCT($J$13:$J$32,O$13:O$32),SUMPRODUCT(Vaccine_Selection!$L$17:$L$36,$J$13:$J$32,O$13:O$32)) -> 0.0589625 | P34: =IF(Vaccine_Selection!$E$8=target1,SUMPRODUCT($J$13:$J$32,P$13:P$32),SUMPRODUCT(Vaccine_Selection!$L$17:$L$36,$J$13:$J$32,P$13:P$32)) -> 0 | Q34: =IF(Vaccine_Selection!$E$8=target1,SUMPRODUCT($J$13:$J$32,Q$13:Q$32),SUMPRODUCT(Vaccine_Selection!$L$17:$L$36,$J$13:$J$32,Q$13:Q$32)) -> 0 | R34: =Translation!C405 -> Total weight of dilution syringes per recipient | S34: =SUMPRODUCT($J$13:$J$32,S$13:S$32) -> 0 | T34: =SUMPRODUCT($J$13:$J$32,T$13:T$32) -> 0 | U34: =SUMPRODUCT($J$13:$J$32,U$13:U$32) -> 0
K35: =CONCATENATE(Translation!C401," ",Vaccine_Selection!$E$8,", g") -> Total weight of injection syringes per Unit of Population , g | M35: =IF(Vaccine_Selection!$E$8=target1,SUMPRODUCT($I$13:$I$32,M$13:M$32),SUMPRODUCT(Vaccine_Selection!$L$17:$L$36,$I$13:$I$32,M$13:M$32)) -> 0.734008 | N35: =IF(Vaccine_Selection!$E$8=target1,SUMPRODUCT($I$13:$I$32,N$13:N$32),SUMPRODUCT(Vaccine_Selection!$L$17:$L$36,$I$13:$I$32,N$13:N$32)) -> 0.734008 | O35: =IF(Vaccine_Selection!$E$8=target1,SUMPRODUCT($I$13:$I$32,O$13:O$32),SUMPRODUCT(Vaccine_Selection!$L$17:$L$36,$I$13:$I$32,O$13:O$32)) -> 0.458755 | P35: =IF(Vaccine_Selection!$E$8=target1,SUMPRODUCT($I$13:$I$32,P$13:P$32),SUMPRODUCT(Vaccine_Selection!$L$17:$L$36,$I$13:$I$32,P$13:P$32)) -> 0 | Q35: =IF(Vaccine_Selection!$E$8=target1,SUMPRODUCT($I$13:$I$32,Q$13:Q$32),SUMPRODUCT(Vaccine_Selection!$L$17:$L$36,$I$13:$I$32,Q$13:Q$32)) -> 0 | R35: =Translation!C406 -> Total weight injection syringes per recipient | S35: =SUMPRODUCT($I$13:$I$32,S$13:S$32) -> 0 | T35: =SUMPRODUCT($I$13:$I$32,T$13:T$32) -> 0 | U35: =SUMPRODUCT($I$13:$I$32,U$13:U$32) -> 0
K36: =CONCATENATE(Translation!C402," ",Vaccine_Selection!$E$8,", g") -> Total weigth of safety box per Unit of Population , g | M36: =IF(Vaccine_Selection!$E$8=target1,SUMPRODUCT($K$13:$K$32,M$13:M$32),SUMPRODUCT(Vaccine_Selection!$L$17:$L$36,$K$13:$K$32,M$13:M$32)) -> 0.59625973 | N36: =IF(Vaccine_Selection!$E$8=target1,SUMPRODUCT($K$13:$K$32,N$13:N$32),SUMPRODUCT(Vaccine_Selection!$L$17:$L$36,$K$13:$K$32,N$13:N$32)) -> 0.59625973 | O36: =IF(Vaccine_Selection!$E$8=target1,SUMPRODUCT($K$13:$K$32,O$13:O$32),SUMPRODUCT(Vaccine_Selection!$L$17:$L$36,$K$13:$K$32,O$13:O$32)) -> 0.59625973 | P36: =IF(Vaccine_Selection!$E$8=target1,SUMPRODUCT($K$13:$K$32,P$13:P$32),SUMPRODUCT(Vaccine_Selection!$L$17:$L$36,$K$13:$K$32,P$13:P$32)) -> 0 | Q36: =IF(Vaccine_Selection!$E$8=target1,SUMPRODUCT($K$13:$K$32,Q$13:Q$32),SUMPRODUCT(Vaccine_Selection!$L$17:$L$36,$K$13:$K$32,Q$13:Q$32)) -> 0 | R36: =Translation!C407 -> Total weight of safety boxes per recipient | S36: =SUMPRODUCT($K$13:$K$32,S$13:S$32) -> 0 | T36: =SUMPRODUCT($K$13:$K$32,T$13:T$32) -> 0 | U36: =SUMPRODUCT($K$13:$K$32,U$13:U$32) -> 0
K38: =CONCATENATE(Translation!C403," ",Vaccine_Selection!$E$8) -> Total weight of injection supplies per Unit of Population | M38: =SUM(M34:M36) -> 1.3892302 | N38: =SUM(N34:N36) -> 1.3892302 | O38: =SUM(O34:O36) -> 1.1139772 | P38: =SUM(P34:P36) -> 0 | Q38: =SUM(Q34:Q36) -> 0 | R38: =Translation!C408 -> Total weight of injection supplies per recipient | S38: =SUM(S34:S36) -> 0 | T38: =SUM(T34:T36) -> 0 | U38: =SUM(U34:U36) -> 0
K39: =Translation!C404 -> Increase of total weight compared to current schedule | N39: =IF(OR($M$38=0,N38=0),"",(N38-$M$38)/$M$38) -> 0 | O39: =IF(OR($M$38=0,O38=0),"",(O38-$M$38)/$M$38) -> -0.19813347 | P39: =IF(OR($M$38=0,P38=0),"",(P38-$M$38)/$M$38) | Q39: =IF(OR($M$38=0,Q38=0),"",(Q38-$M$38)/$M$38) | T39: =IF(OR($S$38=0,T38=0),"",(T38-$S$38)/$S$38) | U39: =IF(OR($S$38=0,U38=0),"",(U38-$S$38)/$S$38)

Sheet Qty_Waste
B2: =Translation!C192 -> Estimate of the amount of injection waste generated per recipient | U2: =Translation!C109 -> Index
B7: =Volume_Inject!B10 -> Characteristics of vaccines selected for use | I7: =Translation!C193 -> Amount of waste | M7: =Volume_Inject!M10 -> National immunization schedule | S7: =Vaccine_Selection!$S$14 -> Supplementary
F8: =Volume_Inject!F11 -> Volume data used | I8: =Translation!C194 -> per recipient, units | M8: =Volume_Inject!M11 -> (Routine vaccinations) | S8: =Vaccine_Selection!$S$15 -> activities (SIAs)
B9: =Volume_Inject!B12 -> Vaccine type | C9: =Volume_Inject!C12 -> Formulation | D9: =Volume_Inject!D12 -> Administration | E9: =Volume_Inject!E12 -> Presentation (doses/vial) | F9: =Volume_Inject!F12 -> Vaccine volume (cm³/dose) | G9: =Volume_Inject!G12 -> Diluent volume (cm³/dose) | I9: No. of empty vials | J9: =Volume_Inject!I12 -> Injection syringe | K9: =Volume_Inject!J12 -> Mixing syringe | M9: =IF(Vaccine_Selection!M16="","",Vaccine_Selection!M16) -> Current schedule | N9: =IF(Vaccine_Selection!N16="","",Vaccine_Selection!N16) -> Current schedule with penta 1d | O9: =IF(Vaccine_Selection!O16="","",Vaccine_Selection!O16) -> Current schedule with penta CAD | P9: =IF(Vaccine_Selection!P16="","",Vaccine_Selection!P16) | Q9: =IF(Vaccine_Selection!Q16="","",Vaccine_Selection!Q16) | S9: =IF(Vaccine_Selection!S16="","",Vaccine_Selection!S16) -> H1N1 campaign | T9: =IF(Vaccine_Selection!T16="","",Vaccine_Selection!T16) | U9: =IF(Vaccine_Selection!U16="","",Vaccine_Selection!U16)
B10: =Volume_Inject!B13 -> BCG | C10: =Volume_Inject!C13 -> freeze-dried | D10: =Volume_Inject!D13 -> ID | E10: =Volume_Inject!E13 -> 20 | F10: =Volume_Inject!F13 -> 1.2102 | G10: =Volume_Inject!G13 -> 1.1256667 | I10: =IF(B10="","",IF(C10="liquid",IF(ISTEXT(E10),IF(OR(D10="Oral",D10="Nasal"),Vaccine_Selection!K17,""),Vaccine_Selection!K17/E10),IF(ISTEXT(E10),1,2/E10)*Vaccine_Selection!K17)) -> 0.2 | J10: =IF(OR(B10="",D10="Oral",D10="Nasal"),"",1.1) -> 1.1 | K10: =IF(OR(B10="",C10="liquid",D10="Oral",D10="Nasal",ISTEXT(E10)),"",(1/E10)*Vaccine_Selection!K17) -> 0.1 | M10: =IF(Vaccine_Selection!M17="","",Vaccine_Selection!M17) -> 1 | N10: =IF(Vaccine_Selection!N17="","",Vaccine_Selection!N17) -> 1 | O10: =IF(Vaccine_Selection!O17="","",Vaccine_Selection!O17) -> 1 | P10: =IF(Vaccine_Selection!P17="","",Vaccine_Selection!P17) | Q10: =IF(Vaccine_Selection!Q17="","",Vaccine_Selection!Q17) | S10: =IF(Vaccine_Selection!S17="","",Vaccine_Selection!S17) | T10: =IF(Vaccine_Selection!T17="","",Vaccine_Selection!T17) | U10: =IF(Vaccine_Selection!U17="","",Vaccine_Selection!U17)
B11: =Volume_Inject!B14 -> OPV | C11: =Volume_Inject!C14 -> liquid | D11: =Volume_Inject!D14 -> Oral | E11: =Volume_Inject!E14 -> 10 | F11: =Volume_Inject!F14 -> 2 | G11: =Volume_Inject!G14 -> 0 | I11: =IF(B11="","",IF(C11="liquid",IF(ISTEXT(E11),IF(OR(D11="Oral",D11="Nasal"),Vaccine_Selection!K18,""),Vaccine_Selection!K18/E11),IF(ISTEXT(E11),1,2/E11)*Vaccine_Selection!K18)) -> 0.13333333 | J11: =IF(OR(B11="",D11="Oral",D11="Nasal"),"",1.1) | K11: =IF(OR(B11="",C11="liquid",D11="Oral",D11="Nasal",ISTEXT(E11)),"",(1/E11)*Vaccine_Selection!K18) | M11: =IF(Vaccine_Selection!M18="","",Vaccine_Selection!M18) -> 4 | N11: =IF(Vaccine_Selection!N18="","",Vaccine_Selection!N18) -> 4 | O11: =IF(Vaccine_Selection!O18="","",Vaccine_Selection!O18) -> 4 | P11: =IF(Vaccine_Selection!P18="","",Vaccine_Selection!P18) | Q11: =IF(Vaccine_Selection!Q18="","",Vaccine_Selection!Q18) | S11: =IF(Vaccine_Selection!S18="","",Vaccine_Selection!S18) | T11: =IF(Vaccine_Selection!T18="","",Vaccine_Selection!T18) | U11: =IF(Vaccine_Selection!U18="","",Vaccine_Selection!U18)
B12: =Volume_Inject!B15 -> DTP-HepB-Hib | C12: =Volume_Inject!C15 -> liquid | D12: =Volume_Inject!D15 -> IM | E12: =Volume_Inject!E15 -> 10 | F12: =Volume_Inject!F15 -> 2.75 | G12: =Volume_Inject!G15 -> 0 | I12: =IF(B12="","",IF(C12="liquid",IF(ISTEXT(E12),IF(OR(D12="Oral",D12="Nasal"),Vaccine_Selection!K19,""),Vaccine_Selection!K19/E12),IF(ISTEXT(E12),1,2/E12)*Vaccine_Selection!K19)) -> 0.13333333 | J12: =IF(OR(B12="",D12="Oral",D12="Nasal"),"",1.1) -> 1.1 | K12: =IF(OR(B12="",C12="liquid",D12="Oral",D12="Nasal",ISTEXT(E12)),"",(1/E12)*Vaccine_Selection!K19) | M12: =IF(Vaccine_Selection!M19="","",Vaccine_Selection!M19) -> 3 | N12: =IF(Vaccine_Selection!N19="","",Vaccine_Selection!N19) | O12: =IF(Vaccine_Selection!O19="","",Vaccine_Selection!O19) | P12: =IF(Vaccine_Selection!P19="","",Vaccine_Selection!P19) | Q12: =IF(Vaccine_Selection!Q19="","",Vaccine_Selection!Q19) | S12: =IF(Vaccine_Selection!S19="","",Vaccine_Selection!S19) | T12: =IF(Vaccine_Selection!T19="","",Vaccine_Selection!T19) | U12: =IF(Vaccine_Selection!U19="","",Vaccine_Selection!U19)
B13: =Volume_Inject!B16 -> DTP-HepB-Hib | C13: =Volume_Inject!C16 -> liquid | D13: =Volume_Inject!D16 -> IM | E13: =Volume_Inject!E16 -> 1 | F13: =Volume_Inject!F16 -> 16.66384 | G13: =Volume_Inject!G16 -> 0 | I13: =IF(B13="","",IF(C13="liquid",IF(ISTEXT(E13),IF(OR(D13="Oral",D13="Nasal"),Vaccine_Selection!K20,""),Vaccine_Selection!K20/E13),IF(ISTEXT(E13),1,2/E13)*Vaccine_Selection!K20)) -> 1.0526316 | J13: =IF(OR(B13="",D13="Oral",D13="Nasal"),"",1.1) -> 1.1 | K13: =IF(OR(B13="",C13="liquid",D13="Oral",D13="Nasal",ISTEXT(E13)),"",(1/E13)*Vaccine_Selection!K20) | M13: =IF(Vaccine_Selection!M20="","",Vaccine_Selection!M20) | N13: =IF(Vaccine_Selection!N20="","",Vaccine_Selection!N20) -> 3 | O13: =IF(Vaccine_Selection!O20="","",Vaccine_Selection!O20) | P13: =IF(Vaccine_Selection!P20="","",Vaccine_Selection!P20) | Q13: =IF(Vaccine_Selection!Q20="","",Vaccine_Selection!Q20) | S13: =IF(Vaccine_Selection!S20="","",Vaccine_Selection!S20) | T13: =IF(Vaccine_Selection!T20="","",Vaccine_Selection!T20) | U13: =IF(Vaccine_Selection!U20="","",Vaccine_Selection!U20)
B14: =Volume_Inject!B17 -> DTP-HepB-Hib | C14: =Volume_Inject!C17 -> liquid | D14: =Volume_Inject!D17 -> IM | E14: =Volume_Inject!E17 -> Uniject | F14: =Volume_Inject!F17 -> 12 | G14: =Volume_Inject!G17 -> 0 | I14: =IF(B14="","",IF(C14="liquid",IF(ISTEXT(E14),IF(OR(D14="Oral",D14="Nasal"),Vaccine_Selection!K21,""),Vaccine_Selection!K21/E14),IF(ISTEXT(E14),1,2/E14)*Vaccine_Selection!K21)) | J14: =IF(OR(B14="",D14="Oral",D14="Nasal"),"",1.1) -> 1.1 | K14: =IF(OR(B14="",C14="liquid",D14="Oral",D14="Nasal",ISTEXT(E14)),"",(1/E14)*Vaccine_Selection!K21) | M14: =IF(Vaccine_Selection!M21="","",Vaccine_Selection!M21) | N14: =IF(Vaccine_Selection!N21="","",Vaccine_Selection!N21) | O14: =IF(Vaccine_Selection!O21="","",Vaccine_Selection!O21) -> 3 | P14: =IF(Vaccine_Selection!P21="","",Vaccine_Selection!P21) | Q14: =IF(Vaccine_Selection!Q21="","",Vaccine_Selection!Q21) | S14: =IF(Vaccine_Selection!S21="","",Vaccine_Selection!S21) | T14: =IF(Vaccine_Selection!T21="","",Vaccine_Selection!T21) | U14: =IF(Vaccine_Selection!U21="","",Vaccine_Selection!U21)
B15: =Volume_Inject!B18 -> Measles | C15: =Volume_Inject!C18 -> freeze-dried | D15: =Volume_Inject!D18 -> SC | E15: =Volume_Inject!E18 -> 10 | F15: =Volume_Inject!F18 -> 2.4002 | G15: =Volume_Inject!G18 -> 3.2 | I15: =IF(B15="","",IF(C15="liquid",IF(ISTEXT(E15),IF(OR(D15="Oral",D15="Nasal"),Vaccine_Selection!K22,""),Vaccine_Selection!K22/E15),IF(ISTEXT(E15),1,2/E15)*Vaccine_Selection!K22)) -> 0.33333333 | J15: =IF(OR(B15="",D15="Oral",D15="Nasal"),"",1.1) -> 1.1 | K15: =IF(OR(B15="",C15="liquid",D15="Oral",D15="Nasal",ISTEXT(E15)),"",(1/E15)*Vaccine_Selection!K22) -> 0.16666667 | M15: =IF(Vaccine_Selection!M22="","",Vaccine_Selection!M22) -> 1 | N15: =IF(Vaccine_Selection!N22="","",Vaccine_Selection!N22) -> 1 | O15: =IF(Vaccine_Selection!O22="","",Vaccine_Selection!O22) -> 1 | P15: =IF(Vaccine_Selection!P22="","",Vaccine_Selection!P22) | Q15: =IF(Vaccine_Selection!Q22="","",Vaccine_Selection!Q22) | S15: =IF(Vaccine_Selection!S22="","",Vaccine_Selection!S22) | T15: =IF(Vaccine_Selection!T22="","",Vaccine_Selection!T22) | U15: =IF(Vaccine_Selection!U22="","",Vaccine_Selection!U22)
B16: =Volume_Inject!B19 -> YF | C16: =Volume_Inject!C19 -> freeze-dried | D16: =Volume_Inject!D19 -> SC | E16: =Volume_Inject!E19 -> 5 | F16: =Volume_Inject!F19 -> 5.4025 | G16: =Volume_Inject!G19 -> 6.75 | I16: =IF(B16="","",IF(C16="liquid",IF(ISTEXT(E16),IF(OR(D16="Oral",D16="Nasal"),Vaccine_Selection!K23,""),Vaccine_Selection!K23/E16),IF(ISTEXT(E16),1,2/E16)*Vaccine_Selection!K23)) -> 0.44444444 | J16: =IF(OR(B16="",D16="Oral",D16="Nasal"),"",1.1) -> 1.1 | K16: =IF(OR(B16="",C16="liquid",D16="Oral",D16="Nasal",ISTEXT(E16)),"",(1/E16)*Vaccine_Selection!K23) -> 0.22222222 | M16: =IF(Vaccine_Selection!M23="","",Vaccine_Selection!M23) -> 1 | N16: =IF(Vaccine_Selection!N23="","",Vaccine_Selection!N23) -> 1 | O16: =IF(Vaccine_Selection!O23="","",Vaccine_Selection!O23) -> 1 | P16: =IF(Vaccine_Selection!P23="","",Vaccine_Selection!P23) | Q16: =IF(Vaccine_Selection!Q23="","",Vaccine_Selection!Q23) | S16: =IF(Vaccine_Selection!S23="","",Vaccine_Selection!S23) | T16: =IF(Vaccine_Selection!T23="","",Vaccine_Selection!T23) | U16: =IF(Vaccine_Selection!U23="","",Vaccine_Selection!U23)
B17: =Volume_Inject!B20 -> TT | C17: =Volume_Inject!C20 -> liquid | D17: =Volume_Inject!D20 -> IM | E17: =Volume_Inject!E20 -> 10 | F17: =Volume_Inject!F20 -> 3.1093333 | G17: =Volume_Inject!G20 -> 0 | I17: =IF(B17="","",IF(C17="liquid",IF(ISTEXT(E17),IF(OR(D17="Oral",D17="Nasal"),Vaccine_Selection!K24,""),Vaccine_Selection!K24/E17),IF(ISTEXT(E17),1,2/E17)*Vaccine_Selection!K24)) -> 0.13333333 | J17: =IF(OR(B17="",D17="Oral",D17="Nasal"),"",1.1) -> 1.1 | K17: =IF(OR(B17="",C17="liquid",D17="Oral",D17="Nasal",ISTEXT(E17)),"",(1/E17)*Vaccine_Selection!K24) | M17: =IF(Vaccine_Selection!M24="","",Vaccine_Selection!M24) -> 2 | N17: =IF(Vaccine_Selection!N24="","",Vaccine_Selection!N24) -> 2 | O17: =IF(Vaccine_Selection!O24="","",Vaccine_Selection!O24) -> 2 | P17: =IF(Vaccine_Selection!P24="","",Vaccine_Selection!P24) | Q17: =IF(Vaccine_Selection!Q24="","",Vaccine_Selection!Q24) | S17: =IF(Vaccine_Selection!S24="","",Vaccine_Selection!S24) | T17: =IF(Vaccine_Selection!T24="","",Vaccine_Selection!T24) | U17: =IF(Vaccine_Selection!U24="","",Vaccine_Selection!U24)
B18: =Volume_Inject!B21 -> PCV-13 | C18: =Volume_Inject!C21 -> liquid | D18: =Volume_Inject!D21 -> IM | E18: =Volume_Inject!E21 -> 1 | F18: =Volume_Inject!F21 -> 13.825247 | G18: =Volume_Inject!G21 -> 0 | I18: =IF(B18="","",IF(C18="liquid",IF(ISTEXT(E18),IF(OR(D18="Oral",D18="Nasal"),Vaccine_Selection!K25,""),Vaccine_Selection!K25/E18),IF(ISTEXT(E18),1,2/E18)*Vaccine_Selection!K25)) -> 1.0526316 | J18: =IF(OR(B18="",D18="Oral",D18="Nasal"),"",1.1) -> 1.1 | K18: =IF(OR(B18="",C18="liquid",D18="Oral",D18="Nasal",ISTEXT(E18)),"",(1/E18)*Vaccine_Selection!K25) | M18: =IF(Vaccine_Selection!M25="","",Vaccine_Selection!M25) | N18: =IF(Vaccine_Selection!N25="","",Vaccine_Selection!N25) | O18: =IF(Vaccine_Selection!O25="","",Vaccine_Selection!O25) | P18: =IF(Vaccine_Selection!P25="","",Vaccine_Selection!P25) | Q18: =IF(Vaccine_Selection!Q25="","",Vaccine_Selection!Q25) | S18: =IF(Vaccine_Selection!S25="","",Vaccine_Selection!S25) | T18: =IF(Vaccine_Selection!T25="","",Vaccine_Selection!T25) | U18: =IF(Vaccine_Selection!U25="","",Vaccine_Selection!U25)
B19: =Volume_Inject!B22 -> Rota_liq | C19: =Volume_Inject!C22 -> liquid | D19: =Volume_Inject!D22 -> Oral | E19: =Volume_Inject!E22 -> 1 | F19: =Volume_Inject!F22 -> 17.1 | G19: =Volume_Inject!G22 -> 0 | I19: =IF(B19="","",IF(C19="liquid",IF(ISTEXT(E19),IF(OR(D19="Oral",D19="Nasal"),Vaccine_Selection!K26,""),Vaccine_Selection!K26/E19),IF(ISTEXT(E19),1,2/E19)*Vaccine_Selection!K26)) -> 1.0526316 | J19: =IF(OR(B19="",D19="Oral",D19="Nasal"),"",1.1) | K19: =IF(OR(B19="",C19="liquid",D19="Oral",D19="Nasal",ISTEXT(E19)),"",(1/E19)*Vaccine_Selection!K26) | M19: =IF(Vaccine_Selection!M26="","",Vaccine_Selection!M26) | N19: =IF(Vaccine_Selection!N26="","",Vaccine_Selection!N26) | O19: =IF(Vaccine_Selection!O26="","",Vaccine_Selection!O26) | P19: =IF(Vaccine_Selection!P26="","",Vaccine_Selection!P26) | Q19: =IF(Vaccine_Selection!Q26="","",Vaccine_Selection!Q26) | S19: =IF(Vaccine_Selection!S26="","",Vaccine_Selection!S26) -> 1 | T19: =IF(Vaccine_Selection!T26="","",Vaccine_Selection!T26) | U19: =IF(Vaccine_Selection!U26="","",Vaccine_Selection!U26)
B20: =Volume_Inject!B23 | C20: =Volume_Inject!C23 | D20: =Volume_Inject!D23 | E20: =Volume_Inject!E23 -> 0 | F20: =Volume_Inject!F23 -> 0 | G20: =Volume_Inject!G23 -> 0 | I20: =IF(B20="","",IF(C20="liquid",IF(ISTEXT(E20),IF(OR(D20="Oral",D20="Nasal"),Vaccine_Selection!K27,""),Vaccine_Selection!K27/E20),IF(ISTEXT(E20),1,2/E20)*Vaccine_Selection!K27)) | J20: =IF(OR(B20="",D20="Oral",D20="Nasal"),"",1.1) | K20: =IF(OR(B20="",C20="liquid",D20="Oral",D20="Nasal",ISTEXT(E20)),"",(1/E20)*Vaccine_Selection!K27) | M20: =IF(Vaccine_Selection!M27="","",Vaccine_Selection!M27) | N20: =IF(Vaccine_Selection!N27="","",Vaccine_Selection!N27) | O20: =IF(Vaccine_Selection!O27="","",Vaccine_Selection!O27) | P20: =IF(Vaccine_Selection!P27="","",Vaccine_Selection!P27) | Q20: =IF(Vaccine_Selection!Q27="","",Vaccine_Selection!Q27) | S20: =IF(Vaccine_Selection!S27="","",Vaccine_Selection!S27) | T20: =IF(Vaccine_Selection!T27="","",Vaccine_Selection!T27) | U20: =IF(Vaccine_Selection!U27="","",Vaccine_Selection!U27)
B21: =Volume_Inject!B24 | C21: =Volume_Inject!C24 | D21: =Volume_Inject!D24 | E21: =Volume_Inject!E24 -> 0 | F21: =Volume_Inject!F24 -> 0 | G21: =Volume_Inject!G24 -> 0 | I21: =IF(B21="","",IF(C21="liquid",IF(ISTEXT(E21),IF(OR(D21="Oral",D21="Nasal"),Vaccine_Selection!K28,""),Vaccine_Selection!K28/E21),IF(ISTEXT(E21),1,2/E21)*Vaccine_Selection!K28)) | J21: =IF(OR(B21="",D21="Oral",D21="Nasal"),"",1.1) | K21: =IF(OR(B21="",C21="liquid",D21="Oral",D21="Nasal",ISTEXT(E21)),"",(1/E21)*Vaccine_Selection!K28) | M21: =IF(Vaccine_Selection!M28="","",Vaccine_Selection!M28) | N21: =IF(Vaccine_Selection!N28="","",Vaccine_Selection!N28) | O21: =IF(Vaccine_Selection!O28="","",Vaccine_Selection!O28) | P21: =IF(Vaccine_Selection!P28="","",Vaccine_Selection!P28) | Q21: =IF(Vaccine_Selection!Q28="","",Vaccine_Selection!Q28) | S21: =IF(Vaccine_Selection!S28="","",Vaccine_Selection!S28) | T21: =IF(Vaccine_Selection!T28="","",Vaccine_Selection!T28) | U21: =IF(Vaccine_Selection!U28="","",Vaccine_Selection!U28)
... B29: =Volume_Inject!B32 | C29: =Volume_Inject!C32 | D29: =Volume_Inject!D32 | E29: =Volume_Inject!E32 -> 0 | F29: =Volume_Inject!F32 -> 0 | G29: =Volume_Inject!G32 -> 0 | I29: =IF(B29="","",IF(C29="liquid",IF(ISTEXT(E29),IF(OR(D29="Oral",D29="Nasal"),Vaccine_Selection!K36,""),Vaccine_Selection!K36/E29),IF(ISTEXT(E29),1,2/E29)*Vaccine_Selection!K36)) | J29: =IF(OR(B29="",D29="Oral",D29="Nasal"),"",1.1) | K29: =IF(OR(B29="",C29="liquid",D29="Oral",D29="Nasal",ISTEXT(E29)),"",(1/E29)*Vaccine_Selection!K36) | M29: =IF(Vaccine_Selection!M36="","",Vaccine_Selection!M36) | N29: =IF(Vaccine_Selection!N36="","",Vaccine_Selection!N36) | O29: =IF(Vaccine_Selection!O36="","",Vaccine_Selection!O36) | P29: =IF(Vaccine_Selection!P36="","",Vaccine_Selection!P36) | Q29: =IF(Vaccine_Selection!Q36="","",Vaccine_Selection!Q36) | S29: =IF(Vaccine_Selection!S36="","",Vaccine_Selection!S36) | T29: =IF(Vaccine_Selection!T36="","",Vaccine_Selection!T36) | U29: =IF(Vaccine_Selection!U36="","",Vaccine_Selection!U36)
K31: =CONCATENATE(Translation!C195," ",Vaccine_Selection!$E$8) -> Nbr. of empty vials, units/ Unit of Population | M31: =IF(Vaccine_Selection!$E$8=target1,SUMPRODUCT($I$10:$I$29,M$10:M$29),SUMPRODUCT(Vaccine_Selection!$L$17:$L$36,$I$10:$I$29,M$10:M$29)) -> 0.040866667 | N31: =IF(Vaccine_Selection!$E$8=target1,SUMPRODUCT($I$10:$I$29,N$10:N$29),SUMPRODUCT(Vaccine_Selection!$L$17:$L$36,$I$10:$I$29,N$10:N$29)) -> 0.093266667 | O31: =IF(Vaccine_Selection!$E$8=target1,SUMPRODUCT($I$10:$I$29,O$10:O$29),SUMPRODUCT(Vaccine_Selection!$L$17:$L$36,$I$10:$I$29,O$10:O$29)) -> 0.033266667 | P31: =IF(Vaccine_Selection!$E$8=target1,SUMPRODUCT($I$10:$I$29,P$10:P$29),SUMPRODUCT(Vaccine_Selection!$L$17:$L$36,$I$10:$I$29,P$10:P$29)) -> 0 | Q31: =IF(Vaccine_Selection!$E$8=target1,SUMPRODUCT($I$10:$I$29,Q$10:Q$29),SUMPRODUCT(Vaccine_Selection!$L$17:$L$36,$I$10:$I$29,Q$10:Q$29)) -> 0 | R31: =Translation!C202 -> Nbr. of empty vials generated per recipient | S31: =SUMPRODUCT($I$10:$I$29,S$10:S$29) -> 1.0526316 | T31: =SUMPRODUCT($I$10:$I$29,T$10:T$29) -> 0 | U31: =SUMPRODUCT($I$10:$I$29,U$10:U$29) -> 0
K32: =CONCATENATE(Translation!C196," ",Vaccine_Selection!$E$8) -> Nbr. of used dilution syringes generated, units/ Unit of Population | M32: =IF(Vaccine_Selection!$E$8=target1,SUMPRODUCT($K$10:$K$29,M$10:M$29),SUMPRODUCT(Vaccine_Selection!$L$17:$L$36,$K$10:$K$29,M$10:M$29)) -> 0.0089 | N32: =IF(Vaccine_Selection!$E$8=target1,SUMPRODUCT($K$10:$K$29,N$10:N$29),SUMPRODUCT(Vaccine_Selection!$L$17:$L$36,$K$10:$K$29,N$10:N$29)) -> 0.0089 | O32: =IF(Vaccine_Selection!$E$8=target1,SUMPRODUCT($K$10:$K$29,O$10:O$29),SUMPRODUCT(Vaccine_Selection!$L$17:$L$36,$K$10:$K$29,O$10:O$29)) -> 0.0089 | P32: =IF(Vaccine_Selection!$E$8=target1,SUMPRODUCT($K$10:$K$29,P$10:P$29),SUMPRODUCT(Vaccine_Selection!$L$17:$L$36,$K$10:$K$29,P$10:P$29)) -> 0 | Q32: =IF(Vaccine_Selection!$E$8=target1,SUMPRODUCT($K$10:$K$29,Q$10:Q$29),SUMPRODUCT(Vaccine_Selection!$L$17:$L$36,$K$10:$K$29,Q$10:Q$29)) -> 0 | R32: =Translation!C203 -> Nbr. of dilution syringes generated per recipient | S32: =SUMPRODUCT($K$10:$K$29,S$10:S$29) -> 0 | T32: =SUMPRODUCT($K$10:$K$29,T$10:T$29) -> 0 | U32: =SUMPRODUCT($K$10:$K$29,U$10:U$29) -> 0
K33: =CONCATENATE(Translation!C197," ",Vaccine_Selection!$E$8) -> Total nbr. of used syringes generated, units/ Unit of Population | M33: =IF(Vaccine_Selection!$E$8=target1,SUMPRODUCT($J$10:$J$29,M$10:M$29),SUMPRODUCT(Vaccine_Selection!$L$17:$L$36,$J$10:$J$29,M$10:M$29))*1.05+M32 -> 0.18446 | N33: =IF(Vaccine_Selection!$E$8=target1,SUMPRODUCT($J$10:$J$29,N$10:N$29),SUMPRODUCT(Vaccine_Selection!$L$17:$L$36,$J$10:$J$29,N$10:N$29))*1.05+N32 -> 0.18446 | O33: =IF(Vaccine_Selection!$E$8=target1,SUMPRODUCT($J$10:$J$29,O$10:O$29),SUMPRODUCT(Vaccine_Selection!$L$17:$L$36,$J$10:$J$29,O$10:O$29))*1.05+O32 -> 0.18446 | P33: =IF(Vaccine_Selection!$E$8=target1,SUMPRODUCT($J$10:$J$29,P$10:P$29),SUMPRODUCT(Vaccine_Selection!$L$17:$L$36,$J$10:$J$29,P$10:P$29))*1.05+P32 -> 0 | Q33: =IF(Vaccine_Selection!$E$8=target1,SUMPRODUCT($J$10:$J$29,Q$10:Q$29),SUMPRODUCT(Vaccine_Selection!$L$17:$L$36,$J$10:$J$29,Q$10:Q$29))*1.05+Q32 -> 0 | R33: =Translation!C204 -> Total nbr. of syringes generated per recipient | S33: =SUMPRODUCT($J$10:$J$29,S$10:S$29)*1.05+S32 -> 0 | T33: =SUMPRODUCT($J$10:$J$29,T$10:T$29)*1.05+T32 -> 0 | U33: =SUMPRODUCT($J$10:$J$29,U$10:U$29)*1.05+U32 -> 0
K34: =CONCATENATE(Translation!C198," ",Vaccine_Selection!$E$8) -> Nbr. of injections, units/ Unit of Population | M34: =IF(Vaccine_Selection!$E$8=target1,SUMPRODUCT($J$10:$J$29,M$10:M$29),SUMPRODUCT(Vaccine_Selection!$L$17:$L$36,$J$10:$J$29,M$10:M$29)) -> 0.1672 | N34: =IF(Vaccine_Selection!$E$8=target1,SUMPRODUCT($J$10:$J$29,N$10:N$29),SUMPRODUCT(Vaccine_Selection!$L$17:$L$36,$J$10:$J$29,N$10:N$29)) -> 0.1672 | O34: =IF(Vaccine_Selection!$E$8=target1,SUMPRODUCT($J$10:$J$29,O$10:O$29),SUMPRODUCT(Vaccine_Selection!$L$17:$L$36,$J$10:$J$29,O$10:O$29)) -> 0.1672 | P34: =IF(Vaccine_Selection!$E$8=target1,SUMPRODUCT($J$10:$J$29,P$10:P$29),SUMPRODUCT(Vaccine_Selection!$L$17:$L$36,$J$10:$J$29,P$10:P$29)) -> 0 | Q34: =IF(Vaccine_Selection!$E$8=target1,SUMPRODUCT($J$10:$J$29,Q$10:Q$29),SUMPRODUCT(Vaccine_Selection!$L$17:$L$36,$J$10:$J$29,Q$10:Q$29)) -> 0 | R34: =Translation!C205 -> Nbr. of injections per recipient | S34: =SUMPRODUCT($J$10:$J$29,S$10:S$29) -> 0 | T34: =SUMPRODUCT($J$10:$J$29,T$10:T$29) -> 0 | U34: =SUMPRODUCT($J$10:$J$29,U$10:U$29) -> 0
K36: =Translation!C199 -> Increase in nbr.of vials compared to current schedule | N36: =IF(OR($M$31=0,N31=0),"",(N31-$M$31)/$M$31) -> 1.2822186 | O36: =IF(OR($M$31=0,O31=0),"",(O31-$M$31)/$M$31) -> -0.18597064 | P36: =IF(OR($M$31=0,P31=0),"",(P31-$M$31)/$M$31) | Q36: =IF(OR($M$31=0,Q31=0),"",(Q31-$M$31)/$M$31) | T36: =IF(OR($S$31=0,T31=0),"",(T31-$S$31)/$S$31) | U36: =IF(OR($S$31=0,U31=0),"",(U31-$S$31)/$S$31)
K37: =Translation!C200 -> Increase in nbr. of syringes compared to current schedule | N37: =IF(OR($M$33=0,N33=0),"",(N33-$M$33)/$M$33) -> 0 | O37: =IF(OR($M$33=0,O33=0),"",(O33-$M$33)/$M$33) -> 0 | P37: =IF(OR($M$33=0,P33=0),"",(P33-$M$33)/$M$33) | Q37: =IF(OR($M$33=0,Q33=0),"",(Q33-$M$33)/$M$33) | T37: =IF(OR($S$33=0,T33=0),"",(T33-$S$33)/$S$33) | U37: =IF(OR($S$33=0,U33=0),"",(U33-$S$33)/$S$33)
K38: =Translation!C201 -> Increase in nbr. of injections compared to current schedule | N38: =IF(OR($M$34=0,N34=0),"",(N34-$M$34)/$M$34) -> 0 | O38: =IF(OR($M$34=0,O34=0),"",(O34-$M$34)/$M$34) -> 0 | P38: =IF(OR($M$34=0,P34=0),"",(P34-$M$34)/$M$34) | Q38: =IF(OR($M$34=0,Q34=0),"",(Q34-$M$34)/$M$34) | T38: =IF(OR($S$34=0,T34=0),"",(T34-$S$34)/$S$34) | U38: =IF(OR($S$34=0,U34=0),"",(U34-$S$34)/$S$34)

Sheet Cost_Supplies
B2: =Translation!C76 -> Cost of vaccines and safe injection equipment per recipient | O2: =Translation!C77 -> Optional data entry only | U2: =Translation!C109 -> Index
B5: =Translation!C78 -> OPTION: Over-ride price of AD syringe, $/unit: | K5: =IF(I5<>"",I5,0.065*1.1) -> 0.0715
B6: =Translation!C79 -> OPTION: Over-ride price of reconstitution syringe, $/unit: | K6: =IF(I6<>"",I6,0.05*1.1) -> 0.055
B7: =Translation!C80 -> OPTION: Over-ride price of safety box, $/unit: | K7: =IF(I7<>"",I7,0.94*1.1) -> 1.034
B10: =Volume_Inject!B10 -> Characteristics of vaccines selected for use | I10: =Translation!C81 -> Price of safe | M10: =Volume_Inject!M10 -> National immunization schedule | S10: =Vaccine_Selection!$S$14 -> Supplementary
F11: =Volume_Inject!F11 -> Volume data used | I11: =Translation!C82 -> injection equipment | M11: =Volume_Inject!M11 -> (Routine vaccinations) | S11: =Vaccine_Selection!$S$15 -> activities (SIAs)
B12: =Volume_Inject!B12 -> Vaccine type | C12: =Volume_Inject!C12 -> Formulation | D12: =Volume_Inject!D12 -> Administration | E12: =Volume_Inject!E12 -> Presentation (doses/vial) | F12: =Volume_Inject!F12 -> Vaccine volume (cm³/dose) | G12: =Volume_Inject!G12 -> Diluent volume (cm³/dose) | I12: =Volume_Inject!I12 -> Injection syringe | J12: =Volume_Inject!J12 -> Mixing syringe | K12: =Volume_Inject!K12 -> Safety boxes | M12: =IF(Vaccine_Selection!M16="","",Vaccine_Selection!M16) -> Current schedule | N12: =IF(Vaccine_Selection!N16="","",Vaccine_Selection!N16) -> Current schedule with penta 1d | O12: =IF(Vaccine_Selection!O16="","",Vaccine_Selection!O16) -> Current schedule with penta CAD | P12: =IF(Vaccine_Selection!P16="","",Vaccine_Selection!P16) | Q12: =IF(Vaccine_Selection!Q16="","",Vaccine_Selection!Q16) | S12: =IF(Vaccine_Selection!S16="","",Vaccine_Selection!S16) -> H1N1 campaign | T12: =IF(Vaccine_Selection!T16="","",Vaccine_Selection!T16) | U12: =IF(Vaccine_Selection!U16="","",Vaccine_Selection!U16)
B13: =Volume_Inject!B13 -> BCG | C13: =Volume_Inject!C13 -> freeze-dried | D13: =Volume_Inject!D13 -> ID | E13: =Volume_Inject!E13 -> 20 | F13: =Volume_Inject!F13 -> 1.2102 | G13: =Volume_Inject!G13 -> 1.1256667 | I13: =IF(OR(B13="",D13="Oral",D13="Nasal"),"",IF(ISTEXT(E13),0,$K$5*1.1)) -> 0.07865 | J13: =IF(OR(B13="",C13="liquid",D13="Oral",D13="Nasal",ISTEXT(E13)),"",$K$6*Vaccine_Selection!K17/E13) -> 0.0055 | K13: =IF(B13="","",(COUNT($I13:$I13)+COUNT($J13:$J13)/IF(ISTEXT($E13),1,$E13))*$K$7/100) -> 0.010857 | M13: =IF(Vaccine_Selection!M17="","",Vaccine_Selection!M17) -> 1 | N13: =IF(Vaccine_Selection!N17="","",Vaccine_Selection!N17) -> 1 | O13: =IF(Vaccine_Selection!O17="","",Vaccine_Selection!O17) -> 1 | P13: =IF(Vaccine_Selection!P17="","",Vaccine_Selection!P17) | Q13: =IF(Vaccine_Selection!Q17="","",Vaccine_Selection!Q17) | S13: =IF(Vaccine_Selection!S17="","",Vaccine_Selection!S17) | T13: =IF(Vaccine_Selection!T17="","",Vaccine_Selection!T17) | U13: =IF(Vaccine_Selection!U17="","",Vaccine_Selection!U17)
B14: =Volume_Inject!B14 -> OPV | C14: =Volume_Inject!C14 -> liquid | D14: =Volume_Inject!D14 -> Oral | E14: =Volume_Inject!E14 -> 10 | F14: =Volume_Inject!F14 -> 2 | G14: =Volume_Inject!G14 -> 0 | I14: =IF(OR(B14="",D14="Oral",D14="Nasal"),"",IF(ISTEXT(E14),0,$K$5*1.1)) | J14: =IF(OR(B14="",C14="liquid",D14="Oral",D14="Nasal",ISTEXT(E14)),"",$K$6*Vaccine_Selection!K18/E14) | K14: =IF(B14="","",(COUNT($I14:$I14)+COUNT($J14:$J14)/IF(ISTEXT($E14),1,$E14))*$K$7/100) -> 0 | M14: =IF(Vaccine_Selection!M18="","",Vaccine_Selection!M18) -> 4 | N14: =IF(Vaccine_Selection!N18="","",Vaccine_Selection!N18) -> 4 | O14: =IF(Vaccine_Selection!O18="","",Vaccine_Selection!O18) -> 4 | P14: =IF(Vaccine_Selection!P18="","",Vaccine_Selection!P18) | Q14: =IF(Vaccine_Selection!Q18="","",Vaccine_Selection!Q18) | S14: =IF(Vaccine_Selection!S18="","",Vaccine_Selection!S18) | T14: =IF(Vaccine_Selection!T18="","",Vaccine_Selection!T18) | U14: =IF(Vaccine_Selection!U18="","",Vaccine_Selection!U18)
B15: =Volume_Inject!B15 -> DTP-HepB-Hib | C15: =Volume_Inject!C15 -> liquid | D15: =Volume_Inject!D15 -> IM | E15: =Volume_Inject!E15 -> 10 | F15: =Volume_Inject!F15 -> 2.75 | G15: =Volume_Inject!G15 -> 0 | I15: =IF(OR(B15="",D15="Oral",D15="Nasal"),"",IF(ISTEXT(E15),0,$K$5*1.1)) -> 0.07865 | J15: =IF(OR(B15="",C15="liquid",D15="Oral",D15="Nasal",ISTEXT(E15)),"",$K$6*Vaccine_Selection!K19/E15) | K15: =IF(B15="","",(COUNT($I15:$I15)+COUNT($J15:$J15)/IF(ISTEXT($E15),1,$E15))*$K$7/100) -> 0.01034 | M15: =IF(Vaccine_Selection!M19="","",Vaccine_Selection!M19) -> 3 | N15: =IF(Vaccine_Selection!N19="","",Vaccine_Selection!N19) | O15: =IF(Vaccine_Selection!O19="","",Vaccine_Selection!O19) | P15: =IF(Vaccine_Selection!P19="","",Vaccine_Selection!P19) | Q15: =IF(Vaccine_Selection!Q19="","",Vaccine_Selection!Q19) | S15: =IF(Vaccine_Selection!S19="","",Vaccine_Selection!S19) | T15: =IF(Vaccine_Selection!T19="","",Vaccine_Selection!T19) | U15: =IF(Vaccine_Selection!U19="","",Vaccine_Selection!U19)
B16: =Volume_Inject!B16 -> DTP-HepB-Hib | C16: =Volume_Inject!C16 -> liquid | D16: =Volume_Inject!D16 -> IM | E16: =Volume_Inject!E16 -> 1 | F16: =Volume_Inject!F16 -> 16.66384 | G16: =Volume_Inject!G16 -> 0 | I16: =IF(OR(B16="",D16="Oral",D16="Nasal"),"",IF(ISTEXT(E16),0,$K$5*1.1)) -> 0.07865 | J16: =IF(OR(B16="",C16="liquid",D16="Oral",D16="Nasal",ISTEXT(E16)),"",$K$6*Vaccine_Selection!K20/E16) | K16: =IF(B16="","",(COUNT($I16:$I16)+COUNT($J16:$J16)/IF(ISTEXT($E16),1,$E16))*$K$7/100) -> 0.01034 | M16: =IF(Vaccine_Selection!M20="","",Vaccine_Selection!M20) | N16: =IF(Vaccine_Selection!N20="","",Vaccine_Selection!N20) -> 3 | O16: =IF(Vaccine_Selection!O20="","",Vaccine_Selection!O20) | P16: =IF(Vaccine_Selection!P20="","",Vaccine_Selection!P20) | Q16: =IF(Vaccine_Selection!Q20="","",Vaccine_Selection!Q20) | S16: =IF(Vaccine_Selection!S20="","",Vaccine_Selection!S20) | T16: =IF(Vaccine_Selection!T20="","",Vaccine_Selection!T20) | U16: =IF(Vaccine_Selection!U20="","",Vaccine_Selection!U20)
B17: =Volume_Inject!B17 -> DTP-HepB-Hib | C17: =Volume_Inject!C17 -> liquid | D17: =Volume_Inject!D17 -> IM | E17: =Volume_Inject!E17 -> Uniject | F17: =Volume_Inject!F17 -> 12 | G17: =Volume_Inject!G17 -> 0 | I17: =IF(OR(B17="",D17="Oral",D17="Nasal"),"",IF(ISTEXT(E17),0,$K$5*1.1)) -> 0 | J17: =IF(OR(B17="",C17="liquid",D17="Oral",D17="Nasal",ISTEXT(E17)),"",$K$6*Vaccine_Selection!K21/E17) | K17: =IF(B17="","",(COUNT($I17:$I17)+COUNT($J17:$J17)/IF(ISTEXT($E17),1,$E17))*$K$7/100) -> 0.01034 | M17: =IF(Vaccine_Selection!M21="","",Vaccine_Selection!M21) | N17: =IF(Vaccine_Selection!N21="","",Vaccine_Selection!N21) | O17: =IF(Vaccine_Selection!O21="","",Vaccine_Selection!O21) -> 3 | P17: =IF(Vaccine_Selection!P21="","",Vaccine_Selection!P21) | Q17: =IF(Vaccine_Selection!Q21="","",Vaccine_Selection!Q21) | S17: =IF(Vaccine_Selection!S21="","",Vaccine_Selection!S21) | T17: =IF(Vaccine_Selection!T21="","",Vaccine_Selection!T21) | U17: =IF(Vaccine_Selection!U21="","",Vaccine_Selection!U21)
B18: =Volume_Inject!B18 -> Measles | C18: =Volume_Inject!C18 -> freeze-dried | D18: =Volume_Inject!D18 -> SC | E18: =Volume_Inject!E18 -> 10 | F18: =Volume_Inject!F18 -> 2.4002 | G18: =Volume_Inject!G18 -> 3.2 | I18: =IF(OR(B18="",D18="Oral",D18="Nasal"),"",IF(ISTEXT(E18),0,$K$5*1.1)) -> 0.07865 | J18: =IF(OR(B18="",C18="liquid",D18="Oral",D18="Nasal",ISTEXT(E18)),"",$K$6*Vaccine_Selection!K22/E18) -> 0.0091666667 | K18: =IF(B18="","",(COUNT($I18:$I18)+COUNT($J18:$J18)/IF(ISTEXT($E18),1,$E18))*$K$7/100) -> 0.011374 | M18: =IF(Vaccine_Selection!M22="","",Vaccine_Selection!M22) -> 1 | N18: =IF(Vaccine_Selection!N22="","",Vaccine_Selection!N22) -> 1 | O18: =IF(Vaccine_Selection!O22="","",Vaccine_Selection!O22) -> 1 | P18: =IF(Vaccine_Selection!P22="","",Vaccine_Selection!P22) | Q18: =IF(Vaccine_Selection!Q22="","",Vaccine_Selection!Q22) | S18: =IF(Vaccine_Selection!S22="","",Vaccine_Selection!S22) | T18: =IF(Vaccine_Selection!T22="","",Vaccine_Selection!T22) | U18: =IF(Vaccine_Selection!U22="","",Vaccine_Selection!U22)
B19: =Volume_Inject!B19 -> YF | C19: =Volume_Inject!C19 -> freeze-dried | D19: =Volume_Inject!D19 -> SC | E19: =Volume_Inject!E19 -> 5 | F19: =Volume_Inject!F19 -> 5.4025 | G19: =Volume_Inject!G19 -> 6.75 | I19: =IF(OR(B19="",D19="Oral",D19="Nasal"),"",IF(ISTEXT(E19),0,$K$5*1.1)) -> 0.07865 | J19: =IF(OR(B19="",C19="liquid",D19="Oral",D19="Nasal",ISTEXT(E19)),"",$K$6*Vaccine_Selection!K23/E19) -> 0.012222222 | K19: =IF(B19="","",(COUNT($I19:$I19)+COUNT($J19:$J19)/IF(ISTEXT($E19),1,$E19))*$K$7/100) -> 0.012408 | M19: =IF(Vaccine_Selection!M23="","",Vaccine_Selection!M23) -> 1 | N19: =IF(Vaccine_Selection!N23="","",Vaccine_Selection!N23) -> 1 | O19: =IF(Vaccine_Selection!O23="","",Vaccine_Selection!O23) -> 1 | P19: =IF(Vaccine_Selection!P23="","",Vaccine_Selection!P23) | Q19: =IF(Vaccine_Selection!Q23="","",Vaccine_Selection!Q23) | S19: =IF(Vaccine_Selection!S23="","",Vaccine_Selection!S23) | T19: =IF(Vaccine_Selection!T23="","",Vaccine_Selection!T23) | U19: =IF(Vaccine_Selection!U23="","",Vaccine_Selection!U23)
B20: =Volume_Inject!B20 -> TT | C20: =Volume_Inject!C20 -> liquid | D20: =Volume_Inject!D20 -> IM | E20: =Volume_Inject!E20 -> 10 | F20: =Volume_Inject!F20 -> 3.1093333 | G20: =Volume_Inject!G20 -> 0 | I20: =IF(OR(B20="",D20="Oral",D20="Nasal"),"",IF(ISTEXT(E20),0,$K$5*1.1)) -> 0.07865 | J20: =IF(OR(B20="",C20="liquid",D20="Oral",D20="Nasal",ISTEXT(E20)),"",$K$6*Vaccine_Selection!K24/E20) | K20: =IF(B20="","",(COUNT($I20:$I20)+COUNT($J20:$J20)/IF(ISTEXT($E20),1,$E20))*$K$7/100) -> 0.01034 | M20: =IF(Vaccine_Selection!M24="","",Vaccine_Selection!M24) -> 2 | N20: =IF(Vaccine_Selection!N24="","",Vaccine_Selection!N24) -> 2 | O20: =IF(Vaccine_Selection!O24="","",Vaccine_Selection!O24) -> 2 | P20: =IF(Vaccine_Selection!P24="","",Vaccine_Selection!P24) | Q20: =IF(Vaccine_Selection!Q24="","",Vaccine_Selection!Q24) | S20: =IF(Vaccine_Selection!S24="","",Vaccine_Selection!S24) | T20: =IF(Vaccine_Selection!T24="","",Vaccine_Selection!T24) | U20: =IF(Vaccine_Selection!U24="","",Vaccine_Selection!U24)
B21: =Volume_Inject!B21 -> PCV-13 | C21: =Volume_Inject!C21 -> liquid | D21: =Volume_Inject!D21 -> IM | E21: =Volume_Inject!E21 -> 1 | F21: =Volume_Inject!F21 -> 13.825247 | G21: =Volume_Inject!G21 -> 0 | I21: =IF(OR(B21="",D21="Oral",D21="Nasal"),"",IF(ISTEXT(E21),0,$K$5*1.1)) -> 0.07865 | J21: =IF(OR(B21="",C21="liquid",D21="Oral",D21="Nasal",ISTEXT(E21)),"",$K$6*Vaccine_Selection!K25/E21) | K21: =IF(B21="","",(COUNT($I21:$I21)+COUNT($J21:$J21)/IF(ISTEXT($E21),1,$E21))*$K$7/100) -> 0.01034 | M21: =IF(Vaccine_Selection!M25="","",Vaccine_Selection!M25) | N21: =IF(Vaccine_Selection!N25="","",Vaccine_Selection!N25) | O21: =IF(Vaccine_Selection!O25="","",Vaccine_Selection!O25) | P21: =IF(Vaccine_Selection!P25="","",Vaccine_Selection!P25) | Q21: =IF(Vaccine_Selection!Q25="","",Vaccine_Selection!Q25) | S21: =IF(Vaccine_Selection!S25="","",Vaccine_Selection!S25) | T21: =IF(Vaccine_Selection!T25="","",Vaccine_Selection!T25) | U21: =IF(Vaccine_Selection!U25="","",Vaccine_Selection!U25)
B22: =Volume_Inject!B22 -> Rota_liq | C22: =Volume_Inject!C22 -> liquid | D22: =Volume_Inject!D22 -> Oral | E22: =Volume_Inject!E22 -> 1 | F22: =Volume_Inject!F22 -> 17.1 | G22: =Volume_Inject!G22 -> 0 | I22: =IF(OR(B22="",D22="Oral",D22="Nasal"),"",IF(ISTEXT(E22),0,$K$5*1.1)) | J22: =IF(OR(B22="",C22="liquid",D22="Oral",D22="Nasal",ISTEXT(E22)),"",$K$6*Vaccine_Selection!K26/E22) | K22: =IF(B22="","",(COUNT($I22:$I22)+COUNT($J22:$J22)/IF(ISTEXT($E22),1,$E22))*$K$7/100) -> 0 | M22: =IF(Vaccine_Selection!M26="","",Vaccine_Selection!M26) | N22: =IF(Vaccine_Selection!N26="","",Vaccine_Selection!N26) | O22: =IF(Vaccine_Selection!O26="","",Vaccine_Selection!O26) | P22: =IF(Vaccine_Selection!P26="","",Vaccine_Selection!P26) | Q22: =IF(Vaccine_Selection!Q26="","",Vaccine_Selection!Q26) | S22: =IF(Vaccine_Selection!S26="","",Vaccine_Selection!S26) -> 1 | T22: =IF(Vaccine_Selection!T26="","",Vaccine_Selection!T26) | U22: =IF(Vaccine_Selection!U26="","",Vaccine_Selection!U26)
B23: =Volume_Inject!B23 | C23: =Volume_Inject!C23 | D23: =Volume_Inject!D23 | E23: =Volume_Inject!E23 -> 0 | F23: =Volume_Inject!F23 -> 0 | G23: =Volume_Inject!G23 -> 0 | I23: =IF(OR(B23="",D23="Oral",D23="Nasal"),"",IF(ISTEXT(E23),0,$K$5*1.1)) | J23: =IF(OR(B23="",C23="liquid",D23="Oral",D23="Nasal",ISTEXT(E23)),"",$K$6*Vaccine_Selection!K27/E23) | K23: =IF(B23="","",(COUNT($I23:$I23)+COUNT($J23:$J23)/IF(ISTEXT($E23),1,$E23))*$K$7/100) | M23: =IF(Vaccine_Selection!M27="","",Vaccine_Selection!M27) | N23: =IF(Vaccine_Selection!N27="","",Vaccine_Selection!N27) | O23: =IF(Vaccine_Selection!O27="","",Vaccine_Selection!O27) | P23: =IF(Vaccine_Selection!P27="","",Vaccine_Selection!P27) | Q23: =IF(Vaccine_Selection!Q27="","",Vaccine_Selection!Q27) | S23: =IF(Vaccine_Selection!S27="","",Vaccine_Selection!S27) | T23: =IF(Vaccine_Selection!T27="","",Vaccine_Selection!T27) | U23: =IF(Vaccine_Selection!U27="","",Vaccine_Selection!U27)
B24: =Volume_Inject!B24 | C24: =Volume_Inject!C24 | D24: =Volume_Inject!D24 | E24: =Volume_Inject!E24 -> 0 | F24: =Volume_Inject!F24 -> 0 | G24: =Volume_Inject!G24 -> 0 | I24: =IF(OR(B24="",D24="Oral",D24="Nasal"),"",IF(ISTEXT(E24),0,$K$5*1.1)) | J24: =IF(OR(B24="",C24="liquid",D24="Oral",D24="Nasal",ISTEXT(E24)),"",$K$6*Vaccine_Selection!K28/E24) | K24: =IF(B24="","",(COUNT($I24:$I24)+COUNT($J24:$J24)/IF(ISTEXT($E24),1,$E24))*$K$7/100) | M24: =IF(Vaccine_Selection!M28="","",Vaccine_Selection!M28) | N24: =IF(Vaccine_Selection!N28="","",Vaccine_Selection!N28) | O24: =IF(Vaccine_Selection!O28="","",Vaccine_Selection!O28) | P24: =IF(Vaccine_Selection!P28="","",Vaccine_Selection!P28) | Q24: =IF(Vaccine_Selection!Q28="","",Vaccine_Selection!Q28) | S24: =IF(Vaccine_Selection!S28="","",Vaccine_Selection!S28) | T24: =IF(Vaccine_Selection!T28="","",Vaccine_Selection!T28) | U24: =IF(Vaccine_Selection!U28="","",Vaccine_Selection!U28)
... B32: =Volume_Inject!B32 | C32: =Volume_Inject!C32 | D32: =Volume_Inject!D32 | E32: =Volume_Inject!E32 -> 0 | F32: =Volume_Inject!F32 -> 0 | G32: =Volume_Inject!G32 -> 0 | I32: =IF(OR(B32="",D32="Oral",D32="Nasal"),"",IF(ISTEXT(E32),0,$K$5*1.1)) | J32: =IF(OR(B32="",C32="liquid",D32="Oral",D32="Nasal",ISTEXT(E32)),"",$K$6*Vaccine_Selection!K36/E32) | K32: =IF(B32="","",(COUNT($I32:$I32)+COUNT($J32:$J32)/IF(ISTEXT($E32),1,$E32))*$K$7/100) | M32: =IF(Vaccine_Selection!M36="","",Vaccine_Selection!M36) | N32: =IF(Vaccine_Selection!N36="","",Vaccine_Selection!N36) | O32: =IF(Vaccine_Selection!O36="","",Vaccine_Selection!O36) | P32: =IF(Vaccine_Selection!P36="","",Vaccine_Selection!P36) | Q32: =IF(Vaccine_Selection!Q36="","",Vaccine_Selection!Q36) | S32: =IF(Vaccine_Selection!S36="","",Vaccine_Selection!S36) | T32: =IF(Vaccine_Selection!T36="","",Vaccine_Selection!T36) | U32: =IF(Vaccine_Selection!U36="","",Vaccine_Selection!U36)
K34: =CONCATENATE(Translation!C83," ",Vaccine_Selection!$E$8) -> Total cost of vaccines per Unit of Population | M34: =IF(Vaccine_Selection!$E$8=target1,SUMPRODUCT(Vaccine_Selection!$H$17:$H$36,M$13:M$32),SUMPRODUCT(Vaccine_Selection!$H$17:$H$36,Vaccine_Selection!$L$17:$L$36,M$13:M$32)) -> 0 | N34: =IF(Vaccine_Selection!$E$8=target1,SUMPRODUCT(Vaccine_Selection!$H$17:$H$36,N$13:N$32),SUMPRODUCT(Vaccine_Selection!$H$17:$H$36,Vaccine_Selection!$L$17:$L$36,N$13:N$32)) -> 0 | O34: =IF(Vaccine_Selection!$E$8=target1,SUMPRODUCT(Vaccine_Selection!$H$17:$H$36,O$13:O$32),SUMPRODUCT(Vaccine_Selection!$H$17:$H$36,Vaccine_Selection!$L$17:$L$36,O$13:O$32)) -> 0 | P34: =IF(Vaccine_Selection!$E$8=target1,SUMPRODUCT(Vaccine_Selection!$H$17:$H$36,P$13:P$32),SUMPRODUCT(Vaccine_Selection!$H$17:$H$36,Vaccine_Selection!$L$17:$L$36,P$13:P$32)) -> 0 | Q34: =IF(Vaccine_Selection!$E$8=target1,SUMPRODUCT(Vaccine_Selection!$H$17:$H$36,Q$13:Q$32),SUMPRODUCT(Vaccine_Selection!$H$17:$H$36,Vaccine_Selection!$L$17:$L$36,Q$13:Q$32)) -> 0 | R34: =Translation!C87 -> Total cost of vaccines per recipient | S34: =SUMPRODUCT(Vaccine_Selection!$H$17:$H$36,S$13:S$32) -> 0 | T34: =SUMPRODUCT(Vaccine_Selection!$H$17:$H$36,T$13:T$32) -> 0 | U34: =SUMPRODUCT(Vaccine_Selection!$H$17:$H$36,U$13:U$32) -> 0
